Workbook

Sheet グローバルリゾート全体収支
A1: 2026年度グローバルリゾート/レジデンス 全体 収支報告
A3: 部門 | B3: 施設 | C3: 内訳 | E3: 1月 | F3: 2月 | G3: 3月 | H3: 4月 | I3: 5月 | J3: 6月 | K3: 7月 | L3: 8月 | M3: 9月 | N3: 10月 | O3: 11月 | P3: 12月 | Q3: 計
A4: ホテル | B4: デルーネ ビュー 本川 天神 玖波 | C4: 売上 | D4: de Lune | E4: =ホテル部門→!B17 -> 6712201 | F4: =ホテル部門→!C17 -> 6486426 | G4: =ホテル部門→!D17 -> 9961885 | H4: =ホテル部門→!E17 -> 8310821 | I4: =ホテル部門→!F17 -> 9884840 | J4: =ホテル部門→!G17 -> 4996865 | K4: =ホテル部門→!H17 -> 1386977 | L4: =ホテル部門→!I17 -> 2069324 | ... P4: =ホテル部門→!M17 -> 147350 | Q4: =SUM(E4:P4) -> 51711522
D5: VIEW | E5: =ホテル部門→!B40 -> 1319475 | F5: =ホテル部門→!C40 -> 1757661 | G5: =ホテル部門→!D40 -> 2882218 | H5: =ホテル部門→!E40 -> 2904045 | I5: =ホテル部門→!F40 -> 3017659 | J5: =ホテル部門→!G40 -> 2196076 | K5: =ホテル部門→!H40 -> 492989 | L5: =ホテル部門→!I40 -> 716260 | ... P5: =ホテル部門→!M40 -> 0 | Q5: =SUM(E5:P5) -> 16024147
D6: 本川 | E6: =ホテル部門→!B59 -> 638232 | F6: =ホテル部門→!C59 -> 1033872 | G6: =ホテル部門→!D59 -> 1357093 | H6: =ホテル部門→!E59 -> 1955058 | I6: =ホテル部門→!F59 -> 1887446 | J6: =ホテル部門→!G59 -> 276276 | K6: =ホテル部門→!H59 -> 417182 | L6: =ホテル部門→!I59 -> 435946 | ... P6: =ホテル部門→!M59 -> 0 | Q6: =SUM(E6:P6) -> 8365293
D7: 天神 | E7: =ホテル部門→!B73 -> 100300 | F7: =ホテル部門→!C73 -> 108270 | G7: =ホテル部門→!D73 -> 189640 | H7: =ホテル部門→!E73 -> 56700 | I7: =ホテル部門→!F73 -> 289480 | J7: =ホテル部門→!G73 -> 72400 | K7: =ホテル部門→!H73 -> 16200 | L7: =ホテル部門→!I73 -> 0 | ... P7: =ホテル部門→!M73 -> 0 | Q7: =SUM(E7:P7) -> 832990
D8: 玖波 | E8: =ホテル部門→!B87 -> 138750 | F8: =ホテル部門→!C87 -> 406500 | G8: =ホテル部門→!D87 -> 794600 | H8: =ホテル部門→!E87 -> 331500 | I8: =ホテル部門→!F87 -> 303810 | J8: =ホテル部門→!G87 -> 190750 | K8: =ホテル部門→!H87 -> 96000 | L8: =ホテル部門→!I87 -> 35000 | ... P8: =ホテル部門→!M87 -> 0 | Q8: =SUM(E8:P8) -> 2336510
D9: 売上合計 | E9: =SUM(E4:E8) -> 8908958 | F9: =SUM(F4:F8) -> 9792729 | G9: =SUM(G4:G8) -> 15185436 | H9: =SUM(H4:H8) -> 13558124 | I9: =SUM(I4:I8) -> 15383235 | J9: =SUM(J4:J8) -> 7732367 | K9: =SUM(K4:K8) -> 2409348 | L9: =SUM(L4:L8) -> 3256530 | ... Q9: =SUM(Q4:Q8) -> 79270462
C10: 経費 | D10: de Lune | E10: 1532400 | F10: 1262197
D11: VIEW | E11: 257028 | F11: 291700
D12: 本川 | E12: 104577 | F12: 149077
D13: 天神 | E13: 16596 | F13: 1005193
D14: 玖波
D15: リゾート | E15: 9211951 | F15: 27179756 | Q15: =SUM(E15:P15) -> 36391707
D16: 経費合計 | E16: =SUM(E10:E15) -> 11122552 | F16: =SUM(F10:F15) -> 29887923 | G16: =SUM(G10:G15) -> 0 | H16: =SUM(H10:H15) -> 0 | I16: =SUM(I10:I15) -> 0 | J16: =SUM(J10:J15) -> 0 | K16: =SUM(K10:K15) -> 0 | L16: =SUM(L10:L15) -> 0 | ... Q16: =SUM(Q10:Q15) -> 36391707
C17: 差引収支 | E17: =E9-E16 -> -2213594 | F17: =F9-F16 -> -20095194 | G17: =G9-G16 -> 15185436 | H17: =H9-H16 -> 13558124 | I17: =I9-I16 -> 15383235 | J17: =J9-J16 -> 7732367 | K17: =K9-K16 -> 2409348 | L17: =L9-L16 -> 3256530 | ... P17: =P9-P16 -> 147350 | Q17: =SUM(Q4:Q8)-SUM(Q10:Q15) -> 42878755
B18: 弥山 | C18: 売上 | E18: =弥山!B4 -> 2906901 | F18: =弥山!C4 -> 4965898 | G18: =弥山!D4 -> 6807485 | H18: =弥山!E4 -> 4004248 | I18: =弥山!F4 -> 6175495 | J18: =弥山!G4 -> 2105073 | K18: =弥山!H4 -> 1056902 | L18: =弥山!I4 -> 1697508 | ... P18: =弥山!M4 -> 20000 | Q18: =SUM(E18:P18) -> 31554666
C19: 経費 | E19: 2280539 | F19: 3403055 | Q19: =SUM(E19:P19) -> 5683594
C20: 差引収支 | E20: =E18-E19 -> 626362 | F20: =F18-F19 -> 1562843 | G20: =G18-G19 -> 6807485 | H20: =H18-H19 -> 4004248 | I20: =I18-I19 -> 6175495 | J20: =J18-J19 -> 2105073 | K20: =K18-K19 -> 1056902 | L20: =L18-L19 -> 1697508 | ... Q20: =Q18-Q19 -> 25871072
B21: 温井 | C21: 売上 | E21: =温井!D3 -> 7428554 | F21: =温井!E3 -> 7562227 | G21: =温井!F3 -> 3799283 | H21: =温井!G3 -> 2330934 | I21: =温井!H3 -> 4784742 | J21: =温井!I3 -> 2087208 | K21: =温井!J3 -> 1038480 | L21: =温井!K3 -> 1446637 | ... P21: =温井!O3 -> 0 | Q21: =SUM(E21:P21) -> 30755817
C22: 経費 | E22: 8916981 | F22: 7426432 | Q22: =SUM(E22:P22) -> 16343413
C23: 差引収支 | E23: =E21-E22 -> -1488427 | F23: =F21-F22 -> 135795 | G23: =G21-G22 -> 3799283 | H23: =H21-H22 -> 2330934 | I23: =I21-I22 -> 4784742 | J23: =J21-J22 -> 2087208 | K23: =K21-K22 -> 1038480 | L23: =L21-L22 -> 1446637 | ... Q23: =Q21-Q22 -> 14412404
B24: いこいの村 | C24: 売上 | E24: =いこいの村!D3 -> 8292624 | F24: =いこいの村!E3 -> 8535484 | G24: =いこいの村!F3 -> 4929332 | H24: =いこいの村!G3 -> 6092392 | I24: =いこいの村!H3 -> 3646914 | J24: =いこいの村!I3 -> 1303991 | K24: =いこいの村!J3 -> 1869506 | L24: =いこいの村!K3 -> 948336 | ... P24: =いこいの村!O3 -> 0 | Q24: =SUM(E24:P24) -> 37827062
C25: 経費 | E25: =いこいの村!C87 -> 5778007 | F25: =いこいの村!D87 -> 5913951 | G25: =いこいの村!E87 -> 0 | H25: =いこいの村!F87 -> 0 | I25: =いこいの村!G87 -> 0 | J25: =いこいの村!H87 -> 0 | K25: =いこいの村!I87 -> 0 | L25: =いこいの村!J87 -> 0 | ... P25: =いこいの村!N87 -> 0 | Q25: =SUM(E25:P25) -> 11691958
C26: 差引収支 | E26: =E24-E25 -> 2514617 | F26: =F24-F25 -> 2621533 | G26: =G24-G25 -> 4929332 | H26: =H24-H25 -> 6092392 | I26: =I24-I25 -> 3646914 | J26: =J24-J25 -> 1303991 | K26: =K24-K25 -> 1869506 | L26: =L24-L25 -> 948336 | ... Q26: =Q24-Q25 -> 26135104
A27: マンスリー | B27: TAKAYA SAIJO壱番館 SIJO弐番館 Otake | C27: 売上 | D27: TAKAYA | E27: =マンスリー部門!B4 -> 251000 | F27: =マンスリー部門!C4 -> 308000 | G27: =マンスリー部門!D4 -> 651000 | H27: =マンスリー部門!E4 -> 455000 | I27: =マンスリー部門!F4 -> 272000 | J27: =マンスリー部門!G4 -> 195000 | K27: =マンスリー部門!H4 -> 78000 | L27: =マンスリー部門!I4 -> 120000 | ... P27: =マンスリー部門!M4 -> 0 | Q27: =SUM(E27:P27) -> 2330000
D28: 壱番館 | E28: =マンスリー部門!B19 -> 155000 | F28: =マンスリー部門!C19 -> 110500 | G28: =マンスリー部門!D19 -> 66000 | H28: =マンスリー部門!E19 -> 101400 | I28: =マンスリー部門!F19 -> 24000 | J28: =マンスリー部門!G19 -> 45000 | K28: =マンスリー部門!H19 -> 0 | L28: =マンスリー部門!I19 -> 0 | ... P28: =マンスリー部門!M19 -> 0 | Q28: =SUM(E28:P28) -> 501900
D29: 弐番館 | E29: =マンスリー部門!B34 -> 0 | F29: =マンスリー部門!C34 -> 42500 | G29: =マンスリー部門!D34 -> 0 | H29: =マンスリー部門!E34 -> 90000 | I29: =マンスリー部門!F34 -> 93000 | J29: =マンスリー部門!G34 -> 46000 | K29: =マンスリー部門!H34 -> 57000 | L29: =マンスリー部門!I34 -> 75000 | ... P29: =マンスリー部門!M34 -> 0 | Q29: =SUM(E29:P29) -> 403500
D30: Otake | E30: =マンスリー部門!B49 -> 77500 | F30: =マンスリー部門!C49 -> 77500 | G30: =マンスリー部門!D49 -> 80000 | H30: =マンスリー部門!E49 -> 105000 | I30: =マンスリー部門!F49 -> 77500 | J30: =マンスリー部門!G49 -> 72500 | K30: =マンスリー部門!H49 -> 0 | L30: =マンスリー部門!I49 -> 0 | ... P30: =マンスリー部門!M49 -> 0 | Q30: =SUM(E30:P30) -> 490000
D31: 合計 | E31: =SUM(E27:E30) -> 483500 | F31: =SUM(F27:F30) -> 538500 | G31: =SUM(G27:G30) -> 797000 | H31: =SUM(H27:H30) -> 751400 | I31: =SUM(I27:I30) -> 466500 | J31: =SUM(J27:J30) -> 358500 | K31: =SUM(K27:K30) -> 135000 | L31: =SUM(L27:L30) -> 195000 | ... Q31: =SUM(Q27:Q30) -> 3725400
C32: 経費 | Q32: =SUM(E32:P32) -> 0
C33: 差引収支 | E33: =E31-E32 -> 483500 | F33: =F31-F32 -> 538500 | G33: =G31-G32 -> 797000 | H33: =H31-H32 -> 751400 | I33: =I31-I32 -> 466500 | J33: =J31-J32 -> 358500 | K33: =K31-K32 -> 135000 | L33: =L31-L32 -> 195000 | ... P33: =P31-P32 -> 0 | Q33: =SUM(Q28:Q30)-Q32 -> 1395400
A34: 指定管理 | B34: 竹原（ﾚｽﾄﾗﾝ含む） | C34: 売上 | E34: =竹原!D3 -> 1247037 | F34: =竹原!E3 -> 1238472 | G34: =竹原!F3 -> 1370148 | H34: =竹原!G3 -> 1202444 | I34: =竹原!H3 -> 789000 | J34: =竹原!I3 -> 683000 | K34: =竹原!J3 -> 683000 | L34: =竹原!K3 -> 683000 | ... P34: =竹原!O3 -> 683000 | Q34: =SUM(E34:P34) -> 10628101
C35: 経費 | E35: =竹原!D48 -> 1603560 | F35: =竹原!E48 -> 1713674 | G35: =竹原!F48 -> 0 | H35: =竹原!G48 -> 0 | I35: =竹原!H48 -> 0 | J35: =竹原!I48 -> 0 | K35: =竹原!J48 -> 0 | L35: =竹原!K48 -> 0 | ... P35: =竹原!O48 -> 0 | Q35: =SUM(E35:P35) -> 3317234
C36: 差引収支 | E36: =E34-E35 -> -356523 | F36: =F34-F35 -> -475202 | G36: =G34-G35 -> 1370148 | H36: =H34-H35 -> 1202444 | I36: =I34-I35 -> 789000 | J36: =J34-J35 -> 683000 | K36: =K34-K35 -> 683000 | L36: =L34-L35 -> 683000 | ... Q36: =Q34-Q35 -> 7310867
B37: フォレストヒルズガーデン | C37: 売上 | E37: =フォレストヒルズガーデン!B3 -> 5670857 | F37: =フォレストヒルズガーデン!C3 -> 5411304 | G37: =フォレストヒルズガーデン!D3 -> 6110445 | H37: =フォレストヒルズガーデン!E3 -> 5535949 | I37: =フォレストヒルズガーデン!F3 -> 7265723 | J37: =フォレストヒルズガーデン!G3 -> 5640457 | K37: =フォレストヒルズガーデン!H3 -> 4902843 | L37: =フォレストヒルズガーデン!I3 -> 5877492 | ... P37: =フォレストヒルズガーデン!M3 -> 4621833 | Q37: =SUM(E37:P37) -> 65185602
C38: 経費 | E38: 4318542 | F38: 4263820 | G38: 0 | H38: 0 | I38: 0 | J38: 0 | K38: 0 | L38: 0 | M38: 0 | N38: 0 | O38: 0 | P38: 0 | Q38: =SUM(E38:P38) -> 8582362
C39: 差引収支 | E39: =E37-E38 -> 1352315 | F39: =F37-F38 -> 1147484 | G39: =G37-G38 -> 6110445 | H39: =H37-H38 -> 5535949 | I39: =I37-I38 -> 7265723 | J39: =J37-J38 -> 5640457 | K39: =K37-K38 -> 4902843 | L39: =L37-L38 -> 5877492 | ... Q39: =Q37-Q38 -> 56603240
B40: グリーンシャワー | C40: 売上 | E40: =深入山GS!C51 -> 248917 | F40: =深入山GS!D51 -> 248917 | G40: =深入山GS!E51 -> 248917 | H40: =深入山GS!F51 -> 626997 | I40: =深入山GS!G51 -> 248917 | J40: =深入山GS!H51 -> 248917 | K40: =深入山GS!I51 -> 248917 | L40: =深入山GS!J51 -> 248917 | ... P40: =深入山GS!N51 -> 248917 | Q40: =SUM(E40:P40) -> 3365084
C41: 経費 | E41: =深入山GS!C60 -> 0 | F41: =深入山GS!D60 -> 0 | G41: =深入山GS!E60 -> 0 | H41: =深入山GS!F60 -> 0 | I41: =深入山GS!G60 -> 0 | J41: =深入山GS!H60 -> 0 | K41: =深入山GS!I60 -> 0 | L41: =深入山GS!J60 -> 0 | ... P41: =深入山GS!N60 -> 0 | Q41: =SUM(E41:P41) -> 0
C42: 差引収支 | E42: =E40-E41 -> 248917 | F42: =F40-F41 -> 248917 | G42: =G40-G41 -> 248917 | H42: =H40-H41 -> 626997 | I42: =I40-I41 -> 248917 | J42: =J40-J41 -> 248917 | K42: =K40-K41 -> 248917 | L42: =L40-L41 -> 248917 | ... Q42: =Q40-Q41 -> 3365084
A43: サウナ | B43: MAKI de SAUNA | C43: 売上 | E43: =サウナ!B3 -> 0 | F43: 134014 | G43: =サウナ!D3 -> 134706 | H43: =サウナ!E3 -> 121831 | I43: =サウナ!F3 -> 36276 | J43: =サウナ!G3 -> 0 | K43: =サウナ!H3 -> 0 | L43: =サウナ!I3 -> 0 | M43: =サウナ!J3 -> 0 | N43: =サウナ!K3 -> 0 | ... P43: =サウナ!M3 -> 0 | Q43: =SUM(E43:P43) -> 426827
C44: 経費 | Q44: =SUM(E44:P44) -> 0
C45: 差引収支 | E45: =E43-E44 -> 0 | F45: =F43-F44 -> 134014 | G45: =G43-G44 -> 134706 | H45: =H43-H44 -> 121831 | I45: =I43-I44 -> 36276 | J45: =J43-J44 -> 0 | K45: =K43-K44 -> 0 | L45: =L43-L44 -> 0 | ... Q45: =Q43-Q44 -> 426827
B46: 周防大島 | C46: 売上 | E46: 0 | G46: 7000 | Q46: =SUM(E46:P46) -> 7000
C47: 経費 | E47: 320335 | F47: 401121 | Q47: =SUM(E47:P47) -> 721456
C48: 差引収支 | E48: =E46-E47 -> -320335 | F48: =F46-F47 -> -401121 | Q48: =Q46-Q47 -> -714456
B49: ほうらいの里 | C49: 売上 | Q49: =SUM(E49:P49) -> 0
C50: 経費 | E50: 736508 | F50: 1011829 | Q50: =SUM(E50:P50) -> 1748337
C51: 差引収支 | E51: =E49-E50 -> -736508 | F51: =F49-F50 -> -1011829 | G51: =G49-G50 -> 0 | H51: =H49-H50 -> 0 | I51: =I49-I50 -> 0 | J51: =J49-J50 -> 0 | K51: =K49-K50 -> 0 | L51: =L49-L50 -> 0 | ... Q51: =Q49-Q50 -> -1748337
A52: カフェ | B52: NorthLinkHirosima（2025年3月31日最終営業） | C52: 売上 | Q52: =SUM(E52:P52) -> 0
C53: 経費 | E53: 60837 | F53: 52171 | Q53: =SUM(E53:P53) -> 113008
C54: 差引収支 | E54: =E52-E53 -> -60837 | F54: =F52-F53 -> -52171 | G54: =G52-G53 -> 0 | H54: =H52-H53 -> 0 | I54: =I52-I53 -> 0 | J54: =J52-J53 -> 0 | K54: =K52-K53 -> 0 | L54: =L52-L53 -> 0 | ... Q54: =Q52-Q53 -> -113008
A55: 経費不明 | B55: 経費 不明金 | C55: リゾート | Q55: =SUM(E55:P55) -> 0
C56: レジデンス | Q56: =SUM(E56:P56) -> 0
C57: 不明金合計 | E57: =E55+E56 -> 0 | G57: =SUM(G55:G56) -> 0 | H57: =SUM(H55:H56) -> 0 | I57: =SUM(I55:I56) -> 0 | J57: =SUM(J55:J56) -> 0 | K57: =SUM(K55:K56) -> 0 | L57: =SUM(L55:L56) -> 0 | M57: =SUM(M55:M56) -> 0 | N57: =SUM(N55:N56) -> 0 | ... P57: =SUM(P55:P56) -> 0 | Q57: =SUM(E57:P57) -> 0
A58: 全施設 | B58: 合計 | C58: 売上 | E58: =SUM(E9+E18+E21+E24+SUM(E31)+E34+E43+E52+E37+E40+E46+E49) -> 35187348 | F58: =SUM(F9+F18+F21+F24+SUM(F31)+F34+F43+F52+F37+F40+F46+F49) -> 38427545 | G58: =SUM(G9+G18+G21+G24+SUM(G31)+G34+G43+G52+G37+G40+G46+G49) -> 39389752 | H58: =SUM(H9+H18+H21+H24+SUM(H31)+H34+H43+H52+H37+H40+H46+H49) -> 34224319 | I58: =SUM(I9+I18+I21+I24+SUM(I31)+I34+I43+I52+I37+I40+I46+I49) -> 38796802 | J58: =SUM(J9+J18+J21+J24+SUM(J31)+J34+J43+J52+J37+J40+J46+J49) -> 20159513 | K58: =SUM(K9+K18+K21+K24+SUM(K31)+K34+K43+K52+K37+K40+K46+K49) -> 12343996 | L58: =SUM(L9+L18+L21+L24+SUM(L31)+L34+L43+L52+L37+L40+L46+L49) -> 14353420 | ... P58: =SUM(P9+P18+P21+P24+SUM(P31)+P34+P43+P52+P37+P40+P46+P49) -> 5721100 | Q58: =SUM(E58:P58) -> 262746021
C59: 経費 | E59: =SUM(E16+E19+E22+E32+E35+E44+E53)+E25+E38+E41+E47+E50+E57 -> 35137861 | F59: =SUM(F16+F19+F22+F32+F35+F44+F53)+F25+F38+F41+F47+F50+F57 -> 54073976 | G59: =SUM(G16+G19+G22+G32+G35+G44+G53)+G25+G38+G41+G47+G50+G57 -> 0 | H59: =SUM(H16+H19+H22+H32+H35+H44+H53)+H25+H38+H41+H47+H50+H57 -> 0 | I59: =SUM(I16+I19+I22+I32+I35+I44+I53)+I25+I38+I41+I47+I50+I57 -> 0 | J59: =SUM(J16+J19+J22+J32+J35+J44+J53)+J25+J38+J41+J47+J50+J57 -> 0 | K59: =SUM(K16+K19+K22+K32+K35+K44+K53)+K25+K38+K41+K47+K50+K57 -> 0 | L59: =SUM(L16+L19+L22+L32+L35+L44+L53)+L25+L38+L41+L47+L50+L57 -> 0 | ... P59: =SUM(P16+P19+P22+P32+P35+P44+P53)+P25+P38+P41+P47+P50+P57 -> 0 | Q59: =SUM(E59:P59) -> 89211837
C60: 差引収支 | E60: =E58-E59 -> 49487 | F60: =F58-F59 -> -15646431 | G60: =G58-G59 -> 39389752 | H60: =H58-H59 -> 34224319 | I60: =I58-I59 -> 38796802 | J60: =J58-J59 -> 20159513 | K60: =K58-K59 -> 12343996 | L60: =L58-L59 -> 14353420 | ... Q60: =Q58-Q59 -> 173534184
M62: ホテル部門 | N62: マンスリー部門 | O62: 指定管理部門 | P62: サウナ部門 | Q62: カフェ部門 | R62: 全体
J63: この部分は未確定 | K63: 総売上 | L63: 今年度 | M63: =Q9+Q18+Q21+Q24+Q46 -> 179415007 | N63: =SUM(Q27:Q30) -> 3725400 | O63: =Q34+Q37+Q40 -> 79178787 | P63: =Q43 -> 426827 | Q63: =Q52 -> 0 | R63: =SUM(M63:Q63) -> 262746021
L64: 昨年度 | M64: =ホテル部門→!N7+弥山!N20 -> 173376507 | N64: =マンスリー部門!N12+マンスリー部門!N27+マンスリー部門!N42+マンスリー部門!N57 -> 7285480 | O64: 0 | P64: 0 | Q64: 6314186
K65: 売上昨年対比 | M65: =M63/M64 -> 1.0348288 | N65: =N63/N64 -> 0.51134586 | O65: =O63/O64 -> #DIV/0! | P65: =P63/P64 -> #DIV/0! | Q65: =Q63/Q64 -> 0 | R65: =R63/R64 -> #DIV/0!
K66: 総経費 | L66: 今年度 | M66: =Q16+Q19+Q22+Q25+Q47 -> 70832128 | N66: =Q32 -> 0 | O66: =Q35+Q38+Q41 -> 11899596 | P66: =Q44 -> 0 | Q66: =Q53 -> 113008 | R66: =SUM(M66:Q66) -> 82844732
L67: 昨年度 | Q67: 5348605
K68: 差引収支 | L68: 今年度 | M68: =M63-M66 -> 108582879 | N68: =N63-N66 -> 3725400 | O68: =O63-O66 -> 67279191 | P68: =P63-P66 -> 426827 | Q68: =Q63-Q66 -> -113008 | R68: =R63-R66 -> 179901289
L69: 昨年度 | M69: =M64-M67 -> 173376507 | N69: =N64-N67 -> 7285480 | P69: =P64-P67 -> 0 | Q69: =Q64-Q67 -> 965581 | R69: =M69+N69+O69+P69 -> 180661987

Sheet 年間　全施設（客室単価・稼働率）
A1: 全施設 年間 宿泊実績・売上データ（客室単価・稼働率）
A2: 2026年1月ー12月まで
A3: 施設名 | B3: 販売客室数 | C3: 利用人数 | D3: 客室単価 | E3: 客単価 | F3: 稼働率 | G3: 客室売上 | H3: 総売上 | I3: 備考
A4: デルーネ | B4: =ホテル部門→!N23 -> 5013 | C4: =ホテル部門→!N24 -> 7359 | D4: =ホテル部門→!N25 -> 9487.8021 | E4: =ホテル部門→!N26 -> 6463.1542 | F4: =ホテル部門→!N22 -> 0.26929895 | G4: =ホテル部門→!N18 -> 47562352 | H4: =ホテル部門→!N17 -> 51711522
A5: ビュー | B5: =ホテル部門→!N46 -> 1668 | C5: =ホテル部門→!N47 -> 2314 | D5: =ホテル部門→!N48 -> 9586.3621 | E5: =ホテル部門→!N49 -> 6910.1348 | F5: =ホテル部門→!N45 -> 0.25388128 | G5: =ホテル部門→!N41 -> 15990052 | H5: =ホテル部門→!N40 -> 16024147
A6: 本川 | B6: =ホテル部門→!N63 -> 1071 | C6: =ホテル部門→!N64 -> 1222 | D6: =ホテル部門→!N65 -> 7810.7311 | E6: =ホテル部門→!N66 -> 6845.5753 | F6: =ホテル部門→!N62 -> 0.3260274 | G6: =ホテル部門→!N59 -> 8365293 | H6: =ホテル部門→!N59 -> 8365293
A7: 天神ハウス | B7: =ホテル部門→!N77 -> 30 | C7: =ホテル部門→!N78 -> 141 | D7: =ホテル部門→!N79 -> 76707.633 | E7: =ホテル部門→!N80 -> 16320.773 | F7: =ホテル部門→!N76 -> 0.082191781 | G7: =ホテル部門→!N73 -> 2301229 | H7: =ホテル部門→!N73 -> 2301229
A8: 玖波 | B8: =ホテル部門→!N91 -> 61 | C8: =ホテル部門→!N92 -> 367 | D8: =ホテル部門→!N93 -> 80844.262 | E8: =ホテル部門→!N94 -> 13437.33 | F8: =ホテル部門→!N90 -> 0.33888889 | G8: =ホテル部門→!N87 -> 4931500 | H8: =ホテル部門→!N87 -> 4931500 | I8: 年間180日の稼働設定のため、月あたり15日の稼働となり、他施設と比較して稼働率が高めに算出される。
A9: 弥山 | B9: =弥山!N10 -> 2267 | C9: =弥山!N11 -> 4461 | D9: =弥山!N12 -> 11845.071 | E9: =弥山!N13 -> 6019.4521 | F9: =弥山!N9 -> 2.0141068 | G9: =弥山!N5 -> 26852776 | H9: =弥山!N4 -> 31554666
A10: 温井 | B10: =温井!P4 -> 1847 | C10: =温井!P5 -> 3538 | D10: =温井!P13 -> 56789.617 | E10: =温井!P14 -> 32680.631 | F10: =温井!P10 -> 1.3390429 | G10: =温井!P29 -> 15012501 | H10: =温井!P3 -> 30755817
A11: いこいの村 | B11: =いこいの村!P4 -> 0 | C11: =いこいの村!P5 -> 0 | D11: =いこいの村!P13 -> 0 | E11: =いこいの村!P14 -> 0 | F11: =いこいの村!P10 -> 0 | G11: =いこいの村!P29 -> 0 | H11: =いこいの村!P3 -> 0
A12: 高屋 | B12: =マンスリー部門!N8 -> 786 | C12: =マンスリー部門!N9 -> 786 | D12: =マンスリー部門!N10 -> #DIV/0! | E12: =マンスリー部門!N11 -> #DIV/0! | F12: =マンスリー部門!N7 -> 0.19576588 | G12: =マンスリー部門!N4 -> 2330000 | H12: =マンスリー部門!N4 -> 2330000
A13: 壱番館 | B13: =マンスリー部門!N23 -> 176 | C13: =マンスリー部門!N24 -> 179 | D13: =マンスリー部門!N25 -> #DIV/0! | E13: =マンスリー部門!N26 -> #DIV/0! | F13: =マンスリー部門!N22 -> 0.080365297 | G13: =マンスリー部門!N19 -> 501900 | H13: =マンスリー部門!N19 -> 501900
A14: 弐番館 | B14: =マンスリー部門!N38 -> 139 | C14: =マンスリー部門!N39 -> 139 | D14: =マンスリー部門!N40 -> #DIV/0! | E14: =マンスリー部門!N41 -> #DIV/0! | F14: =マンスリー部門!N37 -> 0.19041096 | G14: =マンスリー部門!N34 -> 403500 | H14: =マンスリー部門!N34 -> 403500
A15: 大竹 | B15: =マンスリー部門!N53 -> 195 | C15: =マンスリー部門!N54 -> 195 | D15: =マンスリー部門!N55 -> 2512.8205 | E15: =マンスリー部門!N56 -> 2512.8205 | F15: =マンスリー部門!N52 -> 0.26712329 | G15: =マンスリー部門!N49 -> 490000 | H15: =マンスリー部門!N49 -> 490000
A16: 竹原 | B16: =マンスリー部門!N68 -> 89 | C16: =マンスリー部門!N69 -> 93 | D16: =マンスリー部門!N70 -> 4573.0337 | E16: =マンスリー部門!N71 -> 4376.3441 | F16: =マンスリー部門!N67 -> 0.12191781 | G16: =マンスリー部門!N64 -> 407000 | H16: =マンスリー部門!N64 -> 407000
A17: サウナ
A18: フォレスト | B18: =フォレストヒルズガーデン!N9 -> 113 | C18: =フォレストヒルズガーデン!N10 -> 397 | D18: =フォレストヒルズガーデン!N11 -> 40666.265 | E18: =フォレストヒルズガーデン!N12 -> 11575.033 | F18: =フォレストヒルズガーデン!N8 -> 0.03869863 | G18: =フォレストヒルズガーデン!N4 -> 4595288 | H18: =フォレストヒルズガーデン!N4 -> 4595288
A19: 総合計 | B19: =SUM(B4:B18) -> 13455 | C19: =SUM(C4:C18) -> 21191 | G19: =SUM(G4:G18) -> 129743391 | H19: =SUM(H4:H18) -> 154371862
A21: 販売客室数 | C21: 利用人数 | E21: 客室売上 | G21: 総売上
A22: =B19 -> 13455 | B22: 室 | C22: =C19 -> 21191 | D22: 名 | E22: =G19 -> 129743391 | F22: 円 | G22: =H19 -> 154371862 | H22: 円

Sheet ホテル部門→
A1: 2026年 グローバルリゾート売上目標及び売上実績 | M1: 46037
A2: 全体 | B2: １月 | C2: ２月 | D2: ３月 | E2: ４月 | F2: ５月 | G2: ６月 | H2: ７月 | I2: ８月 | J2: ９月 | K2: １０月 | L2: １１月 | M2: １２月 | N2: 合計
A3: 目標売上 | B3: =B16+B39+B58+B72+B86 -> 10796694 | C3: =C16+C39+C58+C72+C86 -> 9067219 | D3: =D16+D39+D58+D72+D86 -> 15831767 | E3: =E16+E39+E58+E72+E86 -> 13205981 | F3: =F16+F39+F58+F72+F86 -> 15256604 | G3: =G16+G39+G58+G72+G86 -> 9008685 | H3: =H16+H39+H58+H72+H86 -> 15974001 | I3: =I16+I39+I58+I72+I86 -> 20766504 | ... M3: =M16+M39+M58+M72+M86 -> 10481301 | N3: =SUM(B3:M3) -> 174190007
A4: 売上進捗 | B4: =B17+B40+B59+B73+B87 -> 8908958 | C4: =C17+C40+C59+C73+C87 -> 9792729 | D4: =D17+D40+D59+D73+D87 -> 15185436 | E4: =E17+E40+E59+E73+E87 -> 13558124 | F4: =F17+F40+F59+F73+F87 -> 15383235 | G4: =G17+G40+G59+G73+G87 -> 7732367 | H4: =H17+H40+H59+H73+H87 -> 2409348 | I4: =I17+I40+I59+I73+I87 -> 3256530 | ... M4: =M17+M40+M59+M73+M87 -> 147350 | N4: =SUM(B4:M4) -> 79270462
A5: 達成率 | B5: =B4/B3 -> 0.82515611 | C5: =C4/C3 -> 1.0800146 | D5: =D4/D3 -> 0.95917506 | E5: =E4/E3 -> 1.0266654 | F5: =F4/F3 -> 1.0083001 | G5: =G4/G3 -> 0.85832361 | H5: =H4/H3 -> 0.15082934 | I5: =I4/I3 -> 0.15681648 | ... N5: =N4/N3 -> 0.45508042
A6: 売上目標差異 | B6: =B4-B3 -> -1887736 | C6: =C4-C3 -> 725510 | D6: =D4-D3 -> -646331 | E6: =E4-E3 -> 352143 | F6: =F4-F3 -> 126631 | G6: =G4-G3 -> -1276318 | H6: =H4-H3 -> -13564653 | I6: =I4-I3 -> -17509974 | ... M6: =M4-M3 -> -10333951 | N6: =SUM(B6:M6) -> -94919545
A7: 昨年売上 | B7: =B36+B53+B67+B81+B95 -> 11682489 | C7: =C36+C53+C67+C81+C95 -> 12430189 | D7: =D36+D53+D67+D81+D95 -> 16314013 | E7: =E36+E53+E67+E81+E95 -> 13357025 | F7: =F36+F53+F67+F81+F95 -> 15040357 | G7: =G36+G53+G67+G81+G95 -> 8892648 | H7: =H36+H53+H67+H81+H95 -> 12500189 | I7: =I36+I53+I67+I81+I95 -> 21549998 | ... M7: =M36+M53+M67+M81+M95 -> 11469908 | N7: =SUM(B7:M7) -> 173376507
A8: 昨年対比 | B8: =B4/B7 -> 0.76259075 | C8: =C4/C7 -> 0.78781819 | D8: =D4/D7 -> 0.93082162 | E8: =E4/E7 -> 1.0150557 | F8: =F4/F7 -> 1.0227972 | G8: =G4/G7 -> 0.86952357 | H8: =H4/H7 -> 0.19274493 | I8: =I4/I7 -> 0.1511151 | ... N8: =N4/N7 -> 0.45721571
A9: 経費予測 | B9: 14000000 | C9: 13500000 | D9: 16000000 | E9: 20000000 | F9: 19000000 | G9: 17000000 | H9: 16000000 | I9: 15000000 | J9: 17500000 | K9: 18500000 | L9: 17500000 | M9: 17000000 | N9: =SUM(B9:M9) -> 201000000
A10: 昨年経費 | B10: 10060899 | C10: 12353825 | D10: 14986723 | E10: 11582455 | F10: 13674200 | G10: 9447256 | H10: 11605483 | I10: 20129350 | J10: 13346312 | K10: 14940477 | L10: 10392780 | M10: 3389135 | N10: =SUM(B10:M10) -> 145908895
A11: 経費実績 | N11: =SUM(B11:M11) -> 0
A12: 経費差異 | B12: =B9-B11 -> 14000000 | C12: =C9-C10 -> 1146175 | D12: =D9-D10 -> 1013277 | E12: =E9-E10 -> 8417545 | F12: =F9-F10 -> 5325800 | G12: =G9-G11 -> 17000000 | H12: =H9-H11 -> 16000000 | I12: =I9-I11 -> 15000000 | J12: =J9-J11 -> 17500000 | K12: =K9-K11 -> 18500000 | L12: =L9-L11 -> 17500000 | M12: 18000000 | N12: =SUM(B12:M12) -> 149402797
A13: 差引収支 | B13: =B4-B11 -> 8908958 | C13: =C4-C11 -> 9792729 | D13: =D4-D11 -> 15185436 | E13: =E4-E11 -> 13558124 | F13: =F4-F11 -> 15383235 | G13: =G4-G11 -> 7732367 | H13: =H4-H11 -> 2409348 | I13: =I4-I11 -> 3256530 | ... M13: =M4-M11 -> 147350 | N13: =SUM(B13:M13) -> 79270462
A15: デルーネ | B15: １月 | C15: ２月 | D15: ３月 | E15: ４月 | F15: ５月 | G15: ６月 | H15: ７月 | I15: ８月 | J15: ９月 | K15: １０月 | L15: １１月 | M15: １２月 | N15: 合計
A16: 目標売上 | B16: 7261662 | C16: 5866776 | D16: 10663661 | E16: 8372542 | F16: 10091773 | G16: 6020957 | H16: 10861148 | I16: 13339294 | J16: 8976175 | K16: 12967689 | L16: 13075844 | M16: 6830956 | N16: 114328477 | O16: 2025年売上実績
A17: 売上進捗 | B17: =B18+B27+B19 -> 6712201 | C17: =C18+C27+C19 -> 6486426 | D17: =D18+D27+D19 -> 9961885 | E17: =E18+E27+E19 -> 8310821 | F17: =F18+F27+F19 -> 9884840 | G17: =G18+G27+G19 -> 4996865 | H17: =H18+H27+H19 -> 1386977 | I17: =I18+I27+I19 -> 2069324 | ... M17: =M18+M27+M19 -> 147350 | N17: =SUM(B17:M17) -> 51711522
A18: 客室売上 | B18: 5993256 | C18: 6022901 | D18: 8920925 | E18: 7531181 | F18: 9185215 | G18: 4897710 | H18: 1299802 | I18: 1946074 | J18: 768782 | K18: 709806 | L18: 141000 | M18: 145700 | N18: =SUM(B18:M18) -> 47562352
A19: レジ売上 | B19: 107885 | C19: 17565 | D19: 99520
A20: 達成率 | B20: =B17/B16 -> 0.92433399 | C20: =C17/C16 -> 1.1056202 | D20: =D17/D16 -> 0.93418996 | E20: =E17/E16 -> 0.99262816 | F20: =F17/F16 -> 0.97949488 | G20: =G17/G16 -> 0.82991209 | H20: =H17/H16 -> 0.12770077 | I20: =I17/I16 -> 0.15512995 | ... M20: =M17/M16 -> 0.021570919 | N20: =N18/N16 -> 0.41601492
A21: 差異 | B21: =B17-B16 -> -549461 | C21: =C17-C16 -> 619650 | D21: =D17-D16 -> -701776 | E21: =E17-E16 -> -61721 | F21: =F17-F16 -> -206933 | G21: =G17-G16 -> -1024092 | H21: =H17-H16 -> -9474171 | I21: =I17-I16 -> -11269970 | ... M21: =M17-M16 -> -6683606 | N21: =SUM(B21:M21) -> -62616955
A22: 稼働率 | B22: =B23/(51*31) -> 0.4345351 | C22: =C23/(51*29) -> 0.46923597 | D22: =D23/(51*31) -> 0.59962049 | E22: =E23/(51*30) -> 0.50915033 | F22: =F23/(51*31) -> 0.56862745 | G22: =G23/(51*30) -> 0.35359477 | H22: =H23/(51*31) -> 0.079696395 | I22: =I23/(51*31) -> 0.080328906 | J22: =J23/(51*30) -> 0.046405229 | K22: =K23/(51*31) -> 0.049968374 | L22: =L23/(51*30) -> 0.020261438 | M22: =M23/(51*31) -> 0.019607843 | N22: =N23/(51*365) -> 0.26929895
A23: 販売客室数 | B23: 687 | C23: 694 | D23: 948 | E23: 779 | F23: 899 | G23: 541 | H23: 126 | I23: 127 | J23: 71 | K23: 79 | L23: 31 | M23: 31 | N23: =SUM(B23:M23) -> 5013
A24: 利用人数 | B24: 928 | C24: 911 | D24: 1441 | E24: 1059 | F24: 1355 | G24: 756 | H24: 242 | I24: 341 | J24: 134 | K24: 130 | L24: 31 | M24: 31 | N24: =SUM(B24:M24) -> 7359
A25: 客室単価 | B25: =B18/B23 -> 8723.8079 | C25: =C18/C23 -> 8678.5317 | D25: =D18/D23 -> 9410.2584 | E25: =E18/E23 -> 9667.7548 | F25: =F18/F23 -> 10217.147 | G25: =G18/G23 -> 9053.0684 | H25: =H18/H23 -> 10315.889 | I25: =I18/I23 -> 15323.417 | ... N25: =N18/N23 -> 9487.8021
A26: 客単価 | B26: =B18/B24 -> 6458.25 | C26: =C18/C24 -> 6611.3074 | D26: =D18/D24 -> 6190.7876 | E26: =E18/E24 -> 7111.5968 | F26: =F18/F24 -> 6778.7565 | G26: =G18/G24 -> 6478.4524 | H26: =H18/H24 -> 5371.0826 | I26: =I18/I24 -> 5706.9619 | ... N26: =N18/N24 -> 6463.1542
A27: 飲食売上 | B27: =B28+B31 -> 611060 | C27: =C28+C31 -> 445960 | D27: =D28+D31 -> 941440 | E27: =E28+E31 -> 779640 | F27: =F28+F31 -> 699625 | G27: =G28+G31 -> 99155 | H27: =H28+H31 -> 87175 | I27: =I28+I31 -> 123250 | ... M27: =M28+M31 -> 1650 | N27: =SUM(B27:M27) -> 3924200
A28: 朝食売上 | B28: 395670 | C28: 333630 | D28: 599280 | E28: 450615 | F28: 428670 | G28: 80355 | H28: 58740 | I28: 82830 | J28: 63525 | K28: 51975 | L28: 1650 | M28: 1650 | N28: =SUM(B28:M28) -> 2548590
A29: 朝食数 | B29: 243 | C29: 207 | D29: 380 | E29: 280 | F29: 267 | G29: 49 | H29: 38 | I29: 55 | J29: 40 | K29: 33 | L29: 1 | M29: 1 | N29: =SUM(B29:M29) -> 1594
A30: 利用率 | B30: =B29/B24 -> 0.26185345 | C30: =C29/C24 -> 0.22722283 | D30: =D29/D24 -> 0.26370576 | E30: =E29/E24 -> 0.26440038 | F30: =F29/F24 -> 0.19704797 | G30: =G29/G24 -> 0.064814815 | H30: =H29/H24 -> 0.15702479 | I30: =I29/I24 -> 0.16129032 | ... N30: =N29/N24 -> 0.21660552
A31: 夕食売上 | B31: 215390 | C31: 112330 | D31: 342160 | E31: 329025 | F31: 270955 | G31: 18800 | H31: 28435 | I31: 40420 | J31: 13395 | K31: 4700 | L31: 0 | M31: 0 | N31: =SUM(B31:M31) -> 1375610
A32: 夕食数 | B32: 90 | C32: 49 | D32: 151 | E32: 137 | F32: 118 | G32: 8 | H32: 13 | I32: 19 | J32: 6 | K32: 2 | L32: 0 | M32: 0 | N32: =SUM(B32:M32) -> 593
A33: 利用率 | B33: =B32/B24 -> 0.096982759 | C33: =C32/C24 -> 0.053787047 | D33: =D32/D24 -> 0.10478834 | E33: =E32/E24 -> 0.12936733 | F33: =F32/F24 -> 0.087084871 | G33: =G32/G24 -> 0.010582011 | H33: =H32/H24 -> 0.053719008 | I33: =I32/I24 -> 0.055718475 | ... N33: =N32/N24 -> 0.080581601
A34: 昨年売上 | B34: 7261662 | C34: 5866776 | D34: 10663661 | E34: 8372542 | F34: 10091773 | G34: 6020957 | H34: 10861148 | I34: 13339294 | J34: 8976175 | K34: 12967689 | L34: 13075844 | M34: 6830956 | N34: 114328477
A35: 昨年対比 | B35: =B17/B34 -> 0.92433399 | C35: =C17/C34 -> 1.1056202 | D35: =D17/D34 -> 0.93418996 | E35: =E17/E34 -> 0.99262816 | F35: =F17/F34 -> 0.97949488 | G35: =G17/G34 -> 0.82991209 | H35: =H17/H34 -> 0.12770077 | I35: =I17/I34 -> 0.15512995 | ... M35: =M17/M34 -> 0.021570919 | N35: =N18/N36 -> 0.41587389
A36: 2024年売上 | B36: 8277657 | C36: 9355406 | D36: 11198747 | E36: 8577026 | F36: 9703126 | G36: 6231420 | H36: 7654906 | I36: 13871118 | J36: 8723067 | K36: 11086919 | L36: 11777413 | M36: 7910443 | N36: =SUM(B36:M36) -> 114367248
A38: ビュー | B38: １月 | C38: ２月 | D38: ３月 | E38: ４月 | F38: ５月 | G38: ６月 | H38: ７月 | I38: ８月 | J38: ９月 | K38: １０月 | L38: １１月 | M38: １２月 | N38: 合計
A39: 目標売上 | B39: 2143056 | C39: 1559909 | D39: 2743253 | E39: 2602903 | F39: 2606733 | G39: 1341712 | H39: 3302659 | I39: 4469894 | J39: 2740428 | K39: 3669167 | L39: 3942044 | M39: 1966245 | N39: 33088003 | O39: 2025年売上実績
A40: 売上進捗 | B40: =B41+B50+B42 -> 1319475 | C40: =C41+C50+C42 -> 1757661 | D40: =D41+D50+D42 -> 2882218 | E40: =E41+E50+E42 -> 2904045 | F40: =F41+F50+F42 -> 3017659 | G40: =G41+G50+G42 -> 2196076 | H40: =H41+H50+H42 -> 492989 | I40: =I41+I50+I42 -> 716260 | ... M40: =M41+M50+M42 -> 0 | N40: =SUM(B40:M40) -> 16024147
A41: 客室売上 | B41: 1313280 | C41: 1749061 | D41: 2862918 | E41: 2904045 | F41: 3017659 | G41: 2196076 | H41: 492989 | I41: 716260 | J41: 540084 | K41: 197680 | L41: 0 | M41: 0 | N41: =SUM(B41:M41) -> 15990052
A42: レジ売上 | B42: 6195 | C42: 8600 | D42: 19300
A43: 達成率 | B43: =B40/B39 -> 0.61569786 | C43: =C40/C39 -> 1.1267715 | D43: =D40/D39 -> 1.050657 | E43: =E40/E39 -> 1.1156947 | F43: =F40/F39 -> 1.1576402 | G43: =G40/G39 -> 1.6367715 | H43: =H40/H39 -> 0.14927033 | I43: =I40/I39 -> 0.16024094 | ... M43: =M40/M39 -> 0 | N43: =N41/N39 -> 0.4832583
A44: 差異 | B44: =B40-B39 -> -823581 | C44: =C40-C39 -> 197752 | D44: =D40-D39 -> 138965 | E44: =E40-E39 -> 301142 | F44: =F40-F39 -> 410926 | G44: =G40-G39 -> 854364 | H44: =H40-H39 -> -2809670 | I44: =I40-I39 -> -3753634 | ... M44: =M40-M39 -> -1966245 | N44: =SUM(B44:M44) -> -17063856
A45: 稼働率 | B45: =B46/(18*31) -> 0.29390681 | C45: =C46/(18*29) -> 0.40996169 | D45: =D46/(18*31) -> 0.53405018 | E45: =E46/(18*30) -> 0.61851852 | F45: =F46/(18*31) -> 0.47670251 | G45: =G46/(18*30) -> 0.3537037 | H45: =H46/(18*31) -> 0.080645161 | I45: =I46/(18*31) -> 0.096774194 | J45: =J46/(18*30) -> 0.15185185 | K45: =K46/(18*31) -> 0.035842294 | L45: =L46/(18*30) -> 0 | M45: =M46/(18*31) -> 0 | N45: =N46/(18*365) -> 0.25388128
A46: 販売客室数 | B46: 164 | C46: 214 | D46: 298 | E46: 334 | F46: 266 | G46: 191 | H46: 45 | I46: 54 | J46: 82 | K46: 20 | L46: 0 | M46: 0 | N46: =SUM(B46:M46) -> 1668
A47: 利用人数 | B47: 183 | C47: 267 | D47: 446 | E47: 436 | F47: 365 | G47: 305 | H47: 78 | I47: 109 | J47: 96 | K47: 29 | L47: 0 | M47: 0 | N47: =SUM(B47:M47) -> 2314
A48: 客室単価 | B48: =B41/B46 -> 8007.8049 | C48: =C41/C46 -> 8173.1822 | D48: =D41/D46 -> 9607.1074 | E48: =E41/E46 -> 8694.7455 | F48: =F41/F46 -> 11344.583 | G48: =G41/G46 -> 11497.78 | H48: =H41/H46 -> 10955.311 | I48: =I41/I46 -> 13264.074 | ... N48: =N41/N46 -> 9586.3621
A49: 客単価 | B49: =B41/B47 -> 7176.3934 | C49: =C41/C47 -> 6550.7903 | D49: =D41/D47 -> 6419.0987 | E49: =E41/E47 -> 6660.6537 | F49: =F41/F47 -> 8267.5589 | G49: =G41/G47 -> 7200.2492 | H49: =H41/H47 -> 6320.3718 | I49: =I41/I47 -> 6571.1927 | ... N49: =N41/N47 -> 6910.1348
A50: 飲食売上 | B50: 0 | C50: 0 | D50: 0 | E50: 0 | F50: 0 | G50: 0 | H50: 0 | I50: 0 | J50: 0 | K50: 0 | L50: 0 | M50: 0 | N50: =SUM(B50:M50) -> 0
A51: 朝食数 | N51: =SUM(B51:M51) -> 0
A52: 利用率 | B52: =B51/B47 -> 0 | C52: =C51/C47 -> 0 | D52: =D51/D47 -> 0 | E52: =E51/E47 -> 0 | F52: =F51/F47 -> 0 | G52: =G51/G47 -> 0 | H52: =H51/H47 -> 0 | I52: =I51/I47 -> 0 | ... N52: =N51/N47 -> 0
A53: 昨年売上 | B53: 2143056 | C53: 1559909 | D53: 2743253 | E53: 2602903 | F53: 2606733 | G53: 1341712 | H53: 3302659 | I53: 4469894 | J53: 2740428 | K53: 3669167 | L53: 3942044 | M53: 1966245 | N53: 33088003
A54: 昨年対比 | B54: =B40/B53 -> 0.61569786 | C54: =C40/C53 -> 1.1267715 | D54: =D40/D53 -> 1.050657 | E54: =E40/E53 -> 1.1156947 | F54: =F40/F53 -> 1.1576402 | G54: =G40/G53 -> 1.6367715 | H54: =H40/H53 -> 0.14927033 | I54: =I40/I53 -> 0.16024094 | ... M54: =M40/M53 -> 0 | N54: =N41/N53 -> 0.4832583
A55: 2024年売上 | B55: 1306334 | C55: 2345950 | D55: 2763223 | E55: 2407998 | F55: 2876426 | G55: 1913642 | H55: 2389268 | I55: 4166729 | J55: 2562088 | K55: 2967375 | L55: 3608455 | M55: 2458358 | N55: =SUM(B55:M55) -> 31765846
A57: 本川 | B57: １月 | C57: ２月 | D57: ３月 | E57: ４月 | F57: ５月 | G57: ６月 | H57: ７月 | I57: ８月 | J57: ９月 | K57: １０月 | L57: １１月 | M57: １２月 | N57: 合計
A58: 目標売上 | B58: 901976 | C58: 970534 | D58: 1394853 | E58: 1600536 | F58: 2028098 | G58: 1051016 | H58: 1110194 | I58: 2097316 | J58: 1566778 | K58: 2477290 | L58: 2350836 | M58: 1139100 | N58: 18688527 | O58: 2025年売上実績
A59: 売上進捗 | B59: 638232 | C59: 1033872 | D59: 1357093 | E59: 1955058 | F59: 1887446 | G59: 276276 | H59: 417182 | I59: 435946 | J59: 128032 | K59: 236156 | L59: 0 | M59: 0 | N59: =SUM(B59:M59) -> 8365293
A60: 達成率 | B60: =B59/B58 -> 0.70759311 | C60: =C59/C58 -> 1.065261 | D60: =D59/D58 -> 0.97292905 | E60: =E59/E58 -> 1.221502 | F60: =F59/F58 -> 0.93064832 | G60: =G59/G58 -> 0.26286565 | H60: =H59/H58 -> 0.37577396 | I60: =I59/I58 -> 0.207859 | ... N60: =N59/N58 -> 0.4476165
A61: 差異 | B61: =B59-B58 -> -263744 | C61: =C59-C58 -> 63338 | D61: =D59-D58 -> -37760 | E61: =E59-E58 -> 354522 | F61: =F59-F58 -> -140652 | G61: =G59-G58 -> -774740 | H61: =H59-H58 -> -693012 | I61: =I59-I58 -> -1661370 | ... M61: =M59-M58 -> -1139100 | N61: =SUM(B61:M61) -> -10323234
A62: 稼働率 | B62: =B63/(9*31) -> 0.39784946 | C62: =C63/(9*29) -> 0.61685824 | D62: =D63/(9*31) -> 0.69892473 | E62: =E63/(9*30) -> 0.85925926 | F62: =F63/(9*31) -> 0.83512545 | G62: =G63/(9*30) -> 0.14074074 | H62: =H63/(9*31) -> 0.13261649 | I62: =I63/(9*31) -> 0.12544803 | J62: =J63/(9*30) -> 0.040740741 | K62: =K63/(9*31) -> 0.064516129 | L62: =L63/(9*30) -> 0 | M62: =M63/(9*31) -> 0 | N62: =N63/(9*365) -> 0.3260274
A63: 販売客室数 | B63: 111 | C63: 161 | D63: 195 | E63: 232 | F63: 233 | G63: 38 | H63: 37 | I63: 35 | J63: 11 | K63: 18 | N63: =SUM(B63:M63) -> 1071
A64: 利用人数 | B64: 123 | C64: 184 | D64: 229 | E64: 263 | F64: 264 | G64: 38 | H64: 46 | I64: 38 | J64: 12 | K64: 25 | N64: =SUM(B64:M64) -> 1222
A65: 客室単価 | B65: =B59/B63 -> 5749.8378 | C65: =C59/C63 -> 6421.5652 | D65: =D59/D63 -> 6959.4513 | E65: =E59/E63 -> 8426.9741 | F65: =F59/F63 -> 8100.6266 | G65: =G59/G63 -> 7270.4211 | H65: =H59/H63 -> 11275.189 | I65: =I59/I63 -> 12455.6 | ... N65: =N59/N63 -> 7810.7311
A66: 客単価 | B66: =B59/B64 -> 5188.878 | C66: =C59/C64 -> 5618.8696 | D66: =D59/D64 -> 5926.1703 | E66: =E59/E64 -> 7433.6806 | F66: =F59/F64 -> 7149.4167 | G66: =G59/G64 -> 7270.4211 | H66: =H59/H64 -> 9069.1739 | I66: =I59/I64 -> 11472.263 | ... N66: =N59/N64 -> 6845.5753
A67: 昨年売上 | B67: 901976 | C67: 970534 | D67: 1394853 | E67: 1600536 | F67: 2028098 | G67: 1051016 | H67: 1110194 | I67: 2097316 | J67: 1566778 | K67: 2477290 | L67: 2350836 | M67: 1139100 | N67: 18688527
A68: 昨年対比 | B68: =B59/B67 -> 0.70759311 | C68: =C59/C67 -> 1.065261 | D68: =D59/D67 -> 0.97292905 | E68: =E59/E67 -> 1.221502 | F68: =F59/F67 -> 0.93064832 | G68: =G59/G67 -> 0.26286565 | H68: =H59/H67 -> 0.37577396 | I68: =I59/I67 -> 0.207859 | ... N68: =N59/N67 -> 0.4476165
A69: 2024年売上 | B69: 0 | C69: 0 | D69: 0 | E69: 0 | F69: 571440 | G69: 710786 | H69: 876554 | I69: 1231315 | J69: 1437292 | K69: 1882390 | L69: 2086663 | M69: 1326852 | N69: =SUM(B69:M69) -> 10123292
A71: 天神ハウス | B71: １月 | C71: ２月 | D71: ３月 | E71: ４月 | F71: ５月 | G71: ６月 | H71: ７月 | I71: ８月 | J71: ９月 | K71: １０月 | L71: １１月 | M71: １２月 | N71: 合計
A72: 目標売上 | B72: 210000 | C72: 320000 | D72: 320000 | E72: 280000 | F72: 250000 | G72: 250000 | H72: 240000 | I72: 290000 | J72: 180000 | K72: 210000 | L72: 150000 | M72: 150000 | N72: =SUM(B72:M72) -> 2850000 | O72: 2025年売上実績
A73: 売上進捗 | B73: 100300 | C73: 108270 | D73: 189640 | E73: 56700 | F73: 289480 | G73: 72400 | H73: 16200 | I73: 0 | J73: 0 | K73: 0 | L73: 0 | M73: 0 | N73: 2301229
A74: 達成率 | B74: =B73/B72 -> 0.47761905 | C74: =C73/C72 -> 0.33834375 | D74: =D73/D72 -> 0.592625 | E74: =E73/E72 -> 0.2025 | F74: =F73/F72 -> 1.15792 | G74: =G73/G72 -> 0.2896 | H74: =H73/H72 -> 0.0675 | I74: =I73/I72 -> 0 | ... N74: =N73/N72 -> 0.80744877
A75: 差異 | B75: =B73-B72 -> -109700 | C75: =C73-C72 -> -211730 | D75: =D73-D72 -> -130360 | E75: =E73-E72 -> -223300 | F75: =F73-F72 -> 39480 | G75: =G73-G72 -> -177600 | H75: =H73-H72 -> -223800 | I75: =I73-I72 -> -290000 | ... M75: =M73-M72 -> -150000 | N75: =SUM(B75:M75) -> -2017010
A76: 稼働率 | B76: =B77/(1*29) -> 0.13793103 | C76: =C77/(1*29) -> 0.17241379 | D76: =D77/(1*31) -> 0.096774194 | E76: =E77/(1*30) -> 0.066666667 | F76: =F77/(1*31) -> 0.35483871 | G76: =G77/(1*30) -> 0.13333333 | H76: =H77/(1*31) -> 0.032258065 | I76: =I77/(1*31) -> 0 | J76: =J77/(1*30) -> 0 | K76: =K77/(1*31) -> 0 | L76: =L77/(1*30) -> 0 | M76: =M77/(1*31) -> 0 | N76: =N77/(1*365) -> 0.082191781
A77: 販売客室数 | B77: 4 | C77: 5 | D77: 3 | E77: 2 | F77: 11 | G77: 4 | H77: 1 | N77: =SUM(B77:M77) -> 30
A78: 利用人数 | B78: 18 | C78: 22 | D78: 33 | E78: 8 | F78: 40 | G78: 16 | H78: 4 | N78: =SUM(B78:M78) -> 141
A79: 客室単価 | B79: =B73/B77 -> 25075 | C79: =C73/C77 -> 21654 | D79: =D73/D77 -> 63213.333 | E79: =E73/E77 -> 28350 | F79: =F73/F77 -> 26316.364 | G79: =G73/G77 -> 18100 | H79: =H73/H77 -> 16200 | I79: =I73/I77 -> #DIV/0! | ... N79: =N73/N77 -> 76707.633
A80: 客単価 | B80: =B73/B78 -> 5572.2222 | C80: =C73/C78 -> 4921.3636 | D80: =D73/D78 -> 5746.6667 | E80: =E73/E78 -> 7087.5 | F80: =F73/F78 -> 7237 | G80: =G73/G78 -> 4525 | H80: =H73/H78 -> 4050 | I80: =I73/I78 -> #DIV/0! | ... N80: =N73/N78 -> 16320.773
A81: 昨年売上 | B81: 32400 | C81: 174440 | D81: 247060 | E81: 115860 | F81: 270500 | G81: 85200 | H81: 214180 | I81: 318420 | J81: 53469 | K81: 261170 | L81: 349410 | M81: 179120 | N81: 2301229
A82: 昨年対比 | B82: =B73/B81 -> 3.095679 | C82: =C73/C81 -> 0.62067186 | D82: =D73/D81 -> 0.76758682 | E82: =E73/E81 -> 0.48938374 | F82: =F73/F81 -> 1.0701664 | G82: =G73/G81 -> 0.84976526 | H82: =H73/H81 -> 0.075637314 | I82: =I73/I81 -> 0 | ... N82: =N73/N81 -> 1
A83: 2024年売上 | B83: 216000 | C83: 318740 | D83: 317100 | E83: 276880 | F83: 251435 | G83: 251435 | H83: 233230 | I83: 289860 | J83: 185030 | K83: 213110 | L83: 146920 | M83: 206190 | N83: =SUM(B83:M83) -> 2905930
A85: 玖波 | B85: １月 | C85: ２月 | D85: ３月 | E85: ４月 | F85: ５月 | G85: ６月 | H85: ７月 | I85: ８月 | J85: ９月 | K85: １０月 | L85: １１月 | M85: １２月 | N85: 合計
A86: 目標売上 | B86: 280000 | C86: 350000 | D86: 710000 | E86: 350000 | F86: 280000 | G86: 345000 | H86: 460000 | I86: 570000 | J86: 450000 | K86: 345000 | L86: 700000 | M86: 395000 | N86: =SUM(B86:M86) -> 5235000 | O86: 2025年売上実績
A87: 売上進捗 | B87: 138750 | C87: 406500 | D87: 794600 | E87: 331500 | F87: 303810 | G87: 190750 | H87: 96000 | I87: 35000 | J87: 39600 | K87: 0 | L87: 0 | M87: 0 | N87: 4931500
A88: 達成率 | B88: =B87/B86 -> 0.49553571 | C88: =C87/C86 -> 1.1614286 | D88: =D87/D86 -> 1.1191549 | E88: =E87/E86 -> 0.94714286 | F88: =F87/F86 -> 1.0850357 | G88: =G87/G86 -> 0.55289855 | H88: =H87/H86 -> 0.20869565 | I88: =I87/I86 -> 0.061403509 | ... N88: =N87/N86 -> 0.94202483
A89: 差異 | B89: =B87-B86 -> -141250 | C89: =C87-C86 -> 56500 | D89: =D87-D86 -> 84600 | E89: =E87-E86 -> -18500 | F89: =F87-F86 -> 23810 | G89: =G87-G86 -> -154250 | H89: =H87-H86 -> -364000 | I89: =I87-I86 -> -535000 | ... M89: =M87-M86 -> -395000 | N89: =SUM(B89:M89) -> -2898490
A90: 稼働率 | B90: =B91/(1*15) -> 0.2 | C90: =C91/(1*15) -> 0.73333333 | D90: =D91/(1*15) -> 1.4666667 | E90: =E91/(1*15) -> 0.6 | F90: =F91/(1*15) -> 0.46666667 | G90: =G91/(1*15) -> 0.33333333 | H90: =H91/(1*15) -> 0.13333333 | I90: =I91/(1*15) -> 0.066666667 | ... M90: =M91/(1*15) -> 0 | N90: =N91/(1*180) -> 0.33888889
A91: 販売客室数 | B91: 3 | C91: 11 | D91: 22 | E91: 9 | F91: 7 | G91: 5 | H91: 2 | I91: 1 | J91: 1 | N91: =SUM(B91:M91) -> 61
A92: 利用人数 | B92: 20 | C92: 63 | D92: 135 | E92: 46 | F92: 41 | G92: 39 | H92: 12 | I92: 5 | J92: 6 | N92: =SUM(B92:M92) -> 367
A93: 客室単価 | B93: =B87/B91 -> 46250 | C93: =C87/C91 -> 36954.545 | D93: =D87/D91 -> 36118.182 | E93: =E87/E91 -> 36833.333 | F93: =F87/F91 -> 43401.429 | G93: =G87/G91 -> 38150 | H93: =H87/H91 -> 48000 | I93: =I87/I91 -> 35000 | ... N93: =N87/N91 -> 80844.262
A94: 客単価 | B94: =B87/B92 -> 6937.5 | C94: =C87/C92 -> 6452.381 | D94: =D87/D92 -> 5885.9259 | E94: =E87/E92 -> 7206.5217 | F94: =F87/F92 -> 7410 | G94: =G87/G92 -> 4891.0256 | H94: =H87/H92 -> 8000 | I94: =I87/I92 -> 7000 | ... N94: =N87/N92 -> 13437.33
A95: 昨年売上 | B95: 327400 | C95: 369900 | D95: 730100 | E95: 460700 | F95: 431900 | G95: 183300 | H95: 218250 | I95: 793250 | J95: 246500 | K95: 418500 | L95: 476700 | M95: 275000 | N95: 4931500
A96: 昨年対比 | B96: =B87/B95 -> 0.42379352 | C96: =C87/C95 -> 1.0989457 | D96: =D87/D95 -> 1.0883441 | E96: =E87/E95 -> 0.7195572 | F96: =F87/F95 -> 0.70342672 | G96: =G87/G95 -> 1.0406438 | H96: =H87/H95 -> 0.43986254 | I96: =I87/I95 -> 0.044122282 | ... N96: =N87/N95 -> 1
A97: 2024年売上 | B97: 260908 | C97: 333729 | D97: 707653 | E97: 320551 | F97: 271773 | G97: 339973 | H97: 451525 | I97: 570328 | J97: 438835 | K97: 332323 | L97: 576702 | M97: 416350 | N97: =SUM(B97:M97) -> 5020650

Sheet 弥山
A1: 2026年 弥山 売上目標及び売上実績
A2: 弥山全体 | B2: １月 | C2: ２月 | D2: ３月 | E2: ４月 | F2: ５月 | G2: ６月 | H2: ７月 | I2: ８月 | J2: ９月 | K2: １０月 | L2: １１月 | M2: １２月 | N2: 合計
A3: 目標売上 | B3: 3701096 | C3: 2980174 | D3: 5584201 | E3: 5487259 | F3: 6761527 | G3: 3942572 | H3: 5866719 | I3: 9564791 | J3: 5465630 | K3: 8958395 | L3: 8362200 | M3: 5672113 | N3: 72346677 | O3: 2025年売上実績
A4: 売上進捗 | B4: =B5+B14+B6 -> 2906901 | C4: =C5+C14+C6 -> 4965898 | D4: =D5+D14+D6 -> 6807485 | E4: =E5+E14+E6 -> 4004248 | F4: =F5+F14+F6 -> 6175495 | G4: =G5+G14+G6 -> 2105073 | H4: =H5+H14+H6 -> 1056902 | I4: =I5+I14+I6 -> 1697508 | ... M4: =M5+M14+M6 -> 20000 | N4: =SUM(B4:M4) -> 31554666
A5: 客室売上 | B5: 2493516 | C5: 4182983 | D5: 5251225 | E5: 3713533 | F5: 5433020 | G5: 1772568 | H5: 998427 | I5: 1575613 | J5: 686771 | K5: 562660 | L5: 170460 | M5: 12000 | N5: =SUM(B5:M5) -> 26852776
A6: レジ売上 | B6: 138235 | C6: 187870 | D6: 685450
A7: 達成率 | B7: =B4/B3 -> 0.78541627 | C7: =C4/C3 -> 1.6663114 | D7: =D4/D3 -> 1.2190616 | E7: =E4/E3 -> 0.72973556 | F7: =F4/F3 -> 0.91332845 | G7: =G4/G3 -> 0.53393394 | H7: =H4/H3 -> 0.18015214 | I7: =I4/I3 -> 0.17747466 | ... N7: =N4/N3 -> 0.43615916
A8: 売上目標差異 | B8: =B4-B3 -> -794195 | C8: =C4-C3 -> 1985724 | D8: =D4-D3 -> 1223284 | E8: =E4-E3 -> -1483011 | F8: =F4-F3 -> -586032 | G8: =G4-G3 -> -1837499 | H8: =H4-H3 -> -4809817 | I8: =I4-I3 -> -7867283 | ... M8: =M4-M3 -> -5652113 | N8: =SUM(B8:M8) -> -40792011
A9: 稼働率 | B9: =B10/(37*31) -> 0.2048823 | C9: =C10/(37*29) -> 0.3028891 | D9: =D10/(37*31) -> 0.37053182 | E9: =E10/(37*30) -> 0.30540541 | F9: =F10/(37*31) -> 0.3722755 | G9: =G10/(37*30) -> 0.18018018 | H9: =H10/(37*31) -> 0.060156931 | I9: =I10/(37*31) -> 0.080209241 | J9: =J10/(37*30) -> 0.05045045 | K9: =K10/(37*31) -> 0.060156931 | L9: =L10/(37*30) -> 0.025225225 | M9: =M10/(37*31) -> 0.0017436792 | N9: =SUM(B9:M9) -> 2.0141068
A10: 販売客室数 | B10: 235 | C10: 325 | D10: 425 | E10: 339 | F10: 427 | G10: 200 | H10: 69 | I10: 92 | J10: 56 | K10: 69 | L10: 28 | M10: 2 | N10: =SUM(B10:M10) -> 2267
A11: 利用人数 | B11: 403 | C11: 762 | D11: 911 | E11: 532 | F11: 753 | G11: 356 | H11: 188 | I11: 302 | J11: 122 | K11: 93 | L11: 37 | M11: 2 | N11: =SUM(B11:M11) -> 4461
A12: 客室単価 | B12: =B5/B10 -> 10610.706 | C12: =C5/C10 -> 12870.717 | D12: =D5/D10 -> 12355.824 | E12: =E5/E10 -> 10954.375 | F12: =F5/F10 -> 12723.7 | G12: =G5/G10 -> 8862.84 | H12: =H5/H10 -> 14469.957 | I12: =I5/I10 -> 17126.228 | ... N12: =N5/N10 -> 11845.071
A13: 客単価 | B13: =B5/B11 -> 6187.3846 | C13: =C5/C11 -> 5489.479 | D13: =D5/D11 -> 5764.2426 | E13: =E5/E11 -> 6980.3252 | F13: =F5/F11 -> 7215.166 | G13: =G5/G11 -> 4979.1236 | H13: =H5/H11 -> 5310.7819 | I13: =I5/I11 -> 5217.2616 | ... N13: =N5/N11 -> 6019.4521
A14: 飲食売上 | B14: =B15+B18 -> 275150 | C14: =C15+C18 -> 595045 | D14: =D15+D18 -> 870810 | E14: =E15+E18 -> 290715 | F14: =F15+F18 -> 742475 | G14: =G15+G18 -> 332505 | H14: =H15+H18 -> 58475 | I14: =I15+I18 -> 121895 | ... N14: =N15+N18 -> 3690335
A15: 朝食売上 | B15: 129030 | C15: 272740 | D15: 465795 | E15: 200475 | F15: 408540 | G15: 156255 | H15: 41085 | I15: 54450 | J15: 51810 | K15: 90255 | L15: 34650 | M15: 3300 | N15: =SUM(B15:M15) -> 1908385
A16: 朝食数 | B16: 80 | C16: 192 | D16: 295 | E16: 123 | F16: 253 | G16: 95 | H16: 27 | I16: 36 | J16: 32 | K16: 55 | L16: 21 | M16: 2 | N16: =SUM(B16:M16) -> 1211
A17: 利用率 | B17: =B16/B11 -> 0.19851117 | C17: =C16/C11 -> 0.2519685 | D17: =D16/D11 -> 0.32381998 | E17: =E16/E11 -> 0.23120301 | F17: =F16/F11 -> 0.33598938 | G17: =G16/G11 -> 0.26685393 | H17: =H16/H11 -> 0.14361702 | I17: =I16/I11 -> 0.1192053 | ... M17: =M16/M11 -> 1
A18: 夕食売上 | B18: 146120 | C18: 322305 | D18: 405015 | E18: 90240 | F18: 333935 | G18: 176250 | H18: 17390 | I18: 67445 | J18: 58750 | K18: 117500 | L18: 42300 | M18: 4700 | N18: =SUM(B18:M18) -> 1781950
A19: 夕食数 | B19: 50 | C19: 134 | D19: 178 | E19: 39 | F19: 146 | G19: 75 | H19: 8 | I19: 32 | J19: 25 | K19: 50 | L19: 18 | M19: 2 | N19: =SUM(B19:M19) -> 757
A20: 利用率 | B20: =B19/B11 -> 0.12406948 | C20: =C19/C11 -> 0.17585302 | D20: =D19/D11 -> 0.19538968 | E20: =E19/E11 -> 0.073308271 | F20: =F19/F11 -> 0.1938911 | G20: =G19/G11 -> 0.21067416 | H20: =H19/H11 -> 0.042553191 | I20: =I19/I11 -> 0.10596026 | ... M20: =M19/M11 -> 1
A21: 経費予測 | B21: 14000000 | C21: 13500000 | D21: 16000000 | E21: 20000000 | F21: 19000000 | G21: 17000000 | H21: 16000000 | I21: 15000000 | J21: 17500000 | K21: 18500000 | L21: 17500000 | M21: 17000000 | N21: =SUM(B21:M21) -> 201000000
A22: 昨年経費 | O22: ←未入力
A23: 経費実績 | N23: =SUM(B23:M23) -> 0
A24: 経費差異 | B24: =B21-B23 -> 14000000 | C24: =C21-C22 -> 13500000 | D24: =D21-D22 -> 16000000 | E24: =E21-E22 -> 20000000 | F24: =F21-F22 -> 19000000 | G24: =G21-G23 -> 17000000 | H24: =H21-H23 -> 16000000 | I24: =I21-I23 -> 15000000 | J24: =J21-J23 -> 17500000 | K24: =K21-K23 -> 18500000 | L24: =L21-L23 -> 17500000 | M24: 18000000 | N24: =SUM(B24:M24) -> 202000000
A25: 差引収支 | B25: =B5-B23 -> 2493516 | C25: =C5-C22 -> 4182983 | D25: =D5-D22 -> 5251225 | E25: =E5-E22 -> 3713533 | F25: =F5-F22 -> 5433020 | G25: =G5-G21 -> -15227432 | H25: =H5-H21 -> -15001573 | I25: =I5-I21 -> -13424387 | J25: =J5-J21 -> -16813229 | K25: =K5-K21 -> -17937340 | L25: =L5-L21 -> -17329540 | M25: =M5-M21 -> -16988000 | N25: =SUM(B25:M25) -> -91647224
A26: 昨年売上 | B26: 3701096 | C26: 2980174 | D26: 5584201 | E26: 5487259 | F26: 6761527 | G26: 3942572 | H26: 5866719 | I26: 9564791 | J26: 5465630 | K26: 8958395 | L26: 8362200 | M26: 5672113 | N26: 72346677
A27: 昨年対比 | B27: =B4/B26 -> 0.78541627 | C27: =C4/C26 -> 1.6663114 | D27: =D4/D26 -> 1.2190616 | E27: =E4/E26 -> 0.72973556 | F27: =F4/F26 -> 0.91332845 | G27: =G4/G26 -> 0.53393394 | H27: =H4/H26 -> 0.18015214 | I27: =I4/I26 -> 0.17747466 | ... M27: =M4/M26 -> 0.0035260228 | N27: =N5/N26 -> 0.37116806
A28: 2024年売上 | B28: 5019767 | C28: 5564351 | D28: 8310430 | E28: 4790923 | F28: 6533622 | G28: 4389116 | H28: 4605120 | I28: 9240258 | J28: 6569181 | K28: 7721028 | L28: 8280505 | M28: 5169972 | N28: =SUM(B28:M28) -> 76194273 | O28: OK
A29: 未販売
A30: 別館1004 | B30: １月 | C30: ２月 | D30: ３月 | E30: ４月 | F30: ５月 | G30: ６月 | H30: ７月 | I30: ８月 | J30: ９月 | K30: １０月 | L30: １１月 | M30: １２月 | N30: 合計
A31: 目標売上 | B31: 50000 | C31: 150000 | D31: 200000 | E31: 210000 | F31: 190000 | G31: 90000 | H31: 90000 | I31: 250000 | J31: 90000 | K31: 130000 | L31: 200000 | M31: 50000 | N31: =SUM(B31:M31) -> 1700000
A32: 売上進捗 | B32: 60000 | C32: 0 | D32: 0 | N32: =SUM(B32:M32) -> 60000
A33: 達成率 | B33: =B32/B31 -> 1.2 | C33: =C32/C31 -> 0 | D33: =D32/D31 -> 0 | E33: =E32/E31 -> 0 | F33: =F32/F31 -> 0 | G33: =G32/G31 -> 0 | H33: =H32/H31 -> 0 | I33: =I32/I31 -> 0 | ... N33: =N32/N31 -> 0.035294118
A34: 差異 | B34: =B32-B31 -> 10000 | C34: =C32-C31 -> -150000 | D34: =D32-D31 -> -200000 | E34: =E32-E31 -> -210000 | F34: =F32-F31 -> -190000 | G34: =G32-G31 -> -90000 | H34: =H32-H31 -> -90000 | I34: =I32-I31 -> -250000 | ... M34: =M32-M31 -> -50000 | N34: =SUM(B34:M34) -> -1640000
A35: 稼働率 | B35: =B36/(1*31) -> 0.032258065 | C35: =C36/(1*29) -> 0 | D35: =D36/(1*31) -> 0 | E35: =E36/(1*30) -> 0 | F35: =F36/(1*31) -> 0 | G35: =G36/(1*30) -> 0 | H35: =H36/(1*31) -> 0 | I35: =I36/(1*31) -> 0 | J35: =J36/(1*30) -> 0 | K35: =K36/(1*31) -> 0 | L35: =L36/(1*30) -> 0 | M35: =M36/(1*31) -> 0
A36: 販売客室数 | B36: 1 | C36: 0 | D36: 0 | N36: =SUM(B36:M36) -> 1
A37: 利用人数 | B37: 3 | C37: 0 | D37: 0 | N37: =SUM(B37:M37) -> 3
A38: 客室単価 | B38: =B32/B36 -> 60000 | C38: =C32/C36 -> #DIV/0! | D38: =D32/D36 -> #DIV/0! | E38: =E32/E36 -> #DIV/0! | F38: =F32/F36 -> #DIV/0! | G38: =G32/G36 -> #DIV/0! | H38: =H32/H36 -> #DIV/0! | I38: =I32/I36 -> #DIV/0! | ... N38: =N32/N36 -> 60000
A39: 客単価 | B39: =B32/B37 -> 20000 | C39: =C32/C37 -> #DIV/0! | D39: =D32/D37 -> #DIV/0! | E39: =E32/E37 -> #DIV/0! | F39: =F32/F37 -> #DIV/0! | G39: =G32/G37 -> #DIV/0! | H39: =H32/H37 -> #DIV/0! | I39: =I32/I37 -> #DIV/0! | ... N39: =N32/N37 -> 20000
A40: 昨年売上 | B40: 49071 | C40: 137999 | D40: 200400 | E40: 205579 | F40: 187337 | G40: 81410 | H40: 89625 | I40: 237984 | J40: 89828 | K40: 129196 | L40: 189315 | M40: 135230 | N40: =SUM(B40:M40) -> 1732974
A41: 昨年対比 | B41: =B32/B40 -> 1.2227181 | C41: =C32/C40 -> 0 | D41: =D32/D40 -> 0 | E41: =E32/E40 -> 0 | F41: =F32/F40 -> 0 | G41: =G32/G40 -> 0 | H41: =H32/H40 -> 0 | I41: =I32/I40 -> 0 | ... N41: =N32/N40 -> 0.034622562
A43: マンスリー利用中
A44: 別館903 | B44: １月 | C44: ２月 | D44: ３月 | E44: ４月 | F44: ５月 | G44: ６月 | H44: ７月 | I44: ８月 | J44: ９月 | K44: １０月 | L44: １１月 | M44: １２月 | N44: 合計
A45: 目標売上 | B45: 50000 | C45: 130000 | D45: 200000 | E45: 150000 | F45: 150000 | G45: 100000 | H45: 150000 | I45: 200000 | J45: 150000 | K45: 130000 | L45: 200000 | M45: 150000 | N45: =SUM(B45:M45) -> 1760000
A46: 売上進捗 | B46: 104000 | C46: 104000 | D46: 104000 | E46: 104000 | F46: 4000 | G46: 4000 | H46: 4000 | I46: 4000 | J46: 4000 | K46: 4000 | L46: 4000 | M46: 4000 | N46: =SUM(B46:M46) -> 448000
A47: 達成率 | B47: =B46/B45 -> 2.08 | C47: =C46/C45 -> 0.8 | D47: =D46/D45 -> 0.52 | E47: =E46/E45 -> 0.69333333 | F47: =F46/F45 -> 0.026666667 | G47: =G46/G45 -> 0.04 | H47: =H46/H45 -> 0.026666667 | I47: =I46/I45 -> 0.02 | ... N47: =N46/N45 -> 0.25454545
A48: 差異 | B48: =B46-B45 -> 54000 | C48: =C46-C45 -> -26000 | D48: =D46-D45 -> -96000 | E48: =E46-E45 -> -46000 | F48: =F46-F45 -> -146000 | G48: =G46-G45 -> -96000 | H48: =H46-H45 -> -146000 | I48: =I46-I45 -> -196000 | ... M48: =M46-M45 -> -146000 | N48: =SUM(B48:M48) -> -1312000
A49: 稼働率 | B49: =B50/(1*31) -> 1 | C49: =C50/(1*29) -> 0.96551724 | D49: =D50/(1*31) -> 1 | E49: =E50/(1*30) -> 1 | F49: =F50/(1*31) -> 1 | G49: =G50/(1*30) -> 1 | H49: =H50/(1*31) -> 1 | I49: =I50/(1*31) -> 1 | J49: =J50/(1*30) -> 1 | K49: =K50/(1*31) -> 1 | L49: =L50/(1*30) -> 1 | M49: =M50/(1*31) -> 1
A50: 販売客室数 | B50: 31 | C50: 28 | D50: 31 | E50: 30 | F50: 31 | G50: 30 | H50: 31 | I50: 31 | J50: 30 | K50: 31 | L50: 30 | M50: 31 | N50: =SUM(B50:M50) -> 365
A51: 利用人数 | B51: 124 | D51: 124 | E51: 120 | F51: 124 | G51: 120 | H51: 124 | I51: 124 | J51: 120 | K51: 124 | L51: 120 | M51: 124 | N51: =SUM(B51:M51) -> 1348
A52: 客室単価 | B52: =B46/B50 -> 3354.8387 | C52: =C46/C50 -> 3714.2857 | D52: =D46/D50 -> 3354.8387 | E52: =E46/E50 -> 3466.6667 | F52: =F46/F50 -> 129.03226 | G52: =G46/G50 -> 133.33333 | H52: =H46/H50 -> 129.03226 | I52: =I46/I50 -> 129.03226 | ... N52: =N46/N50 -> 1227.3973
A53: 客単価 | B53: =B46/B51 -> 838.70968 | C53: =C46/C51 -> #DIV/0! | D53: =D46/D51 -> 838.70968 | E53: =E46/E51 -> 866.66667 | F53: =F46/F51 -> 32.258065 | G53: =G46/G51 -> 33.333333 | H53: =H46/H51 -> 32.258065 | I53: =I46/I51 -> 32.258065 | ... N53: =N46/N51 -> 332.34421
A54: 昨年売上 | B54: 49071 | C54: 137999 | D54: 200400 | E54: 205579 | F54: 187337 | G54: 81410 | H54: 89625 | I54: 237984 | J54: 89828 | K54: 129196 | L54: 158915 | M54: 0 | N54: =SUM(B54:M54) -> 1567344
A55: 昨年対比 | B55: =B46/B54 -> 2.119378 | C55: =C46/C54 -> 0.75362865 | D55: =D46/D54 -> 0.51896208 | E55: =E46/E54 -> 0.50588825 | F55: =F46/F54 -> 0.021351895 | G55: =G46/G54 -> 0.049134013 | H55: =H46/H54 -> 0.044630404 | I55: =I46/I54 -> 0.016807853 | ... N55: =N46/N54 -> 0.28583387
A57: 2026年 グローバルリゾート料飲売上及び原価率
A58: 2025年 | B58: 1月 | C58: 2月 | D58: 3月 | E58: 4月 | F58: 5月 | G58: 6月 | H58: 7月 | I58: 8月 | J58: 9月 | K58: 10月 | L58: 11月 | M58: 12月 | N58: 合計 | P58: 大人朝食 | Q58: 子供朝食 | R58: 大人夕食 | S58: 子供夕食
A59: 朝食数 | B59: =B16+ホテル部門→!B29+ホテル部門→!B51 -> 323 | C59: =C16+ホテル部門→!C29+ホテル部門→!C51 -> 399 | D59: =D16+ホテル部門→!D29+ホテル部門→!D51 -> 675 | E59: =E16+ホテル部門→!E29+ホテル部門→!E51 -> 403 | F59: =F16+ホテル部門→!F29+ホテル部門→!F51 -> 520 | G59: =G16+ホテル部門→!G29+ホテル部門→!G51 -> 144 | H59: =H16+ホテル部門→!H29+ホテル部門→!H51 -> 65 | I59: =I16+ホテル部門→!I29+ホテル部門→!I51 -> 91 | ... M59: =M16+ホテル部門→!M29+ホテル部門→!M51 -> 3 | N59: =SUM(B59:M59) -> 2805 | P59: 1100 | Q59: 770 | R59: 1900 | S59: 1330
A60: 弥山夕食数 | B60: =B19 -> 50 | C60: =C19 -> 134 | D60: =D19 -> 178 | E60: =E19 -> 39 | F60: =F19 -> 146 | G60: =G19 -> 75 | H60: =H19 -> 8 | I60: =I19 -> 32 | ... M60: =M19 -> 2 | N60: =SUM(B60:M60) -> 757
A61: デルーネ （月曜のみ） 夕食数 | B61: 24 | N61: =SUM(B61:M61) -> 24 | P61: （旧）
A62: デルーネ 夕食売上 | B62: 41610 | Q62: 提供数 | R62: 単価 | S62: 売上 | T62: 合計数
A63: 朝食・夕食売上 | B63: =B14+ホテル部門→!B28+ホテル部門→!B50 -> 670820 | C63: =C14+ホテル部門→!C28+ホテル部門→!C50 -> 928675 | D63: =D14+ホテル部門→!D28+ホテル部門→!D50 -> 1470090 | E63: =E14+ホテル部門→!E28+ホテル部門→!E50 -> 741330 | F63: =F14+ホテル部門→!F28+ホテル部門→!F50 -> 1171145 | G63: =G14+ホテル部門→!G28+ホテル部門→!G50 -> 412860 | H63: =H14+ホテル部門→!H28+ホテル部門→!H50 -> 117215 | I63: =I14+ホテル部門→!I28+ホテル部門→!I50 -> 204725 | ... M63: =M14+ホテル部門→!M28+ホテル部門→!M50 -> 9650 | N63: =SUM(B63:M63) -> 6238925 | P63: 大人朝食 | R63: 1100 | S63: =Q63*R63 -> 0 | T63: 朝食合計
A64: 宿泊飲食追加 | N64: =SUM(B64:M64) -> 0 | P64: 子供朝食 | R64: 770 | S64: =Q64*R64 -> 0 | T64: =Q63+Q64 -> 0
A65: 宴会・BBQ 売上 | N65: =SUM(B65:M65) -> 0 | P65: 大人夕食 | Q65: 17 | R65: 1900 | S65: =Q65*R65 -> 32300 | T65: 夕食合計
A66: その他売上 | N66: =SUM(B66:M66) -> 0 | P66: 子供夕食 | Q66: 7 | R66: 1330 | S66: =Q66*R66 -> 9310 | T66: =Q65+Q66 -> 24
A67: 売上合計 | B67: =B62+B63+B64+B65+B66 -> 712430 | C67: =C62+C63+C64+C65+C66 -> 928675 | D67: =D62+D63+D64+D65+D66 -> 1470090 | E67: =E62+E63+E64+E65+E66 -> 741330 | F67: =F62+F63+F64+F65+F66 -> 1171145 | G67: =G62+G63+G64+G65+G66 -> 412860 | H67: =H62+H63+H64+H65+H66 -> 117215 | I67: =I62+I63+I64+I65+I66 -> 204725 | ... M67: =M62+M63+M64+M65+M66 -> 9650 | N67: =SUM(B67:M67) -> 6280535 | R67: 売上合計 | S67: =SUM(S63:S66) -> 41610
A68: 仕入金額 | B68: 313563 | N68: =SUM(B68:M68) -> 313563 | P68: （新）
A69: 人件費 | N69: =SUM(B69:M69) -> 0 | Q69: 提供数 | R69: 単価 | S69: 売上 | T69: 合計数
A70: 原価率 | B70: =B68/B67 -> 0.44013166 | C70: =C68/C67 -> 0 | D70: =D68/D67 -> 0 | E70: =E68/E67 -> 0 | F70: =F68/F67 -> 0 | G70: =G68/G67 -> 0 | H70: =H68/H67 -> 0 | I70: =I68/I67 -> 0 | ... N70: =N68/N67 -> 0.049926161 | P70: 大人朝食 | R70: 1650 | S70: =Q70*R70 -> 0 | T70: 朝食合計
A71: 人件費率 | B71: =B69/B67 -> 0 | C71: =C69/C67 -> 0 | D71: =D69/D67 -> 0 | E71: =E69/E67 -> 0 | F71: =F69/F67 -> 0 | G71: =G69/G67 -> 0 | H71: =H69/H67 -> 0 | I71: =I69/I67 -> 0 | ... N71: =N69/N67 -> 0 | P71: 子供朝食 | R71: 1155 | S71: =Q71*R71 -> 0 | T71: =Q70+Q71 -> 0
A72: 今年度売上 | B72: =B67 -> 712430 | C72: =C67 -> 928675 | D72: =D67 -> 1470090 | E72: =E67 -> 741330 | F72: =F67 -> 1171145 | G72: =G67 -> 412860 | H72: =H67 -> 117215 | I72: =I67 -> 204725 | ... M72: =M67 -> 9650 | N72: =SUM(B72:M72) -> 6280535 | P72: 大人夕食 | Q72: 19 | R72: 2350 | S72: =Q72*R72 -> 44650 | T72: 夕食合計
A73: 前年売上 | D73: 1809040 | E73: 1064870 | F73: 4005940 | G73: 1415030 | H73: 1163290 | I73: 1744210 | J73: 1375240 | K73: 1197720 | L73: 1828330 | M73: 950800 | N73: =SUM(B73:M73) -> 16554470 | P73: 子供夕食 | Q73: 1 | R73: 1645 | S73: =Q73*R73 -> 1645 | T73: =Q72+Q73 -> 20
A74: 昨年対比 | B74: =B72/B73 -> #DIV/0! | C74: =C72/C73 -> #DIV/0! | D74: =D72/D73 -> 0.81263543 | E74: =E72/E73 -> 0.69616949 | F74: =F72/F73 -> 0.29235211 | G74: =G72/G73 -> 0.29176767 | H74: =H72/H73 -> 0.10076163 | I74: =I72/I73 -> 0.11737405 | ... M74: =M72/M73 -> 0.010149348 | R74: 売上合計 | S74: =SUM(S70:S73) -> 46295
A75: 前年原価率 | D75: 0.297 | E75: 0.805 | F75: 0.139 | G75: 0.66 | H75: 0.387 | I75: 0.252 | J75: 0.409 | K75: 0.392 | L75: 0.327 | M75: 0.355 | N75: 0.347

Sheet 温井
A1: GR NUKUI 売上推移表
D2: 1月 | E2: 2月 | F2: 3月 | G2: 4月 | H2: 5月 | I2: 6月 | J2: 7月 | K2: 8月 | L2: 9月 | M2: 10月 | N2: 11月 | O2: 12月 | P2: 合計
A3: 総売上高(GOR) | D3: 7428554 | E3: 7562227 | F3: 3799283 | G3: 2330934 | H3: 4784742 | I3: 2087208 | J3: 1038480 | K3: 1446637 | L3: 100152 | M3: 177600 | P3: =SUM(D3:O3) -> 30755817
A4: 販売室数 | D4: 306 | E4: 360 | F4: 192 | G4: 163 | H4: 226 | I4: 156 | J4: 120 | K4: 284 | L4: 5 | M4: 35 | P4: =SUM(D4:O4) -> 1847
A5: 販売人数 | D5: 632 | E5: 625 | F5: 339 | G5: 215 | H5: 370 | I5: 210 | J5: 241 | K5: 792 | L5: 8 | M5: 106 | P5: =SUM(D5:O5) -> 3538
A6: 大人 | D6: 538 | E6: 584 | F6: 316 | G6: 205 | P6: =SUM(D6:O6) -> 1643
A7: 子供 | D7: 94 | E7: 41 | F7: 23 | G7: 10 | P7: =SUM(D7:O7) -> 168
A8: 販売可能室数 | D8: 837 | E8: 702 | F8: 810 | G8: 729 | P8: =SUM(D8:O8) -> 3078
A9: 販売可能人員 | D9: 3420 | E9: 3420 | F9: 3420 | G9: 3420 | P9: =SUM(D9:O9) -> 13680
A10: 客室稼働率(Occ) | D10: 0.3655914 | E10: 0.51282051 | F10: 0.23703704 | G10: 0.22359396 | P10: =SUM(D10:O10) -> 1.3390429
A11: 人員稼働率 | D11: 0.18479532 | E11: 0.18274854 | F11: 0.099122807 | G11: 0.062865497 | P11: =SUM(D11:O11) -> 0.52953216
A12: 1室平均稼働人員 | D12: 2.0653595 | E12: 1.7361111 | F12: 1.765625 | G12: 1.3190184 | P12: =SUM(D12:O12) -> 6.886114
A13: ADR | D13: 18241.562 | E13: 13774.772 | F13: 14952.411 | G13: 9820.8712 | P13: =SUM(D13:O13) -> 56789.617
A14: APR | D14: 8832.1487 | E14: 7934.2688 | F14: 8468.6224 | G14: 7445.5907 | P14: =SUM(D14:O14) -> 32680.631
A15: Rev.PAR | D15: 6668.9582 | E15: 7063.9858 | F15: 3544.2753 | G15: 2195.8875 | P15: =SUM(D15:O15) -> 19473.107
P16: =SUM(D16:O16) -> 0
A17: レストラン利用者数 | D17: 265 | E17: 278 | F17: 190 | G17: 136 | P17: =SUM(D17:O17) -> 869
A18: 朝食 | C18: =IF(D5=0,"",D18/D5) -> 0.25158228 | D18: 159 | E18: 165 | F18: 117 | G18: 82
A19: 昼食 | D19: 0 | E19: 0 | F19: 0 | G19: 1
A20: 夕食 | C20: =IF(D5=0,"",D20/D5) -> 0.16772152 | D20: 106 | E20: 113 | F20: 73 | G20: 53
A22: 宴会利用者数 | D22: 81 | E22: 148 | F22: 0 | G22: 0 | P22: =SUM(D22:O22) -> 229
A23: 会議/展示会 | D23: 0 | E23: 9 | F23: 0 | G23: 0
A24: 宴会 | D24: 81 | E24: 139 | F24: 0 | G24: 0
A26: 立寄入浴利用者数 | D26: 478 | E26: 499 | F26: 513 | G26: 425 | P26: =SUM(D26:O26) -> 1915
A27: 立寄入浴 | D27: 478 | E27: 499 | F27: 513 | G27: 425
A29: 売上高内訳 | B29: 宿 泊 売 上 | D29: 5581918 | E29: 4958918 | F29: 2870863 | G29: 1600802 | P29: =SUM(D29:O29) -> 15012501
B30: 宿泊売上(大人） | D30: 5565653 | E30: 4958918 | F30: 2870863 | G30: 1593602
B31: 宿泊売上(子人) | D31: 0 | E31: 0 | F31: 0 | G31: 0
B32: 寝具代 | D32: 0 | E32: 0 | F32: 0 | G32: 0
B33: 休憩料 | D33: 4000 | E33: 0 | F33: 0 | G33: 0
D34: 0 | E34: 0 | F34: 0 | G34: 0
B35: キャンセル料 | D35: 12265 | E35: 0 | F35: 0 | G35: 7200
B36: 宿 泊 その他 | D36: 0 | E36: 0 | F36: 0 | G36: 0 | P36: =SUM(D36:O36) -> 0
B37: 電話・FAX・コピー等 | D37: 0 | E37: 0 | F37: 0 | G37: 0 | P37: =SUM(D37:O37) -> 0
D38: 0 | E38: 0 | F38: 0 | G38: 0 | P38: =SUM(D38:O38) -> 0
D39: 0 | E39: 0 | F39: 0 | G39: 0 | P39: =SUM(D39:O39) -> 0
D40: 0 | E40: 0 | F40: 0 | G40: 0 | P40: =SUM(D40:O40) -> 0
B41: レストラン 売 上 | D41: 771900 | E41: 850700 | F41: 606500 | G41: 480700 | P41: =SUM(D41:O41) -> 2709800
B42: 料 理 売 上 | D42: 742400 | E42: 796100 | F42: 591000 | G42: 459200 | P42: =SUM(D42:O42) -> 2588700
B43: (朝 食) | D43: 285800 | E43: 300800 | F43: 211000 | G43: 155000 | P43: =SUM(D43:O43) -> 952600
B44: (昼 食) | D44: 0 | E44: 0 | F44: 0 | G44: 1200 | P44: =SUM(D44:O44) -> 1200
B45: (夕 食) | D45: 456600 | E45: 495300 | F45: 380000 | G45: 303000 | P45: =SUM(D45:O45) -> 1634900
D46: 0 | E46: 0 | F46: 0 | G46: 0 | P46: =SUM(D46:O46) -> 0
P47: =SUM(D47:O47) -> 0
B48: 飲 物 売 上 | D48: 29500 | E48: 54600 | F48: 15500 | G48: 21500 | P48: =SUM(D48:O48) -> 121100
B49: (宿 泊 飲 物) | D49: 29500 | E49: 54600 | F49: 15500 | G49: 20900 | P49: =SUM(D49:O49) -> 120500
B50: (昼 食 飲 物) | D50: 0 | E50: 0 | F50: 0 | G50: 600 | P50: =SUM(D50:O50) -> 600
B51: 個 室 利 用 料 | D51: 0 | E51: 0 | F51: 0 | G51: 0 | P51: =SUM(D51:O51) -> 0
B52: 宴 会 売 上 | D52: 601800 | E52: 1335200 | F52: 0 | G52: 0 | P52: =SUM(D52:O52) -> 1937000
B53: 料 理 売 上 | D53: 454000 | E53: 1027500 | F53: 0 | G53: 0 | P53: =SUM(D53:O53) -> 1481500
B54: 飲 料 売 上 | D54: 147800 | E54: 221700 | F54: 0 | G54: 0 | P54: =SUM(D54:O54) -> 369500
B55: 宴 会 室 料 | D55: 0 | E55: 46000 | F55: 0 | G55: 0 | P55: =SUM(D55:O55) -> 46000
B56: そ の 他 | D56: 0 | E56: 35000 | F56: 0 | G56: 0 | P56: =SUM(D56:O56) -> 35000
B57: 会 議 室 料 | D57: 0 | E57: 5000 | F57: 0 | G57: 0 | P57: =SUM(D57:O57) -> 5000
B58: 会 議 その他 | D58: 0 | E58: 0 | F58: 0 | G58: 0 | P58: =SUM(D58:O58) -> 0
B59: 付 帯 売 上 | D59: 398236 | E59: 334159 | F59: 277970 | G59: 218682 | P59: =SUM(D59:O59) -> 1229047
... B61: 日帰り入浴料 | D61: 213300 | E61: 221790 | F61: 227200 | G61: 189100 | P61: =SUM(D61:O61) -> 851390
B62: アメニティ | D62: 6700 | P62: =SUM(D62:O62) -> 6700
B63: 自動販売機 | D63: 0 | E63: 0 | F63: 0 | G63: 0 | P63: =SUM(D63:O63) -> 0
B64: カ ラ オ ケ | D64: 0 | E64: 5000 | F64: 0 | G64: 0 | P64: =SUM(D64:O64) -> 5000
D65: 146000 | E65: 45000 | P65: =SUM(D65:O65) -> 191000
P66: =SUM(D66:O66) -> 0
P67: =SUM(D67:O67) -> 0
D68: 0 | E68: 0 | F68: 0 | G68: 0 | P68: =SUM(D68:O68) -> 0
B69: 入 湯 税 | D69: 74700 | E69: 83250 | F69: 43950 | G69: 30750 | P69: =SUM(D69:O69) -> 232650
B70: 消 費 税 | D70: 0 | E70: 0 | F70: 0 | G70: 0 | P70: =SUM(D70:O70) -> 0
B71: 立 替 金 | D71: 0 | E71: 0 | F71: 0 | G71: 0 | P71: =SUM(D71:O71) -> 0
B72: 入金合計 | D72: 7480894 | E72: 6516716 | F72: 3647353 | G72: 2348974 | P72: =SUM(D72:O72) -> 19993937
B73: 現 金 | D73: 1254863 | E73: 1205997 | F73: 688590 | G73: 509752 | P73: =SUM(D73:O73) -> 3659202
B74: システム | D74: 5259164 | E74: 4512778 | F74: 2766763 | G74: 1811422 | P74: =SUM(D74:O74) -> 14350127
B75: 売 掛 | D75: 966867 | E75: 797941 | F75: 192000 | G75: 27800 | P75: =SUM(D75:O75) -> 1984608
B76: 過不足 | D76: 52340 | E76: -1045511 | F76: -151930 | G76: 18040 | P76: =SUM(D76:O76) -> -1127061
A79: 経費 | B79: 温井 | C79: １月 | D79: ２月 | E79: ３月 | F79: ４月 | G79: ５月 | H79: ６月 | I79: ７月 | J79: ８月 | K79: ９月 | L79: １０月 | M79: １１月 | N79: １２月 | O79: 合計
B80: 目標売上 | C80: 3022505 | D80: 4261675 | E80: 3738314 | F80: 2113091 | G80: 3281694 | H80: 2228827 | I80: 5237483 | J80: 6962206 | K80: 4111027 | L80: 5703514 | M80: 5651540 | N80: 4532837 | O80: 50844713
B81: 売上進捗 | C81: =D3 -> 7428554 | D81: =E3 -> 7562227 | E81: =F3 -> 3799283 | F81: =G3 -> 2330934 | G81: =H3 -> 4784742 | H81: =I3 -> 2087208 | I81: =J3 -> 1038480 | J81: =K3 -> 1446637 | ... N81: =O3 -> 0 | O81: =SUM(C81:N81) -> 30755817
B82: 達成率 | C82: =C81/C80 -> 2.4577475 | D82: =D81/D80 -> 1.7744729 | E82: =E81/E80 -> 1.0163092 | F82: =F81/F80 -> 1.1030921 | G82: =G81/G80 -> 1.4580098 | H82: =H81/H80 -> 0.9364603 | I82: =I81/I80 -> 0.19827845 | J82: =J81/J80 -> 0.20778429 | ... O82: =O81/O80 -> 0.60489705
B83: 売上目標差異 | C83: =C81-C80 -> 4406049 | D83: =D81-D80 -> 3300552 | E83: =E81-E80 -> 60969 | F83: =F81-F80 -> 217843 | G83: =G81-G80 -> 1503048 | H83: =H81-H80 -> -141619 | I83: =I81-I80 -> -4199003 | J83: =J81-J80 -> -5515569 | ... N83: =N81-N80 -> -4532837 | O83: =SUM(C83:N83) -> -20088896
B84: 昨年売上 | C84: 3022505 | D84: 4261675 | E84: 3738314 | F84: 2113091 | G84: 3281694 | H84: 2228827 | I84: 5237483 | J84: 6962206 | K84: 4111027 | L84: 5703514 | M84: 5651540 | N84: 2520879 | O84: =SUM(C84:N84) -> 48832755 | P84: 11月まで入力済み
B85: 昨年対比 | C85: =C81/C84 -> 2.4577475 | D85: =D81/D84 -> 1.7744729 | E85: =E81/E84 -> 1.0163092 | F85: =F81/F84 -> 1.1030921 | G85: =G81/G84 -> 1.4580098 | H85: =H81/H84 -> 0.9364603 | I85: =I81/I84 -> 0.19827845 | J85: =J81/J84 -> 0.20778429 | ... O85: =O81/O84 -> 0.62981941
B86: 経費予測 | O86: =SUM(C86:N86) -> 0
B87: 昨年経費 | C87: 2059304 | D87: 2334640 | E87: 5917638 | F87: 6785357 | G87: 6789048 | H87: 5520140 | I87: 5057960 | J87: 5678353 | K87: 2742138 | O87: =SUM(C87:N87) -> 42884578
B88: 経費実績 | C88: 3022505 | D88: 4261675 | E88: 3738314 | F88: 2113091 | G88: 3281694 | H88: 2228827 | I88: 5237483 | J88: 6962206 | K88: 4111027 | L88: 5703514 | M88: 5651540 | N88: 4532837 | O88: 50844713
B89: 経費差異 | C89: =C86-C88 -> -3022505 | D89: =D86-D87 -> -2334640 | E89: =E86-E87 -> -5917638 | F89: =F86-F87 -> -6785357 | G89: =G86-G87 -> -6789048 | H89: =H86-H88 -> -2228827 | I89: =I86-I88 -> -5237483 | J89: =J86-J88 -> -6962206 | K89: =K86-K88 -> -4111027 | L89: =L86-L88 -> -5703514 | M89: =M86-M88 -> -5651540 | N89: 18000000 | O89: =SUM(C89:N89) -> -36743785
B90: 差引収支 | C90: =C81-C88 -> 4406049 | D90: =D81-D88 -> 3300552 | E90: =E81-E88 -> 60969 | F90: =F81-F88 -> 217843 | G90: =G81-G88 -> 1503048 | H90: =H81-H88 -> -141619 | I90: =I81-I88 -> -4199003 | J90: =J81-J88 -> -5515569 | ... N90: =N81-N88 -> -4532837 | O90: =SUM(C90:N90) -> -20088896

Sheet いこいの村
A1: GR いこいの村ひろしま 売上推移表
D2: 1月 | E2: 2月 | F2: 3月 | G2: 4月 | H2: 5月 | I2: 6月 | J2: 7月 | K2: 8月 | L2: 9月 | M2: 10月 | N2: 11月 | O2: 12月 | P2: 合計
A3: 総売上高(GOR) | D3: 8292624 | E3: 8535484 | F3: 4929332 | G3: 6092392 | H3: 3646914 | I3: 1303991 | J3: 1869506 | K3: 948336 | L3: 1793043 | M3: 415440
A4: 販売室数 | D4: 303 | E4: 279 | F4: 162 | G4: 182 | H4: 155 | I4: 103 | J4: 183 | K4: 459 | L4: 105 | M4: 83
A5: 販売人数 | D5: 738 | E5: 741 | F5: 426 | G5: 554 | H5: 440 | I5: 273 | J5: 636 | K5: 1969 | L5: 469 | M5: 314
A6: 大人 | D6: 0 | E6: 636 | F6: 116 | G6: 0
A7: 子供 | D7: 0 | E7: 37 | F7: 8 | G7: 0
A8: 販売可能室数 | D8: 837 | E8: 702 | F8: 837 | G8: 648
A9: 販売可能人員 | D9: 3751 | E9: 3146 | F9: 3388 | G9: 3630
A10: 客室稼働率(Occ) | D10: 0.36200717 | E10: 0.3974359 | F10: 0.19354839 | G10: 0.2808642
A11: 人員稼働率 | D11: 0.19674753 | E11: 0.23553719 | F11: 0.1257379 | G11: 0.15261708
A12: 1室平均稼働人員 | D12: 2.4356436 | E12: 2.655914 | F12: 2.6296296 | G12: 3.043956
A13: ADR | D13: 26170.244 | E13: 16863.097 | F13: 16012.79 | G13: 13805.654
A14: APR | D14: 10744.694 | E14: 6349.2632 | F14: 6089.3709 | G14: 4535.4314
A15: Rev.PAR | D15: 9473.816 | E15: 6702 | F15: 3099.2497 | G15: 3877.5139
A17: レストラン利用者数 | D17: 0 | E17: 1015 | F17: 709 | G17: 1469
A18: 朝食 | C18: =IF(J5=0,"",J18/J5) -> 0 | D18: 0 | E18: 512 | F18: 296 | G18: 518
A19: 昼食 | D19: 0 | E19: 0 | F19: 128 | G19: 438
A20: 夕食 | C20: =IF(J5=0,"",J20/J5) -> 0 | D20: 0 | E20: 503 | F20: 285 | G20: 513
A22: 宴会利用者数 | D22: 0 | E22: 0 | F22: 0 | G22: 0
A23: 会議/展示会 | D23: 0 | E23: 0 | F23: 0 | G23: 0
A24: 宴会 | D24: 0 | E24: 0 | F24: 0 | G24: 0
A26: 日帰り入浴利用者数 | D26: 0 | E26: 426 | F26: 226 | G26: 150
A27: 日帰り入浴 | D27: 0 | E27: 426 | F27: 226 | G27: 150
A28: 日帰り入浴（松原自治会）
A29: 売上高内訳 | B29: 宿 泊 売 上 | D29: 7929584 | E29: 4704804 | F29: 2594072 | G29: 2512629
B30: 宿泊売上(大人） | D30: 7929584 | E30: 4694114 | F30: 2588872 | G30: 2512629
B31: 宿泊売上(子人) | D31: 0 | E31: 0 | F31: 0 | G31: 0
B32: 寝具代 | D32: 0 | E32: 0 | F32: 0 | G32: 0
B33: 休憩料 | D33: 0 | E33: 0 | F33: 0 | G33: 0
D34: 0 | E34: 0 | F34: 0 | G34: 0
B35: キャンセル料 | D35: 0 | E35: 10690 | F35: 5200 | G35: 0
B36: 宿 泊 その他 | D36: 0 | E36: 0 | F36: 0 | G36: 0
B37: 電話・FAX・コピー等 | D37: 0 | E37: 0 | F37: 0 | G37: 0
D38: 0 | E38: 0 | F38: 0 | G38: 0
D39: 0 | E39: 0 | F39: 0 | G39: 0
D40: 0 | E40: 0 | F40: 0 | G40: 0
B41: レストラン 売 上 | D41: 7390 | E41: 3163530 | F41: 1686760 | G41: 2802181
B42: 料 理 売 上 | D42: 0 | E42: 3081860 | F42: 1625640 | G42: 2794541
B43: (朝 食) | D43: 0 | E43: 915250 | F43: 531000 | G43: 791840
B44: (昼 食) | D44: 0 | E44: 46610 | F44: 112640 | G44: 385440
B45: (夕 食) | D45: 0 | E45: 2120000 | F45: 982000 | G45: 1617261
B46: (その他) | D46: 0 | E46: 0 | F46: 0 | G46: 0
B48: 飲 物 売 上 | D48: 7390 | E48: 81670 | F48: 61120 | G48: 7640
B49: (宿 泊 飲 物) | D49: 0 | E49: 76770 | F49: 61120 | G49: 7640
B50: (昼 食 飲 物) | D50: 0 | E50: 0 | F50: 0 | G50: 0
B51: 個 室 利 用 料 | D51: 0 | E51: 0 | F51: 0 | G51: 0
B52: 宴 会 売 上 | D52: 0 | E52: 0 | F52: 438130 | G52: 528070
B53: 料 理 売 上 | D53: 0 | E53: 0 | F53: 386100 | G53: 388920
... B61: 日帰り入浴料 | D61: 273200 | E61: 228100 | F61: 125900 | G61: 84200
B62: アメニティ
B63: 自動販売機 | D63: 10190 | E63: 86070 | F63: 0 | G63: 29190
B64: カ ラ オ ケ | D64: 0 | E64: 0 | F64: 0 | G64: 300
B65: その他
D68: 0 | E68: 5560 | F68: 0 | G68: 0
B69: 入 湯 税 | D69: 0 | E69: 0 | F69: 0 | G69: 101600
B70: 消 費 税 | D70: 0 | E70: 0 | F70: 0 | G70: 0
B71: 立 替 金 | D71: 0 | E71: 0 | F71: 0 | G71: 0
B72: 入金合計 | D72: 8553834 | E72: 8595394 | F72: 4850912 | G72: 6087282
B73: 現 金 | D73: 2548955 | E73: 2316903 | F73: 1283288 | G73: 712162
B74: システム | D74: 3359948 | E74: 3064393 | F74: 1380454 | G74: 751610
B75: 売 掛 | D75: 2644931 | E75: 3214098 | F75: 2187170 | G75: 4623510
B76: 過不足 | D76: 278100 | E76: 59910 | F76: -78420 | G76: -5110
B78: いこいの村 | C78: １月 | D78: ２月 | E78: ３月 | F78: ４月 | G78: ５月 | H78: ６月 | I78: ７月 | J78: ８月 | K78: ９月 | L78: １０月 | M78: １１月 | N78: １２月 | O78: 合計
B79: 目標売上 | C79: 0 | D79: 0 | E79: 0 | F79: 5067080 | G79: 5172360 | H79: 5590656 | I79: 8590205 | J79: 14720394 | K79: 5111672 | L79: 5445149 | M79: 5263750 | N79: 4624660 | O79: 59585926
B80: 売上進捗 | C80: =D3 -> 8292624 | D80: =E3 -> 8535484 | E80: =F3 -> 4929332 | F80: =G3 -> 6092392 | G80: =H3 -> 3646914 | H80: =I3 -> 1303991 | I80: =J3 -> 1869506 | J80: =K3 -> 948336 | ... N80: =O3 -> 0 | O80: =SUM(C80:N80) -> 37827062
B81: 達成率 | C81: =C80/C79 -> #DIV/0! | D81: =D80/D79 -> #DIV/0! | E81: =E80/E79 -> #DIV/0! | F81: =F80/F79 -> 1.2023477 | G81: =G80/G79 -> 0.70507737 | H81: =H80/H79 -> 0.23324472 | I81: =I80/I79 -> 0.21763229 | J81: =J80/J79 -> 0.064423276 | ... O81: =O80/O79 -> 0.63483216
B82: 売上目標差異 | C82: =C80-C79 -> 8292624 | D82: =D80-D79 -> 8535484 | E82: =E80-E79 -> 4929332 | F82: =F80-F79 -> 1025312 | G82: =G80-G79 -> -1525446 | H82: =H80-H79 -> -4286665 | I82: =I80-I79 -> -6720699 | J82: =J80-J79 -> -13772058 | ... N82: =N80-N79 -> -4624660 | O82: =SUM(C82:N82) -> -21758864
B83: 昨年売上 | C83: 0 | D83: 0 | E83: 0 | F83: 5067080 | G83: 5172360 | H83: 5590656 | I83: 8590205 | J83: 14720394 | K83: 5111672 | L83: 5445149 | M83: 5263750 | N83: 4624660 | O83: 59585926
B84: 昨年対比 | C84: =C80/C83 -> #DIV/0! | D84: =D80/D83 -> #DIV/0! | E84: =E80/E83 -> #DIV/0! | F84: =F80/F83 -> 1.2023477 | G84: =G80/G83 -> 0.70507737 | H84: =H80/H83 -> 0.23324472 | I84: =I80/I83 -> 0.21763229 | J84: =J80/J83 -> 0.064423276 | ... O84: =O80/O83 -> 0.63483216
B85: 経費予測 | O85: =SUM(C85:N85) -> 0
B86: 昨年経費 | F86: 5067080 | G86: 5172360 | H86: 5590656 | I86: 8590205 | J86: 14720394 | K86: 5111672 | L86: 5445149 | O86: =SUM(C86:N86) -> 49697516
B87: 経費実績 | C87: 5778007 | D87: 5913951 | O87: =SUM(C87:N87) -> 11691958
B88: 経費差異 | C88: =C85-C87 -> -5778007 | D88: =D85-D86 -> 0 | E88: =E85-E86 -> 0 | F88: =F85-F86 -> -5067080 | G88: =G85-G86 -> -5172360 | H88: =H85-H87 -> 0 | I88: =I85-I87 -> 0 | J88: =J85-J87 -> 0 | K88: =K85-K87 -> 0 | L88: =L85-L87 -> 0 | M88: =M85-M87 -> 0 | N88: 18000000 | O88: =SUM(C88:N88) -> 1982553
B89: 差引収支 | C89: =C80-C87 -> 2514617 | D89: =D80-D87 -> 2621533 | E89: =E80-E87 -> 4929332 | F89: =F80-F87 -> 6092392 | G89: =G80-G87 -> 3646914 | H89: =H80-H87 -> 1303991 | I89: =I80-I87 -> 1869506 | J89: =J80-J87 -> 948336 | ... N89: =N80-N87 -> 0 | O89: =SUM(C89:N89) -> 26135104

Sheet 深入山GS
D1: 休業 | O1: 休業
D2: 1月 | E2: 2月 | F2: 3月 | G2: 4月 | H2: 5月 | I2: 6月 | J2: 7月 | K2: 8月 | L2: 9月 | M2: 10月 | N2: 11月 | O2: 12月 | P2: 合計
A3: 総売上高(GOR) | G3: 378080 | P3: =SUM(D3:O3) -> 378080
A4: 利用件数 | G4: 29 | P4: =SUM(D4:O4) -> 29
A5: グランドゴルフ場（大人） | G5: 19 | P5: =SUM(D5:O5) -> 19
A6: グランドゴルフ場（子供） | G6: 0 | P6: =SUM(D6:O6) -> 0
A7: グランドゴルフ場（いこい） | G7: 0 | P7: =SUM(D7:O7) -> 0
A8: オートキャンプ | G8: 5 | P8: =SUM(D8:O8) -> 5
A9: デイキャンプ | G9: 5 | P9: =SUM(D9:O9) -> 5
A10: 体験棟 | G10: 0 | P10: =SUM(D10:O10) -> 0
A11: 多目的広場 | G11: 0 | P11: =SUM(D11:O11) -> 0
A13: 利用人数 | G13: 111 | P13: =SUM(D13:O13) -> 111
A14: グランドゴルフ場（大人）町内 | G14: 56 | P14: =SUM(D14:O14) -> 56
A15: グランドゴルフ場（大人）町外 | G15: 5 | P15: =SUM(D15:O15) -> 5
... A22: 多目的広場 | G22: 0 | P22: =SUM(D22:O22) -> 0
A24: 売上高内訳 | B24: 施設利用料 | G24: 73800 | P24: =SUM(D24:O24) -> 73800
B25: グランドゴルフ場 | G25: 30600 | P25: =SUM(D25:O25) -> 30600
B26: オートキャンプ | G26: 24000 | P26: =SUM(D26:O26) -> 24000
B27: デイキャンプ | G27: 17000 | P27: =SUM(D27:O27) -> 17000
B28: 道具類貸出 | G28: 700 | P28: =SUM(D28:O28) -> 700
B29: 多目的広場 | G29: 1500 | P29: =SUM(D29:O29) -> 1500
B30: 体験棟 | G30: 0 | P30: =SUM(D30:O30) -> 0
G31: 0 | P31: =SUM(D31:O31) -> 0
G32: 0 | P32: =SUM(D32:O32) -> 0
B33: 売店売上 | G33: 304280 | P33: =SUM(D33:O33) -> 304280
B34: おみやげ | G34: 222100 | P34: =SUM(D34:O34) -> 222100
B35: 地域特産品（地元産） | G35: 9100 | P35: =SUM(D35:O35) -> 9100
B36: アイス・氷 | G36: 48880 | P36: =SUM(D36:O36) -> 48880
B37: コーヒー | G37: 24200 | P37: =SUM(D37:O37) -> 24200
B38: 地図 | G38: 0 | P38: =SUM(D38:O38) -> 0
B39: 自動販売機 | G39: 0 | P39: =SUM(D39:O39) -> 0
B40: 弁当 | G40: 0 | P40: =SUM(D40:O40) -> 0
B41: その他 | G41: 0 | P41: =SUM(D41:O41) -> 0
G42: 0
B43: 入金合計 | G43: 378080 | P43: =SUM(D43:O43) -> 378080
B44: 現 金 | G44: 378080 | P44: =SUM(D44:O44) -> 378080
B45: システム | G45: 0 | P45: =SUM(D45:O45) -> 0
B46: 売 掛 | G46: 0 | P46: =SUM(D46:O46) -> 0
B47: 過不足 | P47: =SUM(D47:O47) -> 0
A49: 経費 | B49: GS | C49: １月 | D49: ２月 | E49: ３月 | F49: ４月 | G49: ５月 | H49: ６月 | I49: ７月 | J49: ８月 | K49: ９月 | L49: １０月 | M49: １１月 | N49: １２月 | O49: 合計
B50: 目標売上 | F50: 461140 | G50: 783440 | H50: 442970 | I50: 505440 | J50: 550560 | K50: 529680 | L50: 896640 | M50: 1183910 | O50: 5353780
B51: 総売上 | C51: =C52+C53 -> 248917 | D51: =D52+D53 -> 248917 | E51: =E52+E53 -> 248917 | F51: =F52+F53 -> 626997 | G51: =G52+G53 -> 248917 | H51: =H52+H53 -> 248917 | I51: =I52+I53 -> 248917 | J51: =J52+J53 -> 248917 | ... O51: =O52+O53 -> 3365084
B52: 売上進捗 | C52: =D3 -> 0 | D52: =E3 -> 0 | E52: =F3 -> 0 | F52: =G3 -> 378080 | G52: =H3 -> 0 | H52: =I3 -> 0 | I52: =J3 -> 0 | J52: =K3 -> 0 | ... N52: =O3 -> 0 | O52: =SUM(C52:N52) -> 378080
B53: 指定管理料 | C53: 248917 | D53: 248917 | E53: 248917 | F53: 248917 | G53: 248917 | H53: 248917 | I53: 248917 | J53: 248917 | K53: 248917 | L53: 248917 | M53: 248917 | N53: 248917 | O53: =SUM(C53:N53) -> 2987004
B54: 達成率 | C54: =C52/C50 -> #DIV/0! | D54: =D52/D50 -> #DIV/0! | E54: =E52/E50 -> #DIV/0! | F54: =F52/F50 -> 0.81988116 | G54: =G52/G50 -> 0 | H54: =H52/H50 -> 0 | I54: =I52/I50 -> 0 | J54: =J52/J50 -> 0 | ... O54: =O52/O50 -> 0.070619263
B55: 売上目標差異 | C55: =C52-C50 -> 0 | D55: =D52-D50 -> 0 | E55: =E52-E50 -> 0 | F55: =F52-F50 -> -83060 | G55: =G52-G50 -> -783440 | H55: =H52-H50 -> -442970 | I55: =I52-I50 -> -505440 | J55: =J52-J50 -> -550560 | ... N55: =N52-N50 -> 0 | O55: =SUM(C55:N55) -> -4975700
B56: 昨年売上 | F56: 461140 | G56: 783440 | H56: 442970 | I56: 505440 | J56: 550560 | K56: 529680 | L56: 896640 | M56: 1183910 | O56: =SUM(C56:N56) -> 5353780
B57: 昨年対比 | C57: =C52/C56 -> #DIV/0! | D57: =D52/D56 -> #DIV/0! | E57: =E52/E56 -> #DIV/0! | F57: =F52/F56 -> 0.81988116 | G57: =G52/G56 -> 0 | H57: =H52/H56 -> 0 | I57: =I52/I56 -> 0 | J57: =J52/J56 -> 0 | ... O57: =O52/O56 -> 0.070619263
B58: 経費予測 | O58: =SUM(C58:N58) -> 0
B59: 昨年経費 | C59: 2059304 | D59: 2334640 | E59: 5917638 | F59: 6785357 | G59: 6789048 | H59: 5520140 | I59: 5057960 | J59: 5678353 | K59: 2742138 | O59: =SUM(C59:N59) -> 42884578
B60: 経費実績 | O60: =SUM(C60:N60) -> 0
B61: 経費差異 | C61: =C58-C60 -> 0 | D61: =D58-D59 -> -2334640 | E61: =E58-E59 -> -5917638 | F61: =F58-F59 -> -6785357 | G61: =G58-G59 -> -6789048 | H61: =H58-H60 -> 0 | I61: =I58-I60 -> 0 | J61: =J58-J60 -> 0 | K61: =K58-K60 -> 0 | L61: =L58-L60 -> 0 | M61: =M58-M60 -> 0 | N61: 18000000 | O61: =SUM(C61:N61) -> -3826683
B62: 差引収支 | C62: =C52-C60 -> 0 | D62: =D52-D60 -> 0 | E62: =E52-E60 -> 0 | F62: =F52-F60 -> 378080 | G62: =G52-G60 -> 0 | H62: =H52-H60 -> 0 | I62: =I52-I60 -> 0 | J62: =J52-J60 -> 0 | ... N62: =N52-N60 -> 0 | O62: =SUM(C62:N62) -> 378080
A64: 1年間の指定管理料：2,987,000

Sheet フォレストヒルズガーデン
A1: フォレストヒルズガーデン | B1: １月 | C1: ２月 | D1: ３月 | E1: ４月 | F1: ５月 | G1: ６月 | H1: ７月 | I1: ８月 | J1: ９月 | K1: １０月 | L1: １１月 | M1: １２月 | N1: 合計
A2: 目標売上 | N2: =SUM(B2:M2) -> 0
A3: 総売上 | B3: =B4+B5 -> 5670857 | C3: =C4+C5 -> 5411304 | D3: =D4+D5 -> 6110445 | E3: =E4+E5 -> 5535949 | F3: =F4+F5 -> 7265723 | G3: =G4+G5 -> 5640457 | H3: =H4+H5 -> 4902843 | I3: =I4+I5 -> 5877492 | ... N3: =N4+N5 -> 60057288
A4: 売上進捗 | B4: 1049020 | C4: 789471 | D4: 1488612 | E4: 914116 | F4: 2643890 | G4: 1018624 | H4: 281010 | I4: 1255659 | J4: 208200 | K4: 0 | L4: 75000 | M4: 0 | N4: 4595288
A5: 指定管理料 | B5: 4621837 | C5: 4621833 | D5: 4621833 | E5: 4621833 | F5: 4621833 | G5: 4621833 | H5: 4621833 | I5: 4621833 | J5: 4621833 | K5: 4621833 | L5: 4621833 | M5: 4621833 | N5: =SUM(B5:M5) -> 55462000
A6: 達成率 | B6: =B4/B2 -> #DIV/0! | C6: =C4/C2 -> #DIV/0! | D6: =D4/D2 -> #DIV/0! | E6: =E4/E2 -> #DIV/0! | F6: =F4/F2 -> #DIV/0! | G6: =G4/G2 -> #DIV/0! | H6: =H4/H2 -> #DIV/0! | I6: =I4/I2 -> #DIV/0! | ... N6: =N4/N2 -> #DIV/0!
A7: 差異 | B7: =B4-B2 -> 1049020 | C7: =C4-C2 -> 789471 | D7: =D4-D2 -> 1488612 | E7: =E4-E2 -> 914116 | F7: =F4-F2 -> 2643890 | G7: =G4-G2 -> 1018624 | H7: =H4-H2 -> 281010 | I7: =I4-I2 -> 1255659 | ... M7: =M4-M2 -> 0 | N7: =SUM(B7:M7) -> 9723602
A8: 稼働率 | B8: =B9/(8*29) -> 0.099137931 | C8: =C9/(8*29) -> 0.13362069 | D8: =D9/(8*31) -> 0.16129032 | E8: =E9/(8*30) -> 0.10833333 | F8: =F9/(8*31) -> 0.26209677 | G8: =G9/(8*30) -> 0.12083333 | H8: =H9/(8*31) -> 0.092741935 | I8: =I9/(8*31) -> 0.092741935 | J8: =J9/(8*30) -> 0.020833333 | K8: =K9/(8*31) -> 0.0040322581 | L8: =L9/(8*30) -> 0.033333333 | M8: =M9/(8*31) -> 0.0080645161 | N8: =N9/(8*365) -> 0.03869863
A9: 販売客室数 | B9: 23 | C9: 31 | D9: 40 | E9: 26 | F9: 65 | G9: 29 | H9: 23 | I9: 23 | J9: 5 | K9: 1 | L9: 8 | M9: 2 | N9: 113
A10: 利用人数 | B10: 98 | C10: 97 | D10: 122 | E10: 83 | F10: 214 | G10: 106 | H10: 88 | I10: 88 | J10: 15 | K10: 6 | L10: 23 | M10: 13 | N10: 397
A11: 客室単価 | B11: =B4/B9 -> 45609.565 | C11: =C4/C9 -> 25466.806 | D11: =D4/D9 -> 37215.3 | E11: =E4/E9 -> 35158.308 | F11: =F4/F9 -> 40675.231 | G11: =G4/G9 -> 35124.966 | H11: =H4/H9 -> 12217.826 | I11: =I4/I9 -> 54593.87 | ... N11: =N4/N9 -> 40666.265
A12: 客単価 | B12: =B4/B10 -> 10704.286 | C12: =C4/C10 -> 8138.8763 | D12: =D4/D10 -> 12201.738 | E12: =E4/E10 -> 11013.446 | F12: =F4/F10 -> 12354.626 | G12: =G4/G10 -> 9609.6604 | H12: =H4/H10 -> 3193.2955 | I12: =I4/I10 -> 14268.852 | ... N12: =N4/N10 -> 11575.033
A13: 昨年売上
A14: 昨年対比 | B14: =B4/B13 -> #DIV/0! | C14: =C4/C13 -> #DIV/0! | D14: =D4/D13 -> #DIV/0! | E14: =E4/E13 -> #DIV/0! | F14: =F4/F13 -> #DIV/0! | G14: =G4/G13 -> #DIV/0! | H14: =H4/H13 -> #DIV/0! | I14: =I4/I13 -> #DIV/0! | ... N14: =N4/N13 -> #DIV/0!
A16: 年間指定管理料：55,462,000円

Sheet マンスリー部門
A1: 2026年 マンスリー 売上目標及び売上実績
A2: TAKAYA | B2: １月 | C2: ２月 | D2: ３月 | E2: ４月 | F2: ５月 | G2: ６月 | H2: ７月 | I2: ８月 | J2: ９月 | K2: １０月 | L2: １１月 | M2: １２月 | N2: 合計
A3: 目標売上 | B3: 142000 | C3: 506000 | D3: 517000 | E3: 636000 | F3: 441000 | G3: 421980 | H3: 310000 | I3: 246000 | J3: 96000 | K3: 228000 | L3: 450000 | M3: 323000 | N3: 4316980
A4: 売上進捗 | B4: 251000 | C4: 308000 | D4: 651000 | E4: 455000 | F4: 272000 | G4: 195000 | H4: 78000 | I4: 120000 | J4: 0 | K4: 0 | L4: 0 | M4: 0 | N4: =SUM(B4:M4) -> 2330000
A5: 達成率 | B5: =B4/B3 -> 1.7676056 | C5: =C4/C3 -> 0.60869565 | D5: =D4/D3 -> 1.2591876 | E5: =E4/E3 -> 0.71540881 | F5: =F4/F3 -> 0.61678005 | G5: =G4/G3 -> 0.46210721 | H5: =H4/H3 -> 0.2516129 | I5: =I4/I3 -> 0.48780488 | ... N5: =N4/N3 -> 0.53972916
A6: 差異 | B6: =B4-B3 -> 109000 | C6: =C4-C3 -> -198000 | D6: =D4-D3 -> 134000 | E6: =E4-E3 -> -181000 | F6: =F4-F3 -> -169000 | G6: =G4-G3 -> -226980 | H6: =H4-H3 -> -232000 | I6: =I4-I3 -> -126000 | ... M6: =M4-M3 -> -323000 | N6: =SUM(B6:M6) -> -1986980
A7: 稼働率 | B7: =B8/(12*31) -> 0.23924731 | C7: =C8/(12*29) -> 0.31896552 | D7: =D8/(12*31) -> 0.56989247 | E7: =E8/(12*30) -> 0.41944444 | F7: =F8/(12*31) -> 0.22580645 | G7: =G8/(12*30) -> 0.18055556 | H7: =H8/(11*31) -> 0.076246334 | I7: =I8/(11*31) -> 0.14076246 | J7: =J8/(11*30) -> 0 | K7: =K8/(11*31) -> 0 | L7: =L8/(11*30) -> 0 | M7: =M8/(11*31) -> 0 | N7: =N8/(11*365) -> 0.19576588
A8: 販売客室数 | B8: 89 | C8: 111 | D8: 212 | E8: 151 | F8: 84 | G8: 65 | H8: 26 | I8: 48 | J8: 0 | K8: 0 | L8: 0 | M8: 0 | N8: =SUM(B8:M8) -> 786
A9: 利用人数 | B9: 89 | C9: 111 | D9: 212 | E9: 151 | F9: 84 | G9: 65 | H9: 26 | I9: 48 | J9: 0 | K9: 0 | L9: 0 | M9: 0 | N9: =SUM(B9:M9) -> 786
A10: 客室単価 | B10: =B4/B8 -> 2820.2247 | C10: =C4/C8 -> 2774.7748 | D10: =D4/D8 -> 3070.7547 | E10: =E4/E8 -> 3013.245 | F10: =F4/F8 -> 3238.0952 | G10: =G4/G8 -> 3000 | H10: =H4/H8 -> 3000 | I10: =I4/I8 -> 2500 | ... M10: =M4/M8 -> #DIV/0! | N10: =AVERAGE(B10:M10) -> #DIV/0!
A11: 客単価 | B11: =B4/B9 -> 2820.2247 | C11: =C4/C9 -> 2774.7748 | D11: =D4/D9 -> 3070.7547 | E11: =E4/E9 -> 3013.245 | F11: =F4/F9 -> 3238.0952 | G11: =G4/G9 -> 3000 | H11: =H4/H9 -> 3000 | I11: =I4/I9 -> 2500 | ... M11: =M4/M9 -> #DIV/0! | N11: =AVERAGE(B11:M11) -> #DIV/0!
A12: 昨年売上 | B12: 142000 | C12: 506000 | D12: 517000 | E12: 636000 | F12: 441000 | G12: 421980 | H12: 310000 | I12: 246000 | J12: 96000 | K12: 228000 | L12: 450000 | M12: 323000 | N12: 4316980
A13: 昨年対比 | B13: =B4/B12 -> 1.7676056 | C13: =C4/C12 -> 0.60869565 | D13: =D4/D12 -> 1.2591876 | E13: =E4/E12 -> 0.71540881 | F13: =F4/F12 -> 0.61678005 | G13: =G4/G12 -> 0.46210721 | H13: =H4/H12 -> 0.2516129 | I13: =I4/I12 -> 0.48780488 | ... N13: =N4/N12 -> 0.53972916
A14: 経費実績 | N14: =SUM(B14:M14) -> 0
A15: 売上-経費 | B15: =B4-B14 -> 251000 | C15: =C4-C14 -> 308000 | D15: =D4-D14 -> 651000 | E15: =E4-E14 -> 455000 | F15: =F4-F14 -> 272000 | G15: =G4-G14 -> 195000 | H15: =H4-H14 -> 78000 | I15: =I4-I14 -> 120000 | ... M15: =M4-M14 -> 0 | N15: =SUM(B15:M15) -> 2330000
A17: 壱番館 | B17: １月 | C17: ２月 | D17: ３月 | E17: ４月 | F17: ５月 | G17: ６月 | H17: ７月 | I17: ８月 | J17: ９月 | K17: １０月 | L17: １１月 | M17: １２月 | N17: 合計
A18: 目標売上 | B18: 276000 | C18: 162000 | D18: 189000 | E18: 103500 | F18: 164000 | G18: 165000 | H18: 127500 | I18: 217000 | J18: 142500 | K18: 0 | L18: 183000 | M18: 78000 | N18: 1807500
A19: 売上進捗 | B19: 155000 | C19: 110500 | D19: 66000 | E19: 101400 | F19: 24000 | G19: 45000 | H19: 0 | I19: 0 | J19: 0 | K19: 0 | L19: 0 | M19: 0 | N19: =SUM(B19:M19) -> 501900
A20: 達成率 | B20: =B19/B18 -> 0.5615942 | C20: =C19/C18 -> 0.68209877 | D20: =D19/D18 -> 0.34920635 | E20: =E19/E18 -> 0.97971014 | F20: =F19/F18 -> 0.14634146 | G20: =G19/G18 -> 0.27272727 | H20: =H19/H18 -> 0 | I20: =I19/I18 -> 0 | ... N20: =N19/N18 -> 0.27767635
A21: 差異 | B21: =B19-B18 -> -121000 | C21: =C19-C18 -> -51500 | D21: =D19-D18 -> -123000 | E21: =E19-E18 -> -2100 | F21: =F19-F18 -> -140000 | G21: =G19-G18 -> -120000 | H21: =H19-H18 -> -127500 | I21: =I19-I18 -> -217000 | ... M21: =M19-M18 -> -78000 | N21: =SUM(B21:M21) -> -1305600
A22: 稼働率 | B22: =B23/(6*31) -> 0.27956989 | C22: =C23/(6*29) -> 0.22988506 | D22: 0.47 | E22: =E23/(6*30) -> 0.2 | F22: =F23/(6*31) -> 0.043010753 | G22: =G23/(6*30) -> 0.1 | H22: =H23/(6*31) -> 0 | I22: =I23/(6*31) -> 0 | J22: =J23/(6*30) -> 0 | K22: =K23/(6*31) -> 0 | L22: =L23/(6*30) -> 0 | M22: =M23/(6*31) -> 0 | N22: =N23/(6*365) -> 0.080365297
A23: 販売客室数 | B23: 52 | C23: 40 | D23: 22 | E23: 36 | F23: 8 | G23: 18 | H23: 0 | I23: 0 | J23: 0 | K23: 0 | L23: 0 | M23: 0 | N23: =SUM(B23:M23) -> 176
A24: 利用人数 | B24: 52 | C24: 43 | D24: 22 | E24: 36 | F24: 8 | G24: 18 | H24: 0 | I24: 0 | J24: 0 | K24: 0 | L24: 0 | M24: 0 | N24: =SUM(B24:M24) -> 179
A25: 客室単価 | B25: =B19/B23 -> 2980.7692 | C25: 52 | D25: =D19/D23 -> 3000 | E25: =E19/E23 -> 2816.6667 | F25: =F19/F23 -> 3000 | G25: =G19/G23 -> 2500 | H25: =H19/H23 -> #DIV/0! | I25: =I19/I23 -> #DIV/0! | J25: =J19/J23 -> #DIV/0! | K25: =K19/K23 -> #DIV/0! | ... M25: =M19/M23 -> #DIV/0! | N25: =AVERAGE(B25:M25) -> #DIV/0!
A26: 客単価 | B26: =B19/B24 -> 2980.7692 | C26: =C19/C24 -> 2569.7674 | D26: =D19/D24 -> 3000 | E26: =E19/E24 -> 2816.6667 | F26: =F19/F24 -> 3000 | G26: =G19/G24 -> 2500 | H26: =H19/H24 -> #DIV/0! | I26: =I19/I24 -> #DIV/0! | ... M26: =M19/M24 -> #DIV/0! | N26: =AVERAGE(B26:M26) -> #DIV/0!
A27: 昨年売上 | B27: 276000 | C27: 162000 | D27: 189000 | E27: 103500 | F27: 164000 | G27: 165000 | H27: 127500 | I27: 217000 | J27: 142500 | K27: 0 | L27: 183000 | M27: 78000 | N27: 1807500
A28: 昨年対比 | B28: =B19/B27 -> 0.5615942 | C28: =C19/C27 -> 0.68209877 | D28: =D19/D27 -> 0.34920635 | E28: =E19/E27 -> 0.97971014 | F28: =F19/F27 -> 0.14634146 | G28: =G19/G27 -> 0.27272727 | H28: =H19/H27 -> 0 | I28: =I19/I27 -> 0 | ... N28: =N19/N27 -> 0.27767635
A29: 経費実績 | B29: =C99 -> -50293 | C29: =D99 -> -41060 | D29: =E99 -> -71751 | E29: =F99 -> 0 | F29: =G99 -> 0 | G29: =H99 -> 0 | H29: =I99 -> 0 | I29: =J99 -> 0 | ... M29: =N99 -> 0 | N29: =SUM(B29:M29) -> -163104
A30: 売上-経費 | B30: =B19-B29 -> 205293 | C30: =C19-C29 -> 151560 | D30: =D19-D29 -> 137751 | E30: =E19-E29 -> 101400 | F30: =F19-F29 -> 24000 | G30: =G19-G29 -> 45000 | H30: =H19-H29 -> 0 | I30: =I19-I29 -> 0 | ... M30: =M19-M29 -> 0 | N30: =SUM(B30:M30) -> 665004
A32: 弐番館 | B32: １月 | C32: ２月 | D32: ３月 | E32: ４月 | F32: ５月 | G32: ６月 | H32: ７月 | I32: ８月 | J32: ９月 | K32: １０月 | L32: １１月 | M32: １２月 | N32: 合計
A33: 目標売上 | B33: 60000 | C33: 121500 | D33: 69000 | E33: 58000 | F33: 9000 | G33: 108000 | H33: 63000 | I33: 56500 | J33: 44000 | K33: 57000 | L33: 48000 | M33: 54500 | N33: 748500
A34: 売上進捗 | B34: 0 | C34: 42500 | D34: 0 | E34: 90000 | F34: 93000 | G34: 46000 | H34: 57000 | I34: 75000 | J34: 0 | K34: 0 | L34: 0 | M34: 0 | N34: =SUM(B34:M34) -> 403500
A35: 達成率 | B35: =B34/B33 -> 0 | C35: =C34/C33 -> 0.34979424 | D35: =D34/D33 -> 0 | E35: =E34/E33 -> 1.5517241 | F35: =F34/F33 -> 10.333333 | G35: =G34/G33 -> 0.42592593 | H35: =H34/H33 -> 0.9047619 | I35: =I34/I33 -> 1.3274336 | ... N35: =N34/N33 -> 0.53907816
A36: 売上目標差異 | B36: =B34-B33 -> -60000 | C36: =C34-C33 -> -79000 | D36: =D34-D33 -> -69000 | E36: =E34-E33 -> 32000 | F36: =F34-F33 -> 84000 | G36: =G34-G33 -> -62000 | H36: =H34-H33 -> -6000 | I36: =I34-I33 -> 18500 | ... M36: =M34-M33 -> -54500 | N36: =SUM(B36:M36) -> -345000
A37: 稼働率 | B37: =B38/(2*31) -> 0 | C37: =C38/(2*29) -> 0.29310345 | D37: =D38/(2*31) -> 0 | E37: =E38/(2*30) -> 0.5 | F37: =F38/(2*31) -> 0.5 | G37: =G38/(2*30) -> 0.2 | H37: =H38/(2*31) -> 0.30645161 | I37: =I38/(2*31) -> 0.48387097 | J37: =J38/(2*30) -> 0 | K37: =K38/(2*31) -> 0 | L37: =L38/(2*30) -> 0 | M37: =M38/(2*31) -> 0 | N37: =N38/(2*365) -> 0.19041096
A38: 販売客室数 | B38: 0 | C38: 17 | D38: 0 | E38: 30 | F38: 31 | G38: 12 | H38: 19 | I38: 30 | J38: 0 | K38: 0 | L38: 0 | M38: 0 | N38: =SUM(B38:M38) -> 139
A39: 利用人数 | B39: 0 | C39: 17 | D39: 0 | E39: 30 | F39: 31 | G39: 12 | H39: 19 | I39: 30 | J39: 0 | K39: 0 | L39: 0 | M39: 0 | N39: =SUM(B39:M39) -> 139
A40: 客室単価 | B40: =B34/B38 -> #DIV/0! | C40: =C34/C38 -> 2500 | D40: =D34/D38 -> #DIV/0! | E40: =E34/E38 -> 3000 | F40: =F34/F38 -> 3000 | G40: =G34/G38 -> 3833.3333 | H40: =H34/H38 -> 3000 | I40: =I34/I38 -> 2500 | ... M40: =M34/M38 -> #DIV/0! | N40: =AVERAGE(B40:M40) -> #DIV/0!
A41: 客単価 | B41: =B34/B39 -> #DIV/0! | C41: =C34/C39 -> 2500 | D41: =D34/D39 -> #DIV/0! | E41: =E34/E39 -> 3000 | F41: =F34/F39 -> 3000 | G41: =G34/G39 -> 3833.3333 | H41: =H34/H39 -> 3000 | I41: =I34/I39 -> 2500 | ... M41: =M34/M39 -> #DIV/0! | N41: =AVERAGE(B41:M41) -> #DIV/0!
A42: 昨年売上 | B42: 60000 | C42: 121500 | D42: 69000 | E42: 58000 | F42: 9000 | G42: 108000 | H42: 63000 | I42: 56500 | J42: 44000 | K42: 57000 | L42: 48000 | M42: 54500 | N42: 748500
A43: 昨年対比 | B43: =B34/B42 -> 0 | C43: =C34/C42 -> 0.34979424 | D43: =D34/D42 -> 0 | E43: =E34/E42 -> 1.5517241 | F43: =F34/F42 -> 10.333333 | G43: =G34/G42 -> 0.42592593 | H43: =H34/H42 -> 0.9047619 | I43: =I34/I42 -> 1.3274336 | ... N43: =N34/N42 -> 0.53907816
A44: 経費実績 | B44: =C109 -> -46423 | C44: =D109 -> -31962 | D44: =E109 -> -55726 | E44: =F109 -> 0 | F44: =G109 -> 0 | G44: =H109 -> 0 | H44: =I109 -> 0 | I44: =J109 -> 0 | ... M44: =N109 -> 0 | N44: =SUM(B44:M44) -> -134111
A45: 売上-経費 | B45: =B34-B44 -> 46423 | C45: =C34-C44 -> 74462 | D45: =D34-D44 -> 55726 | E45: =E34-E44 -> 90000 | F45: =F34-F44 -> 93000 | G45: =G34-G44 -> 46000 | H45: =H34-H44 -> 57000 | I45: =I34-I44 -> 75000 | ... M45: =M34-M44 -> 0 | N45: =SUM(B45:M45) -> 537611
A47: Otake | B47: １月 | C47: ２月 | D47: ３月 | E47: ４月 | F47: ５月 | G47: ６月 | H47: ７月 | I47: ８月 | J47: ９月 | K47: １０月 | L47: １１月 | M47: １２月 | N47: 合計
A48: 目標売上 | B48: 0 | C48: 0 | D48: 0 | E48: 0 | F48: 15000 | G48: 0 | H48: 0 | I48: 77500 | J48: 132500 | K48: 75000 | L48: 35000 | M48: 77500 | N48: =SUM(B48:M48) -> 412500
A49: 売上進捗 | B49: 77500 | C49: 77500 | D49: 80000 | E49: 105000 | F49: 77500 | G49: 72500 | H49: 0 | I49: 0 | J49: 0 | K49: 0 | L49: 0 | M49: 0 | N49: =SUM(B49:M49) -> 490000
A50: 達成率 | B50: =B49/B48 -> #DIV/0! | C50: =C49/C48 -> #DIV/0! | D50: =D49/D48 -> #DIV/0! | E50: =E49/E48 -> #DIV/0! | F50: =F49/F48 -> 5.1666667 | G50: =G49/G48 -> #DIV/0! | H50: =H49/H48 -> #DIV/0! | I50: =I49/I48 -> 0 | ... N50: =N49/N48 -> 1.1878788
A51: 売上目標差異 | B51: =B49-B48 -> 77500 | C51: =C49-C48 -> 77500 | D51: =D49-D48 -> 80000 | E51: =E49-E48 -> 105000 | F51: =F49-F48 -> 62500 | G51: =G49-G48 -> 72500 | H51: =H49-H48 -> 0 | I51: =I49-I48 -> -77500 | ... M51: =M49-M48 -> -77500 | N51: =SUM(B51:M51) -> 77500
A52: 稼働率 | B52: =B53/(2*31) -> 0.5 | C52: =C53/(2*29) -> 0.53448276 | D52: =D53/(2*31) -> 0.5 | E52: =E53/(2*30) -> 0.7 | F52: =F53/(2*31) -> 0.5 | G52: =G53/(2*30) -> 0.48333333 | H52: =H53/(2*31) -> 0 | I52: =I53/(2*31) -> 0 | J52: =J53/(2*30) -> 0 | K52: =K53/(2*31) -> 0 | L52: =L53/(2*30) -> 0 | M52: =M53/(2*31) -> 0 | N52: =N53/(2*365) -> 0.26712329
A53: 販売客室数 | B53: 31 | C53: 31 | D53: 31 | E53: 42 | F53: 31 | G53: 29 | H53: 0 | I53: 0 | J53: 0 | K53: 0 | L53: 0 | M53: 0 | N53: =SUM(B53:M53) -> 195
A54: 利用人数 | B54: 31 | C54: 31 | D54: 31 | E54: 42 | F54: 31 | G54: 29 | H54: 0 | I54: 0 | J54: 0 | K54: 0 | L54: 0 | M54: 0 | N54: =SUM(B54:M54) -> 195
A55: 客室単価 | B55: =B49/B53 -> 2500 | C55: =C49/C53 -> 2500 | D55: =D49/D53 -> 2580.6452 | E55: =E49/E53 -> 2500 | F55: =F49/F53 -> 2500 | G55: =G49/G53 -> 2500 | H55: =H49/H53 -> #DIV/0! | I55: =I49/I53 -> #DIV/0! | ... N55: =N49/N53 -> 2512.8205
A56: 客単価 | B56: =B49/B54 -> 2500 | C56: =C49/C54 -> 2500 | D56: =D49/D54 -> 2580.6452 | E56: =E49/E54 -> 2500 | F56: =F49/F54 -> 2500 | G56: =G49/G54 -> 2500 | H56: =H49/H54 -> #DIV/0! | I56: =I49/I54 -> #DIV/0! | ... N56: =N49/N54 -> 2512.8205
A57: 昨年売上 | B57: 0 | C57: 0 | D57: 0 | E57: 0 | F57: 15000 | G57: 0 | H57: 0 | I57: 77500 | J57: 132500 | K57: 75000 | L57: 35000 | M57: 77500 | N57: =SUM(B57:M57) -> 412500
A58: 昨年対比 | B58: =B49/B57 -> #DIV/0! | C58: =C49/C57 -> #DIV/0! | D58: =D49/D57 -> #DIV/0! | E58: =E49/E57 -> #DIV/0! | F58: =F49/F57 -> 5.1666667 | G58: =G49/G57 -> #DIV/0! | H58: =H49/H57 -> #DIV/0! | I58: =I49/I57 -> 0 | ... N58: =N49/N57 -> 1.1878788
A59: 経費実績 | B59: =C119 -> -19550 | C59: =D119 -> -16980 | D59: =E119 -> -19594 | E59: =F119 -> 0 | F59: =G119 -> 0 | G59: =H119 -> 0 | H59: =I119 -> 0 | I59: =J119 -> 0 | ... M59: =N119 -> 0
A60: 売上-経費 | B60: =B49-B59 -> 97050 | C60: =C49-C59 -> 94480 | D60: =D49-D59 -> 99594 | E60: =E49-E59 -> 105000 | F60: =F49-F59 -> 77500 | G60: =G49-G59 -> 72500 | H60: =H49-H59 -> 0 | I60: =I49-I59 -> 0 | ... M60: =M49-M59 -> 0
A62: Takehara | B62: １月 | C62: ２月 | D62: ３月 | E62: ４月 | F62: ５月 | G62: ６月 | H62: ７月 | I62: ８月 | J62: ９月 | K62: １０月 | L62: １１月 | M62: １２月 | N62: 合計
A63: 目標売上 | B63: 10960 | C63: 1494 | D63: 293780 | E63: 117300 | F63: 42340 | G63: 24900 | H63: 105380 | I63: 77500 | J63: 45890 | K63: 76000 | L63: 39500 | M63: 32480 | N63: 867524
A64: 売上進捗 | B64: 46000 | C64: 34500 | D64: 63000 | E64: 157500 | F64: 106000 | G64: 0 | H64: 0 | I64: 0 | J64: 0 | K64: 0 | L64: 0 | M64: 0 | N64: =SUM(B64:M64) -> 407000
A65: 達成率 | B65: =B64/B63 -> 4.1970803 | C65: =C64/C63 -> 23.092369 | D65: =D64/D63 -> 0.21444618 | E65: =E64/E63 -> 1.342711 | F65: =F64/F63 -> 2.5035427 | G65: =G64/G63 -> 0 | H65: =H64/H63 -> 0 | I65: =I64/I63 -> 0 | ... N65: =N64/N63 -> 0.46915129
A66: 売上目標差異 | B66: =B64-B63 -> 35040 | C66: =C64-C63 -> 33006 | D66: =D64-D63 -> -230780 | E66: =E64-E63 -> 40200 | F66: =F64-F63 -> 63660 | G66: =G64-G63 -> -24900 | H66: =H64-H63 -> -105380 | I66: =I64-I63 -> -77500 | ... M66: =M64-M63 -> -32480 | N66: =SUM(B66:M66) -> -460524
A67: 稼働率 | B67: =B68/(6*31) -> 0.048387097 | C67: =C68/(6*29) -> 0.045977011 | D67: =D68/(6*31) -> 0.075268817 | E67: =E68/(6*30) -> 0.19444444 | F67: =F68/(6*31) -> 0.12365591 | G67: =G68/(6*30) -> 0 | H67: =H68/(6*31) -> 0 | I67: =I68/(4*31) -> 0 | J67: =J68/(3*30) -> 0 | K67: =K68/(3*31) -> 0 | L67: =L68/(3*30) -> 0 | M67: =M68/(3*31) -> 0 | N67: =N68/(2*365) -> 0.12191781
A68: 販売客室数 | B68: 9 | C68: 8 | D68: 14 | E68: 35 | F68: 23 | G68: 0 | H68: 0 | I68: 0 | J68: 0 | K68: 0 | L68: 0 | M68: 0 | N68: =SUM(B68:M68) -> 89
A69: 利用人数 | B69: 12 | C69: 8 | D69: 14 | E69: 35 | F69: 24 | G69: 0 | H69: 0 | I69: 0 | J69: 0 | K69: 0 | L69: 0 | M69: 0 | N69: =SUM(B69:M69) -> 93
A70: 客室単価 | B70: =B64/B68 -> 5111.1111 | C70: =C64/C68 -> 4312.5 | D70: =D64/D68 -> 4500 | E70: =E64/E68 -> 4500 | F70: =F64/F68 -> 4608.6957 | G70: =G64/G68 -> #DIV/0! | H70: =H64/H68 -> #DIV/0! | I70: =I64/I68 -> #DIV/0! | ... N70: =N64/N68 -> 4573.0337
A71: 客単価 | B71: =B64/B69 -> 3833.3333 | C71: =C64/C69 -> 4312.5 | D71: =D64/D69 -> 4500 | E71: =E64/E69 -> 4500 | F71: =F64/F69 -> 4416.6667 | G71: =G64/G69 -> #DIV/0! | H71: =H64/H69 -> #DIV/0! | I71: =I64/I69 -> #DIV/0! | ... N71: =N64/N69 -> 4376.3441
A72: 昨年売上 | B72: 10960 | C72: 1494 | D72: 293780 | E72: 117300 | F72: 42340 | G72: 24900 | H72: 105380 | I72: 77500 | J72: 45890 | K72: 76000 | L72: 39500 | M72: 32480 | N72: 867524
A73: 昨年対比 | B73: =B64/B72 -> 4.1970803 | C73: =C64/C72 -> 23.092369 | D73: =D64/D72 -> 0.21444618 | E73: =E64/E72 -> 1.342711 | F73: =F64/F72 -> 2.5035427 | G73: =G64/G72 -> 0 | H73: =H64/H72 -> 0 | I73: =I64/I72 -> 0 | ... N73: =N64/N72 -> 0.46915129
A74: 経費実績 | B74: =C133 -> 0 | C74: =D133 -> 0 | D74: =E133 -> 0 | E74: =F133 -> 0 | F74: =G133 -> 0 | G74: =H133 -> 0 | H74: =I133 -> 0 | I74: =J133 -> 0 | ... M74: =N133 -> 0
A75: 売上-経費 | B75: =B64-B74 -> 46000 | C75: =C64-C74 -> 34500 | D75: =D64-D74 -> 63000 | E75: =E64-E74 -> 157500 | F75: =F64-F74 -> 106000 | G75: =G64-G74 -> 0 | H75: =H64-H74 -> 0 | I75: =I64-I74 -> 0 | ... M75: =M64-M74 -> 0
A78: 各施設収支一覧
A79: 内訳 | C79: １月 | D79: ２月 | E79: ３月 | F79: ４月 | G79: ５月 | H79: ６月 | I79: ７月 | J79: ８月 | K79: ９月 | L79: １０月 | M79: １１月 | N79: １２月 | O79: 合計
A80: TAKAYA | B80: 売上 | C80: =B4 -> 251000 | D80: =C4 -> 308000 | E80: =D4 -> 651000 | F80: =E4 -> 455000 | G80: =F4 -> 272000 | H80: =G4 -> 195000 | I80: =H4 -> 78000 | J80: =I4 -> 120000 | ... N80: =M4 -> 0
B81: 家賃 | C81: 33912 | D81: 121984 | E81: 93479 | O81: =SUM(C81:N81) -> 249375
B82: 電気 | C82: 88260 | D82: 43697 | E82: 42829 | O82: =SUM(C82:N82) -> 174786
B83: ガス | C83: 84510 | D83: 67907 | E83: 41807 | O83: =SUM(C83:N83) -> 194224
B84: 水道 | C84: 34760 | D84: 0 | E84: 34760 | O84: =SUM(C84:N84) -> 69520
B85: 清掃費 | C85: 6000 | D85: 28000 | E85: 10000 | O85: =SUM(C85:N85) -> 44000
B86: 修繕費 | C86: 0 | D86: 0 | E86: 0 | F86: 0 | G86: 0 | H86: 0 | I86: 0 | J86: 0 | K86: 0 | L86: 0 | M86: 0 | N86: 0 | O86: =SUM(C86:N86) -> 0
B87: 通信費 （Wi-Fi） | C87: 66000 | D87: 66000 | E87: 66000 | F87: 66000 | O87: =SUM(C87:N87) -> 264000
B88: 経費合計 | C88: =SUM(C81:C87) -> 313442 | D88: =SUM(D81:D87) -> 327588 | E88: =SUM(E81:E87) -> 288875 | F88: =SUM(F81:F87) -> 66000 | G88: =SUM(G81:G87) -> 0 | H88: =SUM(H81:H87) -> 0 | I88: =SUM(I81:I87) -> 0 | J88: =SUM(J81:J87) -> 0 | ... N88: =SUM(N81:N87) -> 0
B89: GR 収入額 | C89: =C80-C88 -> -62442 | D89: =D80-D88 -> -19588 | E89: =E80-E88 -> 362125 | F89: =F81 -> 0 | G89: =G81 -> 0 | H89: =H81 -> 0 | I89: =I81 -> 0 | J89: =J81 -> 0 | K89: =K81 -> 0 | L89: =L81 -> 0 | M89: =M81 -> 0 | N89: =N81 -> 0 | O89: =SUM(O81:O87) -> 995905
A90: 壱番館 | B90: 売上 | C90: =B19 -> 155000 | D90: =C19 -> 110500 | E90: =D19 -> 66000 | F90: =E19 -> 101400 | G90: =F19 -> 24000 | H90: =G19 -> 45000 | I90: =H19 -> 0 | J90: =I19 -> 0 | ... N90: =M19 -> 0
B91: 家賃 | C91: 79372 | D91: 52920 | E91: 27596 | O91: =SUM(C91:N91) -> 159888
B92: 電気 | C92: 58265 | D92: 28735 | E92: 26372
B93: ガス | C93: ? | D93: 24369 | E93: 20927
B94: 水道 | C94: 22120 | D94: 0 | E94: 22120
B95: 清掃費 | C95: 10800 | D95: 10800 | E95: 6000
B96: 修繕費 | C96: 0 | D96: 0 | E96: 0 | O96: =SUM(C96:N96) -> 0
B97: 通信費 （Wi-Fi） | C97: 34736 | D97: 34736 | E97: 34736 | F97: 34736 | O97: =SUM(C97:N97) -> 138944
B98: 経費合計 | C98: =SUM(C91:C97) -> 205293 | D98: =SUM(D91:D97) -> 151560 | E98: =SUM(E91:E97) -> 137751 | F98: =SUM(F91:F97) -> 34736 | G98: =SUM(G91:G97) -> 0 | H98: =SUM(H91:H97) -> 0 | I98: =SUM(I91:I97) -> 0 | J98: =SUM(J91:J97) -> 0 | ... N98: =SUM(N91:N97) -> 0
B99: GR 収入額 | C99: =C90-C98 -> -50293 | D99: =D90-D98 -> -41060 | E99: =E90-E98 -> -71751 | F99: =F91 -> 0 | G99: =G91 -> 0 | H99: =H91 -> 0 | I99: =I91 -> 0 | J99: =J91 -> 0 | K99: =K91 -> 0 | L99: =L91 -> 0 | M99: =M91 -> 0 | N99: =N91 -> 0 | O99: =SUM(O91:O97) -> 298832
A100: 弐番館 | B100: 売上 | C100: =B34 -> 0 | D100: =C34 -> 42500 | E100: =D34 -> 0 | F100: =E34 -> 90000 | G100: =F34 -> 93000 | H100: =G34 -> 46000 | I100: =H34 -> 57000 | J100: =I34 -> 75000 | ... N100: =M34 -> 0
B101: 家賃 | C101: 17300 | D101: 41685 | E101: 7148 | O101: =SUM(C101:N101) -> 66133
B102: 電気 | C102: 7714 | D102: 12218 | E102: 14159
B103: ガス | C103: ? | D103: 4270 | E103: 10610
B104: 水道 | C104: 6320 | D104: 0 | E104: 6320
B105: 清掃費 | C105: 1200 | D105: 2400 | E105: 3600
B106: 修繕費 | C106: 0 | D106: 0 | E106: 0 | O106: =SUM(C106:N106) -> 0
...

Sheet 竹原
A1: GR竹原マンスリー 及び 海の駅 売上推移表
D2: 1月 | E2: 2月 | F2: 3月 | G2: 4月 | H2: 5月 | I2: 6月 | J2: 7月 | K2: 8月 | L2: 9月 | M2: 10月 | N2: 11月 | O2: 12月 | P2: 合計
A3: 総売上高(GOR) | D3: =D4+D18+D28+D30+D34+D38 -> 1247037 | E3: =E4+E18+E28+E30+E34+E38 -> 1238472 | F3: =F4+F18+F28+F30+F34+F38 -> 1370148 | G3: =G4+G18+G28+G30+G34+G38 -> 1202444 | H3: =H4+H18+H28+H30+H34+H38 -> 789000 | I3: =I4+I18+I28+I30+I34+I38 -> 683000 | J3: =J4+J18+J28+J30+J34+J38 -> 683000 | K3: =K4+K18+K28+K30+K34+K38 -> 683000 | ... P3: =P4+P18+P28+P30+P34+P38 -> 407000
A4: マンスリー売上 | D4: =マンスリー部門!B64 -> 46000 | E4: 16500 | F4: =マンスリー部門!D64 -> 63000 | G4: =マンスリー部門!E64 -> 157500 | H4: =マンスリー部門!F64 -> 106000 | I4: =マンスリー部門!G64 -> 0 | J4: =マンスリー部門!H64 -> 0 | K4: =マンスリー部門!I64 -> 0 | L4: =マンスリー部門!J64 -> 0 | M4: =マンスリー部門!K64 -> 0 | ... P4: =マンスリー部門!N64 -> 407000
A5: 販売室数 | D5: =マンスリー部門!B68 -> 9 | E5: 4 | F5: =マンスリー部門!D68 -> 14 | G5: =マンスリー部門!E68 -> 35 | H5: =マンスリー部門!F68 -> 23 | I5: =マンスリー部門!G68 -> 0 | J5: =マンスリー部門!H68 -> 0 | K5: =マンスリー部門!I68 -> 0 | L5: =マンスリー部門!J68 -> 0 | M5: =マンスリー部門!K68 -> 0 | ... P5: =マンスリー部門!N68 -> 89
A6: 販売人数 | D6: =マンスリー部門!B69 -> 12 | E6: 4 | F6: =マンスリー部門!D69 -> 14 | G6: =マンスリー部門!E69 -> 35 | H6: =マンスリー部門!F69 -> 24 | I6: =マンスリー部門!G69 -> 0 | J6: =マンスリー部門!H69 -> 0 | K6: =マンスリー部門!I69 -> 0 | L6: =マンスリー部門!J69 -> 0 | M6: =マンスリー部門!K69 -> 0 | ... P6: =マンスリー部門!N69 -> 93
A7: 大人
A8: 子供
A9: 販売可能室数
A10: 販売可能人員
A11: 客室稼働率(Occ)
A12: 人員稼働率
A13: 1室平均稼働人員
A14: ADR
A15: APR
A16: Rev.PAR
A18: レストラン 売 上 | D18: 281140 | E18: 294620 | F18: 388608 | G18: 350644
A19: 会計数 | D19: 128 | E19: 121 | F19: 180 | G19: 158
A20: 会計単価 | D20: 2196 | E20: 2435 | F20: 2159 | G20: 2219
A21: 客数 | D21: 188 | E21: 196 | F21: 329 | G21: 230
A22: 客単価 | D22: 1495 | E22: 1503 | F22: 1181 | G22: 1525
A23: 商品数 | D23: 311 | E23: 337 | F23: 453 | G23: 435
A24: 現金 | D24: 187940 | E24: 206410 | F24: 271730 | G24: 288744
A25: 現金その他 | D25: 93200 | E25: 88210 | F25: 116878 | G25: 61900
A26: 割引額 | D26: 0
A28: 駐車場代
A30: 委託料 | D30: =SUM(D31:D32) -> 683000 | E30: =SUM(E31:E32) -> 683000 | F30: =SUM(F31:F32) -> 683000 | G30: =SUM(G31:G32) -> 683000 | H30: =SUM(H31:H32) -> 683000 | I30: =SUM(I31:I32) -> 683000 | J30: =SUM(J31:J32) -> 683000 | K30: =SUM(K31:K32) -> 683000 | ... P30: =SUM(P31:P32) -> 0
A31: 内訳 | B31: 海の駅指定管理（竹原市） | D31: 650000 | E31: 650000 | F31: 650000 | G31: 650000 | H31: 650000 | I31: 650000 | J31: 650000 | K31: 650000 | L31: 650000 | M31: 650000 | N31: 650000 | O31: 650000
B32: 駐車場管理（アマノ） | D32: 33000 | E32: 33000 | F32: 33000 | G32: 33000 | H32: 33000 | I32: 33000 | J32: 33000 | K32: 33000 | L32: 33000 | M32: 33000 | N32: 33000 | O32: 33000
A34: 利用料 | D34: =D35+D36 -> 20700 | E34: =E35+E36 -> 16850 | F34: =F35+F36 -> 27700 | G34: =G35+G36 -> 11300 | H34: =H35+H36 -> 0 | I34: =I35+I36 -> 0 | J34: =J35+J36 -> 0 | K34: =K35+K36 -> 0 | ... P34: =P35+P36 -> 0
A35: 内訳 | B35: 交流ｽﾍﾟｰｽ | D35: 20300 | E35: 16850 | F35: 27300 | G35: 10700
B36: ﾜｰｸｽﾍﾟｰｽ | D36: 400 | E36: 0 | F36: 400 | G36: 600
A38: 家賃請求 | D38: =SUM(D39:D44) -> 216197 | E38: =SUM(E39:E44) -> 227502 | F38: =SUM(F39:F44) -> 207840 | G38: =SUM(G39:G44) -> 0 | H38: =SUM(H39:H44) -> 0 | I38: =SUM(I39:I44) -> 0 | J38: =SUM(J39:J44) -> 0 | K38: =SUM(K39:K44) -> 0 | ... P38: =SUM(P39:P44) -> 0
A39: 内訳 | B39: ﾌｪﾘｰ同盟 | D39: 18542 | E39: 19484 | F39: 17846
B40: 大崎汽船 | D40: 35555 | E40: 37363 | F40: 34219
B41: 竹原海運 | D41: 72821 | E41: 75961 | F41: 70499
B42: 契島運輸 | D42: 10594 | E42: 10909 | F42: 10360
B43: 前川酒店 | D43: 78685 | E43: 83785 | F43: 74916
B44: ﾚｽﾄﾗﾝ | D44: 0
D46: 1月 | E46: 2月 | F46: 3月 | G46: 4月 | H46: 5月 | I46: 6月 | J46: 7月 | K46: 8月 | L46: 9月 | M46: 10月 | N46: 11月 | O46: 12月 | P46: 合計
A47: 総売上高 | D47: =D3 -> 1247037 | E47: =E3 -> 1238472 | F47: =F3 -> 1370148 | G47: =G3 -> 1202444 | H47: =H3 -> 789000 | I47: =I3 -> 683000 | J47: =J3 -> 683000 | K47: =K3 -> 683000 | ... P47: =P3 -> 407000
A48: 経費 | D48: 1603560 | E48: 1713674
A49: 差引収支 | D49: =D47-D48 -> -356523 | E49: =E47-E48 -> -475202 | F49: =F47-F48 -> 1370148 | G49: =G47-G48 -> 1202444 | H49: =H47-H48 -> 789000 | I49: =I47-I48 -> 683000 | J49: =J47-J48 -> 683000 | K49: =K47-K48 -> 683000 | ... P49: =P47-P48 -> 407000

Sheet サウナ
A1: サウナ | B1: １月 | C1: ２月 | D1: ３月 | E1: ４月 | F1: ５月 | G1: ６月 | H1: ７月 | I1: ８月 | J1: ９月 | K1: １０月 | L1: １１月 | M1: １２月 | N1: 合計
A2: 目標売上 | B2: 0 | C2: 134014 | D2: 118994 | E2: 83911 | F2: 90367 | G2: 116684 | H2: 101322 | I2: 186370 | J2: 56609 | K2: 156028 | L2: 71628 | M2: 153076 | N2: 1269003
A3: 売上進捗 | B3: 0 | C3: 113218 | D3: 134706 | E3: 121831 | F3: 36276 | G3: 0 | H3: 0 | I3: 0 | J3: 0 | K3: 0 | L3: 0 | M3: 0 | N3: =SUM(B3:M3) -> 406031
A4: 達成率 | B4: =B3/B2 -> #DIV/0! | C4: =C3/C2 -> 0.84482218 | D4: =D3/D2 -> 1.1320403 | E4: =E3/E2 -> 1.4519074 | F4: =F3/F2 -> 0.40142973 | G4: =G3/G2 -> 0 | H4: =H3/H2 -> 0 | I4: =I3/I2 -> 0 | ... N4: =N3/N2 -> 0.31996063
A5: 予約件数 | B5: 0 | C5: 4 | D5: 5 | E5: 4 | F5: 1 | G5: 0 | H5: 0 | I5: 0 | J5: 0 | K5: 0 | L5: 0 | M5: 0 | N5: =SUM(B5:M5) -> 14
A6: 利用人数 | B6: 0 | C6: 8 | D6: 10 | E6: 9 | F6: 2 | G6: 0 | H6: 0 | I6: 0 | J6: 0 | K6: 0 | L6: 0 | M6: 0 | N6: =SUM(B6:M6) -> 29
A7: 客単価 | B7: =B3/B6 -> #DIV/0! | C7: =C3/C6 -> 14152.25 | D7: =D3/D6 -> 13470.6 | E7: =E3/E6 -> 13536.778 | F7: =F3/F6 -> 18138 | G7: =G3/G6 -> #DIV/0! | H7: =H3/H6 -> #DIV/0! | I7: =I3/I6 -> #DIV/0! | ... M7: =M3/M6 -> #DIV/0! | N7: =AVERAGE(B7:M7) -> #DIV/0!
A8: 稼働率 | B8: =B5/(1*31) -> 0 | C8: =C5/(1*28) -> 0.14285714 | D8: =D5/(1*31) -> 0.16129032 | E8: =E5/(1*30) -> 0.13333333 | F8: =F5/(1*31) -> 0.032258065 | G8: =G5/(1*30) -> 0 | H8: =H5/(1*30) -> 0 | I8: =I5/(1*31) -> 0 | J8: =J5/(1*30) -> 0 | K8: =K5/(1*31) -> 0 | L8: =L5/(1*30) -> 0 | M8: =M5/(1*31) -> 0 | N8: =N5/(1*365) -> 0.038356164
A9: 売上目標差異 | B9: =B3-B2 -> 0 | C9: =C3-C2 -> -20796 | D9: =D3-D2 -> 15712 | E9: =E3-E2 -> 37920 | F9: =F3-F2 -> -54091 | G9: =G3-G2 -> -116684 | H9: =H3-H2 -> -101322 | I9: =I3-I2 -> -186370 | ... M9: =M3-M2 -> -153076 | N9: =SUM(B9:M9) -> -862972
A10: 昨年売上 | B10: 0 | C10: 134014 | D10: 118994 | E10: 83911 | F10: 90367 | G10: 116684 | H10: 101322 | I10: 186370 | J10: 56609 | K10: 156028 | L10: 71628 | M10: 153076 | N10: 1269003
A11: 昨年対比 | B11: =B3/B10 -> #DIV/0! | C11: =C3/C10 -> 0.84482218 | D11: =D3/D10 -> 1.1320403 | E11: =E3/E10 -> 1.4519074 | F11: =F3/F10 -> 0.40142973 | G11: =G3/G10 -> 0 | H11: =H3/H10 -> 0 | I11: =I3/I10 -> 0 | ... N11: =N3/N10 -> 0.31996063
A12: 経費予測 | N12: =SUM(B12:M12) -> 0
A13: 昨年経費 | N13: =SUM(B13:M13) -> 0
A14: 経費実績 | N14: =SUM(B14:M14) -> 0
A15: 経費差異 | B15: =B12-B14 -> 0 | C15: =C12-C13 -> 0 | D15: =D12-D13 -> 0 | E15: =E12-E13 -> 0 | F15: =F12-F13 -> 0 | G15: =G12-G14 -> 0 | H15: =H12-H14 -> 0 | I15: =I12-I14 -> 0 | J15: =J12-J14 -> 0 | K15: =K12-K14 -> 0 | L15: =L12-L14 -> 0 | M15: 18000000 | N15: =SUM(B15:M15) -> 18000000
A16: 差引収支 | B16: =B3-B14 -> 0 | C16: =C3-C13 -> 113218 | D16: =D3-D13 -> 134706 | E16: =E3-E13 -> 121831 | F16: =F3-F13 -> 36276 | G16: =G3-G12 -> 0 | H16: =H3-H12 -> 0 | I16: =I3-I12 -> 0 | J16: =J3-J12 -> 0 | K16: =K3-K12 -> 0 | L16: =L3-L12 -> 0 | M16: =M3-M12 -> 0 | N16: =SUM(B16:M16) -> 406031
