Workbook

Sheet トップ
A1: 全社統合 資金管理ファイル v10（シート集約版＋OTA予測機能）
A3: ■ シート構成（19シート）
A5: 分類 | B5: シート名 | C5: 内容
A6: 概観 | B6: 全社合算サマリー | C6: 6社合計の月別ダッシュボード
A7: 概観 | B7: 全社月次サマリー | C7: 6社×4ヶ月の明細
A8: マスター | B8: マスター_物件 | C8: 物件→会社マッピング
A9: マスター | B9: マスター_勘定科目 | C9: 勘定科目→資金繰り項目マッピング
A10: マスター | B10: マスター_OTA | C10: OTA別の入金サイクル設定
A11: 入力 | B11: 入金入力 | C11: 全社統合の入金入力（会社列でフィルター）
A12: 入力 | B12: 未払予定一覧 | C12: 全社統合の支出予定／カード枠回復統合（会社列でフィルター）
A13: 入力 | B13: 売上入力 | C13: OTA別売上入力（月別／施設別／OTA別）
A14: 計算 | B14: 入金予測 | C14: 売上入力 × OTAサイクル → 予測入金（自動計算）
A15: 日次 | B15: 日次_<会社名> | C15: 会社別の日次キャッシュフロー（5-8月 縦積み・6シート）
A16: 資金繰り | B16: 資金繰り_* | C16: 資金繰り表 4シート（5月起点12ヶ月）
A18: ■ v10での主な変更
A20: ・入金入力／未払予定一覧を会社列で1シートに統合（旧18シート → 2シート）
A21: ・カード枠回復を未払予定一覧の「種別」列で統合（旧6シート → 0シート、未払一覧側へ集約）
A22: ・日次キャッシュフローを社別1枚に4ヶ月縦積み（旧24シート → 6シート）
A23: ・マスター_OTA／売上入力／入金予測を新規追加（OTA別入金サイクル予測）
A24: ・レガシーシート（5月入出金一覧／取引先別集計／注記）を削除
A25: ・シート総数：51 → 19（-32枚 / -63%）

Sheet 全社合算サマリー
A1: 全社合算サマリー（6社合計）
A2: 6社の月別キャッシュフロー集計
A4: ■ 月別合算（6社合計）
A5: 月 | B5: 入金（円） | C5: 支出（円） | D5: 当月差引（円） | E5: 月末累計差引（円） | F5: カード枠回復額（円） | G5: 月末使用可能額（円）
A6: 5月 | B6: =日次_レジデンス!B37+日次_リゾート!B37+日次_モーテル!B37+日次_ザック!B37+日次_ワールド・レイ!B37+日次_ココ・ユニバース!B37 -> 45366181 | C6: =日次_レジデンス!C37+日次_リゾート!C37+日次_モーテル!C37+日次_ザック!C37+日次_ワールド・レイ!C37+日次_ココ・ユニバース!C37 -> 48481617 | D6: =日次_レジデンス!D37+日次_リゾート!D37+日次_モーテル!D37+日次_ザック!D37+日次_ワールド・レイ!D37+日次_ココ・ユニバース!D37 -> -8385436.4 | E6: =日次_レジデンス!E37+日次_リゾート!E37+日次_モーテル!E37+日次_ザック!E37+日次_ワールド・レイ!E37+日次_ココ・ユニバース!E37 -> -8385436.4 | F6: =日次_レジデンス!F37+日次_リゾート!F37+日次_モーテル!F37+日次_ザック!F37+日次_ワールド・レイ!F37+日次_ココ・ユニバース!F37 -> 5270000 | G6: =日次_レジデンス!G37+日次_リゾート!G37+日次_モーテル!G37+日次_ザック!G37+日次_ワールド・レイ!G37+日次_ココ・ユニバース!G37 -> -3115436.4
A7: 6月 | B7: =日次_レジデンス!B70+日次_リゾート!B70+日次_モーテル!B70+日次_ザック!B70+日次_ワールド・レイ!B70+日次_ココ・ユニバース!B70 -> 34253666 | C7: =日次_レジデンス!C70+日次_リゾート!C70+日次_モーテル!C70+日次_ザック!C70+日次_ワールド・レイ!C70+日次_ココ・ユニバース!C70 -> 39932206 | D7: =日次_レジデンス!D70+日次_リゾート!D70+日次_モーテル!D70+日次_ザック!D70+日次_ワールド・レイ!D70+日次_ココ・ユニバース!D70 -> -5678540.3 | E7: =日次_レジデンス!E70+日次_リゾート!E70+日次_モーテル!E70+日次_ザック!E70+日次_ワールド・レイ!E70+日次_ココ・ユニバース!E70 -> -14063977 | F7: =日次_レジデンス!F70+日次_リゾート!F70+日次_モーテル!F70+日次_ザック!F70+日次_ワールド・レイ!F70+日次_ココ・ユニバース!F70 -> 0 | G7: =日次_レジデンス!G70+日次_リゾート!G70+日次_モーテル!G70+日次_ザック!G70+日次_ワールド・レイ!G70+日次_ココ・ユニバース!G70 -> -8793976.7
A8: 7月 | B8: =日次_レジデンス!B104+日次_リゾート!B104+日次_モーテル!B104+日次_ザック!B104+日次_ワールド・レイ!B104+日次_ココ・ユニバース!B104 -> 30777994 | C8: =日次_レジデンス!C104+日次_リゾート!C104+日次_モーテル!C104+日次_ザック!C104+日次_ワールド・レイ!C104+日次_ココ・ユニバース!C104 -> 37223663 | D8: =日次_レジデンス!D104+日次_リゾート!D104+日次_モーテル!D104+日次_ザック!D104+日次_ワールド・レイ!D104+日次_ココ・ユニバース!D104 -> -6445668.6 | E8: =日次_レジデンス!E104+日次_リゾート!E104+日次_モーテル!E104+日次_ザック!E104+日次_ワールド・レイ!E104+日次_ココ・ユニバース!E104 -> -20509645 | F8: =日次_レジデンス!F104+日次_リゾート!F104+日次_モーテル!F104+日次_ザック!F104+日次_ワールド・レイ!F104+日次_ココ・ユニバース!F104 -> 0 | G8: =日次_レジデンス!G104+日次_リゾート!G104+日次_モーテル!G104+日次_ザック!G104+日次_ワールド・レイ!G104+日次_ココ・ユニバース!G104 -> -15239645
A9: 8月 | B9: =日次_レジデンス!B138+日次_リゾート!B138+日次_モーテル!B138+日次_ザック!B138+日次_ワールド・レイ!B138+日次_ココ・ユニバース!B138 -> 39570607 | C9: =日次_レジデンス!C138+日次_リゾート!C138+日次_モーテル!C138+日次_ザック!C138+日次_ワールド・レイ!C138+日次_ココ・ユニバース!C138 -> 38086901 | D9: =日次_レジデンス!D138+日次_リゾート!D138+日次_モーテル!D138+日次_ザック!D138+日次_ワールド・レイ!D138+日次_ココ・ユニバース!D138 -> 1483706.2 | E9: =日次_レジデンス!E138+日次_リゾート!E138+日次_モーテル!E138+日次_ザック!E138+日次_ワールド・レイ!E138+日次_ココ・ユニバース!E138 -> -19025939 | F9: =日次_レジデンス!F138+日次_リゾート!F138+日次_モーテル!F138+日次_ザック!F138+日次_ワールド・レイ!F138+日次_ココ・ユニバース!F138 -> 0 | G9: =日次_レジデンス!G138+日次_リゾート!G138+日次_モーテル!G138+日次_ザック!G138+日次_ワールド・レイ!G138+日次_ココ・ユニバース!G138 -> -13755939
A10: 4ヶ月合計 | B10: =SUM(B6:B9) -> 1.4996845e+08 | C10: =SUM(C6:C9) -> 163724387 | D10: =SUM(D6:D9) -> -19025939 | E10: =E9 -> -19025939 | F10: =SUM(F6:F9) -> 5270000 | G10: =G9 -> -13755939

Sheet 全社月次サマリー
A1: 全社月次サマリー（6社×4ヶ月）
A3: 会社 | B3: 月 | C3: 入金（円） | D3: 支出（円） | E3: 当月差引（円） | F3: 月末累計差引（円） | G3: カード枠回復額（円） | H3: 月末使用可能額（円）
A4: レジデンス | B4: 5月 | C4: =日次_レジデンス!B37 -> 9692753 | D4: =日次_レジデンス!C37 -> 6684291 | E4: =日次_レジデンス!D37 -> 3008462 | F4: =日次_レジデンス!E37 -> 3008462 | G4: =日次_レジデンス!F37 -> 0 | H4: =日次_レジデンス!G37 -> 3008462
A5: レジデンス | B5: 6月 | C5: =日次_レジデンス!B70 -> 0 | D5: =日次_レジデンス!C70 -> 6177138 | E5: =日次_レジデンス!D70 -> -6177138 | F5: =日次_レジデンス!E70 -> -3168676 | G5: =日次_レジデンス!F70 -> 0 | H5: =日次_レジデンス!G70 -> -3168676
A6: レジデンス | B6: 7月 | C6: =日次_レジデンス!B104 -> 0 | D6: =日次_レジデンス!C104 -> 6177138 | E6: =日次_レジデンス!D104 -> -6177138 | F6: =日次_レジデンス!E104 -> -9345814 | G6: =日次_レジデンス!F104 -> 0 | H6: =日次_レジデンス!G104 -> -9345814
A7: レジデンス | B7: 8月 | C7: =日次_レジデンス!B138 -> 0 | D7: =日次_レジデンス!C138 -> 6177138 | E7: =日次_レジデンス!D138 -> -6177138 | F7: =日次_レジデンス!E138 -> -15522952 | G7: =日次_レジデンス!F138 -> 0 | H7: =日次_レジデンス!G138 -> -15522952
A8: レジデンス | B8: 4ヶ月合計 | C8: =SUM(C4:C7) -> 9692753 | D8: =SUM(D4:D7) -> 25215705 | E8: =SUM(E4:E7) -> -15522952 | F8: =F7 -> -15522952 | G8: =SUM(G4:G7) -> 0 | H8: =H7 -> -15522952
A10: リゾート | B10: 5月 | C10: =日次_リゾート!B37 -> 24503948 | D10: =日次_リゾート!C37 -> 34253022 | E10: =日次_リゾート!D37 -> -15019074 | F10: =日次_リゾート!E37 -> -15019074 | G10: =日次_リゾート!F37 -> 5270000 | H10: =日次_リゾート!G37 -> -9749074.1
A11: リゾート | B11: 6月 | C11: =日次_リゾート!B70 -> 25595864 | D11: =日次_リゾート!C70 -> 30740710 | E11: =日次_リゾート!D70 -> -5144846.5 | F11: =日次_リゾート!E70 -> -20163921 | G11: =日次_リゾート!F70 -> 0 | H11: =日次_リゾート!G70 -> -14893921
A12: リゾート | B12: 7月 | C12: =日次_リゾート!B104 -> 23257259 | D12: =日次_リゾート!C104 -> 28032167 | E12: =日次_リゾート!D104 -> -4774908.2 | F12: =日次_リゾート!E104 -> -24938829 | G12: =日次_リゾート!F104 -> 0 | H12: =日次_リゾート!G104 -> -19668829
A13: リゾート | B13: 8月 | C13: =日次_リゾート!B138 -> 30710595 | D13: =日次_リゾート!C138 -> 29167405 | E13: =日次_リゾート!D138 -> 1543190.2 | F13: =日次_リゾート!E138 -> -23395639 | G13: =日次_リゾート!F138 -> 0 | H13: =日次_リゾート!G138 -> -18125639
A14: リゾート | B14: 4ヶ月合計 | C14: =SUM(C10:C13) -> 1.0406767e+08 | D14: =SUM(D10:D13) -> 122193304 | E14: =SUM(E10:E13) -> -23395639 | F14: =F13 -> -23395639 | G14: =SUM(G10:G13) -> 5270000 | H14: =H13 -> -18125639
A16: モーテル | B16: 5月 | C16: =日次_モーテル!B37 -> 8046038.3 | D16: =日次_モーテル!C37 -> 1998914 | E16: =日次_モーテル!D37 -> 6047124.3 | F16: =日次_モーテル!E37 -> 6047124.3 | G16: =日次_モーテル!F37 -> 0 | H16: =日次_モーテル!G37 -> 6047124.3
A17: モーテル | B17: 6月 | C17: =日次_モーテル!B70 -> 4753795.2 | D17: =日次_モーテル!C70 -> 185173 | E17: =日次_モーテル!D70 -> 4568622.2 | F17: =日次_モーテル!E70 -> 10615746 | G17: =日次_モーテル!F70 -> 0 | H17: =日次_モーテル!G70 -> 10615746
A18: モーテル | B18: 7月 | C18: =日次_モーテル!B104 -> 3640308 | D18: =日次_モーテル!C104 -> 185173 | E18: =日次_モーテル!D104 -> 3455135 | F18: =日次_モーテル!E104 -> 14070881 | G18: =日次_モーテル!F104 -> 0 | H18: =日次_モーテル!G104 -> 14070881
A19: モーテル | B19: 8月 | C19: =日次_モーテル!B138 -> 4983212 | D19: =日次_モーテル!C138 -> 185173 | E19: =日次_モーテル!D138 -> 4798039 | F19: =日次_モーテル!E138 -> 18868920 | G19: =日次_モーテル!F138 -> 0 | H19: =日次_モーテル!G138 -> 18868920
A20: モーテル | B20: 4ヶ月合計 | C20: =SUM(C16:C19) -> 21423353 | D20: =SUM(D16:D19) -> 2554433 | E20: =SUM(E16:E19) -> 18868920 | F20: =F19 -> 18868920 | G20: =SUM(G16:G19) -> 0 | H20: =H19 -> 18868920
A22: ザック | B22: 5月 | C22: =日次_ザック!B37 -> 5441.4 | D22: =日次_ザック!C37 -> 278050 | E22: =日次_ザック!D37 -> -272608.6 | F22: =日次_ザック!E37 -> -272608.6 | G22: =日次_ザック!F37 -> 0 | H22: =日次_ザック!G37 -> -272608.6
A23: ザック | B23: 6月 | C23: =日次_ザック!B70 -> 27207 | D23: =日次_ザック!C70 -> 272000 | E23: =日次_ザック!D70 -> -244793 | F23: =日次_ザック!E70 -> -517401.6 | G23: =日次_ザック!F70 -> 0 | H23: =日次_ザック!G70 -> -517401.6
A24: ザック | B24: 7月 | C24: =日次_ザック!B104 -> 3627.6 | D24: =日次_ザック!C104 -> 272000 | E24: =日次_ザック!D104 -> -268372.4 | F24: =日次_ザック!E104 -> -785774 | G24: =日次_ザック!F104 -> 0 | H24: =日次_ザック!G104 -> -785774
A25: ザック | B25: 8月 | C25: =日次_ザック!B138 -> 0 | D25: =日次_ザック!C138 -> 0 | E25: =日次_ザック!D138 -> 0 | F25: =日次_ザック!E138 -> -785774 | G25: =日次_ザック!F138 -> 0 | H25: =日次_ザック!G138 -> -785774
A26: ザック | B26: 4ヶ月合計 | C26: =SUM(C22:C25) -> 36276 | D26: =SUM(D22:D25) -> 822050 | E26: =SUM(E22:E25) -> -785774 | F26: =F25 -> -785774 | G26: =SUM(G22:G25) -> 0 | H26: =H25 -> -785774
A28: ワールド・レイ | B28: 5月 | C28: =日次_ワールド・レイ!B37 -> 863000 | D28: =日次_ワールド・レイ!C37 -> 2163774 | E28: =日次_ワールド・レイ!D37 -> -1300774 | F28: =日次_ワールド・レイ!E37 -> -1300774 | G28: =日次_ワールド・レイ!F37 -> 0 | H28: =日次_ワールド・レイ!G37 -> -1300774
A29: ワールド・レイ | B29: 6月 | C29: =日次_ワールド・レイ!B70 -> 300000 | D29: =日次_ワールド・レイ!C70 -> 1441937 | E29: =日次_ワールド・レイ!D70 -> -1141937 | F29: =日次_ワールド・レイ!E70 -> -2442711 | G29: =日次_ワールド・レイ!F70 -> 0 | H29: =日次_ワールド・レイ!G70 -> -2442711
A30: ワールド・レイ | B30: 7月 | C30: =日次_ワールド・レイ!B104 -> 300000 | D30: =日次_ワールド・レイ!C104 -> 1441937 | E30: =日次_ワールド・レイ!D104 -> -1141937 | F30: =日次_ワールド・レイ!E104 -> -3584648 | G30: =日次_ワールド・レイ!F104 -> 0 | H30: =日次_ワールド・レイ!G104 -> -3584648
A31: ワールド・レイ | B31: 8月 | C31: =日次_ワールド・レイ!B138 -> 300000 | D31: =日次_ワールド・レイ!C138 -> 1441937 | E31: =日次_ワールド・レイ!D138 -> -1141937 | F31: =日次_ワールド・レイ!E138 -> -4726585 | G31: =日次_ワールド・レイ!F138 -> 0 | H31: =日次_ワールド・レイ!G138 -> -4726585
A32: ワールド・レイ | B32: 4ヶ月合計 | C32: =SUM(C28:C31) -> 1763000 | D32: =SUM(D28:D31) -> 6489585 | E32: =SUM(E28:E31) -> -4726585 | F32: =F31 -> -4726585 | G32: =SUM(G28:G31) -> 0 | H32: =H31 -> -4726585
A34: ココ・ユニバース | B34: 5月 | C34: =日次_ココ・ユニバース!B37 -> 2255000 | D34: =日次_ココ・ユニバース!C37 -> 3103566 | E34: =日次_ココ・ユニバース!D37 -> -848566 | F34: =日次_ココ・ユニバース!E37 -> -848566 | G34: =日次_ココ・ユニバース!F37 -> 0 | H34: =日次_ココ・ユニバース!G37 -> -848566
A35: ココ・ユニバース | B35: 6月 | C35: =日次_ココ・ユニバース!B70 -> 3576800 | D35: =日次_ココ・ユニバース!C70 -> 1115248 | E35: =日次_ココ・ユニバース!D70 -> 2461552 | F35: =日次_ココ・ユニバース!E70 -> 1612986 | G35: =日次_ココ・ユニバース!F70 -> 0 | H35: =日次_ココ・ユニバース!G70 -> 1612986
A36: ココ・ユニバース | B36: 7月 | C36: =日次_ココ・ユニバース!B104 -> 3576800 | D36: =日次_ココ・ユニバース!C104 -> 1115248 | E36: =日次_ココ・ユニバース!D104 -> 2461552 | F36: =日次_ココ・ユニバース!E104 -> 4074538 | G36: =日次_ココ・ユニバース!F104 -> 0 | H36: =日次_ココ・ユニバース!G104 -> 4074538
A37: ココ・ユニバース | B37: 8月 | C37: =日次_ココ・ユニバース!B138 -> 3576800 | D37: =日次_ココ・ユニバース!C138 -> 1115248 | E37: =日次_ココ・ユニバース!D138 -> 2461552 | F37: =日次_ココ・ユニバース!E138 -> 6536090 | G37: =日次_ココ・ユニバース!F138 -> 0 | H37: =日次_ココ・ユニバース!G138 -> 6536090
A38: ココ・ユニバース | B38: 4ヶ月合計 | C38: =SUM(C34:C37) -> 12985400 | D38: =SUM(D34:D37) -> 6449310 | E38: =SUM(E34:E37) -> 6536090 | F38: =F37 -> 6536090 | G38: =SUM(G34:G37) -> 0 | H38: =H37 -> 6536090
A40: 全社合計 | C40: =SUM(C4:C7)+SUM(C10:C13)+SUM(C16:C19)+SUM(C22:C25)+SUM(C28:C31)+SUM(C34:C37) -> 1.4996845e+08 | D40: =SUM(D4:D7)+SUM(D10:D13)+SUM(D16:D19)+SUM(D22:D25)+SUM(D28:D31)+SUM(D34:D37) -> 163724387 | E40: =SUM(E4:E7)+SUM(E10:E13)+SUM(E16:E19)+SUM(E22:E25)+SUM(E28:E31)+SUM(E34:E37) -> -19025939 | G40: =SUM(G4:G7)+SUM(G10:G13)+SUM(G16:G19)+SUM(G22:G25)+SUM(G28:G31)+SUM(G34:G37) -> 5270000

Sheet 支払可能性分析
A1: 支払可能性分析（月次収支予測 + 未払繰越の優先度別支払可能性）
A2: 入金予測（売上予測+OTAサイクル+手動入力）と支出予測（月次予定+反復予測）から、各月の余剰を計算。残高内で支払可能な未払繰越を優先度順に判定。
A4: ■ Section 1：月次収支予測（全社合算）
A5: 月 | B5: 入金予測（円） | C5: 支出予測（円） | D5: 月次差引（円） | E5: 累計余剰（円） | F5: カード枠回復（円） | G5: 実質使用可能額（円） | H5: 判定
A6: 5月 | B6: =全社合算サマリー!B6 -> 45366181 | C6: =全社合算サマリー!C6 -> 48481617 | D6: =B6-C6 -> -3115436.4 | E6: =全社合算サマリー!E6 -> -8385436.4 | F6: =全社合算サマリー!F6 -> 5270000 | G6: =全社合算サマリー!G6 -> -3115436.4 | H6: =IF(G6>=10000000,"◎ 余裕",IF(G6>=0,"○ 適正",IF(G6>=-5000000,"△ 注意","✕ 資金不足"))) -> △ 注意
A7: 6月 | B7: =全社合算サマリー!B7 -> 34253666 | C7: =全社合算サマリー!C7 -> 39932206 | D7: =B7-C7 -> -5678540.3 | E7: =全社合算サマリー!E7 -> -14063977 | F7: =全社合算サマリー!F7 -> 0 | G7: =全社合算サマリー!G7 -> -8793976.7 | H7: =IF(G7>=10000000,"◎ 余裕",IF(G7>=0,"○ 適正",IF(G7>=-5000000,"△ 注意","✕ 資金不足"))) -> ✕ 資金不足
A8: 7月 | B8: =全社合算サマリー!B8 -> 30777994 | C8: =全社合算サマリー!C8 -> 37223663 | D8: =B8-C8 -> -6445668.6 | E8: =全社合算サマリー!E8 -> -20509645 | F8: =全社合算サマリー!F8 -> 0 | G8: =全社合算サマリー!G8 -> -15239645 | H8: =IF(G8>=10000000,"◎ 余裕",IF(G8>=0,"○ 適正",IF(G8>=-5000000,"△ 注意","✕ 資金不足"))) -> ✕ 資金不足
A9: 8月 | B9: =全社合算サマリー!B9 -> 39570607 | C9: =全社合算サマリー!C9 -> 38086901 | D9: =B9-C9 -> 1483706.2 | E9: =全社合算サマリー!E9 -> -19025939 | F9: =全社合算サマリー!F9 -> 0 | G9: =全社合算サマリー!G9 -> -13755939 | H9: =IF(G9>=10000000,"◎ 余裕",IF(G9>=0,"○ 適正",IF(G9>=-5000000,"△ 注意","✕ 資金不足"))) -> ✕ 資金不足
A11: ■ Section 2：未払繰越の優先度別リスト（全件）
A12: # | B12: 会社 | C12: 物件 | D12: 概要 | E12: 累積未払額 | F12: 優先度 | G12: 累計支払額 | H12: 判定（支払可否）
A13: 1 | B13: リゾート | C13: リゾート | D13: アイパス [予定日設定済] | E13: 801900 | F13: 高 | G13: =E13 -> 801900 | H13: =IF(G13<=$G9,"○ 支払可能","✕ 不足") -> ✕ 不足
A14: 2 | B14: リゾート | C14: リゾート | D14: クリンプロ（4か月分） [予定日設定済] | E14: 488840 | F14: 高 | G14: =G13+E14 -> 1290740 | H14: =IF(G14<=$G9,"○ 支払可能","✕ 不足") -> ✕ 不足
A15: 3 | B15: リゾート | C15: リゾート | D15: 百姓屋（4か月分） [予定日設定済] | E15: 187000 | F15: 高 | G15: =G14+E15 -> 1477740 | H15: =IF(G15<=$G9,"○ 支払可能","✕ 不足") -> ✕ 不足
A16: 4 | B16: リゾート | C16: リゾート | D16: 第一興商（5か月分） [予定日設定済] | E16: 187000 | F16: 高 | G16: =G15+E16 -> 1664740 | H16: =IF(G16<=$G9,"○ 支払可能","✕ 不足") -> ✕ 不足
A17: 5 | B17: レジデンス | C17: レジデンス | D17: あしたば [予定日設定済] | E17: 132000 | F17: 高 | G17: =G16+E17 -> 1796740 | H17: =IF(G17<=$G9,"○ 支払可能","✕ 不足") -> ✕ 不足
A18: 6 | B18: リゾート | C18: フォレスト | D18: みどりのまち（3ヶ月分） [予定日設定済] | E18: 124300 | F18: 高 | G18: =G17+E18 -> 1921040 | H18: =IF(G18<=$G9,"○ 支払可能","✕ 不足") -> ✕ 不足
A19: 7 | B19: リゾート | C19: リゾート | D19: 安芸クリーナー（5か月分） [予定日設定済] | E19: 110000 | F19: 高 | G19: =G18+E19 -> 2031040 | H19: =IF(G19<=$G9,"○ 支払可能","✕ 不足") -> ✕ 不足
A20: 8 | B20: リゾート | C20: リゾート | D20: 西部環境（4か月分） | E20: 92400 | F20: 高 | G20: =G19+E20 -> 2123440 | H20: =IF(G20<=$G9,"○ 支払可能","✕ 不足") -> ✕ 不足
A21: 9 | B21: リゾート | C21: リゾート | D21: 竹原クリーナー（5か月分） [予定日設定済] | E21: 88000 | F21: 高 | G21: =G20+E21 -> 2211440 | H21: =IF(G21<=$G9,"○ 支払可能","✕ 不足") -> ✕ 不足
A22: 10 | B22: リゾート | C22: リゾート | D22: アシード（5か月分） [予定日設定済] | E22: 70400 | F22: 高 | G22: =G21+E22 -> 2281840 | H22: =IF(G22<=$G9,"○ 支払可能","✕ 不足") -> ✕ 不足
A23: 11 | B23: リゾート | C23: リゾート | D23: 第一興商 [予定日設定済] | E23: 66000 | F23: 高 | G23: =G22+E23 -> 2347840 | H23: =IF(G23<=$G9,"○ 支払可能","✕ 不足") -> ✕ 不足
A24: 12 | B24: リゾート | C24: リゾート | D24: 青原木材（3ヶ月分） | E24: 486420 | F24: 中 | G24: =G23+E24 -> 2834260 | H24: =IF(G24<=$G9,"○ 支払可能","✕ 不足") -> ✕ 不足
A25: 13 | B25: リゾート | C25: リゾート | D25: あしたば [予定日設定済] | E25: 264000 | F25: 中 | G25: =G24+E25 -> 3098260 | H25: =IF(G25<=$G9,"○ 支払可能","✕ 不足") -> ✕ 不足
A26: 14 | B26: リゾート | C26: リゾート | D26: アペックス（3ヶ月分） [予定日設定済] | E26: 92495 | F26: 中 | G26: =G25+E26 -> 3190755 | H26: =IF(G26<=$G9,"○ 支払可能","✕ 不足") -> ✕ 不足
A27: 15 | B27: リゾート | C27: リゾート | D27: アペックス（3ヶ月分） [予定日設定済] | E27: 48540 | F27: 中 | G27: =G26+E27 -> 3239295 | H27: =IF(G27<=$G9,"○ 支払可能","✕ 不足") -> ✕ 不足
A28: 16 | B28: モーテル | C28: モーテル | D28: ふくや（3ヶ月分） [予定日設定済] | E28: 25651 | F28: 中 | G28: =G27+E28 -> 3264946 | H28: =IF(G28<=$G9,"○ 支払可能","✕ 不足") -> ✕ 不足
A29: 17 | B29: リゾート | C29: リゾート | D29: イマイチ（3ヶ月分） [予定日設定済] | E29: 24486 | F29: 中 | G29: =G28+E29 -> 3289432 | H29: =IF(G29<=$G9,"○ 支払可能","✕ 不足") -> ✕ 不足
A30: 18 | B30: リゾート | C30: リゾート | D30: キャノン [予定日設定済] | E30: 23702 | F30: 中 | G30: =G29+E30 -> 3313134 | H30: =IF(G30<=$G9,"○ 支払可能","✕ 不足") -> ✕ 不足
A31: 19 | B31: モーテル | C31: モーテル | D31: あしたば（4月分） [予定日設定済] | E31: 22000 | F31: 中 | G31: =G30+E31 -> 3335134 | H31: =IF(G31<=$G9,"○ 支払可能","✕ 不足") -> ✕ 不足
A32: 20 | B32: リゾート | C32: フォレスト | D32: フォワード [予定日設定済] | E32: 18648 | F32: 中 | G32: =G31+E32 -> 3353782 | H32: =IF(G32<=$G9,"○ 支払可能","✕ 不足") -> ✕ 不足
A33: 21 | B33: モーテル | C33: モーテル | D33: ASKUL（2か月分） [予定日設定済] | E33: 15932 | F33: 低 | G33: =G32+E33 -> 3369714 | H33: =IF(G33<=$G9,"○ 支払可能","✕ 不足") -> ✕ 不足
A35: 未払繰越合計 | E35: =SUM(E13:E33) -> 3369714 | G35: =G33 -> 3369714
A37: ■ Section 3：総括（8月末時点の使用可能額との比較）
A39: 8月末使用可能額 | B39: =G9 -> -13755939
A40: 優先度「高」未払合計 | B40: =SUMPRODUCT((未払予定一覧!$B$4:$B$803="未払繰越")*(未払予定一覧!$M$4:$M$803="高")*(未払予定一覧!$P$4:$P$803<>"済")*(未払予定一覧!$P$4:$P$803<>"取消")*未払予定一覧!$L$4:$L$803) -> 2499640
A41: 優先度「中」未払合計 | B41: =SUMPRODUCT((未払予定一覧!$B$4:$B$803="未払繰越")*(未払予定一覧!$M$4:$M$803="中")*(未払予定一覧!$P$4:$P$803<>"済")*(未払予定一覧!$P$4:$P$803<>"取消")*未払予定一覧!$L$4:$L$803) -> 1242347
A42: 優先度「低」未払合計 | B42: =SUMPRODUCT((未払予定一覧!$B$4:$B$803="未払繰越")*(未払予定一覧!$M$4:$M$803="低")*(未払予定一覧!$P$4:$P$803<>"済")*(未払予定一覧!$P$4:$P$803<>"取消")*未払予定一覧!$L$4:$L$803) -> 15932
A44: 「高」完済後の余剰 | C44: =G9-B40 -> -16255579 | D44: =IF(C44>=0,"◎ 「高」全件支払可能","✕ 「高」一部支払不可") -> ✕ 「高」一部支払不可
A45: 「高」+「中」完済後の余剰 | C45: =G9-B40-B41 -> -17497926 | D45: =IF(C45>=0,"○ 「中」まで全件可","✕ 「中」一部支払不可") -> ✕ 「中」一部支払不可
A46: 全優先度完済後の余剰 | C46: =G9-B40-B41-B42 -> -17513858 | D46: =IF(C46>=0,"◎ 全件支払可","✕ 一部支払不可") -> ✕ 一部支払不可

Sheet 2025-2026比較
A1: 2025年実績 vs 2026年予測 比較分析（施設×月）
A2: 充足率 = 2026予測 / 2025実績。緑=80%以上、黄=30-80%、赤=30%未満（要補正）
A4: 施設 | B4: 年区分 | C4: 1月 | D4: 2月 | E4: 3月 | F4: 4月 | G4: 5月 | H4: 6月 | I4: 7月 | J4: 8月 | K4: 9月 | L4: 10月 | M4: 11月 | N4: 12月 | O4: 年計
A5: de Lune | B5: 2025実績 | C5: 7261662 | D5: 5866776 | E5: 10663661 | F5: 8372542 | G5: 10091773 | H5: 6020957 | I5: 10861148 | J5: 13339294 | K5: 8976175 | L5: 12967689 | M5: 13075844 | N5: 6830956 | O5: 114328477
B6: 2026予測（5/13） | C6: 0 | D6: 0 | E6: 0 | F6: 8310821 | G6: 9120696 | H6: 2157347 | I6: 869144 | J6: 1477233 | K6: 468498 | L6: 601121 | M6: 142650 | N6: 145700 | O6: 23293210
B7: 充足率 | C7: 0 | D7: 0 | E7: 0 | F7: 0.99262816 | G7: 0.90377538 | H7: 0.35830633 | I7: 0.080023217 | J7: 0.11074297 | K7: 0.052193501 | L7: 0.046355291 | M7: 0.01090943 | N7: 0.021329372 | O7: 0.20373935
A9: VIEW | B9: 2025実績 | C9: 2143056 | D9: 1559909 | E9: 2743253 | F9: 2602903 | G9: 2606733 | H9: 1341712 | I9: 3302659 | J9: 4469894 | K9: 2740428 | L9: 3669167 | M9: 3942044 | N9: 1966245 | O9: 33088003
B10: 2026予測（5/13） | C10: 0 | D10: 0 | E10: 0 | F10: 2904045 | G10: 2785752 | H10: 613130 | I10: 320289 | J10: 312594 | K10: 492830 | L10: 112580 | M10: 0 | N10: 0 | O10: 7541220
B11: 充足率 | C11: 0 | D11: 0 | E11: 0 | F11: 1.1156947 | G11: 1.0686756 | H11: 0.45697586 | I11: 0.096979131 | J11: 0.069933202 | K11: 0.17983687 | L11: 0.030682714 | M11: 0 | N11: 0 | O11: 0.22791403
A13: 本川 | B13: 2025実績 | C13: 901976 | D13: 970534 | E13: 1394853 | F13: 1600536 | G13: 2028098 | H13: 1051016 | I13: 1110194 | J13: 2097316 | K13: 1566778 | L13: 2477290 | M13: 2350836 | N13: 1139100 | O13: 18688527
B14: 2026予測（5/13） | C14: 0 | D14: 0 | E14: 0 | F14: 1955058 | G14: 1560292 | H14: 249824 | I14: 396582 | J14: 411126 | K14: 109252 | L14: 159276 | M14: 0 | N14: 0 | O14: 4841410
B15: 充足率 | C15: 0 | D15: 0 | E15: 0 | F15: 1.221502 | G15: 0.76933758 | H15: 0.23769762 | I15: 0.35721865 | J15: 0.19602482 | K15: 0.069730364 | L15: 0.064294451 | M15: 0 | N15: 0 | O15: 0.25905787
A17: 天神 | B17: 2025実績 | C17: 32400 | D17: 174440 | E17: 247060 | F17: 115860 | G17: 270500 | H17: 85200 | I17: 214180 | J17: 318420 | K17: 53469 | L17: 261170 | M17: 349410 | N17: 179120 | O17: 2301229
B18: 2026予測（5/13） | C18: 0 | D18: 0 | E18: 0 | F18: 56700 | G18: 176080 | H18: 32400 | I18: 0 | J18: 0 | K18: 0 | L18: 0 | M18: 0 | N18: 0 | O18: 265180
B19: 充足率 | C19: 0 | D19: 0 | E19: 0 | F19: 0.48938374 | G19: 0.6509427 | H19: 0.38028169 | I19: 0 | J19: 0 | K19: 0 | L19: 0 | M19: 0 | N19: 0 | O19: 0.11523408
A21: 玖波 | B21: 2025実績 | C21: 327400 | D21: 369900 | E21: 730100 | F21: 460700 | G21: 431900 | H21: 183300 | I21: 218250 | J21: 793250 | K21: 246500 | L21: 418500 | M21: 476700 | N21: 275000 | O21: 4931500
B22: 2026予測（5/13） | C22: 0 | D22: 0 | E22: 0 | F22: 331500 | G22: 280500 | H22: 190750 | I22: 96000 | J22: 0 | K22: 0 | L22: 0 | M22: 0 | N22: 0 | O22: 898750
B23: 充足率 | C23: 0 | D23: 0 | E23: 0 | F23: 0.7195572 | G23: 0.64945589 | H23: 1.0406438 | I23: 0.43986254 | J23: 0 | K23: 0 | L23: 0 | M23: 0 | N23: 0 | O23: 0.18224678
A25: 弥山 | B25: 2025実績 | C25: 3701096 | D25: 2980174 | E25: 5584201 | F25: 5487259 | G25: 6761527 | H25: 3942572 | I25: 5866719 | J25: 9564791 | K25: 5465630 | L25: 8958395 | M25: 8362200 | N25: 5672113 | O25: 72346677
B26: 2026予測（5/13） | C26: 0 | D26: 0 | E26: 0 | F26: 4004248 | G26: 5707582 | H26: 1940810 | I26: 593347 | J26: 1509171 | K26: 362863 | L26: 533648 | M26: 237410 | N26: 20000 | O26: 14909079
B27: 充足率 | C27: 0 | D27: 0 | E27: 0 | F27: 0.72973556 | G27: 0.84412619 | H27: 0.49227002 | I27: 0.10113779 | J27: 0.157784 | K27: 0.066389968 | L27: 0.059569599 | M27: 0.028390854 | N27: 0.0035260228 | O27: 0.20607828
A29: 温井 | B29: 2025実績 | C29: 3022505 | D29: 4261675 | E29: 3738314 | F29: 2113091 | G29: 3281694 | H29: 2228827 | I29: 5237483 | J29: 6962206 | K29: 4111027 | L29: 5703514 | M29: 5651540 | N29: 4532837 | O29: 50844713
B30: 2026予測（5/13） | C30: 0 | D30: 0 | E30: 0 | F30: 2330934 | G30: 4564062 | H30: 1719708 | I30: 1045292 | J30: 1433757 | K30: 83838 | L30: 66600 | M30: 0 | N30: 0 | O30: 11244191
B31: 充足率 | C31: 0 | D31: 0 | E31: 0 | F31: 1.1030921 | G31: 1.390764 | H31: 0.77157536 | I31: 0.19957907 | J31: 0.2059343 | K31: 0.020393444 | L31: 0.011677012 | M31: 0 | N31: 0 | O31: 0.22114769
A33: いこいの村 | B33: 2025実績 | C33: 0 | D33: 0 | E33: 0 | F33: 5067080 | G33: 5172360 | H33: 5590656 | I33: 8590205 | J33: 14720394 | K33: 5111672 | L33: 5445149 | M33: 5263750 | N33: 4624660 | O33: 59585926
B34: 2026予測（5/13） | C34: 0 | D34: 0 | E34: 0 | F34: 6092392 | G34: 2928671 | H34: 1212724 | I34: 1777188 | J34: 963416 | K34: 1722323 | L34: 405410 | M34: 0 | N34: 0 | O34: 15102124
B35: 充足率 | F35: 1.2023477 | G35: 0.56621562 | H35: 0.2169198 | I35: 0.2068854 | J35: 0.065447705 | K35: 0.33693926 | L35: 0.074453426 | M35: 0 | N35: 0 | O35: 0.25345119
A37: TAKAYA | B37: 2025実績 | C37: 142000 | D37: 506000 | E37: 517000 | F37: 636000 | G37: 441000 | H37: 421980 | I37: 310000 | J37: 246000 | K37: 96000 | L37: 228000 | M37: 450000 | N37: 323000 | O37: 4316980
B38: 2026予測（5/13） | C38: 0 | D38: 0 | E38: 0 | F38: 455000 | G38: 272000 | H38: 195000 | I38: 78000 | J38: 120000 | K38: 0 | L38: 0 | M38: 0 | N38: 0 | O38: 1120000
B39: 充足率 | C39: 0 | D39: 0 | E39: 0 | F39: 0.71540881 | G39: 0.61678005 | H39: 0.46210721 | I39: 0.2516129 | J39: 0.48780488 | K39: 0 | L39: 0 | M39: 0 | N39: 0 | O39: 0.25944063
A41: 壱番館 | B41: 2025実績 | C41: 276000 | D41: 162000 | E41: 189000 | F41: 103500 | G41: 164000 | H41: 165000 | I41: 127500 | J41: 217000 | K41: 142500 | L41: 0 | M41: 183000 | N41: 78000 | O41: 1807500
B42: 2026予測（5/13） | C42: 0 | D42: 0 | E42: 0 | F42: 101400 | G42: 24000 | H42: 45000 | I42: 0 | J42: 0 | K42: 0 | L42: 0 | M42: 0 | N42: 0 | O42: 170400
B43: 充足率 | C43: 0 | D43: 0 | E43: 0 | F43: 0.97971014 | G43: 0.14634146 | H43: 0.27272727 | I43: 0 | J43: 0 | K43: 0 | M43: 0 | N43: 0 | O43: 0.094273859
A45: 弐番館 | B45: 2025実績 | C45: 60000 | D45: 121500 | E45: 69000 | F45: 58000 | G45: 9000 | H45: 108000 | I45: 63000 | J45: 56500 | K45: 44000 | L45: 57000 | M45: 48000 | N45: 54500 | O45: 748500
B46: 2026予測（5/13） | C46: 0 | D46: 0 | E46: 0 | F46: 90000 | G46: 0 | H46: 0 | I46: 0 | J46: 75000 | K46: 0 | L46: 0 | M46: 0 | N46: 0 | O46: 165000
B47: 充足率 | C47: 0 | D47: 0 | E47: 0 | F47: 1.5517241 | G47: 0 | H47: 0 | I47: 0 | J47: 1.3274336 | K47: 0 | L47: 0 | M47: 0 | N47: 0 | O47: 0.22044088
A49: Otake | B49: 2025実績 | C49: 0 | D49: 0 | E49: 0 | F49: 0 | G49: 15000 | H49: 0 | I49: 0 | J49: 77500 | K49: 132500 | L49: 75000 | M49: 35000 | N49: 77500 | O49: 412500
B50: 2026予測（5/13） | C50: 0 | D50: 0 | E50: 0 | F50: 105000 | G50: 77500 | H50: 72500 | I50: 0 | J50: 0 | K50: 0 | L50: 0 | M50: 0 | N50: 0 | O50: 255000
B51: 充足率 | G51: 5.1666667 | J51: 0 | K51: 0 | L51: 0 | M51: 0 | N51: 0 | O51: 0.61818182
A53: 竹原（ﾚｽﾄﾗﾝ含む） | B53: 2025実績 | C53: 1568869 | D53: 1184756 | E53: 1834990 | F53: 3032420 | G53: 1954383 | H53: 1736192 | I53: 1423207 | J53: 1213337 | K53: 1539082 | L53: 1127424 | M53: 593424 | N53: 593424 | O53: 17801508
B54: 2026予測（5/13） | C54: 0 | D54: 0 | E54: 0 | F54: 1202444 | G54: 789000 | H54: 683000 | I54: 683000 | J54: 683000 | K54: 683000 | L54: 683000 | M54: 683000 | N54: 683000 | O54: 6772444
B55: 充足率 | C55: 0 | D55: 0 | E55: 0 | F55: 0.3965295 | G55: 0.40370797 | H55: 0.39338967 | I55: 0.47990208 | J55: 0.56291039 | K55: 0.44377103 | L55: 0.6058058 | M55: 1.1509477 | N55: 1.1509477 | O55: 0.38044215
A57: フォレストヒルズガーデン | B57: 2025実績 | C57: 0 | D57: 0 | E57: 0 | F57: 0 | G57: 0 | H57: 0 | I57: 40000 | J57: 600770 | K57: 193228 | L57: 558820 | M57: 1559105 | N57: 1643365 | O57: 4595288
B58: 2026予測（5/13） | C58: 0 | D58: 0 | E58: 0 | F58: 5535949 | G58: 7143323 | H58: 5391573 | I58: 4875243 | J58: 5265522 | K58: 4758433 | L58: 4621833 | M58: 4696833 | N58: 4621833 | O58: 46910542
B59: 充足率 | I59: 121.88107 | J59: 8.7646221 | K59: 24.626001 | L59: 8.2707008 | M59: 3.0125187 | N59: 2.8124202 | O59: 10.208401
A61: グリーンシャワー | B61: 2025実績 | C61: 0 | D61: 0 | E61: 0 | F61: 461140 | G61: 783440 | H61: 442970 | I61: 505440 | J61: 550560 | K61: 529680 | L61: 896640 | M61: 1183910 | N61: 0 | O61: 5353780
B62: 2026予測（5/13） | C62: 0 | D62: 0 | E62: 0 | F62: 626997 | G62: 248917 | H62: 248917 | I62: 248917 | J62: 248917 | K62: 248917 | L62: 248917 | M62: 248917 | N62: 248917 | O62: 2618333
B63: 充足率 | F63: 1.3596673 | G63: 0.31772312 | H63: 0.56192744 | I63: 0.49247586 | J63: 0.45211603 | K63: 0.46993845 | L63: 0.27761086 | M63: 0.21024993 | O63: 0.48906249
A65: MAKI de SAUNA | B65: 2025実績 | C65: 0 | D65: 134014 | E65: 118994 | F65: 83911 | G65: 90367 | H65: 116684 | I65: 101322 | J65: 186370 | K65: 56609 | L65: 156028 | M65: 71628 | N65: 153076 | O65: 1269003
B66: 2026予測（5/13） | C66: 0 | D66: 0 | E66: 0 | F66: 121831 | G66: 36276 | H66: 0 | I66: 0 | J66: 0 | K66: 0 | L66: 0 | M66: 0 | N66: 0 | O66: 158107
B67: 充足率 | D67: 0 | E67: 0 | F67: 1.4519074 | G67: 0.40142973 | H67: 0 | I67: 0 | J67: 0 | K67: 0 | L67: 0 | M67: 0 | N67: 0 | O67: 0.12459151
A69: 合計（全施設） | B69: 2025実績 | C69: 19436964 | D69: 18291678 | E69: 27830426 | F69: 30194942 | G69: 34101775 | H69: 23435066 | I69: 37971307 | J69: 55413602 | K69: 31005278 | L69: 42999786 | M69: 43596391 | N69: 28142896 | O69: 392420111
B70: 2026予測 | C70: 0 | D70: 0 | E70: 0 | F70: 34224319 | G70: 35714651 | H70: 14752683 | I70: 10983002 | J70: 12499736 | K70: 8929954 | L70: 7432385 | M70: 6008810 | N70: 5719450 | O70: 136264990
B71: 充足率 | C71: 0 | D71: 0 | E71: 0 | F71: 1.1334454 | G71: 1.047296 | H71: 0.62951318 | I71: 0.28924477 | J71: 0.22557162 | K71: 0.288014 | L71: 0.17284702 | M71: 0.13782815 | N71: 0.20322891 | O71: 0.34724263

Sheet マスター_物件
A1: 物件→会社 マッピング表
A3: 物件名 | B3: 所属会社 | C3: 備考
A4: リゾート | B4: リゾート
A5: ほうらい | B5: リゾート
A6: フォレスト | B6: リゾート
A7: ｸﾞﾘｰﾝｼｬﾜｰ | B7: リゾート
A8: 周防大島 | B8: リゾート
A9: モーテル | B9: モーテル
A10: レジデンス | B10: レジデンス
A11: ココユニバース | B11: ザック

Sheet マスター_勘定科目
A1: 勘定科目→資金繰り項目 マッピング表
A3: 勘定科目 | B3: 資金繰り項目 | C3: 備考
A4: 水道光熱費 | B4: 買掛金支払
A5: 設備費 | B5: 買掛金支払
A6: 通信費 | B6: 買掛金支払
A7: 衛生管理費 | B7: 買掛金支払
A8: 食材費 | B8: 買掛金支払
A9: システム利用料 | B9: 買掛金支払
A10: 業務委託料 | B10: 買掛金支払
A11: 備品消耗品費 | B11: 買掛金支払
A12: ゴミ収集費 | B12: 買掛金支払
A13: 租税公課 | B13: 税金・社会保険料
A14: 保険 | B14: その他経費
A15: 手数料 | B15: その他経費
... A22: 社員給与 | B22: 従業員給与

Sheet マスター_OTA
A1: OTA／決済サイクル マスター（売上計上月に対する入金タイミング）
A2: ※ 当月・翌月・翌々月への分配比率（合計が100%になるように設定）／入金日も指定
A3: OTA／決済名 | B3: 当月比率(%) | C3: 翌月比率(%) | D3: 翌々月比率(%) | E3: 入金日（当月） | F3: 入金日（翌月） | G3: 入金日（翌々月）
A4: Booking | B4: 0 | C4: 100 | D4: 0 | F4: 5
A5: 楽天 | B5: 0 | C5: 100 | D5: 0 | F5: 10
A6: 楽天-25日 | B6: 0 | C6: 100 | D6: 0 | F6: 25
A7: じゃらん | B7: 0 | C7: 100 | D7: 0 | F7: 25
A8: 一休 | B8: 0 | C8: 100 | D8: 0 | F8: 28
A9: Expedia | B9: 0 | C9: 100 | D9: 0 | F9: 25
A10: Agoda | B10: 0 | C10: 100 | D10: 0 | F10: 25
A11: スマレジ | B11: 0 | C11: 100 | D11: 0 | F11: 23
A12: JCB | B12: 0 | C12: 100 | D12: 0 | F12: 23
A13: GMO | B13: 0 | C13: 100 | D13: 0 | F13: 23
A14: JMS | B14: 0 | C14: 100 | D14: 0 | F14: 23
A15: PayPay | B15: 0 | C15: 100 | D15: 0 | F15: 5
A16: カード | B16: 0 | C16: 100 | D16: 0 | F16: 25
A17: 現金売上 | B17: 100 | C17: 0 | D17: 0 | E17: 20
A18: ホテル売上 | B18: 15 | C18: 75 | D18: 10 | E18: 20 | F18: 10 | G18: 25
A19: 竹原市 | B19: 0 | C19: 100 | D19: 0 | F19: 15
A20: 売上 | B20: 15 | C20: 75 | D20: 10 | E20: 20 | F20: 10 | G20: 25
A21: リクルートペイメント | B21: 0 | C21: 100 | D21: 0 | F21: 15
A22: リクルートポイント | B22: 0 | C22: 100 | D22: 0 | F22: 25
A23: イッキュウ | B23: 0 | C23: 100 | D23: 0 | F23: 28
A24: コカ・コーラ | B24: 0 | C24: 100 | D24: 0 | F24: 20
A25: JTB | B25: 0 | C25: 100 | D25: 0 | F25: 25
A26: メルペイ | B26: 0 | C26: 100 | D26: 0 | F26: 10
A27: 振込代行リクルート | B27: 0 | C27: 100 | D27: 0 | F27: 25
A28: 白菱 | B28: 0 | C28: 100 | D28: 0 | F28: 2
A29: ラインプロフェクト | B29: 100 | C29: 0 | D29: 0 | E29: 5

Sheet 入金入力
A1: 入金入力（全社統合・会社列で識別）
A2: ※ 区分は資金繰り表項目／フィルターで会社別／OTA売上連動は「売上入力」へ
A3: 会社 | B3: 日付 | C3: 項目 | D3: 区分 | E3: 金額（円） | F3: 備考 | G3: 入金確認
A4: ココ・ユニバース | B4: 46120 | C4: ユ)パルコ | D4: 現金売上 | E4: 1900000 | F4: 広島銀行0208510 | G4: 確認済
A5: ココ・ユニバース | B5: 46125 | C5: カ)ワールドレイ | D5: 現金売上 | E5: 150000 | F5: 広島銀行0208510 | G5: 確認済
A6: ココ・ユニバース | B6: 46125 | C6: カ)ココユニバース | D6: 現金売上 | E6: 700000 | F6: 広島銀行0208510-社内振替 | G6: 確認済
A7: ココ・ユニバース | B7: 46127 | C7: カ)ケアイコミュニティ | D7: 現金売上 | E7: 730900 | F7: 広島銀行0208510 | G7: 確認済
A8: ココ・ユニバース | B8: 46133 | C8: 振込入金 | D8: 現金売上 | E8: 401500 | F8: 広島銀行0208510 | G8: 確認済
A9: ココ・ユニバース | B9: 46133 | C9: ユ)パルコ | D9: 現金売上 | E9: 921800 | F9: 広島銀行0208510 | G9: 確認済
A10: ココ・ユニバース | B10: 46137 | C10: カ)ココユニバース | D10: 現金売上 | E10: 560000 | F10: 広島銀行0208510-社内振替 | G10: 確認済
A11: ココ・ユニバース | B11: 46144 | C11: カ)ココユニバース | D11: 現金売上 | E11: 300000 | F11: 広島銀行0208510-社内振替 | G11: 確認済
A12: ココ・ユニバース | B12: 46153 | C12: ユ)パルコ | D12: 現金売上 | E12: 1900000 | F12: 広島銀行0208510 | G12: 確認済
A13: ココ・ユニバース | B13: 46181 | C13: ユ)パルコ（月次予測） | D13: 現金売上 | E13: 1900000 | F13: パルコ系月次予測 | G13: 予測
A14: ココ・ユニバース | B14: 46194 | C14: ユ)パルコ（月次予測） | D14: 現金売上 | E14: 921800 | F14: パルコ系月次予測 | G14: 予測
A15: ココ・ユニバース | B15: 46188 | C15: カ)ケアイコミュニティ（月次予測） | D15: 現金売上 | E15: 700000 | F15: ケアイコミュニティ月次予測 | G15: 予測
... A380: モーテル | B380: 46173 | C380: 現金売上 | D380: 現金売上 | E380: 377864 | F380: 4月実績ベース予測（4/30相当） | G380: 予測
A505: 合計 | E505: =SUM(E4:E503) -> 209454107

Sheet 売上入力
A1: 売上入力（OTA別／施設別／月別の売上）
A2: ※ 売上計上月にOTA・施設・売上額を入力 → マスター_OTAの分配比率で入金予測へ自動展開
A3: 計上月 | B3: 会社 | C3: 施設 | D3: OTA／決済 | E3: 売上額（円） | F3: 備考
A4: 46113 | B4: ザック | C4: MAKI de SAUNA | D4: 売上 | E4: 0 | F4: [サウナ] 5/13予約ベース [元売上額: 121,831円 - 入金確認表で実績計上済みのためゼロ化]
A5: 46113 | B5: リゾート | C5: Otake | D5: 売上 | E5: 0 | F5: [マンスリー] 5/13予約ベース [元売上額: 105,000円 - 入金確認表で実績計上済みのためゼロ化]
A6: 46113 | B6: リゾート | C6: TAKAYA | D6: 売上 | E6: 0 | F6: [マンスリー] 5/13予約ベース [元売上額: 455,000円 - 入金確認表で実績計上済みのためゼロ化]
A7: 46113 | B7: リゾート | C7: VIEW | D7: ホテル売上 | E7: 0 | F7: [ホテル] 5/13予約ベース [元売上額: 2,904,045円 - 入金確認表で実績計上済みのためゼロ化]
A8: 46113 | B8: リゾート | C8: de Lune | D8: ホテル売上 | E8: 0 | F8: [ホテル] 5/13予約ベース [元売上額: 8,310,821円 - 入金確認表で実績計上済みのためゼロ化]
A9: 46113 | B9: リゾート | C9: いこいの村 | D9: ホテル売上 | E9: 0 | F9: [ホテル] 5/13予約ベース [元売上額: 6,092,392円 - 入金確認表で実績計上済みのためゼロ化]
A10: 46113 | B10: リゾート | C10: グリーンシャワー | D10: 売上 | E10: 0 | F10: [指定管理] 5/13予約ベース [元売上額: 626,997円 - 入金確認表で実績計上済みのためゼロ化]
A11: 46113 | B11: リゾート | C11: フォレストヒルズガーデン | D11: 売上 | E11: 0 | F11: [指定管理] 5/13予約ベース [元売上額: 5,535,949円 - 入金確認表で実績計上済みのためゼロ化]
A12: 46113 | B12: リゾート | C12: 壱番館 | D12: 売上 | E12: 0 | F12: [マンスリー] 5/13予約ベース [元売上額: 101,400円 - 入金確認表で実績計上済みのためゼロ化]
A13: 46113 | B13: リゾート | C13: 天神 | D13: ホテル売上 | E13: 0 | F13: [ホテル] 5/13予約ベース [元売上額: 56,700円 - 入金確認表で実績計上済みのためゼロ化]
A14: 46113 | B14: リゾート | C14: 弐番館 | D14: 売上 | E14: 0 | F14: [マンスリー] 5/13予約ベース [元売上額: 90,000円 - 入金確認表で実績計上済みのためゼロ化]
A15: 46113 | B15: モーテル | C15: 弥山 | D15: ホテル売上 | E15: 0 | F15: [ホテル] 5/13予約ベース [元売上額: 4,004,248円 - 入金確認表で実績計上済みのためゼロ化]
... A98: 46357 | B98: リゾート | C98: 竹原（ﾚｽﾄﾗﾝ含む） | D98: 竹原市 | E98: 683000 | F98: [指定管理] 5/13予約ベース
A205: 合計 | E205: =SUM(E4:E203) -> 247638350

Sheet 入金予測
A1: 入金予測（売上入力 × マスター_OTA の比率で自動計算）
A2: ※ 売上入力1行につき最大3行（当月/翌月/翌々月）の予測を自動展開／月次サマリーの入金へ自動加算
A3: 予測入金日 | B3: 会社 | C3: 施設 | D3: OTA／決済 | E3: 予測入金額（円） | F3: 売上計上月 | G3: 備考
A4: =IFERROR(IF(売上入力!A4="","",IF(INDEX(マスター_OTA!$B$4:$B$29,MATCH(売上入力!D4,マスター_OTA!$A$4:$A$29,0))=0,"",DATE(YEAR(売上入力!A4),MONTH(売上入力!A4),IFERROR(INDEX(マスター_OTA!$E$4:$E$29,MATCH(売上入力!D4,マスター_OTA!$A$4:$A$29,0)),28)))),"") -> 46132 | B4: =IF(売上入力!B4="","",売上入力!B4) -> ザック | C4: =IF(売上入力!C4="","",売上入力!C4) -> MAKI de SAUNA | D4: =IF(売上入力!D4="","",売上入力!D4) -> 売上 | E4: =IFERROR(IF(売上入力!E4="",0,売上入力!E4*INDEX(マスター_OTA!$B$4:$B$29,MATCH(売上入力!D4,マスター_OTA!$A$4:$A$29,0))/100),0) -> 0 | F4: =IF(売上入力!A4="","",売上入力!A4) -> 46113 | G4: 当月分
A5: =IFERROR(IF(売上入力!A4="","",IF(INDEX(マスター_OTA!$C$4:$C$29,MATCH(売上入力!D4,マスター_OTA!$A$4:$A$29,0))=0,"",DATE(YEAR(売上入力!A4),MONTH(売上入力!A4)+1,IFERROR(INDEX(マスター_OTA!$F$4:$F$29,MATCH(売上入力!D4,マスター_OTA!$A$4:$A$29,0)),25)))),"") -> 46152 | B5: =IF(売上入力!B4="","",売上入力!B4) -> ザック | C5: =IF(売上入力!C4="","",売上入力!C4) -> MAKI de SAUNA | D5: =IF(売上入力!D4="","",売上入力!D4) -> 売上 | E5: =IFERROR(IF(売上入力!E4="",0,売上入力!E4*INDEX(マスター_OTA!$C$4:$C$29,MATCH(売上入力!D4,マスター_OTA!$A$4:$A$29,0))/100),0) -> 0 | F5: =IF(売上入力!A4="","",売上入力!A4) -> 46113 | G5: 翌月分
A6: =IFERROR(IF(売上入力!A4="","",IF(INDEX(マスター_OTA!$D$4:$D$29,MATCH(売上入力!D4,マスター_OTA!$A$4:$A$29,0))=0,"",DATE(YEAR(売上入力!A4),MONTH(売上入力!A4)+2,IFERROR(INDEX(マスター_OTA!$G$4:$G$29,MATCH(売上入力!D4,マスター_OTA!$A$4:$A$29,0)),25)))),"") -> 46198 | B6: =IF(売上入力!B4="","",売上入力!B4) -> ザック | C6: =IF(売上入力!C4="","",売上入力!C4) -> MAKI de SAUNA | D6: =IF(売上入力!D4="","",売上入力!D4) -> 売上 | E6: =IFERROR(IF(売上入力!E4="",0,売上入力!E4*INDEX(マスター_OTA!$D$4:$D$29,MATCH(売上入力!D4,マスター_OTA!$A$4:$A$29,0))/100),0) -> 0 | F6: =IF(売上入力!A4="","",売上入力!A4) -> 46113 | G6: 翌々月分
A7: =IFERROR(IF(売上入力!A5="","",IF(INDEX(マスター_OTA!$B$4:$B$29,MATCH(売上入力!D5,マスター_OTA!$A$4:$A$29,0))=0,"",DATE(YEAR(売上入力!A5),MONTH(売上入力!A5),IFERROR(INDEX(マスター_OTA!$E$4:$E$29,MATCH(売上入力!D5,マスター_OTA!$A$4:$A$29,0)),28)))),"") -> 46132 | B7: =IF(売上入力!B5="","",売上入力!B5) -> リゾート | C7: =IF(売上入力!C5="","",売上入力!C5) -> Otake | D7: =IF(売上入力!D5="","",売上入力!D5) -> 売上 | E7: =IFERROR(IF(売上入力!E5="",0,売上入力!E5*INDEX(マスター_OTA!$B$4:$B$29,MATCH(売上入力!D5,マスター_OTA!$A$4:$A$29,0))/100),0) -> 0 | F7: =IF(売上入力!A5="","",売上入力!A5) -> 46113 | G7: 当月分
A8: =IFERROR(IF(売上入力!A5="","",IF(INDEX(マスター_OTA!$C$4:$C$29,MATCH(売上入力!D5,マスター_OTA!$A$4:$A$29,0))=0,"",DATE(YEAR(売上入力!A5),MONTH(売上入力!A5)+1,IFERROR(INDEX(マスター_OTA!$F$4:$F$29,MATCH(売上入力!D5,マスター_OTA!$A$4:$A$29,0)),25)))),"") -> 46152 | B8: =IF(売上入力!B5="","",売上入力!B5) -> リゾート | C8: =IF(売上入力!C5="","",売上入力!C5) -> Otake | D8: =IF(売上入力!D5="","",売上入力!D5) -> 売上 | E8: =IFERROR(IF(売上入力!E5="",0,売上入力!E5*INDEX(マスター_OTA!$C$4:$C$29,MATCH(売上入力!D5,マスター_OTA!$A$4:$A$29,0))/100),0) -> 0 | F8: =IF(売上入力!A5="","",売上入力!A5) -> 46113 | G8: 翌月分
A9: =IFERROR(IF(売上入力!A5="","",IF(INDEX(マスター_OTA!$D$4:$D$29,MATCH(売上入力!D5,マスター_OTA!$A$4:$A$29,0))=0,"",DATE(YEAR(売上入力!A5),MONTH(売上入力!A5)+2,IFERROR(INDEX(マスター_OTA!$G$4:$G$29,MATCH(売上入力!D5,マスター_OTA!$A$4:$A$29,0)),25)))),"") -> 46198 | B9: =IF(売上入力!B5="","",売上入力!B5) -> リゾート | C9: =IF(売上入力!C5="","",売上入力!C5) -> Otake | D9: =IF(売上入力!D5="","",売上入力!D5) -> 売上 | E9: =IFERROR(IF(売上入力!E5="",0,売上入力!E5*INDEX(マスター_OTA!$D$4:$D$29,MATCH(売上入力!D5,マスター_OTA!$A$4:$A$29,0))/100),0) -> 0 | F9: =IF(売上入力!A5="","",売上入力!A5) -> 46113 | G9: 翌々月分
A10: =IFERROR(IF(売上入力!A6="","",IF(INDEX(マスター_OTA!$B$4:$B$29,MATCH(売上入力!D6,マスター_OTA!$A$4:$A$29,0))=0,"",DATE(YEAR(売上入力!A6),MONTH(売上入力!A6),IFERROR(INDEX(マスター_OTA!$E$4:$E$29,MATCH(売上入力!D6,マスター_OTA!$A$4:$A$29,0)),28)))),"") -> 46132 | B10: =IF(売上入力!B6="","",売上入力!B6) -> リゾート | C10: =IF(売上入力!C6="","",売上入力!C6) -> TAKAYA | D10: =IF(売上入力!D6="","",売上入力!D6) -> 売上 | E10: =IFERROR(IF(売上入力!E6="",0,売上入力!E6*INDEX(マスター_OTA!$B$4:$B$29,MATCH(売上入力!D6,マスター_OTA!$A$4:$A$29,0))/100),0) -> 0 | F10: =IF(売上入力!A6="","",売上入力!A6) -> 46113 | G10: 当月分
A11: =IFERROR(IF(売上入力!A6="","",IF(INDEX(マスター_OTA!$C$4:$C$29,MATCH(売上入力!D6,マスター_OTA!$A$4:$A$29,0))=0,"",DATE(YEAR(売上入力!A6),MONTH(売上入力!A6)+1,IFERROR(INDEX(マスター_OTA!$F$4:$F$29,MATCH(売上入力!D6,マスター_OTA!$A$4:$A$29,0)),25)))),"") -> 46152 | B11: =IF(売上入力!B6="","",売上入力!B6) -> リゾート | C11: =IF(売上入力!C6="","",売上入力!C6) -> TAKAYA | D11: =IF(売上入力!D6="","",売上入力!D6) -> 売上 | E11: =IFERROR(IF(売上入力!E6="",0,売上入力!E6*INDEX(マスター_OTA!$C$4:$C$29,MATCH(売上入力!D6,マスター_OTA!$A$4:$A$29,0))/100),0) -> 0 | F11: =IF(売上入力!A6="","",売上入力!A6) -> 46113 | G11: 翌月分
A12: =IFERROR(IF(売上入力!A6="","",IF(INDEX(マスター_OTA!$D$4:$D$29,MATCH(売上入力!D6,マスター_OTA!$A$4:$A$29,0))=0,"",DATE(YEAR(売上入力!A6),MONTH(売上入力!A6)+2,IFERROR(INDEX(マスター_OTA!$G$4:$G$29,MATCH(売上入力!D6,マスター_OTA!$A$4:$A$29,0)),25)))),"") -> 46198 | B12: =IF(売上入力!B6="","",売上入力!B6) -> リゾート | C12: =IF(売上入力!C6="","",売上入力!C6) -> TAKAYA | D12: =IF(売上入力!D6="","",売上入力!D6) -> 売上 | E12: =IFERROR(IF(売上入力!E6="",0,売上入力!E6*INDEX(マスター_OTA!$D$4:$D$29,MATCH(売上入力!D6,マスター_OTA!$A$4:$A$29,0))/100),0) -> 0 | F12: =IF(売上入力!A6="","",売上入力!A6) -> 46113 | G12: 翌々月分
A13: =IFERROR(IF(売上入力!A7="","",IF(INDEX(マスター_OTA!$B$4:$B$29,MATCH(売上入力!D7,マスター_OTA!$A$4:$A$29,0))=0,"",DATE(YEAR(売上入力!A7),MONTH(売上入力!A7),IFERROR(INDEX(マスター_OTA!$E$4:$E$29,MATCH(売上入力!D7,マスター_OTA!$A$4:$A$29,0)),28)))),"") -> 46132 | B13: =IF(売上入力!B7="","",売上入力!B7) -> リゾート | C13: =IF(売上入力!C7="","",売上入力!C7) -> VIEW | D13: =IF(売上入力!D7="","",売上入力!D7) -> ホテル売上 | E13: =IFERROR(IF(売上入力!E7="",0,売上入力!E7*INDEX(マスター_OTA!$B$4:$B$29,MATCH(売上入力!D7,マスター_OTA!$A$4:$A$29,0))/100),0) -> 0 | F13: =IF(売上入力!A7="","",売上入力!A7) -> 46113 | G13: 当月分
A14: =IFERROR(IF(売上入力!A7="","",IF(INDEX(マスター_OTA!$C$4:$C$29,MATCH(売上入力!D7,マスター_OTA!$A$4:$A$29,0))=0,"",DATE(YEAR(売上入力!A7),MONTH(売上入力!A7)+1,IFERROR(INDEX(マスター_OTA!$F$4:$F$29,MATCH(売上入力!D7,マスター_OTA!$A$4:$A$29,0)),25)))),"") -> 46152 | B14: =IF(売上入力!B7="","",売上入力!B7) -> リゾート | C14: =IF(売上入力!C7="","",売上入力!C7) -> VIEW | D14: =IF(売上入力!D7="","",売上入力!D7) -> ホテル売上 | E14: =IFERROR(IF(売上入力!E7="",0,売上入力!E7*INDEX(マスター_OTA!$C$4:$C$29,MATCH(売上入力!D7,マスター_OTA!$A$4:$A$29,0))/100),0) -> 0 | F14: =IF(売上入力!A7="","",売上入力!A7) -> 46113 | G14: 翌月分
A15: =IFERROR(IF(売上入力!A7="","",IF(INDEX(マスター_OTA!$D$4:$D$29,MATCH(売上入力!D7,マスター_OTA!$A$4:$A$29,0))=0,"",DATE(YEAR(売上入力!A7),MONTH(売上入力!A7)+2,IFERROR(INDEX(マスター_OTA!$G$4:$G$29,MATCH(売上入力!D7,マスター_OTA!$A$4:$A$29,0)),25)))),"") -> 46198 | B15: =IF(売上入力!B7="","",売上入力!B7) -> リゾート | C15: =IF(売上入力!C7="","",売上入力!C7) -> VIEW | D15: =IF(売上入力!D7="","",売上入力!D7) -> ホテル売上 | E15: =IFERROR(IF(売上入力!E7="",0,売上入力!E7*INDEX(マスター_OTA!$D$4:$D$29,MATCH(売上入力!D7,マスター_OTA!$A$4:$A$29,0))/100),0) -> 0 | F15: =IF(売上入力!A7="","",売上入力!A7) -> 46113 | G15: 翌々月分
A16: =IFERROR(IF(売上入力!A8="","",IF(INDEX(マスター_OTA!$B$4:$B$29,MATCH(売上入力!D8,マスター_OTA!$A$4:$A$29,0))=0,"",DATE(YEAR(売上入力!A8),MONTH(売上入力!A8),IFERROR(INDEX(マスター_OTA!$E$4:$E$29,MATCH(売上入力!D8,マスター_OTA!$A$4:$A$29,0)),28)))),"") -> 46132 | B16: =IF(売上入力!B8="","",売上入力!B8) -> リゾート | C16: =IF(売上入力!C8="","",売上入力!C8) -> de Lune | D16: =IF(売上入力!D8="","",売上入力!D8) -> ホテル売上 | E16: =IFERROR(IF(売上入力!E8="",0,売上入力!E8*INDEX(マスター_OTA!$B$4:$B$29,MATCH(売上入力!D8,マスター_OTA!$A$4:$A$29,0))/100),0) -> 0 | F16: =IF(売上入力!A8="","",売上入力!A8) -> 46113 | G16: 当月分
A17: =IFERROR(IF(売上入力!A8="","",IF(INDEX(マスター_OTA!$C$4:$C$29,MATCH(売上入力!D8,マスター_OTA!$A$4:$A$29,0))=0,"",DATE(YEAR(売上入力!A8),MONTH(売上入力!A8)+1,IFERROR(INDEX(マスター_OTA!$F$4:$F$29,MATCH(売上入力!D8,マスター_OTA!$A$4:$A$29,0)),25)))),"") -> 46152 | B17: =IF(売上入力!B8="","",売上入力!B8) -> リゾート | C17: =IF(売上入力!C8="","",売上入力!C8) -> de Lune | D17: =IF(売上入力!D8="","",売上入力!D8) -> ホテル売上 | E17: =IFERROR(IF(売上入力!E8="",0,売上入力!E8*INDEX(マスター_OTA!$C$4:$C$29,MATCH(売上入力!D8,マスター_OTA!$A$4:$A$29,0))/100),0) -> 0 | F17: =IF(売上入力!A8="","",売上入力!A8) -> 46113 | G17: 翌月分
A18: =IFERROR(IF(売上入力!A8="","",IF(INDEX(マスター_OTA!$D$4:$D$29,MATCH(売上入力!D8,マスター_OTA!$A$4:$A$29,0))=0,"",DATE(YEAR(売上入力!A8),MONTH(売上入力!A8)+2,IFERROR(INDEX(マスター_OTA!$G$4:$G$29,MATCH(売上入力!D8,マスター_OTA!$A$4:$A$29,0)),25)))),"") -> 46198 | B18: =IF(売上入力!B8="","",売上入力!B8) -> リゾート | C18: =IF(売上入力!C8="","",売上入力!C8) -> de Lune | D18: =IF(売上入力!D8="","",売上入力!D8) -> ホテル売上 | E18: =IFERROR(IF(売上入力!E8="",0,売上入力!E8*INDEX(マスター_OTA!$D$4:$D$29,MATCH(売上入力!D8,マスター_OTA!$A$4:$A$29,0))/100),0) -> 0 | F18: =IF(売上入力!A8="","",売上入力!A8) -> 46113 | G18: 翌々月分
A19: =IFERROR(IF(売上入力!A9="","",IF(INDEX(マスター_OTA!$B$4:$B$29,MATCH(売上入力!D9,マスター_OTA!$A$4:$A$29,0))=0,"",DATE(YEAR(売上入力!A9),MONTH(売上入力!A9),IFERROR(INDEX(マスター_OTA!$E$4:$E$29,MATCH(売上入力!D9,マスター_OTA!$A$4:$A$29,0)),28)))),"") -> 46132 | B19: =IF(売上入力!B9="","",売上入力!B9) -> リゾート | C19: =IF(売上入力!C9="","",売上入力!C9) -> いこいの村 | D19: =IF(売上入力!D9="","",売上入力!D9) -> ホテル売上 | E19: =IFERROR(IF(売上入力!E9="",0,売上入力!E9*INDEX(マスター_OTA!$B$4:$B$29,MATCH(売上入力!D9,マスター_OTA!$A$4:$A$29,0))/100),0) -> 0 | F19: =IF(売上入力!A9="","",売上入力!A9) -> 46113 | G19: 当月分
A20: =IFERROR(IF(売上入力!A9="","",IF(INDEX(マスター_OTA!$C$4:$C$29,MATCH(売上入力!D9,マスター_OTA!$A$4:$A$29,0))=0,"",DATE(YEAR(売上入力!A9),MONTH(売上入力!A9)+1,IFERROR(INDEX(マスター_OTA!$F$4:$F$29,MATCH(売上入力!D9,マスター_OTA!$A$4:$A$29,0)),25)))),"") -> 46152 | B20: =IF(売上入力!B9="","",売上入力!B9) -> リゾート | C20: =IF(売上入力!C9="","",売上入力!C9) -> いこいの村 | D20: =IF(売上入力!D9="","",売上入力!D9) -> ホテル売上 | E20: =IFERROR(IF(売上入力!E9="",0,売上入力!E9*INDEX(マスター_OTA!$C$4:$C$29,MATCH(売上入力!D9,マスター_OTA!$A$4:$A$29,0))/100),0) -> 0 | F20: =IF(売上入力!A9="","",売上入力!A9) -> 46113 | G20: 翌月分
A21: =IFERROR(IF(売上入力!A9="","",IF(INDEX(マスター_OTA!$D$4:$D$29,MATCH(売上入力!D9,マスター_OTA!$A$4:$A$29,0))=0,"",DATE(YEAR(売上入力!A9),MONTH(売上入力!A9)+2,IFERROR(INDEX(マスター_OTA!$G$4:$G$29,MATCH(売上入力!D9,マスター_OTA!$A$4:$A$29,0)),25)))),"") -> 46198 | B21: =IF(売上入力!B9="","",売上入力!B9) -> リゾート | C21: =IF(売上入力!C9="","",売上入力!C9) -> いこいの村 | D21: =IF(売上入力!D9="","",売上入力!D9) -> ホテル売上 | E21: =IFERROR(IF(売上入力!E9="",0,売上入力!E9*INDEX(マスター_OTA!$D$4:$D$29,MATCH(売上入力!D9,マスター_OTA!$A$4:$A$29,0))/100),0) -> 0 | F21: =IF(売上入力!A9="","",売上入力!A9) -> 46113 | G21: 翌々月分
A22: =IFERROR(IF(売上入力!A10="","",IF(INDEX(マスター_OTA!$B$4:$B$29,MATCH(売上入力!D10,マスター_OTA!$A$4:$A$29,0))=0,"",DATE(YEAR(売上入力!A10),MONTH(売上入力!A10),IFERROR(INDEX(マスター_OTA!$E$4:$E$29,MATCH(売上入力!D10,マスター_OTA!$A$4:$A$29,0)),28)))),"") -> 46132 | B22: =IF(売上入力!B10="","",売上入力!B10) -> リゾート | C22: =IF(売上入力!C10="","",売上入力!C10) -> グリーンシャワー | D22: =IF(売上入力!D10="","",売上入力!D10) -> 売上 | E22: =IFERROR(IF(売上入力!E10="",0,売上入力!E10*INDEX(マスター_OTA!$B$4:$B$29,MATCH(売上入力!D10,マスター_OTA!$A$4:$A$29,0))/100),0) -> 0 | F22: =IF(売上入力!A10="","",売上入力!A10) -> 46113 | G22: 当月分
A23: =IFERROR(IF(売上入力!A10="","",IF(INDEX(マスター_OTA!$C$4:$C$29,MATCH(売上入力!D10,マスター_OTA!$A$4:$A$29,0))=0,"",DATE(YEAR(売上入力!A10),MONTH(売上入力!A10)+1,IFERROR(INDEX(マスター_OTA!$F$4:$F$29,MATCH(売上入力!D10,マスター_OTA!$A$4:$A$29,0)),25)))),"") -> 46152 | B23: =IF(売上入力!B10="","",売上入力!B10) -> リゾート | C23: =IF(売上入力!C10="","",売上入力!C10) -> グリーンシャワー | D23: =IF(売上入力!D10="","",売上入力!D10) -> 売上 | E23: =IFERROR(IF(売上入力!E10="",0,売上入力!E10*INDEX(マスター_OTA!$C$4:$C$29,MATCH(売上入力!D10,マスター_OTA!$A$4:$A$29,0))/100),0) -> 0 | F23: =IF(売上入力!A10="","",売上入力!A10) -> 46113 | G23: 翌月分
A24: =IFERROR(IF(売上入力!A10="","",IF(INDEX(マスター_OTA!$D$4:$D$29,MATCH(売上入力!D10,マスター_OTA!$A$4:$A$29,0))=0,"",DATE(YEAR(売上入力!A10),MONTH(売上入力!A10)+2,IFERROR(INDEX(マスター_OTA!$G$4:$G$29,MATCH(売上入力!D10,マスター_OTA!$A$4:$A$29,0)),25)))),"") -> 46198 | B24: =IF(売上入力!B10="","",売上入力!B10) -> リゾート | C24: =IF(売上入力!C10="","",売上入力!C10) -> グリーンシャワー | D24: =IF(売上入力!D10="","",売上入力!D10) -> 売上 | E24: =IFERROR(IF(売上入力!E10="",0,売上入力!E10*INDEX(マスター_OTA!$D$4:$D$29,MATCH(売上入力!D10,マスター_OTA!$A$4:$A$29,0))/100),0) -> 0 | F24: =IF(売上入力!A10="","",売上入力!A10) -> 46113 | G24: 翌々月分
A25: =IFERROR(IF(売上入力!A11="","",IF(INDEX(マスター_OTA!$B$4:$B$29,MATCH(売上入力!D11,マスター_OTA!$A$4:$A$29,0))=0,"",DATE(YEAR(売上入力!A11),MONTH(売上入力!A11),IFERROR(INDEX(マスター_OTA!$E$4:$E$29,MATCH(売上入力!D11,マスター_OTA!$A$4:$A$29,0)),28)))),"") -> 46132 | B25: =IF(売上入力!B11="","",売上入力!B11) -> リゾート | C25: =IF(売上入力!C11="","",売上入力!C11) -> フォレストヒルズガーデン | D25: =IF(売上入力!D11="","",売上入力!D11) -> 売上 | E25: =IFERROR(IF(売上入力!E11="",0,売上入力!E11*INDEX(マスター_OTA!$B$4:$B$29,MATCH(売上入力!D11,マスター_OTA!$A$4:$A$29,0))/100),0) -> 0 | F25: =IF(売上入力!A11="","",売上入力!A11) -> 46113 | G25: 当月分
A26: =IFERROR(IF(売上入力!A11="","",IF(INDEX(マスター_OTA!$C$4:$C$29,MATCH(売上入力!D11,マスター_OTA!$A$4:$A$29,0))=0,"",DATE(YEAR(売上入力!A11),MONTH(売上入力!A11)+1,IFERROR(INDEX(マスター_OTA!$F$4:$F$29,MATCH(売上入力!D11,マスター_OTA!$A$4:$A$29,0)),25)))),"") -> 46152 | B26: =IF(売上入力!B11="","",売上入力!B11) -> リゾート | C26: =IF(売上入力!C11="","",売上入力!C11) -> フォレストヒルズガーデン | D26: =IF(売上入力!D11="","",売上入力!D11) -> 売上 | E26: =IFERROR(IF(売上入力!E11="",0,売上入力!E11*INDEX(マスター_OTA!$C$4:$C$29,MATCH(売上入力!D11,マスター_OTA!$A$4:$A$29,0))/100),0) -> 0 | F26: =IF(売上入力!A11="","",売上入力!A11) -> 46113 | G26: 翌月分
A27: =IFERROR(IF(売上入力!A11="","",IF(INDEX(マスター_OTA!$D$4:$D$29,MATCH(売上入力!D11,マスター_OTA!$A$4:$A$29,0))=0,"",DATE(YEAR(売上入力!A11),MONTH(売上入力!A11)+2,IFERROR(INDEX(マスター_OTA!$G$4:$G$29,MATCH(売上入力!D11,マスター_OTA!$A$4:$A$29,0)),25)))),"") -> 46198 | B27: =IF(売上入力!B11="","",売上入力!B11) -> リゾート | C27: =IF(売上入力!C11="","",売上入力!C11) -> フォレストヒルズガーデン | D27: =IF(売上入力!D11="","",売上入力!D11) -> 売上 | E27: =IFERROR(IF(売上入力!E11="",0,売上入力!E11*INDEX(マスター_OTA!$D$4:$D$29,MATCH(売上入力!D11,マスター_OTA!$A$4:$A$29,0))/100),0) -> 0 | F27: =IF(売上入力!A11="","",売上入力!A11) -> 46113 | G27: 翌々月分
A28: =IFERROR(IF(売上入力!A12="","",IF(INDEX(マスター_OTA!$B$4:$B$29,MATCH(売上入力!D12,マスター_OTA!$A$4:$A$29,0))=0,"",DATE(YEAR(売上入力!A12),MONTH(売上入力!A12),IFERROR(INDEX(マスター_OTA!$E$4:$E$29,MATCH(売上入力!D12,マスター_OTA!$A$4:$A$29,0)),28)))),"") -> 46132 | B28: =IF(売上入力!B12="","",売上入力!B12) -> リゾート | C28: =IF(売上入力!C12="","",売上入力!C12) -> 壱番館 | D28: =IF(売上入力!D12="","",売上入力!D12) -> 売上 | E28: =IFERROR(IF(売上入力!E12="",0,売上入力!E12*INDEX(マスター_OTA!$B$4:$B$29,MATCH(売上入力!D12,マスター_OTA!$A$4:$A$29,0))/100),0) -> 0 | F28: =IF(売上入力!A12="","",売上入力!A12) -> 46113 | G28: 当月分
A29: =IFERROR(IF(売上入力!A12="","",IF(INDEX(マスター_OTA!$C$4:$C$29,MATCH(売上入力!D12,マスター_OTA!$A$4:$A$29,0))=0,"",DATE(YEAR(売上入力!A12),MONTH(売上入力!A12)+1,IFERROR(INDEX(マスター_OTA!$F$4:$F$29,MATCH(売上入力!D12,マスター_OTA!$A$4:$A$29,0)),25)))),"") -> 46152 | B29: =IF(売上入力!B12="","",売上入力!B12) -> リゾート | C29: =IF(売上入力!C12="","",売上入力!C12) -> 壱番館 | D29: =IF(売上入力!D12="","",売上入力!D12) -> 売上 | E29: =IFERROR(IF(売上入力!E12="",0,売上入力!E12*INDEX(マスター_OTA!$C$4:$C$29,MATCH(売上入力!D12,マスター_OTA!$A$4:$A$29,0))/100),0) -> 0 | F29: =IF(売上入力!A12="","",売上入力!A12) -> 46113 | G29: 翌月分
A30: =IFERROR(IF(売上入力!A12="","",IF(INDEX(マスター_OTA!$D$4:$D$29,MATCH(売上入力!D12,マスター_OTA!$A$4:$A$29,0))=0,"",DATE(YEAR(売上入力!A12),MONTH(売上入力!A12)+2,IFERROR(INDEX(マスター_OTA!$G$4:$G$29,MATCH(売上入力!D12,マスター_OTA!$A$4:$A$29,0)),25)))),"") -> 46198 | B30: =IF(売上入力!B12="","",売上入力!B12) -> リゾート | C30: =IF(売上入力!C12="","",売上入力!C12) -> 壱番館 | D30: =IF(売上入力!D12="","",売上入力!D12) -> 売上 | E30: =IFERROR(IF(売上入力!E12="",0,売上入力!E12*INDEX(マスター_OTA!$D$4:$D$29,MATCH(売上入力!D12,マスター_OTA!$A$4:$A$29,0))/100),0) -> 0 | F30: =IF(売上入力!A12="","",売上入力!A12) -> 46113 | G30: 翌々月分
A31: =IFERROR(IF(売上入力!A13="","",IF(INDEX(マスター_OTA!$B$4:$B$29,MATCH(売上入力!D13,マスター_OTA!$A$4:$A$29,0))=0,"",DATE(YEAR(売上入力!A13),MONTH(売上入力!A13),IFERROR(INDEX(マスター_OTA!$E$4:$E$29,MATCH(売上入力!D13,マスター_OTA!$A$4:$A$29,0)),28)))),"") -> 46132 | B31: =IF(売上入力!B13="","",売上入力!B13) -> リゾート | C31: =IF(売上入力!C13="","",売上入力!C13) -> 天神 | D31: =IF(売上入力!D13="","",売上入力!D13) -> ホテル売上 | E31: =IFERROR(IF(売上入力!E13="",0,売上入力!E13*INDEX(マスター_OTA!$B$4:$B$29,MATCH(売上入力!D13,マスター_OTA!$A$4:$A$29,0))/100),0) -> 0 | F31: =IF(売上入力!A13="","",売上入力!A13) -> 46113 | G31: 当月分
A32: =IFERROR(IF(売上入力!A13="","",IF(INDEX(マスター_OTA!$C$4:$C$29,MATCH(売上入力!D13,マスター_OTA!$A$4:$A$29,0))=0,"",DATE(YEAR(売上入力!A13),MONTH(売上入力!A13)+1,IFERROR(INDEX(マスター_OTA!$F$4:$F$29,MATCH(売上入力!D13,マスター_OTA!$A$4:$A$29,0)),25)))),"") -> 46152 | B32: =IF(売上入力!B13="","",売上入力!B13) -> リゾート | C32: =IF(売上入力!C13="","",売上入力!C13) -> 天神 | D32: =IF(売上入力!D13="","",売上入力!D13) -> ホテル売上 | E32: =IFERROR(IF(売上入力!E13="",0,売上入力!E13*INDEX(マスター_OTA!$C$4:$C$29,MATCH(売上入力!D13,マスター_OTA!$A$4:$A$29,0))/100),0) -> 0 | F32: =IF(売上入力!A13="","",売上入力!A13) -> 46113 | G32: 翌月分
A33: =IFERROR(IF(売上入力!A13="","",IF(INDEX(マスター_OTA!$D$4:$D$29,MATCH(売上入力!D13,マスター_OTA!$A$4:$A$29,0))=0,"",DATE(YEAR(売上入力!A13),MONTH(売上入力!A13)+2,IFERROR(INDEX(マスター_OTA!$G$4:$G$29,MATCH(売上入力!D13,マスター_OTA!$A$4:$A$29,0)),25)))),"") -> 46198 | B33: =IF(売上入力!B13="","",売上入力!B13) -> リゾート | C33: =IF(売上入力!C13="","",売上入力!C13) -> 天神 | D33: =IF(売上入力!D13="","",売上入力!D13) -> ホテル売上 | E33: =IFERROR(IF(売上入力!E13="",0,売上入力!E13*INDEX(マスター_OTA!$D$4:$D$29,MATCH(売上入力!D13,マスター_OTA!$A$4:$A$29,0))/100),0) -> 0 | F33: =IF(売上入力!A13="","",売上入力!A13) -> 46113 | G33: 翌々月分
A34: =IFERROR(IF(売上入力!A14="","",IF(INDEX(マスター_OTA!$B$4:$B$29,MATCH(売上入力!D14,マスター_OTA!$A$4:$A$29,0))=0,"",DATE(YEAR(売上入力!A14),MONTH(売上入力!A14),IFERROR(INDEX(マスター_OTA!$E$4:$E$29,MATCH(売上入力!D14,マスター_OTA!$A$4:$A$29,0)),28)))),"") -> 46132 | B34: =IF(売上入力!B14="","",売上入力!B14) -> リゾート | C34: =IF(売上入力!C14="","",売上入力!C14) -> 弐番館 | D34: =IF(売上入力!D14="","",売上入力!D14) -> 売上 | E34: =IFERROR(IF(売上入力!E14="",0,売上入力!E14*INDEX(マスター_OTA!$B$4:$B$29,MATCH(売上入力!D14,マスター_OTA!$A$4:$A$29,0))/100),0) -> 0 | F34: =IF(売上入力!A14="","",売上入力!A14) -> 46113 | G34: 当月分
A35: =IFERROR(IF(売上入力!A14="","",IF(INDEX(マスター_OTA!$C$4:$C$29,MATCH(売上入力!D14,マスター_OTA!$A$4:$A$29,0))=0,"",DATE(YEAR(売上入力!A14),MONTH(売上入力!A14)+1,IFERROR(INDEX(マスター_OTA!$F$4:$F$29,MATCH(売上入力!D14,マスター_OTA!$A$4:$A$29,0)),25)))),"") -> 46152 | B35: =IF(売上入力!B14="","",売上入力!B14) -> リゾート | C35: =IF(売上入力!C14="","",売上入力!C14) -> 弐番館 | D35: =IF(売上入力!D14="","",売上入力!D14) -> 売上 | E35: =IFERROR(IF(売上入力!E14="",0,売上入力!E14*INDEX(マスター_OTA!$C$4:$C$29,MATCH(売上入力!D14,マスター_OTA!$A$4:$A$29,0))/100),0) -> 0 | F35: =IF(売上入力!A14="","",売上入力!A14) -> 46113 | G35: 翌月分
A36: =IFERROR(IF(売上入力!A14="","",IF(INDEX(マスター_OTA!$D$4:$D$29,MATCH(売上入力!D14,マスター_OTA!$A$4:$A$29,0))=0,"",DATE(YEAR(売上入力!A14),MONTH(売上入力!A14)+2,IFERROR(INDEX(マスター_OTA!$G$4:$G$29,MATCH(売上入力!D14,マスター_OTA!$A$4:$A$29,0)),25)))),"") -> 46198 | B36: =IF(売上入力!B14="","",売上入力!B14) -> リゾート | C36: =IF(売上入力!C14="","",売上入力!C14) -> 弐番館 | D36: =IF(売上入力!D14="","",売上入力!D14) -> 売上 | E36: =IFERROR(IF(売上入力!E14="",0,売上入力!E14*INDEX(マスター_OTA!$D$4:$D$29,MATCH(売上入力!D14,マスター_OTA!$A$4:$A$29,0))/100),0) -> 0 | F36: =IF(売上入力!A14="","",売上入力!A14) -> 46113 | G36: 翌々月分
A37: =IFERROR(IF(売上入力!A15="","",IF(INDEX(マスター_OTA!$B$4:$B$29,MATCH(売上入力!D15,マスター_OTA!$A$4:$A$29,0))=0,"",DATE(YEAR(売上入力!A15),MONTH(売上入力!A15),IFERROR(INDEX(マスター_OTA!$E$4:$E$29,MATCH(売上入力!D15,マスター_OTA!$A$4:$A$29,0)),28)))),"") -> 46132 | B37: =IF(売上入力!B15="","",売上入力!B15) -> モーテル | C37: =IF(売上入力!C15="","",売上入力!C15) -> 弥山 | D37: =IF(売上入力!D15="","",売上入力!D15) -> ホテル売上 | E37: =IFERROR(IF(売上入力!E15="",0,売上入力!E15*INDEX(マスター_OTA!$B$4:$B$29,MATCH(売上入力!D15,マスター_OTA!$A$4:$A$29,0))/100),0) -> 0 | F37: =IF(売上入力!A15="","",売上入力!A15) -> 46113 | G37: 当月分
A38: =IFERROR(IF(売上入力!A15="","",IF(INDEX(マスター_OTA!$C$4:$C$29,MATCH(売上入力!D15,マスター_OTA!$A$4:$A$29,0))=0,"",DATE(YEAR(売上入力!A15),MONTH(売上入力!A15)+1,IFERROR(INDEX(マスター_OTA!$F$4:$F$29,MATCH(売上入力!D15,マスター_OTA!$A$4:$A$29,0)),25)))),"") -> 46152 | B38: =IF(売上入力!B15="","",売上入力!B15) -> モーテル | C38: =IF(売上入力!C15="","",売上入力!C15) -> 弥山 | D38: =IF(売上入力!D15="","",売上入力!D15) -> ホテル売上 | E38: =IFERROR(IF(売上入力!E15="",0,売上入力!E15*INDEX(マスター_OTA!$C$4:$C$29,MATCH(売上入力!D15,マスター_OTA!$A$4:$A$29,0))/100),0) -> 0 | F38: =IF(売上入力!A15="","",売上入力!A15) -> 46113 | G38: 翌月分
A39: =IFERROR(IF(売上入力!A15="","",IF(INDEX(マスター_OTA!$D$4:$D$29,MATCH(売上入力!D15,マスター_OTA!$A$4:$A$29,0))=0,"",DATE(YEAR(売上入力!A15),MONTH(売上入力!A15)+2,IFERROR(INDEX(マスター_OTA!$G$4:$G$29,MATCH(売上入力!D15,マスター_OTA!$A$4:$A$29,0)),25)))),"") -> 46198 | B39: =IF(売上入力!B15="","",売上入力!B15) -> モーテル | C39: =IF(売上入力!C15="","",売上入力!C15) -> 弥山 | D39: =IF(売上入力!D15="","",売上入力!D15) -> ホテル売上 | E39: =IFERROR(IF(売上入力!E15="",0,売上入力!E15*INDEX(マスター_OTA!$D$4:$D$29,MATCH(売上入力!D15,マスター_OTA!$A$4:$A$29,0))/100),0) -> 0 | F39: =IF(売上入力!A15="","",売上入力!A15) -> 46113 | G39: 翌々月分
A40: =IFERROR(IF(売上入力!A16="","",IF(INDEX(マスター_OTA!$B$4:$B$29,MATCH(売上入力!D16,マスター_OTA!$A$4:$A$29,0))=0,"",DATE(YEAR(売上入力!A16),MONTH(売上入力!A16),IFERROR(INDEX(マスター_OTA!$E$4:$E$29,MATCH(売上入力!D16,マスター_OTA!$A$4:$A$29,0)),28)))),"") -> 46132 | B40: =IF(売上入力!B16="","",売上入力!B16) -> リゾート | C40: =IF(売上入力!C16="","",売上入力!C16) -> 本川 | D40: =IF(売上入力!D16="","",売上入力!D16) -> ホテル売上 | E40: =IFERROR(IF(売上入力!E16="",0,売上入力!E16*INDEX(マスター_OTA!$B$4:$B$29,MATCH(売上入力!D16,マスター_OTA!$A$4:$A$29,0))/100),0) -> 0 | F40: =IF(売上入力!A16="","",売上入力!A16) -> 46113 | G40: 当月分
A41: =IFERROR(IF(売上入力!A16="","",IF(INDEX(マスター_OTA!$C$4:$C$29,MATCH(売上入力!D16,マスター_OTA!$A$4:$A$29,0))=0,"",DATE(YEAR(売上入力!A16),MONTH(売上入力!A16)+1,IFERROR(INDEX(マスター_OTA!$F$4:$F$29,MATCH(売上入力!D16,マスター_OTA!$A$4:$A$29,0)),25)))),"") -> 46152 | B41: =IF(売上入力!B16="","",売上入力!B16) -> リゾート | C41: =IF(売上入力!C16="","",売上入力!C16) -> 本川 | D41: =IF(売上入力!D16="","",売上入力!D16) -> ホテル売上 | E41: =IFERROR(IF(売上入力!E16="",0,売上入力!E16*INDEX(マスター_OTA!$C$4:$C$29,MATCH(売上入力!D16,マスター_OTA!$A$4:$A$29,0))/100),0) -> 0 | F41: =IF(売上入力!A16="","",売上入力!A16) -> 46113 | G41: 翌月分
A42: =IFERROR(IF(売上入力!A16="","",IF(INDEX(マスター_OTA!$D$4:$D$29,MATCH(売上入力!D16,マスター_OTA!$A$4:$A$29,0))=0,"",DATE(YEAR(売上入力!A16),MONTH(売上入力!A16)+2,IFERROR(INDEX(マスター_OTA!$G$4:$G$29,MATCH(売上入力!D16,マスター_OTA!$A$4:$A$29,0)),25)))),"") -> 46198 | B42: =IF(売上入力!B16="","",売上入力!B16) -> リゾート | C42: =IF(売上入力!C16="","",売上入力!C16) -> 本川 | D42: =IF(売上入力!D16="","",売上入力!D16) -> ホテル売上 | E42: =IFERROR(IF(売上入力!E16="",0,売上入力!E16*INDEX(マスター_OTA!$D$4:$D$29,MATCH(売上入力!D16,マスター_OTA!$A$4:$A$29,0))/100),0) -> 0 | F42: =IF(売上入力!A16="","",売上入力!A16) -> 46113 | G42: 翌々月分
A43: =IFERROR(IF(売上入力!A17="","",IF(INDEX(マスター_OTA!$B$4:$B$29,MATCH(売上入力!D17,マスター_OTA!$A$4:$A$29,0))=0,"",DATE(YEAR(売上入力!A17),MONTH(売上入力!A17),IFERROR(INDEX(マスター_OTA!$E$4:$E$29,MATCH(売上入力!D17,マスター_OTA!$A$4:$A$29,0)),28)))),"") -> 46132 | B43: =IF(売上入力!B17="","",売上入力!B17) -> リゾート | C43: =IF(売上入力!C17="","",売上入力!C17) -> 温井 | D43: =IF(売上入力!D17="","",売上入力!D17) -> ホテル売上 | E43: =IFERROR(IF(売上入力!E17="",0,売上入力!E17*INDEX(マスター_OTA!$B$4:$B$29,MATCH(売上入力!D17,マスター_OTA!$A$4:$A$29,0))/100),0) -> 0 | F43: =IF(売上入力!A17="","",売上入力!A17) -> 46113 | G43: 当月分
A44: =IFERROR(IF(売上入力!A17="","",IF(INDEX(マスター_OTA!$C$4:$C$29,MATCH(売上入力!D17,マスター_OTA!$A$4:$A$29,0))=0,"",DATE(YEAR(売上入力!A17),MONTH(売上入力!A17)+1,IFERROR(INDEX(マスター_OTA!$F$4:$F$29,MATCH(売上入力!D17,マスター_OTA!$A$4:$A$29,0)),25)))),"") -> 46152 | B44: =IF(売上入力!B17="","",売上入力!B17) -> リゾート | C44: =IF(売上入力!C17="","",売上入力!C17) -> 温井 | D44: =IF(売上入力!D17="","",売上入力!D17) -> ホテル売上 | E44: =IFERROR(IF(売上入力!E17="",0,売上入力!E17*INDEX(マスター_OTA!$C$4:$C$29,MATCH(売上入力!D17,マスター_OTA!$A$4:$A$29,0))/100),0) -> 0 | F44: =IF(売上入力!A17="","",売上入力!A17) -> 46113 | G44: 翌月分
A45: =IFERROR(IF(売上入力!A17="","",IF(INDEX(マスター_OTA!$D$4:$D$29,MATCH(売上入力!D17,マスター_OTA!$A$4:$A$29,0))=0,"",DATE(YEAR(売上入力!A17),MONTH(売上入力!A17)+2,IFERROR(INDEX(マスター_OTA!$G$4:$G$29,MATCH(売上入力!D17,マスター_OTA!$A$4:$A$29,0)),25)))),"") -> 46198 | B45: =IF(売上入力!B17="","",売上入力!B17) -> リゾート | C45: =IF(売上入力!C17="","",売上入力!C17) -> 温井 | D45: =IF(売上入力!D17="","",売上入力!D17) -> ホテル売上 | E45: =IFERROR(IF(売上入力!E17="",0,売上入力!E17*INDEX(マスター_OTA!$D$4:$D$29,MATCH(売上入力!D17,マスター_OTA!$A$4:$A$29,0))/100),0) -> 0 | F45: =IF(売上入力!A17="","",売上入力!A17) -> 46113 | G45: 翌々月分
A46: =IFERROR(IF(売上入力!A18="","",IF(INDEX(マスター_OTA!$B$4:$B$29,MATCH(売上入力!D18,マスター_OTA!$A$4:$A$29,0))=0,"",DATE(YEAR(売上入力!A18),MONTH(売上入力!A18),IFERROR(INDEX(マスター_OTA!$E$4:$E$29,MATCH(売上入力!D18,マスター_OTA!$A$4:$A$29,0)),28)))),"") -> 46132 | B46: =IF(売上入力!B18="","",売上入力!B18) -> リゾート | C46: =IF(売上入力!C18="","",売上入力!C18) -> 玖波 | D46: =IF(売上入力!D18="","",売上入力!D18) -> ホテル売上 | E46: =IFERROR(IF(売上入力!E18="",0,売上入力!E18*INDEX(マスター_OTA!$B$4:$B$29,MATCH(売上入力!D18,マスター_OTA!$A$4:$A$29,0))/100),0) -> 0 | F46: =IF(売上入力!A18="","",売上入力!A18) -> 46113 | G46: 当月分
A47: =IFERROR(IF(売上入力!A18="","",IF(INDEX(マスター_OTA!$C$4:$C$29,MATCH(売上入力!D18,マスター_OTA!$A$4:$A$29,0))=0,"",DATE(YEAR(売上入力!A18),MONTH(売上入力!A18)+1,IFERROR(INDEX(マスター_OTA!$F$4:$F$29,MATCH(売上入力!D18,マスター_OTA!$A$4:$A$29,0)),25)))),"") -> 46152 | B47: =IF(売上入力!B18="","",売上入力!B18) -> リゾート | C47: =IF(売上入力!C18="","",売上入力!C18) -> 玖波 | D47: =IF(売上入力!D18="","",売上入力!D18) -> ホテル売上 | E47: =IFERROR(IF(売上入力!E18="",0,売上入力!E18*INDEX(マスター_OTA!$C$4:$C$29,MATCH(売上入力!D18,マスター_OTA!$A$4:$A$29,0))/100),0) -> 0 | F47: =IF(売上入力!A18="","",売上入力!A18) -> 46113 | G47: 翌月分
A48: =IFERROR(IF(売上入力!A18="","",IF(INDEX(マスター_OTA!$D$4:$D$29,MATCH(売上入力!D18,マスター_OTA!$A$4:$A$29,0))=0,"",DATE(YEAR(売上入力!A18),MONTH(売上入力!A18)+2,IFERROR(INDEX(マスター_OTA!$G$4:$G$29,MATCH(売上入力!D18,マスター_OTA!$A$4:$A$29,0)),25)))),"") -> 46198 | B48: =IF(売上入力!B18="","",売上入力!B18) -> リゾート | C48: =IF(売上入力!C18="","",売上入力!C18) -> 玖波 | D48: =IF(売上入力!D18="","",売上入力!D18) -> ホテル売上 | E48: =IFERROR(IF(売上入力!E18="",0,売上入力!E18*INDEX(マスター_OTA!$D$4:$D$29,MATCH(売上入力!D18,マスター_OTA!$A$4:$A$29,0))/100),0) -> 0 | F48: =IF(売上入力!A18="","",売上入力!A18) -> 46113 | G48: 翌々月分
A49: =IFERROR(IF(売上入力!A19="","",IF(INDEX(マスター_OTA!$B$4:$B$29,MATCH(売上入力!D19,マスター_OTA!$A$4:$A$29,0))=0,"",DATE(YEAR(売上入力!A19),MONTH(売上入力!A19),IFERROR(INDEX(マスター_OTA!$E$4:$E$29,MATCH(売上入力!D19,マスター_OTA!$A$4:$A$29,0)),28)))),"") | B49: =IF(売上入力!B19="","",売上入力!B19) -> リゾート | C49: =IF(売上入力!C19="","",売上入力!C19) -> 竹原（ﾚｽﾄﾗﾝ含む） | D49: =IF(売上入力!D19="","",売上入力!D19) -> 竹原市 | E49: =IFERROR(IF(売上入力!E19="",0,売上入力!E19*INDEX(マスター_OTA!$B$4:$B$29,MATCH(売上入力!D19,マスター_OTA!$A$4:$A$29,0))/100),0) -> 0 | F49: =IF(売上入力!A19="","",売上入力!A19) -> 46113 | G49: 当月分
A50: =IFERROR(IF(売上入力!A19="","",IF(INDEX(マスター_OTA!$C$4:$C$29,MATCH(売上入力!D19,マスター_OTA!$A$4:$A$29,0))=0,"",DATE(YEAR(売上入力!A19),MONTH(売上入力!A19)+1,IFERROR(INDEX(マスター_OTA!$F$4:$F$29,MATCH(売上入力!D19,マスター_OTA!$A$4:$A$29,0)),25)))),"") -> 46157 | B50: =IF(売上入力!B19="","",売上入力!B19) -> リゾート | C50: =IF(売上入力!C19="","",売上入力!C19) -> 竹原（ﾚｽﾄﾗﾝ含む） | D50: =IF(売上入力!D19="","",売上入力!D19) -> 竹原市 | E50: =IFERROR(IF(売上入力!E19="",0,売上入力!E19*INDEX(マスター_OTA!$C$4:$C$29,MATCH(売上入力!D19,マスター_OTA!$A$4:$A$29,0))/100),0) -> 0 | F50: =IF(売上入力!A19="","",売上入力!A19) -> 46113 | G50: 翌月分
A51: =IFERROR(IF(売上入力!A19="","",IF(INDEX(マスター_OTA!$D$4:$D$29,MATCH(売上入力!D19,マスター_OTA!$A$4:$A$29,0))=0,"",DATE(YEAR(売上入力!A19),MONTH(売上入力!A19)+2,IFERROR(INDEX(マスター_OTA!$G$4:$G$29,MATCH(売上入力!D19,マスター_OTA!$A$4:$A$29,0)),25)))),"") | B51: =IF(売上入力!B19="","",売上入力!B19) -> リゾート | C51: =IF(売上入力!C19="","",売上入力!C19) -> 竹原（ﾚｽﾄﾗﾝ含む） | D51: =IF(売上入力!D19="","",売上入力!D19) -> 竹原市 | E51: =IFERROR(IF(売上入力!E19="",0,売上入力!E19*INDEX(マスター_OTA!$D$4:$D$29,MATCH(売上入力!D19,マスター_OTA!$A$4:$A$29,0))/100),0) -> 0 | F51: =IF(売上入力!A19="","",売上入力!A19) -> 46113 | G51: 翌々月分
A52: =IFERROR(IF(売上入力!A20="","",IF(INDEX(マスター_OTA!$B$4:$B$29,MATCH(売上入力!D20,マスター_OTA!$A$4:$A$29,0))=0,"",DATE(YEAR(売上入力!A20),MONTH(売上入力!A20),IFERROR(INDEX(マスター_OTA!$E$4:$E$29,MATCH(売上入力!D20,マスター_OTA!$A$4:$A$29,0)),28)))),"") -> 46162 | B52: =IF(売上入力!B20="","",売上入力!B20) -> ザック | C52: =IF(売上入力!C20="","",売上入力!C20) -> MAKI de SAUNA | D52: =IF(売上入力!D20="","",売上入力!D20) -> 売上 | E52: =IFERROR(IF(売上入力!E20="",0,売上入力!E20*INDEX(マスター_OTA!$B$4:$B$29,MATCH(売上入力!D20,マスター_OTA!$A$4:$A$29,0))/100),0) -> 5441.4 | F52: =IF(売上入力!A20="","",売上入力!A20) -> 46143 | G52: 当月分
A53: =IFERROR(IF(売上入力!A20="","",IF(INDEX(マスター_OTA!$C$4:$C$29,MATCH(売上入力!D20,マスター_OTA!$A$4:$A$29,0))=0,"",DATE(YEAR(売上入力!A20),MONTH(売上入力!A20)+1,IFERROR(INDEX(マスター_OTA!$F$4:$F$29,MATCH(売上入力!D20,マスター_OTA!$A$4:$A$29,0)),25)))),"") -> 46183 | B53: =IF(売上入力!B20="","",売上入力!B20) -> ザック | C53: =IF(売上入力!C20="","",売上入力!C20) -> MAKI de SAUNA | D53: =IF(売上入力!D20="","",売上入力!D20) -> 売上 | E53: =IFERROR(IF(売上入力!E20="",0,売上入力!E20*INDEX(マスター_OTA!$C$4:$C$29,MATCH(売上入力!D20,マスター_OTA!$A$4:$A$29,0))/100),0) -> 27207 | F53: =IF(売上入力!A20="","",売上入力!A20) -> 46143 | G53: 翌月分
A54: =IFERROR(IF(売上入力!A20="","",IF(INDEX(マスター_OTA!$D$4:$D$29,MATCH(売上入力!D20,マスター_OTA!$A$4:$A$29,0))=0,"",DATE(YEAR(売上入力!A20),MONTH(売上入力!A20)+2,IFERROR(INDEX(マスター_OTA!$G$4:$G$29,MATCH(売上入力!D20,マスター_OTA!$A$4:$A$29,0)),25)))),"") -> 46228 | B54: =IF(売上入力!B20="","",売上入力!B20) -> ザック | C54: =IF(売上入力!C20="","",売上入力!C20) -> MAKI de SAUNA | D54: =IF(売上入力!D20="","",売上入力!D20) -> 売上 | E54: =IFERROR(IF(売上入力!E20="",0,売上入力!E20*INDEX(マスター_OTA!$D$4:$D$29,MATCH(売上入力!D20,マスター_OTA!$A$4:$A$29,0))/100),0) -> 3627.6 | F54: =IF(売上入力!A20="","",売上入力!A20) -> 46143 | G54: 翌々月分
A55: =IFERROR(IF(売上入力!A21="","",IF(INDEX(マスター_OTA!$B$4:$B$29,MATCH(売上入力!D21,マスター_OTA!$A$4:$A$29,0))=0,"",DATE(YEAR(売上入力!A21),MONTH(売上入力!A21),IFERROR(INDEX(マスター_OTA!$E$4:$E$29,MATCH(売上入力!D21,マスター_OTA!$A$4:$A$29,0)),28)))),"") -> 46162 | B55: =IF(売上入力!B21="","",売上入力!B21) -> リゾート | C55: =IF(売上入力!C21="","",売上入力!C21) -> Otake | D55: =IF(売上入力!D21="","",売上入力!D21) -> 売上 | E55: =IFERROR(IF(売上入力!E21="",0,売上入力!E21*INDEX(マスター_OTA!$B$4:$B$29,MATCH(売上入力!D21,マスター_OTA!$A$4:$A$29,0))/100),0) -> 11625 | F55: =IF(売上入力!A21="","",売上入力!A21) -> 46143 | G55: 当月分
A56: =IFERROR(IF(売上入力!A21="","",IF(INDEX(マスター_OTA!$C$4:$C$29,MATCH(売上入力!D21,マスター_OTA!$A$4:$A$29,0))=0,"",DATE(YEAR(売上入力!A21),MONTH(売上入力!A21)+1,IFERROR(INDEX(マスター_OTA!$F$4:$F$29,MATCH(売上入力!D21,マスター_OTA!$A$4:$A$29,0)),25)))),"") -> 46183 | B56: =IF(売上入力!B21="","",売上入力!B21) -> リゾート | C56: =IF(売上入力!C21="","",売上入力!C21) -> Otake | D56: =IF(売上入力!D21="","",売上入力!D21) -> 売上 | E56: =IFERROR(IF(売上入力!E21="",0,売上入力!E21*INDEX(マスター_OTA!$C$4:$C$29,MATCH(売上入力!D21,マスター_OTA!$A$4:$A$29,0))/100),0) -> 58125 | F56: =IF(売上入力!A21="","",売上入力!A21) -> 46143 | G56: 翌月分
A57: =IFERROR(IF(売上入力!A21="","",IF(INDEX(マスター_OTA!$D$4:$D$29,MATCH(売上入力!D21,マスター_OTA!$A$4:$A$29,0))=0,"",DATE(YEAR(売上入力!A21),MONTH(売上入力!A21)+2,IFERROR(INDEX(マスター_OTA!$G$4:$G$29,MATCH(売上入力!D21,マスター_OTA!$A$4:$A$29,0)),25)))),"") -> 46228 | B57: =IF(売上入力!B21="","",売上入力!B21) -> リゾート | C57: =IF(売上入力!C21="","",売上入力!C21) -> Otake | D57: =IF(売上入力!D21="","",売上入力!D21) -> 売上 | E57: =IFERROR(IF(売上入力!E21="",0,売上入力!E21*INDEX(マスター_OTA!$D$4:$D$29,MATCH(売上入力!D21,マスター_OTA!$A$4:$A$29,0))/100),0) -> 7750 | F57: =IF(売上入力!A21="","",売上入力!A21) -> 46143 | G57: 翌々月分
A58: =IFERROR(IF(売上入力!A22="","",IF(INDEX(マスター_OTA!$B$4:$B$29,MATCH(売上入力!D22,マスター_OTA!$A$4:$A$29,0))=0,"",DATE(YEAR(売上入力!A22),MONTH(売上入力!A22),IFERROR(INDEX(マスター_OTA!$E$4:$E$29,MATCH(売上入力!D22,マスター_OTA!$A$4:$A$29,0)),28)))),"") -> 46162 | B58: =IF(売上入力!B22="","",売上入力!B22) -> リゾート | C58: =IF(売上入力!C22="","",売上入力!C22) -> TAKAYA | D58: =IF(売上入力!D22="","",売上入力!D22) -> 売上 | E58: =IFERROR(IF(売上入力!E22="",0,売上入力!E22*INDEX(マスター_OTA!$B$4:$B$29,MATCH(売上入力!D22,マスター_OTA!$A$4:$A$29,0))/100),0) -> 40800 | F58: =IF(売上入力!A22="","",売上入力!A22) -> 46143 | G58: 当月分
A59: =IFERROR(IF(売上入力!A22="","",IF(INDEX(マスター_OTA!$C$4:$C$29,MATCH(売上入力!D22,マスター_OTA!$A$4:$A$29,0))=0,"",DATE(YEAR(売上入力!A22),MONTH(売上入力!A22)+1,IFERROR(INDEX(マスター_OTA!$F$4:$F$29,MATCH(売上入力!D22,マスター_OTA!$A$4:$A$29,0)),25)))),"") -> 46183 | B59: =IF(売上入力!B22="","",売上入力!B22) -> リゾート | C59: =IF(売上入力!C22="","",売上入力!C22) -> TAKAYA | D59: =IF(売上入力!D22="","",売上入力!D22) -> 売上 | E59: =IFERROR(IF(売上入力!E22="",0,売上入力!E22*INDEX(マスター_OTA!$C$4:$C$29,MATCH(売上入力!D22,マスター_OTA!$A$4:$A$29,0))/100),0) -> 204000 | F59: =IF(売上入力!A22="","",売上入力!A22) -> 46143 | G59: 翌月分
A60: =IFERROR(IF(売上入力!A22="","",IF(INDEX(マスター_OTA!$D$4:$D$29,MATCH(売上入力!D22,マスター_OTA!$A$4:$A$29,0))=0,"",DATE(YEAR(売上入力!A22),MONTH(売上入力!A22)+2,IFERROR(INDEX(マスター_OTA!$G$4:$G$29,MATCH(売上入力!D22,マスター_OTA!$A$4:$A$29,0)),25)))),"") -> 46228 | B60: =IF(売上入力!B22="","",売上入力!B22) -> リゾート | C60: =IF(売上入力!C22="","",売上入力!C22) -> TAKAYA | D60: =IF(売上入力!D22="","",売上入力!D22) -> 売上 | E60: =IFERROR(IF(売上入力!E22="",0,売上入力!E22*INDEX(マスター_OTA!$D$4:$D$29,MATCH(売上入力!D22,マスター_OTA!$A$4:$A$29,0))/100),0) -> 27200 | F60: =IF(売上入力!A22="","",売上入力!A22) -> 46143 | G60: 翌々月分
A61: =IFERROR(IF(売上入力!A23="","",IF(INDEX(マスター_OTA!$B$4:$B$29,MATCH(売上入力!D23,マスター_OTA!$A$4:$A$29,0))=0,"",DATE(YEAR(売上入力!A23),MONTH(売上入力!A23),IFERROR(INDEX(マスター_OTA!$E$4:$E$29,MATCH(売上入力!D23,マスター_OTA!$A$4:$A$29,0)),28)))),"") -> 46162 | B61: =IF(売上入力!B23="","",売上入力!B23) -> リゾート | C61: =IF(売上入力!C23="","",売上入力!C23) -> VIEW | D61: =IF(売上入力!D23="","",売上入力!D23) -> ホテル売上 | E61: =IFERROR(IF(売上入力!E23="",0,売上入力!E23*INDEX(マスター_OTA!$B$4:$B$29,MATCH(売上入力!D23,マスター_OTA!$A$4:$A$29,0))/100),0) -> 417862.8 | F61: =IF(売上入力!A23="","",売上入力!A23) -> 46143 | G61: 当月分
A62: =IFERROR(IF(売上入力!A23="","",IF(INDEX(マスター_OTA!$C$4:$C$29,MATCH(売上入力!D23,マスター_OTA!$A$4:$A$29,0))=0,"",DATE(YEAR(売上入力!A23),MONTH(売上入力!A23)+1,IFERROR(INDEX(マスター_OTA!$F$4:$F$29,MATCH(売上入力!D23,マスター_OTA!$A$4:$A$29,0)),25)))),"") -> 46183 | B62: =IF(売上入力!B23="","",売上入力!B23) -> リゾート | C62: =IF(売上入力!C23="","",売上入力!C23) -> VIEW | D62: =IF(売上入力!D23="","",売上入力!D23) -> ホテル売上 | E62: =IFERROR(IF(売上入力!E23="",0,売上入力!E23*INDEX(マスター_OTA!$C$4:$C$29,MATCH(売上入力!D23,マスター_OTA!$A$4:$A$29,0))/100),0) -> 2089314 | F62: =IF(売上入力!A23="","",売上入力!A23) -> 46143 | G62: 翌月分
A63: =IFERROR(IF(売上入力!A23="","",IF(INDEX(マスター_OTA!$D$4:$D$29,MATCH(売上入力!D23,マスター_OTA!$A$4:$A$29,0))=0,"",DATE(YEAR(売上入力!A23),MONTH(売上入力!A23)+2,IFERROR(INDEX(マスター_OTA!$G$4:$G$29,MATCH(売上入力!D23,マスター_OTA!$A$4:$A$29,0)),25)))),"") -> 46228 | B63: =IF(売上入力!B23="","",売上入力!B23) -> リゾート | C63: =IF(売上入力!C23="","",売上入力!C23) -> VIEW | D63: =IF(売上入力!D23="","",売上入力!D23) -> ホテル売上 | E63: =IFERROR(IF(売上入力!E23="",0,売上入力!E23*INDEX(マスター_OTA!$D$4:$D$29,MATCH(売上入力!D23,マスター_OTA!$A$4:$A$29,0))/100),0) -> 278575.2 | F63: =IF(売上入力!A23="","",売上入力!A23) -> 46143 | G63: 翌々月分
A64: =IFERROR(IF(売上入力!A24="","",IF(INDEX(マスター_OTA!$B$4:$B$29,MATCH(売上入力!D24,マスター_OTA!$A$4:$A$29,0))=0,"",DATE(YEAR(売上入力!A24),MONTH(売上入力!A24),IFERROR(INDEX(マスター_OTA!$E$4:$E$29,MATCH(売上入力!D24,マスター_OTA!$A$4:$A$29,0)),28)))),"") -> 46162 | B64: =IF(売上入力!B24="","",売上入力!B24) -> リゾート | C64: =IF(売上入力!C24="","",売上入力!C24) -> de Lune | D64: =IF(売上入力!D24="","",売上入力!D24) -> ホテル売上 | E64: =IFERROR(IF(売上入力!E24="",0,売上入力!E24*INDEX(マスター_OTA!$B$4:$B$29,MATCH(売上入力!D24,マスター_OTA!$A$4:$A$29,0))/100),0) -> 1368104.4 | F64: =IF(売上入力!A24="","",売上入力!A24) -> 46143 | G64: 当月分
A65: =IFERROR(IF(売上入力!A24="","",IF(INDEX(マスター_OTA!$C$4:$C$29,MATCH(売上入力!D24,マスター_OTA!$A$4:$A$29,0))=0,"",DATE(YEAR(売上入力!A24),MONTH(売上入力!A24)+1,IFERROR(INDEX(マスター_OTA!$F$4:$F$29,MATCH(売上入力!D24,マスター_OTA!$A$4:$A$29,0)),25)))),"") -> 46183 | B65: =IF(売上入力!B24="","",売上入力!B24) -> リゾート | C65: =IF(売上入力!C24="","",売上入力!C24) -> de Lune | D65: =IF(売上入力!D24="","",売上入力!D24) -> ホテル売上 | E65: =IFERROR(IF(売上入力!E24="",0,売上入力!E24*INDEX(マスター_OTA!$C$4:$C$29,MATCH(売上入力!D24,マスター_OTA!$A$4:$A$29,0))/100),0) -> 6840522 | F65: =IF(売上入力!A24="","",売上入力!A24) -> 46143 | G65: 翌月分
A66: =IFERROR(IF(売上入力!A24="","",IF(INDEX(マスター_OTA!$D$4:$D$29,MATCH(売上入力!D24,マスター_OTA!$A$4:$A$29,0))=0,"",DATE(YEAR(売上入力!A24),MONTH(売上入力!A24)+2,IFERROR(INDEX(マスター_OTA!$G$4:$G$29,MATCH(売上入力!D24,マスター_OTA!$A$4:$A$29,0)),25)))),"") -> 46228 | B66: =IF(売上入力!B24="","",売上入力!B24) -> リゾート | C66: =IF(売上入力!C24="","",売上入力!C24) -> de Lune | D66: =IF(売上入力!D24="","",売上入力!D24) -> ホテル売上 | E66: =IFERROR(IF(売上入力!E24="",0,売上入力!E24*INDEX(マスター_OTA!$D$4:$D$29,MATCH(売上入力!D24,マスター_OTA!$A$4:$A$29,0))/100),0) -> 912069.6 | F66: =IF(売上入力!A24="","",売上入力!A24) -> 46143 | G66: 翌々月分
A67: =IFERROR(IF(売上入力!A25="","",IF(INDEX(マスター_OTA!$B$4:$B$29,MATCH(売上入力!D25,マスター_OTA!$A$4:$A$29,0))=0,"",DATE(YEAR(売上入力!A25),MONTH(売上入力!A25),IFERROR(INDEX(マスター_OTA!$E$4:$E$29,MATCH(売上入力!D25,マスター_OTA!$A$4:$A$29,0)),28)))),"") -> 46162 | B67: =IF(売上入力!B25="","",売上入力!B25) -> リゾート | C67: =IF(売上入力!C25="","",売上入力!C25) -> いこいの村 | D67: =IF(売上入力!D25="","",売上入力!D25) -> ホテル売上 | E67: =IFERROR(IF(売上入力!E25="",0,売上入力!E25*INDEX(マスター_OTA!$B$4:$B$29,MATCH(売上入力!D25,マスター_OTA!$A$4:$A$29,0))/100),0) -> 439300.65 | F67: =IF(売上入力!A25="","",売上入力!A25) -> 46143 | G67: 当月分
A68: =IFERROR(IF(売上入力!A25="","",IF(INDEX(マスター_OTA!$C$4:$C$29,MATCH(売上入力!D25,マスター_OTA!$A$4:$A$29,0))=0,"",DATE(YEAR(売上入力!A25),MONTH(売上入力!A25)+1,IFERROR(INDEX(マスター_OTA!$F$4:$F$29,MATCH(売上入力!D25,マスター_OTA!$A$4:$A$29,0)),25)))),"") -> 46183 | B68: =IF(売上入力!B25="","",売上入力!B25) -> リゾート | C68: =IF(売上入力!C25="","",売上入力!C25) -> いこいの村 | D68: =IF(売上入力!D25="","",売上入力!D25) -> ホテル売上 | E68: =IFERROR(IF(売上入力!E25="",0,売上入力!E25*INDEX(マスター_OTA!$C$4:$C$29,MATCH(売上入力!D25,マスター_OTA!$A$4:$A$29,0))/100),0) -> 2196503.2 | F68: =IF(売上入力!A25="","",売上入力!A25) -> 46143 | G68: 翌月分
A69: =IFERROR(IF(売上入力!A25="","",IF(INDEX(マスター_OTA!$D$4:$D$29,MATCH(売上入力!D25,マスター_OTA!$A$4:$A$29,0))=0,"",DATE(YEAR(売上入力!A25),MONTH(売上入力!A25)+2,IFERROR(INDEX(マスター_OTA!$G$4:$G$29,MATCH(売上入力!D25,マスター_OTA!$A$4:$A$29,0)),25)))),"") -> 46228 | B69: =IF(売上入力!B25="","",売上入力!B25) -> リゾート | C69: =IF(売上入力!C25="","",売上入力!C25) -> いこいの村 | D69: =IF(売上入力!D25="","",売上入力!D25) -> ホテル売上 | E69: =IFERROR(IF(売上入力!E25="",0,売上入力!E25*INDEX(マスター_OTA!$D$4:$D$29,MATCH(売上入力!D25,マスター_OTA!$A$4:$A$29,0))/100),0) -> 292867.1 | F69: =IF(売上入力!A25="","",売上入力!A25) -> 46143 | G69: 翌々月分
A70: =IFERROR(IF(売上入力!A26="","",IF(INDEX(マスター_OTA!$B$4:$B$29,MATCH(売上入力!D26,マスター_OTA!$A$4:$A$29,0))=0,"",DATE(YEAR(売上入力!A26),MONTH(売上入力!A26),IFERROR(INDEX(マスター_OTA!$E$4:$E$29,MATCH(売上入力!D26,マスター_OTA!$A$4:$A$29,0)),28)))),"") -> 46162 | B70: =IF(売上入力!B26="","",売上入力!B26) -> リゾート | C70: =IF(売上入力!C26="","",売上入力!C26) -> グリーンシャワー | D70: =IF(売上入力!D26="","",売上入力!D26) -> 売上 | E70: =IFERROR(IF(売上入力!E26="",0,売上入力!E26*INDEX(マスター_OTA!$B$4:$B$29,MATCH(売上入力!D26,マスター_OTA!$A$4:$A$29,0))/100),0) -> 37337.55 | F70: =IF(売上入力!A26="","",売上入力!A26) -> 46143 | G70: 当月分
A71: =IFERROR(IF(売上入力!A26="","",IF(INDEX(マスター_OTA!$C$4:$C$29,MATCH(売上入力!D26,マスター_OTA!$A$4:$A$29,0))=0,"",DATE(YEAR(売上入力!A26),MONTH(売上入力!A26)+1,IFERROR(INDEX(マスター_OTA!$F$4:$F$29,MATCH(売上入力!D26,マスター_OTA!$A$4:$A$29,0)),25)))),"") -> 46183 | B71: =IF(売上入力!B26="","",売上入力!B26) -> リゾート | C71: =IF(売上入力!C26="","",売上入力!C26) -> グリーンシャワー | D71: =IF(売上入力!D26="","",売上入力!D26) -> 売上 | E71: =IFERROR(IF(売上入力!E26="",0,売上入力!E26*INDEX(マスター_OTA!$C$4:$C$29,MATCH(売上入力!D26,マスター_OTA!$A$4:$A$29,0))/100),0) -> 186687.75 | F71: =IF(売上入力!A26="","",売上入力!A26) -> 46143 | G71: 翌月分
A72: =IFERROR(IF(売上入力!A26="","",IF(INDEX(マスター_OTA!$D$4:$D$29,MATCH(売上入力!D26,マスター_OTA!$A$4:$A$29,0))=0,"",DATE(YEAR(売上入力!A26),MONTH(売上入力!A26)+2,IFERROR(INDEX(マスター_OTA!$G$4:$G$29,MATCH(売上入力!D26,マスター_OTA!$A$4:$A$29,0)),25)))),"") -> 46228 | B72: =IF(売上入力!B26="","",売上入力!B26) -> リゾート | C72: =IF(売上入力!C26="","",売上入力!C26) -> グリーンシャワー | D72: =IF(売上入力!D26="","",売上入力!D26) -> 売上 | E72: =IFERROR(IF(売上入力!E26="",0,売上入力!E26*INDEX(マスター_OTA!$D$4:$D$29,MATCH(売上入力!D26,マスター_OTA!$A$4:$A$29,0))/100),0) -> 24891.7 | F72: =IF(売上入力!A26="","",売上入力!A26) -> 46143 | G72: 翌々月分
A73: =IFERROR(IF(売上入力!A27="","",IF(INDEX(マスター_OTA!$B$4:$B$29,MATCH(売上入力!D27,マスター_OTA!$A$4:$A$29,0))=0,"",DATE(YEAR(売上入力!A27),MONTH(売上入力!A27),IFERROR(INDEX(マスター_OTA!$E$4:$E$29,MATCH(売上入力!D27,マスター_OTA!$A$4:$A$29,0)),28)))),"") -> 46162 | B73: =IF(売上入力!B27="","",売上入力!B27) -> リゾート | C73: =IF(売上入力!C27="","",売上入力!C27) -> フォレストヒルズガーデン | D73: =IF(売上入力!D27="","",売上入力!D27) -> 売上 | E73: =IFERROR(IF(売上入力!E27="",0,売上入力!E27*INDEX(マスター_OTA!$B$4:$B$29,MATCH(売上入力!D27,マスター_OTA!$A$4:$A$29,0))/100),0) -> 1071498.4 | F73: =IF(売上入力!A27="","",売上入力!A27) -> 46143 | G73: 当月分
A74: =IFERROR(IF(売上入力!A27="","",IF(INDEX(マスター_OTA!$C$4:$C$29,MATCH(売上入力!D27,マスター_OTA!$A$4:$A$29,0))=0,"",DATE(YEAR(売上入力!A27),MONTH(売上入力!A27)+1,IFERROR(INDEX(マスター_OTA!$F$4:$F$29,MATCH(売上入力!D27,マスター_OTA!$A$4:$A$29,0)),25)))),"") -> 46183 | B74: =IF(売上入力!B27="","",売上入力!B27) -> リゾート | C74: =IF(売上入力!C27="","",売上入力!C27) -> フォレストヒルズガーデン | D74: =IF(売上入力!D27="","",売上入力!D27) -> 売上 | E74: =IFERROR(IF(売上入力!E27="",0,売上入力!E27*INDEX(マスター_OTA!$C$4:$C$29,MATCH(売上入力!D27,マスター_OTA!$A$4:$A$29,0))/100),0) -> 5357492.2 | F74: =IF(売上入力!A27="","",売上入力!A27) -> 46143 | G74: 翌月分
A75: =IFERROR(IF(売上入力!A27="","",IF(INDEX(マスター_OTA!$D$4:$D$29,MATCH(売上入力!D27,マスター_OTA!$A$4:$A$29,0))=0,"",DATE(YEAR(売上入力!A27),MONTH(売上入力!A27)+2,IFERROR(INDEX(マスター_OTA!$G$4:$G$29,MATCH(売上入力!D27,マスター_OTA!$A$4:$A$29,0)),25)))),"") -> 46228 | B75: =IF(売上入力!B27="","",売上入力!B27) -> リゾート | C75: =IF(売上入力!C27="","",売上入力!C27) -> フォレストヒルズガーデン | D75: =IF(売上入力!D27="","",売上入力!D27) -> 売上 | E75: =IFERROR(IF(売上入力!E27="",0,売上入力!E27*INDEX(マスター_OTA!$D$4:$D$29,MATCH(売上入力!D27,マスター_OTA!$A$4:$A$29,0))/100),0) -> 714332.3 | F75: =IF(売上入力!A27="","",売上入力!A27) -> 46143 | G75: 翌々月分
A76: =IFERROR(IF(売上入力!A28="","",IF(INDEX(マスター_OTA!$B$4:$B$29,MATCH(売上入力!D28,マスター_OTA!$A$4:$A$29,0))=0,"",DATE(YEAR(売上入力!A28),MONTH(売上入力!A28),IFERROR(INDEX(マスター_OTA!$E$4:$E$29,MATCH(売上入力!D28,マスター_OTA!$A$4:$A$29,0)),28)))),"") -> 46162 | B76: =IF(売上入力!B28="","",売上入力!B28) -> リゾート | C76: =IF(売上入力!C28="","",売上入力!C28) -> 壱番館 | D76: =IF(売上入力!D28="","",売上入力!D28) -> 売上 | E76: =IFERROR(IF(売上入力!E28="",0,売上入力!E28*INDEX(マスター_OTA!$B$4:$B$29,MATCH(売上入力!D28,マスター_OTA!$A$4:$A$29,0))/100),0) -> 3600 | F76: =IF(売上入力!A28="","",売上入力!A28) -> 46143 | G76: 当月分
A77: =IFERROR(IF(売上入力!A28="","",IF(INDEX(マスター_OTA!$C$4:$C$29,MATCH(売上入力!D28,マスター_OTA!$A$4:$A$29,0))=0,"",DATE(YEAR(売上入力!A28),MONTH(売上入力!A28)+1,IFERROR(INDEX(マスター_OTA!$F$4:$F$29,MATCH(売上入力!D28,マスター_OTA!$A$4:$A$29,0)),25)))),"") -> 46183 | B77: =IF(売上入力!B28="","",売上入力!B28) -> リゾート | C77: =IF(売上入力!C28="","",売上入力!C28) -> 壱番館 | D77: =IF(売上入力!D28="","",売上入力!D28) -> 売上 | E77: =IFERROR(IF(売上入力!E28="",0,売上入力!E28*INDEX(マスター_OTA!$C$4:$C$29,MATCH(売上入力!D28,マスター_OTA!$A$4:$A$29,0))/100),0) -> 18000 | F77: =IF(売上入力!A28="","",売上入力!A28) -> 46143 | G77: 翌月分
A78: =IFERROR(IF(売上入力!A28="","",IF(INDEX(マスター_OTA!$D$4:$D$29,MATCH(売上入力!D28,マスター_OTA!$A$4:$A$29,0))=0,"",DATE(YEAR(売上入力!A28),MONTH(売上入力!A28)+2,IFERROR(INDEX(マスター_OTA!$G$4:$G$29,MATCH(売上入力!D28,マスター_OTA!$A$4:$A$29,0)),25)))),"") -> 46228 | B78: =IF(売上入力!B28="","",売上入力!B28) -> リゾート | C78: =IF(売上入力!C28="","",売上入力!C28) -> 壱番館 | D78: =IF(売上入力!D28="","",売上入力!D28) -> 売上 | E78: =IFERROR(IF(売上入力!E28="",0,売上入力!E28*INDEX(マスター_OTA!$D$4:$D$29,MATCH(売上入力!D28,マスター_OTA!$A$4:$A$29,0))/100),0) -> 2400 | F78: =IF(売上入力!A28="","",売上入力!A28) -> 46143 | G78: 翌々月分
A79: =IFERROR(IF(売上入力!A29="","",IF(INDEX(マスター_OTA!$B$4:$B$29,MATCH(売上入力!D29,マスター_OTA!$A$4:$A$29,0))=0,"",DATE(YEAR(売上入力!A29),MONTH(売上入力!A29),IFERROR(INDEX(マスター_OTA!$E$4:$E$29,MATCH(売上入力!D29,マスター_OTA!$A$4:$A$29,0)),28)))),"") -> 46162 | B79: =IF(売上入力!B29="","",売上入力!B29) -> リゾート | C79: =IF(売上入力!C29="","",売上入力!C29) -> 天神 | D79: =IF(売上入力!D29="","",売上入力!D29) -> ホテル売上 | E79: =IFERROR(IF(売上入力!E29="",0,売上入力!E29*INDEX(マスター_OTA!$B$4:$B$29,MATCH(売上入力!D29,マスター_OTA!$A$4:$A$29,0))/100),0) -> 26412 | F79: =IF(売上入力!A29="","",売上入力!A29) -> 46143 | G79: 当月分
A80: =IFERROR(IF(売上入力!A29="","",IF(INDEX(マスター_OTA!$C$4:$C$29,MATCH(売上入力!D29,マスター_OTA!$A$4:$A$29,0))=0,"",DATE(YEAR(売上入力!A29),MONTH(売上入力!A29)+1,IFERROR(INDEX(マスター_OTA!$F$4:$F$29,MATCH(売上入力!D29,マスター_OTA!$A$4:$A$29,0)),25)))),"") -> 46183 | B80: =IF(売上入力!B29="","",売上入力!B29) -> リゾート | C80: =IF(売上入力!C29="","",売上入力!C29) -> 天神 | D80: =IF(売上入力!D29="","",売上入力!D29) -> ホテル売上 | E80: =IFERROR(IF(売上入力!E29="",0,売上入力!E29*INDEX(マスター_OTA!$C$4:$C$29,MATCH(売上入力!D29,マスター_OTA!$A$4:$A$29,0))/100),0) -> 132060 | F80: =IF(売上入力!A29="","",売上入力!A29) -> 46143 | G80: 翌月分
A81: =IFERROR(IF(売上入力!A29="","",IF(INDEX(マスター_OTA!$D$4:$D$29,MATCH(売上入力!D29,マスター_OTA!$A$4:$A$29,0))=0,"",DATE(YEAR(売上入力!A29),MONTH(売上入力!A29)+2,IFERROR(INDEX(マスター_OTA!$G$4:$G$29,MATCH(売上入力!D29,マスター_OTA!$A$4:$A$29,0)),25)))),"") -> 46228 | B81: =IF(売上入力!B29="","",売上入力!B29) -> リゾート | C81: =IF(売上入力!C29="","",売上入力!C29) -> 天神 | D81: =IF(売上入力!D29="","",売上入力!D29) -> ホテル売上 | E81: =IFERROR(IF(売上入力!E29="",0,売上入力!E29*INDEX(マスター_OTA!$D$4:$D$29,MATCH(売上入力!D29,マスター_OTA!$A$4:$A$29,0))/100),0) -> 17608 | F81: =IF(売上入力!A29="","",売上入力!A29) -> 46143 | G81: 翌々月分
A82: =IFERROR(IF(売上入力!A30="","",IF(INDEX(マスター_OTA!$B$4:$B$29,MATCH(売上入力!D30,マスター_OTA!$A$4:$A$29,0))=0,"",DATE(YEAR(売上入力!A30),MONTH(売上入力!A30),IFERROR(INDEX(マスター_OTA!$E$4:$E$29,MATCH(売上入力!D30,マスター_OTA!$A$4:$A$29,0)),28)))),"") -> 46162 | B82: =IF(売上入力!B30="","",売上入力!B30) -> モーテル | C82: =IF(売上入力!C30="","",売上入力!C30) -> 弥山 | D82: =IF(売上入力!D30="","",売上入力!D30) -> ホテル売上 | E82: =IFERROR(IF(売上入力!E30="",0,売上入力!E30*INDEX(マスター_OTA!$B$4:$B$29,MATCH(売上入力!D30,マスター_OTA!$A$4:$A$29,0))/100),0) -> 856137.3 | F82: =IF(売上入力!A30="","",売上入力!A30) -> 46143 | G82: 当月分
A83: =IFERROR(IF(売上入力!A30="","",IF(INDEX(マスター_OTA!$C$4:$C$29,MATCH(売上入力!D30,マスター_OTA!$A$4:$A$29,0))=0,"",DATE(YEAR(売上入力!A30),MONTH(売上入力!A30)+1,IFERROR(INDEX(マスター_OTA!$F$4:$F$29,MATCH(売上入力!D30,マスター_OTA!$A$4:$A$29,0)),25)))),"") -> 46183 | B83: =IF(売上入力!B30="","",売上入力!B30) -> モーテル | C83: =IF(売上入力!C30="","",売上入力!C30) -> 弥山 | D83: =IF(売上入力!D30="","",売上入力!D30) -> ホテル売上 | E83: =IFERROR(IF(売上入力!E30="",0,売上入力!E30*INDEX(マスター_OTA!$C$4:$C$29,MATCH(売上入力!D30,マスター_OTA!$A$4:$A$29,0))/100),0) -> 4280686.5 | F83: =IF(売上入力!A30="","",売上入力!A30) -> 46143 | G83: 翌月分
A84: =IFERROR(IF(売上入力!A30="","",IF(INDEX(マスター_OTA!$D$4:$D$29,MATCH(売上入力!D30,マスター_OTA!$A$4:$A$29,0))=0,"",DATE(YEAR(売上入力!A30),MONTH(売上入力!A30)+2,IFERROR(INDEX(マスター_OTA!$G$4:$G$29,MATCH(売上入力!D30,マスター_OTA!$A$4:$A$29,0)),25)))),"") -> 46228 | B84: =IF(売上入力!B30="","",売上入力!B30) -> モーテル | C84: =IF(売上入力!C30="","",売上入力!C30) -> 弥山 | D84: =IF(売上入力!D30="","",売上入力!D30) -> ホテル売上 | E84: =IFERROR(IF(売上入力!E30="",0,売上入力!E30*INDEX(マスター_OTA!$D$4:$D$29,MATCH(売上入力!D30,マスター_OTA!$A$4:$A$29,0))/100),0) -> 570758.2 | F84: =IF(売上入力!A30="","",売上入力!A30) -> 46143 | G84: 翌々月分
A85: =IFERROR(IF(売上入力!A31="","",IF(INDEX(マスター_OTA!$B$4:$B$29,MATCH(売上入力!D31,マスター_OTA!$A$4:$A$29,0))=0,"",DATE(YEAR(売上入力!A31),MONTH(売上入力!A31),IFERROR(INDEX(マスター_OTA!$E$4:$E$29,MATCH(売上入力!D31,マスター_OTA!$A$4:$A$29,0)),28)))),"") -> 46162 | B85: =IF(売上入力!B31="","",売上入力!B31) -> リゾート | C85: =IF(売上入力!C31="","",売上入力!C31) -> 本川 | D85: =IF(売上入力!D31="","",売上入力!D31) -> ホテル売上 | E85: =IFERROR(IF(売上入力!E31="",0,売上入力!E31*INDEX(マスター_OTA!$B$4:$B$29,MATCH(売上入力!D31,マスター_OTA!$A$4:$A$29,0))/100),0) -> 234043.8 | F85: =IF(売上入力!A31="","",売上入力!A31) -> 46143 | G85: 当月分
A86: =IFERROR(IF(売上入力!A31="","",IF(INDEX(マスター_OTA!$C$4:$C$29,MATCH(売上入力!D31,マスター_OTA!$A$4:$A$29,0))=0,"",DATE(YEAR(売上入力!A31),MONTH(売上入力!A31)+1,IFERROR(INDEX(マスター_OTA!$F$4:$F$29,MATCH(売上入力!D31,マスター_OTA!$A$4:$A$29,0)),25)))),"") -> 46183 | B86: =IF(売上入力!B31="","",売上入力!B31) -> リゾート | C86: =IF(売上入力!C31="","",売上入力!C31) -> 本川 | D86: =IF(売上入力!D31="","",売上入力!D31) -> ホテル売上 | E86: =IFERROR(IF(売上入力!E31="",0,売上入力!E31*INDEX(マスター_OTA!$C$4:$C$29,MATCH(売上入力!D31,マスター_OTA!$A$4:$A$29,0))/100),0) -> 1170219 | F86: =IF(売上入力!A31="","",売上入力!A31) -> 46143 | G86: 翌月分
A87: =IFERROR(IF(売上入力!A31="","",IF(INDEX(マスター_OTA!$D$4:$D$29,MATCH(売上入力!D31,マスター_OTA!$A$4:$A$29,0))=0,"",DATE(YEAR(売上入力!A31),MONTH(売上入力!A31)+2,IFERROR(INDEX(マスター_OTA!$G$4:$G$29,MATCH(売上入力!D31,マスター_OTA!$A$4:$A$29,0)),25)))),"") -> 46228 | B87: =IF(売上入力!B31="","",売上入力!B31) -> リゾート | C87: =IF(売上入力!C31="","",売上入力!C31) -> 本川 | D87: =IF(売上入力!D31="","",売上入力!D31) -> ホテル売上 | E87: =IFERROR(IF(売上入力!E31="",0,売上入力!E31*INDEX(マスター_OTA!$D$4:$D$29,MATCH(売上入力!D31,マスター_OTA!$A$4:$A$29,0))/100),0) -> 156029.2 | F87: =IF(売上入力!A31="","",売上入力!A31) -> 46143 | G87: 翌々月分
A88: =IFERROR(IF(売上入力!A32="","",IF(INDEX(マスター_OTA!$B$4:$B$29,MATCH(売上入力!D32,マスター_OTA!$A$4:$A$29,0))=0,"",DATE(YEAR(売上入力!A32),MONTH(売上入力!A32),IFERROR(INDEX(マスター_OTA!$E$4:$E$29,MATCH(売上入力!D32,マスター_OTA!$A$4:$A$29,0)),28)))),"") -> 46162 | B88: =IF(売上入力!B32="","",売上入力!B32) -> リゾート | C88: =IF(売上入力!C32="","",売上入力!C32) -> 温井 | D88: =IF(売上入力!D32="","",売上入力!D32) -> ホテル売上 | E88: =IFERROR(IF(売上入力!E32="",0,売上入力!E32*INDEX(マスター_OTA!$B$4:$B$29,MATCH(売上入力!D32,マスター_OTA!$A$4:$A$29,0))/100),0) -> 684609.3 | F88: =IF(売上入力!A32="","",売上入力!A32) -> 46143 | G88: 当月分
A89: =IFERROR(IF(売上入力!A32="","",IF(INDEX(マスター_OTA!$C$4:$C$29,MATCH(売上入力!D32,マスター_OTA!$A$4:$A$29,0))=0,"",DATE(YEAR(売上入力!A32),MONTH(売上入力!A32)+1,IFERROR(INDEX(マスター_OTA!$F$4:$F$29,MATCH(売上入力!D32,マスター_OTA!$A$4:$A$29,0)),25)))),"") -> 46183 | B89: =IF(売上入力!B32="","",売上入力!B32) -> リゾート | C89: =IF(売上入力!C32="","",売上入力!C32) -> 温井 | D89: =IF(売上入力!D32="","",売上入力!D32) -> ホテル売上 | E89: =IFERROR(IF(売上入力!E32="",0,売上入力!E32*INDEX(マスター_OTA!$C$4:$C$29,MATCH(売上入力!D32,マスター_OTA!$A$4:$A$29,0))/100),0) -> 3423046.5 | F89: =IF(売上入力!A32="","",売上入力!A32) -> 46143 | G89: 翌月分
A90: =IFERROR(IF(売上入力!A32="","",IF(INDEX(マスター_OTA!$D$4:$D$29,MATCH(売上入力!D32,マスター_OTA!$A$4:$A$29,0))=0,"",DATE(YEAR(売上入力!A32),MONTH(売上入力!A32)+2,IFERROR(INDEX(マスター_OTA!$G$4:$G$29,MATCH(売上入力!D32,マスター_OTA!$A$4:$A$29,0)),25)))),"") -> 46228 | B90: =IF(売上入力!B32="","",売上入力!B32) -> リゾート | C90: =IF(売上入力!C32="","",売上入力!C32) -> 温井 | D90: =IF(売上入力!D32="","",売上入力!D32) -> ホテル売上 | E90: =IFERROR(IF(売上入力!E32="",0,売上入力!E32*INDEX(マスター_OTA!$D$4:$D$29,MATCH(売上入力!D32,マスター_OTA!$A$4:$A$29,0))/100),0) -> 456406.2 | F90: =IF(売上入力!A32="","",売上入力!A32) -> 46143 | G90: 翌々月分
A91: =IFERROR(IF(売上入力!A33="","",IF(INDEX(マスター_OTA!$B$4:$B$29,MATCH(売上入力!D33,マスター_OTA!$A$4:$A$29,0))=0,"",DATE(YEAR(売上入力!A33),MONTH(売上入力!A33),IFERROR(INDEX(マスター_OTA!$E$4:$E$29,MATCH(売上入力!D33,マスター_OTA!$A$4:$A$29,0)),28)))),"") -> 46162 | B91: =IF(売上入力!B33="","",売上入力!B33) -> リゾート | C91: =IF(売上入力!C33="","",売上入力!C33) -> 玖波 | D91: =IF(売上入力!D33="","",売上入力!D33) -> ホテル売上 | E91: =IFERROR(IF(売上入力!E33="",0,売上入力!E33*INDEX(マスター_OTA!$B$4:$B$29,MATCH(売上入力!D33,マスター_OTA!$A$4:$A$29,0))/100),0) -> 42075 | F91: =IF(売上入力!A33="","",売上入力!A33) -> 46143 | G91: 当月分
A92: =IFERROR(IF(売上入力!A33="","",IF(INDEX(マスター_OTA!$C$4:$C$29,MATCH(売上入力!D33,マスター_OTA!$A$4:$A$29,0))=0,"",DATE(YEAR(売上入力!A33),MONTH(売上入力!A33)+1,IFERROR(INDEX(マスター_OTA!$F$4:$F$29,MATCH(売上入力!D33,マスター_OTA!$A$4:$A$29,0)),25)))),"") -> 46183 | B92: =IF(売上入力!B33="","",売上入力!B33) -> リゾート | C92: =IF(売上入力!C33="","",売上入力!C33) -> 玖波 | D92: =IF(売上入力!D33="","",売上入力!D33) -> ホテル売上 | E92: =IFERROR(IF(売上入力!E33="",0,売上入力!E33*INDEX(マスター_OTA!$C$4:$C$29,MATCH(売上入力!D33,マスター_OTA!$A$4:$A$29,0))/100),0) -> 210375 | F92: =IF(売上入力!A33="","",売上入力!A33) -> 46143 | G92: 翌月分
A93: =IFERROR(IF(売上入力!A33="","",IF(INDEX(マスター_OTA!$D$4:$D$29,MATCH(売上入力!D33,マスター_OTA!$A$4:$A$29,0))=0,"",DATE(YEAR(売上入力!A33),MONTH(売上入力!A33)+2,IFERROR(INDEX(マスター_OTA!$G$4:$G$29,MATCH(売上入力!D33,マスター_OTA!$A$4:$A$29,0)),25)))),"") -> 46228 | B93: =IF(売上入力!B33="","",売上入力!B33) -> リゾート | C93: =IF(売上入力!C33="","",売上入力!C33) -> 玖波 | D93: =IF(売上入力!D33="","",売上入力!D33) -> ホテル売上 | E93: =IFERROR(IF(売上入力!E33="",0,売上入力!E33*INDEX(マスター_OTA!$D$4:$D$29,MATCH(売上入力!D33,マスター_OTA!$A$4:$A$29,0))/100),0) -> 28050 | F93: =IF(売上入力!A33="","",売上入力!A33) -> 46143 | G93: 翌々月分
A94: =IFERROR(IF(売上入力!A34="","",IF(INDEX(マスター_OTA!$B$4:$B$29,MATCH(売上入力!D34,マスター_OTA!$A$4:$A$29,0))=0,"",DATE(YEAR(売上入力!A34),MONTH(売上入力!A34),IFERROR(INDEX(マスター_OTA!$E$4:$E$29,MATCH(売上入力!D34,マスター_OTA!$A$4:$A$29,0)),28)))),"") | B94: =IF(売上入力!B34="","",売上入力!B34) -> リゾート | C94: =IF(売上入力!C34="","",売上入力!C34) -> 竹原（ﾚｽﾄﾗﾝ含む） | D94: =IF(売上入力!D34="","",売上入力!D34) -> 竹原市 | E94: =IFERROR(IF(売上入力!E34="",0,売上入力!E34*INDEX(マスター_OTA!$B$4:$B$29,MATCH(売上入力!D34,マスター_OTA!$A$4:$A$29,0))/100),0) -> 0 | F94: =IF(売上入力!A34="","",売上入力!A34) -> 46143 | G94: 当月分
A95: =IFERROR(IF(売上入力!A34="","",IF(INDEX(マスター_OTA!$C$4:$C$29,MATCH(売上入力!D34,マスター_OTA!$A$4:$A$29,0))=0,"",DATE(YEAR(売上入力!A34),MONTH(売上入力!A34)+1,IFERROR(INDEX(マスター_OTA!$F$4:$F$29,MATCH(売上入力!D34,マスター_OTA!$A$4:$A$29,0)),25)))),"") -> 46188 | B95: =IF(売上入力!B34="","",売上入力!B34) -> リゾート | C95: =IF(売上入力!C34="","",売上入力!C34) -> 竹原（ﾚｽﾄﾗﾝ含む） | D95: =IF(売上入力!D34="","",売上入力!D34) -> 竹原市 | E95: =IFERROR(IF(売上入力!E34="",0,売上入力!E34*INDEX(マスター_OTA!$C$4:$C$29,MATCH(売上入力!D34,マスター_OTA!$A$4:$A$29,0))/100),0) -> 789000 | F95: =IF(売上入力!A34="","",売上入力!A34) -> 46143 | G95: 翌月分
A96: =IFERROR(IF(売上入力!A34="","",IF(INDEX(マスター_OTA!$D$4:$D$29,MATCH(売上入力!D34,マスター_OTA!$A$4:$A$29,0))=0,"",DATE(YEAR(売上入力!A34),MONTH(売上入力!A34)+2,IFERROR(INDEX(マスター_OTA!$G$4:$G$29,MATCH(売上入力!D34,マスター_OTA!$A$4:$A$29,0)),25)))),"") | B96: =IF(売上入力!B34="","",売上入力!B34) -> リゾート | C96: =IF(売上入力!C34="","",売上入力!C34) -> 竹原（ﾚｽﾄﾗﾝ含む） | D96: =IF(売上入力!D34="","",売上入力!D34) -> 竹原市 | E96: =IFERROR(IF(売上入力!E34="",0,売上入力!E34*INDEX(マスター_OTA!$D$4:$D$29,MATCH(売上入力!D34,マスター_OTA!$A$4:$A$29,0))/100),0) -> 0 | F96: =IF(売上入力!A34="","",売上入力!A34) -> 46143 | G96: 翌々月分
A97: =IFERROR(IF(売上入力!A35="","",IF(INDEX(マスター_OTA!$B$4:$B$29,MATCH(売上入力!D35,マスター_OTA!$A$4:$A$29,0))=0,"",DATE(YEAR(売上入力!A35),MONTH(売上入力!A35),IFERROR(INDEX(マスター_OTA!$E$4:$E$29,MATCH(売上入力!D35,マスター_OTA!$A$4:$A$29,0)),28)))),"") -> 46193 | B97: =IF(売上入力!B35="","",売上入力!B35) -> リゾート | C97: =IF(売上入力!C35="","",売上入力!C35) -> Otake | D97: =IF(売上入力!D35="","",売上入力!D35) -> 売上 | E97: =IFERROR(IF(売上入力!E35="",0,売上入力!E35*INDEX(マスター_OTA!$B$4:$B$29,MATCH(売上入力!D35,マスター_OTA!$A$4:$A$29,0))/100),0) -> 10875 | F97: =IF(売上入力!A35="","",売上入力!A35) -> 46174 | G97: 当月分
A98: =IFERROR(IF(売上入力!A35="","",IF(INDEX(マスター_OTA!$C$4:$C$29,MATCH(売上入力!D35,マスター_OTA!$A$4:$A$29,0))=0,"",DATE(YEAR(売上入力!A35),MONTH(売上入力!A35)+1,IFERROR(INDEX(マスター_OTA!$F$4:$F$29,MATCH(売上入力!D35,マスター_OTA!$A$4:$A$29,0)),25)))),"") -> 46213 | B98: =IF(売上入力!B35="","",売上入力!B35) -> リゾート | C98: =IF(売上入力!C35="","",売上入力!C35) -> Otake | D98: =IF(売上入力!D35="","",売上入力!D35) -> 売上 | E98: =IFERROR(IF(売上入力!E35="",0,売上入力!E35*INDEX(マスター_OTA!$C$4:$C$29,MATCH(売上入力!D35,マスター_OTA!$A$4:$A$29,0))/100),0) -> 54375 | F98: =IF(売上入力!A35="","",売上入力!A35) -> 46174 | G98: 翌月分
A99: =IFERROR(IF(売上入力!A35="","",IF(INDEX(マスター_OTA!$D$4:$D$29,MATCH(売上入力!D35,マスター_OTA!$A$4:$A$29,0))=0,"",DATE(YEAR(売上入力!A35),MONTH(売上入力!A35)+2,IFERROR(INDEX(マスター_OTA!$G$4:$G$29,MATCH(売上入力!D35,マスター_OTA!$A$4:$A$29,0)),25)))),"") -> 46259 | B99: =IF(売上入力!B35="","",売上入力!B35) -> リゾート | C99: =IF(売上入力!C35="","",売上入力!C35) -> Otake | D99: =IF(売上入力!D35="","",売上入力!D35) -> 売上 | E99: =IFERROR(IF(売上入力!E35="",0,売上入力!E35*INDEX(マスター_OTA!$D$4:$D$29,MATCH(売上入力!D35,マスター_OTA!$A$4:$A$29,0))/100),0) -> 7250 | F99: =IF(売上入力!A35="","",売上入力!A35) -> 46174 | G99: 翌々月分
A100: =IFERROR(IF(売上入力!A36="","",IF(INDEX(マスター_OTA!$B$4:$B$29,MATCH(売上入力!D36,マスター_OTA!$A$4:$A$29,0))=0,"",DATE(YEAR(売上入力!A36),MONTH(売上入力!A36),IFERROR(INDEX(マスター_OTA!$E$4:$E$29,MATCH(売上入力!D36,マスター_OTA!$A$4:$A$29,0)),28)))),"") -> 46193 | B100: =IF(売上入力!B36="","",売上入力!B36) -> リゾート | C100: =IF(売上入力!C36="","",売上入力!C36) -> TAKAYA | D100: =IF(売上入力!D36="","",売上入力!D36) -> 売上 | E100: =IFERROR(IF(売上入力!E36="",0,売上入力!E36*INDEX(マスター_OTA!$B$4:$B$29,MATCH(売上入力!D36,マスター_OTA!$A$4:$A$29,0))/100),0) -> 50637.6 | F100: =IF(売上入力!A36="","",売上入力!A36) -> 46174 | G100: 当月分
...

Sheet 未払予定一覧
A1: 未払予定一覧（全社統合・カード枠回復統合・会社列で識別）
A2: 優先度: | B2: 高 | C2: 中 | D2: 低 | E2: 月次 | F2: カード枠回復 | H2: ※ 支払予定日入力で月次サマリー自動反映／状況"済"で支払完了表示／請求書PDFパスをQ列に貼付
A3: 会社 | B3: 種別 | C3: 物件 | D3: 概要 | E3: 勘定科目 | F3: 期日 | G3: 請求先 | H3: 当月分 | I3: 前月繰越 | J3: 前々月繰越 | K3: 前々々月以前 | L3: 累積未払合計 | M3: 優先度 | N3: 支払予定日 | O3: 支払予定額 | P3: 支払状況 | Q3: 請求書ファイル
A4: ザック | B4: 月次予定 | C4: ココユニバース | D4: トラストユアサービス | E4: 通信費 | F4: 46173 | G4: SAUNA | H4: 6050 | I4: 0 | J4: 0 | K4: 0 | L4: 6050 | M4: 月次 | N4: 46173 | O4: 6050
A5: モーテル | B5: 未払繰越 | C5: モーテル | D5: ASKUL（2か月分） | E5: 備品消耗品費 | F5: 46157 | G5: 弥山 | H5: 39871 | I5: 15932 | J5: 0 | K5: 0 | L5: 15932 | M5: 低 | N5: 46157 | O5: 39871
A6: モーテル | B6: 未払繰越 | C6: モーテル | D6: あしたば（4月分） | E6: 業務委託料 | F6: 46157 | G6: 弥山 | H6: 11000 | I6: 11000 | J6: 11000 | K6: 0 | L6: 22000 | M6: 中 | N6: 46157 | O6: 11000
A7: モーテル | B7: 未払繰越 | C7: モーテル | D7: ふくや（3ヶ月分） | E7: 食材費 | F7: 46171 | G7: 弥山 | H7: 6249 | I7: 12741 | J7: 12910 | K7: 0 | L7: 25651 | M7: 中 | N7: 46171 | O7: 6249
A9: モーテル | B9: 月次予定 | C9: モーテル | D9: JTB商事 | E9: 備品消耗品費 | F9: 46157 | G9: 弥山 | H9: 131472 | I9: 0 | J9: 0 | K9: 0 | L9: 131472 | M9: 月次 | N9: 46157 | O9: 131472
A12: モーテル | B12: 月次予定 | C12: モーテル | D12: シーエスプロ | E12: 備品消耗品費 | F12: 46171 | G12: 弥山 | H12: 20240 | I12: 0 | J12: 0 | K12: 0 | L12: 20240 | M12: 月次 | N12: 46171 | O12: 20240
A13: モーテル | B13: 月次予定 | C13: モーテル | D13: トラストユアサービス | E13: 通信費 | F13: 46171 | G13: 弥山 | H13: 5000 | I13: 0 | J13: 0 | K13: 0 | L13: 5000 | M13: 月次 | N13: 46171 | O13: 5000
A14: モーテル | B14: 月次予定 | C14: モーテル | D14: ネットシスジャパン | E14: システム利用料 | F14: 46157 | G14: 弥山 | H14: 13750 | I14: 0 | J14: 0 | K14: 0 | L14: 13750 | M14: 月次 | N14: 46157 | O14: 56100
A16: モーテル | B16: 月次予定 | C16: モーテル | D16: フロンテイアリネン（3月分） | E16: 衛生管理費 | F16: 46157 | G16: 弥山 | H16: 1153421 | I16: 0 | J16: 0 | K16: 0 | L16: 1153421 | M16: 月次 | N16: 46157 | O16: 1153421
A17: モーテル | B17: 月次予定 | C17: モーテル | D17: リクルート（じゃらん） | E17: システム利用料 | F17: 46153 | G17: 弥山 | H17: 144004 | I17: 0 | J17: 0 | K17: 0 | L17: 144004 | M17: 月次 | N17: 46153 | O17: 144004
A18: モーテル | B18: 月次予定 | C18: モーテル | D18: 新宮島観光旅館組合 | E18: 諸会費 | F18: 46171 | G18: 弥山 | H18: 18000 | I18: 0 | J18: 0 | K18: 0 | L18: 18000 | M18: 月次 | N18: 46171 | O18: 18000
A19: モーテル | B19: 月次予定 | C19: モーテル | D19: 日本食研 | E19: 食材費 | F19: 46162 | G19: 弥山 | H19: 10026 | I19: 0 | J19: 0 | K19: 0 | L19: 10026 | M19: 月次 | N19: 46162 | O19: 10026
... A22: リゾート | B22: 未払繰越 | C22: フォレスト | D22: フォワード | E22: 備品消耗品費 | F22: 46171 | G22: フォレストヒルズ | H22: 7346 | I22: 0 | J22: 18648 | K22: 0 | L22: 18648 | M22: 中 | N22: 46171 | O22: 7346
A23: リゾート | B23: 未払繰越 | C23: リゾート | D23: あしたば | E23: 業務委託費 | F23: 46157 | H23: 132000 | I23: 132000 | J23: 132000 | K23: 0 | L23: 264000 | M23: 中 | N23: 46157 | O23: 132000
A24: リゾート | B24: 未払繰越 | C24: リゾート | D24: アイパス | E24: システム利用料 | F24: 46171 | H24: 193050 | I24: 193050 | J24: 303050 | K24: 305800 | L24: 801900 | M24: 高 | N24: 46171 | O24: 193050
A25: リゾート | B25: 未払繰越 | C25: リゾート | D25: アシード（5か月分） | E25: リース料 | F25: 46171 | G25: デルーネ | H25: 17600 | I25: 17600 | J25: 17600 | K25: 35200 | L25: 70400 | M25: 高 | N25: 46171 | O25: 17600
A26: リゾート | B26: 未払繰越 | C26: リゾート | D26: アペックス（3ヶ月分） | E26: 備品消耗品費 | F26: 46171 | G26: たけはら | H26: 13200 | I26: 35340 | J26: 13200 | K26: 0 | L26: 48540 | M26: 中 | N26: 46171 | O26: 46530
A28: リゾート | B28: 未払繰越 | C28: リゾート | D28: イマイチ（3ヶ月分） | E28: 備品消耗品費 | F28: 46171 | G28: たけはら | H28: 13860 | I28: 13860 | J28: 10626 | K28: 0 | L28: 24486 | M28: 中 | N28: 46171 | O28: 13860
A29: リゾート | B29: 未払繰越 | C29: リゾート | D29: キャノン | E29: 備品消耗品費 | F29: 46167 | G29: ビュー | H29: 9852 | I29: 7893 | J29: 15809 | K29: 0 | L29: 23702 | M29: 中 | N29: 46167 | O29: 9852
A30: リゾート | B30: 未払繰越 | C30: リゾート | D30: クリンプロ（4か月分） | E30: 衛生管理費 | F30: 46171 | G30: 温井 | H30: 96800 | I30: 173800 | J30: 194040 | K30: 121000 | L30: 488840 | M30: 高 | N30: 46171 | O30: 96800
A31: リゾート | B31: 未払繰越 | C31: リゾート | D31: 安芸クリーナー（5か月分） | E31: ゴミ収集費 | F31: 46171 | G31: ビュー | H31: 27500 | I31: 27500 | J31: 27500 | K31: 55000 | L31: 110000 | M31: 高 | N31: 46171 | O31: 27500
A32: リゾート | B32: 未払繰越 | C32: リゾート | D32: 百姓屋（4か月分） | E32: 食材費 | F32: 46171 | G32: いこいの村 | H32: 33000 | I32: 82500 | J32: 60500 | K32: 44000 | L32: 187000 | M32: 高 | N32: 46171 | O32: 33000
A33: リゾート | B33: 未払繰越 | C33: リゾート | D33: 竹原クリーナー（5か月分） | E33: ゴミ収集費 | F33: 46171 | G33: たけはら | H33: 22000 | I33: 22000 | J33: 22000 | K33: 44000 | L33: 88000 | M33: 高 | N33: 46171 | O33: 22000
A34: リゾート | B34: 未払繰越 | C34: リゾート | D34: 第一興商 | E34: 通信費 | F34: 46150 | G34: たけはら | H34: 0 | I34: 0 | J34: 22000 | K34: 44000 | L34: 66000 | M34: 高 | N34: 46149 | O34: 100000
A35: リゾート | B35: 未払繰越 | C35: リゾート | D35: 第一興商（5か月分） | E35: 通信費 | F35: 46171 | G35: いこいの村 | H35: 46750 | I35: 46750 | J35: 46750 | K35: 93500 | L35: 187000 | M35: 高 | N35: 46171 | O35: 46750
A36: リゾート | B36: 未払繰越 | C36: リゾート | D36: 西部環境（4か月分） | E36: ゴミ収集費 | F36: 46171 | G36: 温井 | H36: 30800 | I36: 30800 | J36: 30800 | K36: 30800 | L36: 92400 | M36: 高 | O36: 92400
A37: リゾート | B37: 未払繰越 | C37: リゾート | D37: 青原木材（3ヶ月分） | E37: 備品消耗品費 | F37: 46171 | G37: 温井 | H37: 319440 | I37: 372405 | J37: 114015 | K37: 0 | L37: 486420 | M37: 中 | O37: 486420
A38: リゾート | B38: 月次予定 | C38: ほうらい | D38: ネットシスジャパン | E38: システム利用料 | F38: 46157 | H38: 16500 | I38: 0 | J38: 0 | K38: 0 | L38: 16500 | M38: 月次 | N38: 46172 | O38: 89800
A39: リゾート | B39: 月次予定 | C39: ほうらい | D39: 中国電力（1004） | E39: 水道光熱費 | F39: 46160 | H39: 5927 | I39: 0 | J39: 0 | K39: 0 | L39: 5927 | M39: 月次 | N39: 46160 | O39: 5927
A40: リゾート | B40: 月次予定 | C40: ほうらい | D40: 中国電力（残高不足により引落不能） | E40: 水道光熱費 | F40: 46149 | H40: 363435 | I40: 0 | J40: 0 | K40: 0 | L40: 363435 | M40: 月次 | N40: 46149 | O40: 363435
A42: リゾート | B42: 月次予定 | C42: フォレスト | D42: チュウブ(第1回） | E42: 業務委託費 | F42: 46149 | G42: フォレストヒルズ | H42: 660000 | I42: 0 | J42: 0 | K42: 0 | L42: 660000 | M42: 月次 | N42: 46149 | O42: 660000
A43: リゾート | B43: 月次予定 | C43: フォレスト | D43: チュウブ(第2回） | E43: 業務委託費 | F43: 46153 | G43: フォレストヒルズ | H43: 660000 | I43: 0 | J43: 0 | K43: 0 | L43: 660000 | M43: 月次 | N43: 46153 | O43: 660000
A44: リゾート | B44: 月次予定 | C44: フォレスト | D44: チュウブ(第3回） | E44: 業務委託費 | F44: 46160 | G44: フォレストヒルズ | H44: 660000 | I44: 0 | J44: 0 | K44: 0 | L44: 660000 | M44: 月次 | N44: 46160 | O44: 660000
A45: リゾート | B45: 月次予定 | C45: フォレスト | D45: チュウブ(第4回）※計2,640,000 | E45: 業務委託費 | F45: 46171 | G45: フォレストヒルズ | H45: 660000 | I45: 0 | J45: 0 | K45: 0 | L45: 660000 | M45: 月次 | N45: 46171 | O45: 660000
A47: リゾート | B47: 月次予定 | C47: フォレスト | D47: 半田電気管理 | E47: 設備費 | F47: 46171 | G47: フォレストヒルズ | H47: 23100 | I47: 0 | J47: 0 | K47: 0 | L47: 23100 | M47: 月次 | N47: 46171 | O47: 23100
A48: リゾート | B48: 月次予定 | C48: フォレスト | D48: 広島ガスプロパン | E48: 水道光熱費 | F48: 46171 | G48: フォレストヒルズ | H48: 9207 | I48: 0 | J48: 0 | K48: 0 | L48: 9207 | M48: 月次 | N48: 46171 | O48: 9207
A49: リゾート | B49: 月次予定 | C49: フォレスト | D49: 日本基準寝具 | E49: 衛生管理費 | F49: 46157 | G49: フォレストヒルズ | H49: 132929 | I49: 0 | J49: 0 | K49: 0 | L49: 132929 | M49: 月次 | N49: 46157 | O49: 33000
A50: リゾート | B50: 月次予定 | C50: フォレスト | D50: 日本食研 | E50: 食材費 | F50: 46162 | G50: フォレストヒルズ | H50: 11774 | I50: 0 | J50: 0 | K50: 0 | L50: 11774 | M50: 月次 | N50: 46162 | O50: 189334
A51: リゾート | B51: 月次予定 | C51: リゾート | D51: E-MAN（1月分） | E51: 業務委託費 | F51: 46153 | G51: フォレストヒルズ | H51: 262500 | I51: 0 | J51: 0 | K51: 0 | L51: 262500 | M51: 月次 | N51: 46153 | O51: 262500
A52: リゾート | B52: 月次予定 | C52: リゾート | D52: E-MAN（2月分） | E52: 業務委託費 | F52: 46157 | G52: フォレストヒルズ | H52: 262500 | I52: 0 | J52: 0 | K52: 0 | L52: 262500 | M52: 月次 | N52: 46157 | O52: 262500
A54: リゾート | B54: 月次予定 | C54: リゾート | D54: E-MAN（4月分） | E54: 業務委託費 | F54: 46171 | G54: フォレストヒルズ | H54: 225000 | I54: 0 | J54: 0 | K54: 0 | L54: 225000 | M54: 月次 | N54: 46171 | O54: 225000
A55: リゾート | B55: 月次予定 | C55: リゾート | D55: JTB商事 | E55: 備品消耗品費 | F55: 46157 | G55: デルーネ | H55: 107625 | I55: 0 | J55: 0 | K55: 0 | L55: 107625 | M55: 月次 | N55: 46157 | O55: 206646
A57: リゾート | B57: 月次予定 | C57: リゾート | D57: NTTドコモ | E57: 通信費 | F57: 46152 | H57: 880 | I57: 0 | J57: 0 | K57: 0 | L57: 880 | M57: 月次 | N57: 46152 | O57: 880
A63: リゾート | B63: 月次予定 | C63: リゾート | D63: アマノマネジメントサービス | E63: 賃料 | F63: 46153 | G63: たけはら | H63: 387200 | I63: 0 | J63: 0 | K63: 0 | L63: 387200 | M63: 月次 | N63: 46153 | O63: 387200
A64: リゾート | B64: 月次予定 | C64: リゾート | D64: イノベートリンク（消防点検） | E64: 設備費 | F64: 46171 | G64: いこいの村 | H64: 341000 | I64: 0 | J64: 0 | K64: 0 | L64: 341000 | M64: 月次 | N64: 46171 | O64: 341000
A66: リゾート | B66: 月次予定 | C66: リゾート | D66: エムケイ興産 | E66: 設備費 | F66: 46171 | G66: たけはら | H66: 136301 | I66: 0 | J66: 0 | K66: 0 | L66: 136301 | M66: 月次 | N66: 46149 | O66: 260000
A68: リゾート | B68: 月次予定 | C68: リゾート | D68: オーチスエレベータ | E68: 設備費 | F68: 46149 | G68: 温井 | H68: 37400 | I68: 0 | J68: 0 | K68: 0 | L68: 37400 | M68: 月次 | N68: 46149 | O68: 37400
A71: リゾート | B71: 月次予定 | C71: リゾート | D71: クレディセゾン | E71: 手数料 | F71: 46146 | H71: 182265 | I71: 0 | J71: 0 | K71: 0 | L71: 182265 | M71: 月次 | N71: 46146 | O71: 182265
A72: リゾート | B72: 月次予定 | C72: リゾート | D72: コカ・コーラ | E72: 備品消耗品費 | F72: 46171 | G72: いこいの村 | H72: 34660 | I72: 0 | J72: 0 | K72: 0 | L72: 34660 | M72: 月次 | N72: 46171 | O72: 34660
A73: リゾート | B73: 月次予定 | C73: リゾート | D73: シンエナジー | E73: 水道光熱費 | F73: 46147 | H73: 178844 | I73: 0 | J73: 0 | K73: 0 | L73: 178844 | M73: 月次 | N73: 46157 | O73: 198016
A76: リゾート | B76: 月次予定 | C76: リゾート | D76: タナカ米穀（残高不足により引落不能） | E76: 水道光熱費 | F76: 46149 | G76: ビュー | H76: 5667 | I76: 0 | J76: 0 | K76: 0 | L76: 5667 | M76: 月次 | N76: 46149 | O76: 55354
A78: リゾート | B78: 月次予定 | C78: リゾート | D78: トラストユアサービス | E78: 通信費 | F78: 46171 | H78: 56250 | I78: 0 | J78: 0 | K78: 0 | L78: 56250 | M78: 月次 | N78: 46171 | O78: 56250
A82: リゾート | B82: 月次予定 | C82: リゾート | D82: ネットシスジャパン※分割支払 | E82: システム利用料 | F82: 46160 | H82: 89800 | I82: 0 | J82: 0 | K82: 0 | L82: 89800 | M82: 月次 | N82: 46171 | O82: 89800
A84: リゾート | B84: 月次予定 | C84: リゾート | D84: ネットシスジャパン※分割支払（計539,000） | E84: システム利用料 | F84: 46153 | H84: 89800 | I84: 0 | J84: 0 | K84: 0 | L84: 89800 | M84: 月次 | N84: 46153 | O84: 89800
A86: リゾート | B86: 月次予定 | C86: リゾート | D86: ライフサービス※分割支払 | E86: 衛生管理費 | F86: 46160 | G86: 温井 | H86: 200000 | I86: 0 | J86: 0 | K86: 0 | L86: 200000 | M86: 月次 | N86: 46160 | O86: 200000
A87: リゾート | B87: 月次予定 | C87: リゾート | D87: ライフサービス※分割支払（計800,000) | E87: 衛生管理費 | F87: 46171 | G87: 温井 | H87: 200000 | I87: 0 | J87: 0 | K87: 0 | L87: 200000 | M87: 月次 | N87: 46171 | O87: 200000
A88: リゾート | B88: 月次予定 | C88: リゾート | D88: リクルート（じゃらん） | E88: システム利用料 | F88: 46171 | G88: 温井 | H88: 56508 | I88: 0 | J88: 0 | K88: 0 | L88: 56508 | M88: 月次 | N88: 46171 | O88: 77308
A90: リゾート | B90: 月次予定 | C90: リゾート | D90: 中国電力 | E90: 水道光熱費 | F90: 46160 | G90: いこいの村 | H90: 612 | I90: 0 | J90: 0 | K90: 0 | L90: 612 | M90: 月次 | N90: 46167 | O90: 8790
A92: リゾート | B92: 月次予定 | C92: リゾート | D92: 仁谷さん（2月分分割金）第4回目 | E92: 業務委託費 | F92: 46158 | H92: 43896 | I92: 0 | J92: 0 | K92: 0 | L92: 43896 | M92: 月次 | N92: 46158 | O92: 43896
A93: リゾート | B93: 月次予定 | C93: リゾート | D93: 北広島町市県民税 | E93: 租税公課 | F93: 46153 | H93: 1700 | I93: 0 | J93: 0 | K93: 0 | L93: 1700 | M93: 月次 | N93: 46153 | O93: 1700
A94: リゾート | B94: 月次予定 | C94: リゾート | D94: 古本さん※3月分 | E94: 業務委託費 | F94: 46153 | H94: 400000 | I94: 0 | J94: 0 | K94: 0 | L94: 400000 | M94: 月次 | N94: 46153 | O94: 400000
A95: リゾート | B95: 月次予定 | C95: リゾート | D95: 大竹市県民税 | E95: 租税公課 | F95: 46153 | H95: 5800 | I95: 0 | J95: 0 | K95: 0 | L95: 5800 | M95: 月次 | N95: 46153 | O95: 5800
A97: リゾート | B97: 月次予定 | C97: リゾート | D97: 安芸太田町市県民税 | E97: 租税公課 | F97: 46153 | H97: 11100 | I97: 0 | J97: 0 | K97: 0 | L97: 11100 | M97: 月次 | N97: 46153 | O97: 11100
A98: リゾート | B98: 月次予定 | C98: リゾート | D98: 富士フィルム | E98: 備品消耗品費 | F98: 46171 | G98: たけはら | H98: 3730 | I98: 0 | J98: 0 | K98: 0 | L98: 3730 | M98: 月次 | N98: 46171 | O98: 3730
A99: リゾート | B99: 月次予定 | C99: リゾート | D99: 島根県浜田市民税 | E99: 租税公課 | F99: 46153 | H99: 18600 | I99: 0 | J99: 0 | K99: 0 | L99: 18600 | M99: 月次 | N99: 46153 | O99: 18600
A100: リゾート | B100: 月次予定 | C100: リゾート | D100: 巴商会 | E100: 設備費 | F100: 46171 | G100: いこいの村 | H100: 156200 | I100: 0 | J100: 0 | K100: 0 | L100: 156200 | M100: 月次 | N100: 46171 | O100: 156200
A101: リゾート | B101: 月次予定 | C101: リゾート | D101: 広島ガス西中国 | E101: 水道光熱費 | F101: 46171 | G101: 玖波 | H101: 17622 | I101: 0 | J101: 0 | K101: 0 | L101: 17622 | M101: 月次 | N101: 46171 | O101: 17622
A102: リゾート | B102: 月次予定 | C102: リゾート | D102: 広島ケロシンサービス（3月分） | E102: 燃料費 | F102: 46157 | G102: 温井 | H102: 2543200 | I102: 0 | J102: 0 | K102: 0 | L102: 2543200 | M102: 月次 | N102: 46157 | O102: 2543200
A103: リゾート | B103: 月次予定 | C103: リゾート | D103: 広島市県民税 | E103: 租税公課 | F103: 46153 | H103: 56200 | I103: 0 | J103: 0 | K103: 0 | L103: 56200 | M103: 月次 | N103: 46153 | O103: 60100
A105: リゾート | B105: 月次予定 | C105: リゾート | D105: 広島市農業協同組合 | E105: 設備費 | F105: 46171 | G105: いこいの村 | H105: 3410 | I105: 0 | J105: 0 | K105: 0 | L105: 3410 | M105: 月次 | N105: 46171 | O105: 3410
A106: リゾート | B106: 月次予定 | C106: リゾート | D106: 廿日市市県民税 | E106: 租税公課 | F106: 46153 | H106: 4000 | I106: 0 | J106: 0 | K106: 0 | L106: 4000 | M106: 月次 | N106: 46153 | O106: 54700
A109: リゾート | B109: 月次予定 | C109: リゾート | D109: 廿日市市（道路占用継続） | E109: 租税公課 | F109: 46162 | H109: 100 | I109: 0 | J109: 0 | K109: 0 | L109: 100 | M109: 月次 | N109: 46162 | O109: 100
A110: リゾート | B110: 月次予定 | C110: リゾート | D110: 新宮島観光旅館組合 | E110: 諸会費 | F110: 46171 | G110: デルーネ | H110: 18000 | I110: 0 | J110: 0 | K110: 0 | L110: 18000 | M110: 月次 | N110: 46171 | O110: 18000
A116: リゾート | B116: 月次予定 | C116: リゾート | D116: 竹原市県民税 | E116: 租税公課 | F116: 46153 | H116: 6200 | I116: 0 | J116: 0 | K116: 0 | L116: 6200 | M116: 月次 | N116: 46153 | O116: 6200
A118: リゾート | B118: 月次予定 | C118: リゾート | D118: 筒賀建設 | E118: 設備費 | F118: 46171 | G118: いこいの村 | H118: 414700 | I118: 0 | J118: 0 | K118: 0 | L118: 414700 | M118: 月次 | N118: 46171 | O118: 414700
A119: リゾート | B119: 月次予定 | C119: リゾート | D119: 西原商会 | E119: 食材費 | F119: 46171 | G119: 温井 | H119: 54200 | I119: 0 | J119: 0 | K119: 0 | L119: 54200 | M119: 月次 | N119: 46171 | O119: 367972
A121: リゾート | B121: 月次予定 | C121: リゾート | D121: 高宮さん | E121: 業務委託費 | F121: 46167 | G121: 温井 | H121: 600000 | I121: 0 | J121: 0 | K121: 0 | L121: 600000 | M121: 月次 | N121: 46167 | O121: 600000
A122: リゾート | B122: カード枠回復 | D122: JCB | E122: カード | F122: 46153 | H122: 970000 | I122: 0 | J122: 0 | K122: 0 | L122: 970000 | M122: カード枠回復 | N122: 46153 | O122: 970000
A123: リゾート | B123: カード枠回復 | D123: セゾンYUSO | E123: カード | F123: 46149 | H123: 2600000 | I123: 0 | J123: 0 | K123: 0 | L123: 2600000 | M123: カード枠回復 | N123: 46149 | O123: 2600000
A124: リゾート | B124: カード枠回復 | D124: セゾンパルコ | E124: カード | F124: 46149 | H124: 1700000 | I124: 0 | J124: 0 | K124: 0 | L124: 1700000 | M124: カード枠回復 | N124: 46149 | O124: 1700000
A125: レジデンス | B125: 未払繰越 | C125: レジデンス | D125: あしたば | E125: 業務委託料 | F125: 46157 | G125: レジデンス | H125: 33000 | I125: 33000 | J125: 33000 | K125: 66000 | L125: 132000 | M125: 高 | N125: 46157 | O125: 33000
A127: レジデンス | B127: 月次予定 | C127: レジデンス | D127: カシモWiMAX | E127: 通信費 | F127: 46171 | G127: レジデンス | H127: 13932 | I127: 0 | J127: 0 | K127: 0 | L127: 13932 | M127: 月次 | N127: 46171 | O127: 13932
A128: レジデンス | B128: 月次予定 | C128: レジデンス | D128: トラストユアサービス | E128: 通信費 | F128: 46171 | G128: レジデンス | H128: 112800 | I128: 0 | J128: 0 | K128: 0 | L128: 112800 | M128: 月次 | N128: 46171 | O128: 112800
A129: レジデンス | B129: 月次予定 | D129: カ）グロ－バル | E129: その他 | F129: 46142 | G129: 広島信用金庫 | H129: 382102 | I129: 0 | J129: 0 | K129: 0 | L129: 382102 | M129: 月次 | N129: 46142 | O129: 382102 | P129: 済 | Q129: 振込一覧.xlsx
A130: レジデンス | B130: 月次予定 | D130: カ）シヨウエイジドウシヤセンタ－ | E130: その他 | F130: 46142 | G130: 広島銀行 | H130: 24290 | I130: 0 | J130: 0 | K130: 0 | L130: 24290 | M130: 月次 | N130: 46142 | O130: 24290 | P130: 済 | Q130: 振込一覧.xlsx
A131: レジデンス | B131: 月次予定 | D131: カ）プレコ | E131: その他 | F131: 46142 | G131: もみじ銀行 | H131: 6745 | I131: 0 | J131: 0 | K131: 0 | L131: 6745 | M131: 月次 | N131: 46142 | O131: 6745 | P131: 済 | Q131: 振込一覧.xlsx
A132: レジデンス | B132: 月次予定 | D132: トラストユアサ－ビス（カ | E132: その他 | F132: 46142 | G132: ＰａｙＰａｙ銀行 | H132: 30250 | I132: 0 | J132: 0 | K132: 0 | L132: 30250 | M132: 月次 | N132: 46142 | O132: 30250 | P132: 済 | Q132: 振込一覧.xlsx
A133: レジデンス | B133: 月次予定 | D133: トラストユアサ－ビス（カ | E133: その他 | F133: 46142 | G133: ＰａｙＰａｙ銀行 | H133: 114589 | I133: 0 | J133: 0 | K133: 0 | L133: 114589 | M133: 月次 | N133: 46142 | O133: 114589 | P133: 済 | Q133: 振込一覧.xlsx
A134: レジデンス | B134: 月次予定 | D134: ユ）サカエコウムテン | E134: その他 | F134: 46141 | G134: 山口銀行 | H134: 151945 | I134: 0 | J134: 0 | K134: 0 | L134: 151945 | M134: 月次 | N134: 46141 | O134: 151945 | P134: 済 | Q134: 振込一覧.xlsx
A135: レジデンス | B135: 月次予定 | D135: シマヤセツビ（カ | E135: 設備費 | F135: 46141 | G135: 広島銀行 | H135: 33145 | I135: 0 | J135: 0 | K135: 0 | L135: 33145 | M135: 月次 | N135: 46141 | O135: 33145 | P135: 済 | Q135: 振込一覧.xlsx
A136: レジデンス | B136: 月次予定 | D136: ユ－デンキ（カ | E136: 水道光熱費 | F136: 46141 | G136: 広島信用金庫 | H136: 33145 | I136: 0 | J136: 0 | K136: 0 | L136: 33145 | M136: 月次 | N136: 46141 | O136: 33145 | P136: 済 | Q136: 振込一覧.xlsx
A137: レジデンス | B137: 月次予定 | D137: フジイ トシキ | E137: その他 | F137: 46141 | G137: 広島銀行 | H137: 165145 | I137: 0 | J137: 0 | K137: 0 | L137: 165145 | M137: 月次 | N137: 46141 | O137: 165145 | P137: 済 | Q137: 振込一覧.xlsx
A138: レジデンス | B138: 月次予定 | D138: ヒロカツセツビ（カ | E138: 設備費 | F138: 46141 | G138: 広島市信用組合 | H138: 98045 | I138: 0 | J138: 0 | K138: 0 | L138: 98045 | M138: 月次 | N138: 46141 | O138: 98045 | P138: 済 | Q138: 振込一覧.xlsx
A139: レジデンス | B139: 月次予定 | D139: ヤマベ アキノリ | E139: その他 | F139: 46141 | G139: 広島銀行 | H139: 66549 | I139: 0 | J139: 0 | K139: 0 | L139: 66549 | M139: 月次 | N139: 46141 | O139: 66549 | P139: 済 | Q139: 振込一覧.xlsx
A140: レジデンス | B140: 月次予定 | D140: カ）メビウスマネジメントサ－ビス | E140: その他 | F140: 46141 | G140: 広島銀行 | H140: 122145 | I140: 0 | J140: 0 | K140: 0 | L140: 122145 | M140: 月次 | N140: 46141 | O140: 122145 | P140: 済 | Q140: 振込一覧.xlsx
... A185: レジデンス | B185: 月次予定 | D185: カ）グロ－バルリゾ－トレジデンス | E185: その他 | F185: 46031 | G185: ＰａｙＰａｙ銀行 | H185: 3000000 | I185: 0 | J185: 0 | K185: 0 | L185: 3000000 | M185: 月次 | N185: 46031 | O185: 3000000 | P185: 済 | Q185: 振込一覧.xlsx
A186: レジデンス | B186: 月次予定 | D186: カ）グロ－バル（月次予測） | E186: その他 | F186: 46172 | G186: 振込一覧.xlsxより推定 | H186: 372017 | I186: 0 | J186: 0 | K186: 0 | L186: 372017 | M186: 月次 | N186: 46172 | O186: 372017 | Q186: 通帳履歴より自動予測
...

Sheet 日次_レジデンス
A1: 日次キャッシュフロー — レジデンス（5月〜8月 縦積み）
A2: 入金=入金入力（会社=本社）+入金予測／支出=未払予定一覧（カード枠回復除く）／使用可能額=累計差引+累計カード枠回復
A3: 日付 | B3: 入金（円） | C3: 支出（円） | D3: 日次差引（円） | E3: 累計差引（円） | F3: カード枠回復額（円） | G3: 使用可能額（円） | H3: 備考
A4: ■ 5月
A5: 46142 | B5: =SUMIFS(入金入力!$E$4:$E$580,入金入力!$B$4:$B$580,A5,入金入力!$A$4:$A$580,"レジデンス")+SUMIFS(入金予測!$E$4:$E$603,入金予測!$A$4:$A$603,A5,入金予測!$B$4:$B$603,"レジデンス") -> 89000 | C5: =SUMIFS(未払予定一覧!$O$4:$O$830,未払予定一覧!$N$4:$N$830,A5,未払予定一覧!$A$4:$A$830,"レジデンス",未払予定一覧!$B$4:$B$830,"未払繰越")+SUMIFS(未払予定一覧!$O$4:$O$830,未払予定一覧!$N$4:$N$830,A5,未払予定一覧!$A$4:$A$830,"レジデンス",未払予定一覧!$B$4:$B$830,"月次予定") -> 976912 | D5: =B5-C5-F5 -> -887912 | E5: =D5 -> -887912 | F5: =SUMIFS(未払予定一覧!$O$4:$O$830,未払予定一覧!$N$4:$N$830,A5,未払予定一覧!$A$4:$A$830,"レジデンス",未払予定一覧!$B$4:$B$830,"カード枠回復") -> 0 | G5: =D5+F5 -> -887912
A6: 46143 | B6: =SUMIFS(入金入力!$E$4:$E$580,入金入力!$B$4:$B$580,A6,入金入力!$A$4:$A$580,"レジデンス")+SUMIFS(入金予測!$E$4:$E$603,入金予測!$A$4:$A$603,A6,入金予測!$B$4:$B$603,"レジデンス") -> 24506 | C6: =SUMIFS(未払予定一覧!$O$4:$O$830,未払予定一覧!$N$4:$N$830,A6,未払予定一覧!$A$4:$A$830,"レジデンス",未払予定一覧!$B$4:$B$830,"未払繰越")+SUMIFS(未払予定一覧!$O$4:$O$830,未払予定一覧!$N$4:$N$830,A6,未払予定一覧!$A$4:$A$830,"レジデンス",未払予定一覧!$B$4:$B$830,"月次予定") -> 0 | D6: =B6-C6-F6 -> 24506 | E6: =E5+D6 -> -863406 | F6: =SUMIFS(未払予定一覧!$O$4:$O$830,未払予定一覧!$N$4:$N$830,A6,未払予定一覧!$A$4:$A$830,"レジデンス",未払予定一覧!$B$4:$B$830,"カード枠回復") -> 0 | G6: =G5+D6+F6 -> -863406
A7: 46144 | B7: =SUMIFS(入金入力!$E$4:$E$580,入金入力!$B$4:$B$580,A7,入金入力!$A$4:$A$580,"レジデンス")+SUMIFS(入金予測!$E$4:$E$603,入金予測!$A$4:$A$603,A7,入金予測!$B$4:$B$603,"レジデンス") -> 0 | C7: =SUMIFS(未払予定一覧!$O$4:$O$830,未払予定一覧!$N$4:$N$830,A7,未払予定一覧!$A$4:$A$830,"レジデンス",未払予定一覧!$B$4:$B$830,"未払繰越")+SUMIFS(未払予定一覧!$O$4:$O$830,未払予定一覧!$N$4:$N$830,A7,未払予定一覧!$A$4:$A$830,"レジデンス",未払予定一覧!$B$4:$B$830,"月次予定") -> 0 | D7: =B7-C7-F7 -> 0 | E7: =E6+D7 -> -863406 | F7: =SUMIFS(未払予定一覧!$O$4:$O$830,未払予定一覧!$N$4:$N$830,A7,未払予定一覧!$A$4:$A$830,"レジデンス",未払予定一覧!$B$4:$B$830,"カード枠回復") -> 0 | G7: =G6+D7+F7 -> -863406 | H7: 土
A8: 46145 | B8: =SUMIFS(入金入力!$E$4:$E$580,入金入力!$B$4:$B$580,A8,入金入力!$A$4:$A$580,"レジデンス")+SUMIFS(入金予測!$E$4:$E$603,入金予測!$A$4:$A$603,A8,入金予測!$B$4:$B$603,"レジデンス") -> 0 | C8: =SUMIFS(未払予定一覧!$O$4:$O$830,未払予定一覧!$N$4:$N$830,A8,未払予定一覧!$A$4:$A$830,"レジデンス",未払予定一覧!$B$4:$B$830,"未払繰越")+SUMIFS(未払予定一覧!$O$4:$O$830,未払予定一覧!$N$4:$N$830,A8,未払予定一覧!$A$4:$A$830,"レジデンス",未払予定一覧!$B$4:$B$830,"月次予定") -> 0 | D8: =B8-C8-F8 -> 0 | E8: =E7+D8 -> -863406 | F8: =SUMIFS(未払予定一覧!$O$4:$O$830,未払予定一覧!$N$4:$N$830,A8,未払予定一覧!$A$4:$A$830,"レジデンス",未払予定一覧!$B$4:$B$830,"カード枠回復") -> 0 | G8: =G7+D8+F8 -> -863406 | H8: 日
A9: 46146 | B9: =SUMIFS(入金入力!$E$4:$E$580,入金入力!$B$4:$B$580,A9,入金入力!$A$4:$A$580,"レジデンス")+SUMIFS(入金予測!$E$4:$E$603,入金予測!$A$4:$A$603,A9,入金予測!$B$4:$B$603,"レジデンス") -> 0 | C9: =SUMIFS(未払予定一覧!$O$4:$O$830,未払予定一覧!$N$4:$N$830,A9,未払予定一覧!$A$4:$A$830,"レジデンス",未払予定一覧!$B$4:$B$830,"未払繰越")+SUMIFS(未払予定一覧!$O$4:$O$830,未払予定一覧!$N$4:$N$830,A9,未払予定一覧!$A$4:$A$830,"レジデンス",未払予定一覧!$B$4:$B$830,"月次予定") -> 0 | D9: =B9-C9-F9 -> 0 | E9: =E8+D9 -> -863406 | F9: =SUMIFS(未払予定一覧!$O$4:$O$830,未払予定一覧!$N$4:$N$830,A9,未払予定一覧!$A$4:$A$830,"レジデンス",未払予定一覧!$B$4:$B$830,"カード枠回復") -> 0 | G9: =G8+D9+F9 -> -863406
A10: 46147 | B10: =SUMIFS(入金入力!$E$4:$E$580,入金入力!$B$4:$B$580,A10,入金入力!$A$4:$A$580,"レジデンス")+SUMIFS(入金予測!$E$4:$E$603,入金予測!$A$4:$A$603,A10,入金予測!$B$4:$B$603,"レジデンス") -> 0 | C10: =SUMIFS(未払予定一覧!$O$4:$O$830,未払予定一覧!$N$4:$N$830,A10,未払予定一覧!$A$4:$A$830,"レジデンス",未払予定一覧!$B$4:$B$830,"未払繰越")+SUMIFS(未払予定一覧!$O$4:$O$830,未払予定一覧!$N$4:$N$830,A10,未払予定一覧!$A$4:$A$830,"レジデンス",未払予定一覧!$B$4:$B$830,"月次予定") -> 0 | D10: =B10-C10-F10 -> 0 | E10: =E9+D10 -> -863406 | F10: =SUMIFS(未払予定一覧!$O$4:$O$830,未払予定一覧!$N$4:$N$830,A10,未払予定一覧!$A$4:$A$830,"レジデンス",未払予定一覧!$B$4:$B$830,"カード枠回復") -> 0 | G10: =G9+D10+F10 -> -863406
A11: 46148 | B11: =SUMIFS(入金入力!$E$4:$E$580,入金入力!$B$4:$B$580,A11,入金入力!$A$4:$A$580,"レジデンス")+SUMIFS(入金予測!$E$4:$E$603,入金予測!$A$4:$A$603,A11,入金予測!$B$4:$B$603,"レジデンス") -> 0 | C11: =SUMIFS(未払予定一覧!$O$4:$O$830,未払予定一覧!$N$4:$N$830,A11,未払予定一覧!$A$4:$A$830,"レジデンス",未払予定一覧!$B$4:$B$830,"未払繰越")+SUMIFS(未払予定一覧!$O$4:$O$830,未払予定一覧!$N$4:$N$830,A11,未払予定一覧!$A$4:$A$830,"レジデンス",未払予定一覧!$B$4:$B$830,"月次予定") -> 0 | D11: =B11-C11-F11 -> 0 | E11: =E10+D11 -> -863406 | F11: =SUMIFS(未払予定一覧!$O$4:$O$830,未払予定一覧!$N$4:$N$830,A11,未払予定一覧!$A$4:$A$830,"レジデンス",未払予定一覧!$B$4:$B$830,"カード枠回復") -> 0 | G11: =G10+D11+F11 -> -863406
A12: 46149 | B12: =SUMIFS(入金入力!$E$4:$E$580,入金入力!$B$4:$B$580,A12,入金入力!$A$4:$A$580,"レジデンス")+SUMIFS(入金予測!$E$4:$E$603,入金予測!$A$4:$A$603,A12,入金予測!$B$4:$B$603,"レジデンス") -> 0 | C12: =SUMIFS(未払予定一覧!$O$4:$O$830,未払予定一覧!$N$4:$N$830,A12,未払予定一覧!$A$4:$A$830,"レジデンス",未払予定一覧!$B$4:$B$830,"未払繰越")+SUMIFS(未払予定一覧!$O$4:$O$830,未払予定一覧!$N$4:$N$830,A12,未払予定一覧!$A$4:$A$830,"レジデンス",未払予定一覧!$B$4:$B$830,"月次予定") -> 18150 | D12: =B12-C12-F12 -> -18150 | E12: =E11+D12 -> -881556 | F12: =SUMIFS(未払予定一覧!$O$4:$O$830,未払予定一覧!$N$4:$N$830,A12,未払予定一覧!$A$4:$A$830,"レジデンス",未払予定一覧!$B$4:$B$830,"カード枠回復") -> 0 | G12: =G11+D12+F12 -> -881556
A13: 46150 | B13: =SUMIFS(入金入力!$E$4:$E$580,入金入力!$B$4:$B$580,A13,入金入力!$A$4:$A$580,"レジデンス")+SUMIFS(入金予測!$E$4:$E$603,入金予測!$A$4:$A$603,A13,入金予測!$B$4:$B$603,"レジデンス") -> 0 | C13: =SUMIFS(未払予定一覧!$O$4:$O$830,未払予定一覧!$N$4:$N$830,A13,未払予定一覧!$A$4:$A$830,"レジデンス",未払予定一覧!$B$4:$B$830,"未払繰越")+SUMIFS(未払予定一覧!$O$4:$O$830,未払予定一覧!$N$4:$N$830,A13,未払予定一覧!$A$4:$A$830,"レジデンス",未払予定一覧!$B$4:$B$830,"月次予定") -> 6766 | D13: =B13-C13-F13 -> -6766 | E13: =E12+D13 -> -888322 | F13: =SUMIFS(未払予定一覧!$O$4:$O$830,未払予定一覧!$N$4:$N$830,A13,未払予定一覧!$A$4:$A$830,"レジデンス",未払予定一覧!$B$4:$B$830,"カード枠回復") -> 0 | G13: =G12+D13+F13 -> -888322
A14: 46151 | B14: =SUMIFS(入金入力!$E$4:$E$580,入金入力!$B$4:$B$580,A14,入金入力!$A$4:$A$580,"レジデンス")+SUMIFS(入金予測!$E$4:$E$603,入金予測!$A$4:$A$603,A14,入金予測!$B$4:$B$603,"レジデンス") -> 0 | D14: =B14-C14-F14 -> 0 | E14: =E13+D14 -> -888322 | F14: =SUMIFS(未払予定一覧!$O$4:$O$830,未払予定一覧!$N$4:$N$830,A14,未払予定一覧!$A$4:$A$830,"レジデンス",未払予定一覧!$B$4:$B$830,"カード枠回復") -> 0 | G14: =G13+D14+F14 -> -888322 | H14: 土
A15: 46152 | B15: =SUMIFS(入金入力!$E$4:$E$580,入金入力!$B$4:$B$580,A15,入金入力!$A$4:$A$580,"レジデンス")+SUMIFS(入金予測!$E$4:$E$603,入金予測!$A$4:$A$603,A15,入金予測!$B$4:$B$603,"レジデンス") -> 0 | C15: =SUMIFS(未払予定一覧!$O$4:$O$830,未払予定一覧!$N$4:$N$830,A15,未払予定一覧!$A$4:$A$830,"レジデンス",未払予定一覧!$B$4:$B$830,"未払繰越")+SUMIFS(未払予定一覧!$O$4:$O$830,未払予定一覧!$N$4:$N$830,A15,未払予定一覧!$A$4:$A$830,"レジデンス",未払予定一覧!$B$4:$B$830,"月次予定") -> 0 | D15: =B15-C15-F15 -> 0 | E15: =E14+D15 -> -888322 | F15: =SUMIFS(未払予定一覧!$O$4:$O$830,未払予定一覧!$N$4:$N$830,A15,未払予定一覧!$A$4:$A$830,"レジデンス",未払予定一覧!$B$4:$B$830,"カード枠回復") -> 0 | G15: =G14+D15+F15 -> -888322 | H15: 日
A16: 46153 | B16: =SUMIFS(入金入力!$E$4:$E$580,入金入力!$B$4:$B$580,A16,入金入力!$A$4:$A$580,"レジデンス")+SUMIFS(入金予測!$E$4:$E$603,入金予測!$A$4:$A$603,A16,入金予測!$B$4:$B$603,"レジデンス") -> 0 | C16: =SUMIFS(未払予定一覧!$O$4:$O$830,未払予定一覧!$N$4:$N$830,A16,未払予定一覧!$A$4:$A$830,"レジデンス",未払予定一覧!$B$4:$B$830,"未払繰越")+SUMIFS(未払予定一覧!$O$4:$O$830,未払予定一覧!$N$4:$N$830,A16,未払予定一覧!$A$4:$A$830,"レジデンス",未払予定一覧!$B$4:$B$830,"月次予定") -> 52810 | D16: =B16-C16-F16 -> -52810 | E16: =E15+D16 -> -941132 | F16: =SUMIFS(未払予定一覧!$O$4:$O$830,未払予定一覧!$N$4:$N$830,A16,未払予定一覧!$A$4:$A$830,"レジデンス",未払予定一覧!$B$4:$B$830,"カード枠回復") -> 0 | G16: =G15+D16+F16 -> -941132
A17: 46154 | B17: =SUMIFS(入金入力!$E$4:$E$580,入金入力!$B$4:$B$580,A17,入金入力!$A$4:$A$580,"レジデンス")+SUMIFS(入金予測!$E$4:$E$603,入金予測!$A$4:$A$603,A17,入金予測!$B$4:$B$603,"レジデンス") -> 8944000 | D17: =B17-C17-F17 -> 8944000 | E17: =E16+D17 -> 8002868 | F17: =SUMIFS(未払予定一覧!$O$4:$O$830,未払予定一覧!$N$4:$N$830,A17,未払予定一覧!$A$4:$A$830,"レジデンス",未払予定一覧!$B$4:$B$830,"カード枠回復") -> 0 | G17: =G16+D17+F17 -> 8002868
A18: 46155 | B18: =SUMIFS(入金入力!$E$4:$E$580,入金入力!$B$4:$B$580,A18,入金入力!$A$4:$A$580,"レジデンス")+SUMIFS(入金予測!$E$4:$E$603,入金予測!$A$4:$A$603,A18,入金予測!$B$4:$B$603,"レジデンス") -> 15000 | C18: =SUMIFS(未払予定一覧!$O$4:$O$830,未払予定一覧!$N$4:$N$830,A18,未払予定一覧!$A$4:$A$830,"レジデンス",未払予定一覧!$B$4:$B$830,"未払繰越")+SUMIFS(未払予定一覧!$O$4:$O$830,未払予定一覧!$N$4:$N$830,A18,未払予定一覧!$A$4:$A$830,"レジデンス",未払予定一覧!$B$4:$B$830,"月次予定") -> 1824691 | D18: =B18-C18-F18 -> -1809691 | E18: =E17+D18 -> 6193177 | F18: =SUMIFS(未払予定一覧!$O$4:$O$830,未払予定一覧!$N$4:$N$830,A18,未払予定一覧!$A$4:$A$830,"レジデンス",未払予定一覧!$B$4:$B$830,"カード枠回復") -> 0 | G18: =G17+D18+F18 -> 6193177
A19: 46156 | B19: =SUMIFS(入金入力!$E$4:$E$580,入金入力!$B$4:$B$580,A19,入金入力!$A$4:$A$580,"レジデンス")+SUMIFS(入金予測!$E$4:$E$603,入金予測!$A$4:$A$603,A19,入金予測!$B$4:$B$603,"レジデンス") -> 0 | C19: =SUMIFS(未払予定一覧!$O$4:$O$830,未払予定一覧!$N$4:$N$830,A19,未払予定一覧!$A$4:$A$830,"レジデンス",未払予定一覧!$B$4:$B$830,"未払繰越")+SUMIFS(未払予定一覧!$O$4:$O$830,未払予定一覧!$N$4:$N$830,A19,未払予定一覧!$A$4:$A$830,"レジデンス",未払予定一覧!$B$4:$B$830,"月次予定") -> 0 | D19: =B19-C19-F19 -> 0 | E19: =E18+D19 -> 6193177 | F19: =SUMIFS(未払予定一覧!$O$4:$O$830,未払予定一覧!$N$4:$N$830,A19,未払予定一覧!$A$4:$A$830,"レジデンス",未払予定一覧!$B$4:$B$830,"カード枠回復") -> 0 | G19: =G18+D19+F19 -> 6193177
A20: 46157 | B20: =SUMIFS(入金入力!$E$4:$E$580,入金入力!$B$4:$B$580,A20,入金入力!$A$4:$A$580,"レジデンス")+SUMIFS(入金予測!$E$4:$E$603,入金予測!$A$4:$A$603,A20,入金予測!$B$4:$B$603,"レジデンス") -> 620247 | C20: =SUMIFS(未払予定一覧!$O$4:$O$830,未払予定一覧!$N$4:$N$830,A20,未払予定一覧!$A$4:$A$830,"レジデンス",未払予定一覧!$B$4:$B$830,"未払繰越")+SUMIFS(未払予定一覧!$O$4:$O$830,未払予定一覧!$N$4:$N$830,A20,未払予定一覧!$A$4:$A$830,"レジデンス",未払予定一覧!$B$4:$B$830,"月次予定") -> 633000 | D20: =B20-C20-F20 -> -12753 | E20: =E19+D20 -> 6180424 | F20: =SUMIFS(未払予定一覧!$O$4:$O$830,未払予定一覧!$N$4:$N$830,A20,未払予定一覧!$A$4:$A$830,"レジデンス",未払予定一覧!$B$4:$B$830,"カード枠回復") -> 0 | G20: =G19+D20+F20 -> 6180424
A21: 46158 | B21: =SUMIFS(入金入力!$E$4:$E$580,入金入力!$B$4:$B$580,A21,入金入力!$A$4:$A$580,"レジデンス")+SUMIFS(入金予測!$E$4:$E$603,入金予測!$A$4:$A$603,A21,入金予測!$B$4:$B$603,"レジデンス") -> 0 | C21: =SUMIFS(未払予定一覧!$O$4:$O$830,未払予定一覧!$N$4:$N$830,A21,未払予定一覧!$A$4:$A$830,"レジデンス",未払予定一覧!$B$4:$B$830,"未払繰越")+SUMIFS(未払予定一覧!$O$4:$O$830,未払予定一覧!$N$4:$N$830,A21,未払予定一覧!$A$4:$A$830,"レジデンス",未払予定一覧!$B$4:$B$830,"月次予定") -> 107395 | D21: =B21-C21-F21 -> -107395 | E21: =E20+D21 -> 6073029 | F21: =SUMIFS(未払予定一覧!$O$4:$O$830,未払予定一覧!$N$4:$N$830,A21,未払予定一覧!$A$4:$A$830,"レジデンス",未払予定一覧!$B$4:$B$830,"カード枠回復") -> 0 | G21: =G20+D21+F21 -> 6073029 | H21: 土
A22: 46159 | B22: =SUMIFS(入金入力!$E$4:$E$580,入金入力!$B$4:$B$580,A22,入金入力!$A$4:$A$580,"レジデンス")+SUMIFS(入金予測!$E$4:$E$603,入金予測!$A$4:$A$603,A22,入金予測!$B$4:$B$603,"レジデンス") -> 0 | C22: =SUMIFS(未払予定一覧!$O$4:$O$830,未払予定一覧!$N$4:$N$830,A22,未払予定一覧!$A$4:$A$830,"レジデンス",未払予定一覧!$B$4:$B$830,"未払繰越")+SUMIFS(未払予定一覧!$O$4:$O$830,未払予定一覧!$N$4:$N$830,A22,未払予定一覧!$A$4:$A$830,"レジデンス",未払予定一覧!$B$4:$B$830,"月次予定") -> 0 | D22: =B22-C22-F22 -> 0 | E22: =E21+D22 -> 6073029 | F22: =SUMIFS(未払予定一覧!$O$4:$O$830,未払予定一覧!$N$4:$N$830,A22,未払予定一覧!$A$4:$A$830,"レジデンス",未払予定一覧!$B$4:$B$830,"カード枠回復") -> 0 | G22: =G21+D22+F22 -> 6073029 | H22: 日
A23: 46160 | B23: =SUMIFS(入金入力!$E$4:$E$580,入金入力!$B$4:$B$580,A23,入金入力!$A$4:$A$580,"レジデンス")+SUMIFS(入金予測!$E$4:$E$603,入金予測!$A$4:$A$603,A23,入金予測!$B$4:$B$603,"レジデンス") -> 0 | C23: =SUMIFS(未払予定一覧!$O$4:$O$830,未払予定一覧!$N$4:$N$830,A23,未払予定一覧!$A$4:$A$830,"レジデンス",未払予定一覧!$B$4:$B$830,"未払繰越")+SUMIFS(未払予定一覧!$O$4:$O$830,未払予定一覧!$N$4:$N$830,A23,未払予定一覧!$A$4:$A$830,"レジデンス",未払予定一覧!$B$4:$B$830,"月次予定") -> 0 | D23: =B23-C23-F23 -> 0 | E23: =E22+D23 -> 6073029 | F23: =SUMIFS(未払予定一覧!$O$4:$O$830,未払予定一覧!$N$4:$N$830,A23,未払予定一覧!$A$4:$A$830,"レジデンス",未払予定一覧!$B$4:$B$830,"カード枠回復") -> 0 | G23: =G22+D23+F23 -> 6073029
A24: 46161 | B24: =SUMIFS(入金入力!$E$4:$E$580,入金入力!$B$4:$B$580,A24,入金入力!$A$4:$A$580,"レジデンス")+SUMIFS(入金予測!$E$4:$E$603,入金予測!$A$4:$A$603,A24,入金予測!$B$4:$B$603,"レジデンス") -> 0 | C24: =SUMIFS(未払予定一覧!$O$4:$O$830,未払予定一覧!$N$4:$N$830,A24,未払予定一覧!$A$4:$A$830,"レジデンス",未払予定一覧!$B$4:$B$830,"未払繰越")+SUMIFS(未払予定一覧!$O$4:$O$830,未払予定一覧!$N$4:$N$830,A24,未払予定一覧!$A$4:$A$830,"レジデンス",未払予定一覧!$B$4:$B$830,"月次予定") -> 0 | D24: =B24-C24-F24 -> 0 | E24: =E23+D24 -> 6073029 | F24: =SUMIFS(未払予定一覧!$O$4:$O$830,未払予定一覧!$N$4:$N$830,A24,未払予定一覧!$A$4:$A$830,"レジデンス",未払予定一覧!$B$4:$B$830,"カード枠回復") -> 0 | G24: =G23+D24+F24 -> 6073029
A25: 46162 | B25: =SUMIFS(入金入力!$E$4:$E$580,入金入力!$B$4:$B$580,A25,入金入力!$A$4:$A$580,"レジデンス")+SUMIFS(入金予測!$E$4:$E$603,入金予測!$A$4:$A$603,A25,入金予測!$B$4:$B$603,"レジデンス") -> 0 | C25: =SUMIFS(未払予定一覧!$O$4:$O$830,未払予定一覧!$N$4:$N$830,A25,未払予定一覧!$A$4:$A$830,"レジデンス",未払予定一覧!$B$4:$B$830,"未払繰越")+SUMIFS(未払予定一覧!$O$4:$O$830,未払予定一覧!$N$4:$N$830,A25,未払予定一覧!$A$4:$A$830,"レジデンス",未払予定一覧!$B$4:$B$830,"月次予定") -> 523618 | D25: =B25-C25-F25 -> -523618 | E25: =E24+D25 -> 5549411 | F25: =SUMIFS(未払予定一覧!$O$4:$O$830,未払予定一覧!$N$4:$N$830,A25,未払予定一覧!$A$4:$A$830,"レジデンス",未払予定一覧!$B$4:$B$830,"カード枠回復") -> 0 | G25: =G24+D25+F25 -> 5549411
A26: 46163 | B26: =SUMIFS(入金入力!$E$4:$E$580,入金入力!$B$4:$B$580,A26,入金入力!$A$4:$A$580,"レジデンス")+SUMIFS(入金予測!$E$4:$E$603,入金予測!$A$4:$A$603,A26,入金予測!$B$4:$B$603,"レジデンス") -> 0 | C26: =SUMIFS(未払予定一覧!$O$4:$O$830,未払予定一覧!$N$4:$N$830,A26,未払予定一覧!$A$4:$A$830,"レジデンス",未払予定一覧!$B$4:$B$830,"未払繰越")+SUMIFS(未払予定一覧!$O$4:$O$830,未払予定一覧!$N$4:$N$830,A26,未払予定一覧!$A$4:$A$830,"レジデンス",未払予定一覧!$B$4:$B$830,"月次予定") -> 0 | D26: =B26-C26-F26 -> 0 | E26: =E25+D26 -> 5549411 | F26: =SUMIFS(未払予定一覧!$O$4:$O$830,未払予定一覧!$N$4:$N$830,A26,未払予定一覧!$A$4:$A$830,"レジデンス",未払予定一覧!$B$4:$B$830,"カード枠回復") -> 0 | G26: =G25+D26+F26 -> 5549411
A27: 46164 | B27: =SUMIFS(入金入力!$E$4:$E$580,入金入力!$B$4:$B$580,A27,入金入力!$A$4:$A$580,"レジデンス")+SUMIFS(入金予測!$E$4:$E$603,入金予測!$A$4:$A$603,A27,入金予測!$B$4:$B$603,"レジデンス") -> 0 | C27: =SUMIFS(未払予定一覧!$O$4:$O$830,未払予定一覧!$N$4:$N$830,A27,未払予定一覧!$A$4:$A$830,"レジデンス",未払予定一覧!$B$4:$B$830,"未払繰越")+SUMIFS(未払予定一覧!$O$4:$O$830,未払予定一覧!$N$4:$N$830,A27,未払予定一覧!$A$4:$A$830,"レジデンス",未払予定一覧!$B$4:$B$830,"月次予定") -> 0 | D27: =B27-C27-F27 -> 0 | E27: =E26+D27 -> 5549411 | F27: =SUMIFS(未払予定一覧!$O$4:$O$830,未払予定一覧!$N$4:$N$830,A27,未払予定一覧!$A$4:$A$830,"レジデンス",未払予定一覧!$B$4:$B$830,"カード枠回復") -> 0 | G27: =G26+D27+F27 -> 5549411
A28: 46165 | B28: =SUMIFS(入金入力!$E$4:$E$580,入金入力!$B$4:$B$580,A28,入金入力!$A$4:$A$580,"レジデンス")+SUMIFS(入金予測!$E$4:$E$603,入金予測!$A$4:$A$603,A28,入金予測!$B$4:$B$603,"レジデンス") -> 0 | C28: =SUMIFS(未払予定一覧!$O$4:$O$830,未払予定一覧!$N$4:$N$830,A28,未払予定一覧!$A$4:$A$830,"レジデンス",未払予定一覧!$B$4:$B$830,"未払繰越")+SUMIFS(未払予定一覧!$O$4:$O$830,未払予定一覧!$N$4:$N$830,A28,未払予定一覧!$A$4:$A$830,"レジデンス",未払予定一覧!$B$4:$B$830,"月次予定") -> 0 | D28: =B28-C28-F28 -> 0 | E28: =E27+D28 -> 5549411 | F28: =SUMIFS(未払予定一覧!$O$4:$O$830,未払予定一覧!$N$4:$N$830,A28,未払予定一覧!$A$4:$A$830,"レジデンス",未払予定一覧!$B$4:$B$830,"カード枠回復") -> 0 | G28: =G27+D28+F28 -> 5549411 | H28: 土
A29: 46166 | B29: =SUMIFS(入金入力!$E$4:$E$580,入金入力!$B$4:$B$580,A29,入金入力!$A$4:$A$580,"レジデンス")+SUMIFS(入金予測!$E$4:$E$603,入金予測!$A$4:$A$603,A29,入金予測!$B$4:$B$603,"レジデンス") -> 0 | C29: =SUMIFS(未払予定一覧!$O$4:$O$830,未払予定一覧!$N$4:$N$830,A29,未払予定一覧!$A$4:$A$830,"レジデンス",未払予定一覧!$B$4:$B$830,"未払繰越")+SUMIFS(未払予定一覧!$O$4:$O$830,未払予定一覧!$N$4:$N$830,A29,未払予定一覧!$A$4:$A$830,"レジデンス",未払予定一覧!$B$4:$B$830,"月次予定") -> 0 | D29: =B29-C29-F29 -> 0 | E29: =E28+D29 -> 5549411 | F29: =SUMIFS(未払予定一覧!$O$4:$O$830,未払予定一覧!$N$4:$N$830,A29,未払予定一覧!$A$4:$A$830,"レジデンス",未払予定一覧!$B$4:$B$830,"カード枠回復") -> 0 | G29: =G28+D29+F29 -> 5549411 | H29: 日
A30: 46167 | B30: =SUMIFS(入金入力!$E$4:$E$580,入金入力!$B$4:$B$580,A30,入金入力!$A$4:$A$580,"レジデンス")+SUMIFS(入金予測!$E$4:$E$603,入金予測!$A$4:$A$603,A30,入金予測!$B$4:$B$603,"レジデンス") -> 0 | C30: =SUMIFS(未払予定一覧!$O$4:$O$830,未払予定一覧!$N$4:$N$830,A30,未払予定一覧!$A$4:$A$830,"レジデンス",未払予定一覧!$B$4:$B$830,"未払繰越")+SUMIFS(未払予定一覧!$O$4:$O$830,未払予定一覧!$N$4:$N$830,A30,未払予定一覧!$A$4:$A$830,"レジデンス",未払予定一覧!$B$4:$B$830,"月次予定") -> 1059878 | D30: =B30-C30-F30 -> -1059878 | E30: =E29+D30 -> 4489533 | F30: =SUMIFS(未払予定一覧!$O$4:$O$830,未払予定一覧!$N$4:$N$830,A30,未払予定一覧!$A$4:$A$830,"レジデンス",未払予定一覧!$B$4:$B$830,"カード枠回復") -> 0 | G30: =G29+D30+F30 -> 4489533
A31: 46168 | B31: =SUMIFS(入金入力!$E$4:$E$580,入金入力!$B$4:$B$580,A31,入金入力!$A$4:$A$580,"レジデンス")+SUMIFS(入金予測!$E$4:$E$603,入金予測!$A$4:$A$603,A31,入金予測!$B$4:$B$603,"レジデンス") -> 0 | C31: =SUMIFS(未払予定一覧!$O$4:$O$830,未払予定一覧!$N$4:$N$830,A31,未払予定一覧!$A$4:$A$830,"レジデンス",未払予定一覧!$B$4:$B$830,"未払繰越")+SUMIFS(未払予定一覧!$O$4:$O$830,未払予定一覧!$N$4:$N$830,A31,未払予定一覧!$A$4:$A$830,"レジデンス",未払予定一覧!$B$4:$B$830,"月次予定") -> 0 | D31: =B31-C31-F31 -> 0 | E31: =E30+D31 -> 4489533 | F31: =SUMIFS(未払予定一覧!$O$4:$O$830,未払予定一覧!$N$4:$N$830,A31,未払予定一覧!$A$4:$A$830,"レジデンス",未払予定一覧!$B$4:$B$830,"カード枠回復") -> 0 | G31: =G30+D31+F31 -> 4489533
A32: 46169 | B32: =SUMIFS(入金入力!$E$4:$E$580,入金入力!$B$4:$B$580,A32,入金入力!$A$4:$A$580,"レジデンス")+SUMIFS(入金予測!$E$4:$E$603,入金予測!$A$4:$A$603,A32,入金予測!$B$4:$B$603,"レジデンス") -> 0 | C32: =SUMIFS(未払予定一覧!$O$4:$O$830,未払予定一覧!$N$4:$N$830,A32,未払予定一覧!$A$4:$A$830,"レジデンス",未払予定一覧!$B$4:$B$830,"未払繰越")+SUMIFS(未払予定一覧!$O$4:$O$830,未払予定一覧!$N$4:$N$830,A32,未払予定一覧!$A$4:$A$830,"レジデンス",未払予定一覧!$B$4:$B$830,"月次予定") -> 0 | D32: =B32-C32-F32 -> 0 | E32: =E31+D32 -> 4489533 | F32: =SUMIFS(未払予定一覧!$O$4:$O$830,未払予定一覧!$N$4:$N$830,A32,未払予定一覧!$A$4:$A$830,"レジデンス",未払予定一覧!$B$4:$B$830,"カード枠回復") -> 0 | G32: =G31+D32+F32 -> 4489533
A33: 46170 | B33: =SUMIFS(入金入力!$E$4:$E$580,入金入力!$B$4:$B$580,A33,入金入力!$A$4:$A$580,"レジデンス")+SUMIFS(入金予測!$E$4:$E$603,入金予測!$A$4:$A$603,A33,入金予測!$B$4:$B$603,"レジデンス") -> 0 | C33: =SUMIFS(未払予定一覧!$O$4:$O$830,未払予定一覧!$N$4:$N$830,A33,未払予定一覧!$A$4:$A$830,"レジデンス",未払予定一覧!$B$4:$B$830,"未払繰越")+SUMIFS(未払予定一覧!$O$4:$O$830,未払予定一覧!$N$4:$N$830,A33,未払予定一覧!$A$4:$A$830,"レジデンス",未払予定一覧!$B$4:$B$830,"月次予定") -> 310562 | D33: =B33-C33-F33 -> -310562 | E33: =E32+D33 -> 4178971 | F33: =SUMIFS(未払予定一覧!$O$4:$O$830,未払予定一覧!$N$4:$N$830,A33,未払予定一覧!$A$4:$A$830,"レジデンス",未払予定一覧!$B$4:$B$830,"カード枠回復") -> 0 | G33: =G32+D33+F33 -> 4178971
A34: 46171 | B34: =SUMIFS(入金入力!$E$4:$E$580,入金入力!$B$4:$B$580,A34,入金入力!$A$4:$A$580,"レジデンス")+SUMIFS(入金予測!$E$4:$E$603,入金予測!$A$4:$A$603,A34,入金予測!$B$4:$B$603,"レジデンス") -> 0 | C34: =SUMIFS(未払予定一覧!$O$4:$O$830,未払予定一覧!$N$4:$N$830,A34,未払予定一覧!$A$4:$A$830,"レジデンス",未払予定一覧!$B$4:$B$830,"未払繰越")+SUMIFS(未払予定一覧!$O$4:$O$830,未払予定一覧!$N$4:$N$830,A34,未払予定一覧!$A$4:$A$830,"レジデンス",未払予定一覧!$B$4:$B$830,"月次予定") -> 677161 | D34: =B34-C34-F34 -> -677161 | E34: =E33+D34 -> 3501810 | F34: =SUMIFS(未払予定一覧!$O$4:$O$830,未払予定一覧!$N$4:$N$830,A34,未払予定一覧!$A$4:$A$830,"レジデンス",未払予定一覧!$B$4:$B$830,"カード枠回復") -> 0 | G34: =G33+D34+F34 -> 3501810
A35: 46172 | B35: =SUMIFS(入金入力!$E$4:$E$580,入金入力!$B$4:$B$580,A35,入金入力!$A$4:$A$580,"レジデンス")+SUMIFS(入金予測!$E$4:$E$603,入金予測!$A$4:$A$603,A35,入金予測!$B$4:$B$603,"レジデンス") -> 0 | C35: =SUMIFS(未払予定一覧!$O$4:$O$830,未払予定一覧!$N$4:$N$830,A35,未払予定一覧!$A$4:$A$830,"レジデンス",未払予定一覧!$B$4:$B$830,"未払繰越")+SUMIFS(未払予定一覧!$O$4:$O$830,未払予定一覧!$N$4:$N$830,A35,未払予定一覧!$A$4:$A$830,"レジデンス",未払予定一覧!$B$4:$B$830,"月次予定") -> 493348 | D35: =B35-C35-F35 -> -493348 | E35: =E34+D35 -> 3008462 | F35: =SUMIFS(未払予定一覧!$O$4:$O$830,未払予定一覧!$N$4:$N$830,A35,未払予定一覧!$A$4:$A$830,"レジデンス",未払予定一覧!$B$4:$B$830,"カード枠回復") -> 0 | G35: =G34+D35+F35 -> 3008462 | H35: 土
A36: 46173 | B36: =SUMIFS(入金入力!$E$4:$E$580,入金入力!$B$4:$B$580,A36,入金入力!$A$4:$A$580,"レジデンス")+SUMIFS(入金予測!$E$4:$E$603,入金予測!$A$4:$A$603,A36,入金予測!$B$4:$B$603,"レジデンス") -> 0 | C36: =SUMIFS(未払予定一覧!$O$4:$O$830,未払予定一覧!$N$4:$N$830,A36,未払予定一覧!$A$4:$A$830,"レジデンス",未払予定一覧!$B$4:$B$830,"未払繰越")+SUMIFS(未払予定一覧!$O$4:$O$830,未払予定一覧!$N$4:$N$830,A36,未払予定一覧!$A$4:$A$830,"レジデンス",未払予定一覧!$B$4:$B$830,"月次予定") -> 0 | D36: =B36-C36-F36 -> 0 | E36: =E35+D36 -> 3008462 | F36: =SUMIFS(未払予定一覧!$O$4:$O$830,未払予定一覧!$N$4:$N$830,A36,未払予定一覧!$A$4:$A$830,"レジデンス",未払予定一覧!$B$4:$B$830,"カード枠回復") -> 0 | G36: =G35+D36+F36 -> 3008462 | H36: 日
A37: 5月合計 | B37: =SUM(B5:B36) -> 9692753 | C37: =SUM(C5:C36) -> 6684291 | D37: =B37-C37-F37 -> 3008462 | E37: =E36 -> 3008462 | F37: =SUM(F5:F36) -> 0 | G37: =G36 -> 3008462 | H37: 月合計
A39: ■ 6月
A40: 46174 | B40: =SUMIFS(入金入力!$E$4:$E$580,入金入力!$B$4:$B$580,A40,入金入力!$A$4:$A$580,"レジデンス")+SUMIFS(入金予測!$E$4:$E$603,入金予測!$A$4:$A$603,A40,入金予測!$B$4:$B$603,"レジデンス") -> 0 | C40: =SUMIFS(未払予定一覧!$O$4:$O$830,未払予定一覧!$N$4:$N$830,A40,未払予定一覧!$A$4:$A$830,"レジデンス",未払予定一覧!$B$4:$B$830,"未払繰越")+SUMIFS(未払予定一覧!$O$4:$O$830,未払予定一覧!$N$4:$N$830,A40,未払予定一覧!$A$4:$A$830,"レジデンス",未払予定一覧!$B$4:$B$830,"月次予定") -> 0 | D40: =B40-C40-F40 -> 0 | E40: =E37+D40 -> 3008462 | F40: =SUMIFS(未払予定一覧!$O$4:$O$830,未払予定一覧!$N$4:$N$830,A40,未払予定一覧!$A$4:$A$830,"レジデンス",未払予定一覧!$B$4:$B$830,"カード枠回復") -> 0 | G40: =G37+D40+F40 -> 3008462
A41: 46175 | B41: =SUMIFS(入金入力!$E$4:$E$580,入金入力!$B$4:$B$580,A41,入金入力!$A$4:$A$580,"レジデンス")+SUMIFS(入金予測!$E$4:$E$603,入金予測!$A$4:$A$603,A41,入金予測!$B$4:$B$603,"レジデンス") -> 0 | C41: =SUMIFS(未払予定一覧!$O$4:$O$830,未払予定一覧!$N$4:$N$830,A41,未払予定一覧!$A$4:$A$830,"レジデンス",未払予定一覧!$B$4:$B$830,"未払繰越")+SUMIFS(未払予定一覧!$O$4:$O$830,未払予定一覧!$N$4:$N$830,A41,未払予定一覧!$A$4:$A$830,"レジデンス",未払予定一覧!$B$4:$B$830,"月次予定") -> 0 | D41: =B41-C41-F41 -> 0 | E41: =E40+D41 -> 3008462 | F41: =SUMIFS(未払予定一覧!$O$4:$O$830,未払予定一覧!$N$4:$N$830,A41,未払予定一覧!$A$4:$A$830,"レジデンス",未払予定一覧!$B$4:$B$830,"カード枠回復") -> 0 | G41: =G40+D41+F41 -> 3008462
A42: 46176 | B42: =SUMIFS(入金入力!$E$4:$E$580,入金入力!$B$4:$B$580,A42,入金入力!$A$4:$A$580,"レジデンス")+SUMIFS(入金予測!$E$4:$E$603,入金予測!$A$4:$A$603,A42,入金予測!$B$4:$B$603,"レジデンス") -> 0 | C42: =SUMIFS(未払予定一覧!$O$4:$O$830,未払予定一覧!$N$4:$N$830,A42,未払予定一覧!$A$4:$A$830,"レジデンス",未払予定一覧!$B$4:$B$830,"未払繰越")+SUMIFS(未払予定一覧!$O$4:$O$830,未払予定一覧!$N$4:$N$830,A42,未払予定一覧!$A$4:$A$830,"レジデンス",未払予定一覧!$B$4:$B$830,"月次予定") -> 0 | D42: =B42-C42-F42 -> 0 | E42: =E41+D42 -> 3008462 | F42: =SUMIFS(未払予定一覧!$O$4:$O$830,未払予定一覧!$N$4:$N$830,A42,未払予定一覧!$A$4:$A$830,"レジデンス",未払予定一覧!$B$4:$B$830,"カード枠回復") -> 0 | G42: =G41+D42+F42 -> 3008462
A43: 46177 | B43: =SUMIFS(入金入力!$E$4:$E$580,入金入力!$B$4:$B$580,A43,入金入力!$A$4:$A$580,"レジデンス")+SUMIFS(入金予測!$E$4:$E$603,入金予測!$A$4:$A$603,A43,入金予測!$B$4:$B$603,"レジデンス") -> 0 | C43: =SUMIFS(未払予定一覧!$O$4:$O$830,未払予定一覧!$N$4:$N$830,A43,未払予定一覧!$A$4:$A$830,"レジデンス",未払予定一覧!$B$4:$B$830,"未払繰越")+SUMIFS(未払予定一覧!$O$4:$O$830,未払予定一覧!$N$4:$N$830,A43,未払予定一覧!$A$4:$A$830,"レジデンス",未払予定一覧!$B$4:$B$830,"月次予定") -> 0 | D43: =B43-C43-F43 -> 0 | E43: =E42+D43 -> 3008462 | F43: =SUMIFS(未払予定一覧!$O$4:$O$830,未払予定一覧!$N$4:$N$830,A43,未払予定一覧!$A$4:$A$830,"レジデンス",未払予定一覧!$B$4:$B$830,"カード枠回復") -> 0 | G43: =G42+D43+F43 -> 3008462
A44: 46178 | B44: =SUMIFS(入金入力!$E$4:$E$580,入金入力!$B$4:$B$580,A44,入金入力!$A$4:$A$580,"レジデンス")+SUMIFS(入金予測!$E$4:$E$603,入金予測!$A$4:$A$603,A44,入金予測!$B$4:$B$603,"レジデンス") -> 0 | C44: =SUMIFS(未払予定一覧!$O$4:$O$830,未払予定一覧!$N$4:$N$830,A44,未払予定一覧!$A$4:$A$830,"レジデンス",未払予定一覧!$B$4:$B$830,"未払繰越")+SUMIFS(未払予定一覧!$O$4:$O$830,未払予定一覧!$N$4:$N$830,A44,未払予定一覧!$A$4:$A$830,"レジデンス",未払予定一覧!$B$4:$B$830,"月次予定") -> 0 | D44: =B44-C44-F44 -> 0 | E44: =E43+D44 -> 3008462 | F44: =SUMIFS(未払予定一覧!$O$4:$O$830,未払予定一覧!$N$4:$N$830,A44,未払予定一覧!$A$4:$A$830,"レジデンス",未払予定一覧!$B$4:$B$830,"カード枠回復") -> 0 | G44: =G43+D44+F44 -> 3008462
A45: 46179 | B45: =SUMIFS(入金入力!$E$4:$E$580,入金入力!$B$4:$B$580,A45,入金入力!$A$4:$A$580,"レジデンス")+SUMIFS(入金予測!$E$4:$E$603,入金予測!$A$4:$A$603,A45,入金予測!$B$4:$B$603,"レジデンス") -> 0 | C45: =SUMIFS(未払予定一覧!$O$4:$O$830,未払予定一覧!$N$4:$N$830,A45,未払予定一覧!$A$4:$A$830,"レジデンス",未払予定一覧!$B$4:$B$830,"未払繰越")+SUMIFS(未払予定一覧!$O$4:$O$830,未払予定一覧!$N$4:$N$830,A45,未払予定一覧!$A$4:$A$830,"レジデンス",未払予定一覧!$B$4:$B$830,"月次予定") -> 0 | D45: =B45-C45-F45 -> 0 | E45: =E44+D45 -> 3008462 | F45: =SUMIFS(未払予定一覧!$O$4:$O$830,未払予定一覧!$N$4:$N$830,A45,未払予定一覧!$A$4:$A$830,"レジデンス",未払予定一覧!$B$4:$B$830,"カード枠回復") -> 0 | G45: =G44+D45+F45 -> 3008462 | H45: 土
A46: 46180 | B46: =SUMIFS(入金入力!$E$4:$E$580,入金入力!$B$4:$B$580,A46,入金入力!$A$4:$A$580,"レジデンス")+SUMIFS(入金予測!$E$4:$E$603,入金予測!$A$4:$A$603,A46,入金予測!$B$4:$B$603,"レジデンス") -> 0 | C46: =SUMIFS(未払予定一覧!$O$4:$O$830,未払予定一覧!$N$4:$N$830,A46,未払予定一覧!$A$4:$A$830,"レジデンス",未払予定一覧!$B$4:$B$830,"未払繰越")+SUMIFS(未払予定一覧!$O$4:$O$830,未払予定一覧!$N$4:$N$830,A46,未払予定一覧!$A$4:$A$830,"レジデンス",未払予定一覧!$B$4:$B$830,"月次予定") -> 0 | D46: =B46-C46-F46 -> 0 | E46: =E45+D46 -> 3008462 | F46: =SUMIFS(未払予定一覧!$O$4:$O$830,未払予定一覧!$N$4:$N$830,A46,未払予定一覧!$A$4:$A$830,"レジデンス",未払予定一覧!$B$4:$B$830,"カード枠回復") -> 0 | G46: =G45+D46+F46 -> 3008462 | H46: 日
A47: 46181 | B47: =SUMIFS(入金入力!$E$4:$E$580,入金入力!$B$4:$B$580,A47,入金入力!$A$4:$A$580,"レジデンス")+SUMIFS(入金予測!$E$4:$E$603,入金予測!$A$4:$A$603,A47,入金予測!$B$4:$B$603,"レジデンス") -> 0 | C47: =SUMIFS(未払予定一覧!$O$4:$O$830,未払予定一覧!$N$4:$N$830,A47,未払予定一覧!$A$4:$A$830,"レジデンス",未払予定一覧!$B$4:$B$830,"未払繰越")+SUMIFS(未払予定一覧!$O$4:$O$830,未払予定一覧!$N$4:$N$830,A47,未払予定一覧!$A$4:$A$830,"レジデンス",未払予定一覧!$B$4:$B$830,"月次予定") -> 0 | D47: =B47-C47-F47 -> 0 | E47: =E46+D47 -> 3008462 | F47: =SUMIFS(未払予定一覧!$O$4:$O$830,未払予定一覧!$N$4:$N$830,A47,未払予定一覧!$A$4:$A$830,"レジデンス",未払予定一覧!$B$4:$B$830,"カード枠回復") -> 0 | G47: =G46+D47+F47 -> 3008462
A48: 46182 | B48: =SUMIFS(入金入力!$E$4:$E$580,入金入力!$B$4:$B$580,A48,入金入力!$A$4:$A$580,"レジデンス")+SUMIFS(入金予測!$E$4:$E$603,入金予測!$A$4:$A$603,A48,入金予測!$B$4:$B$603,"レジデンス") -> 0 | C48: =SUMIFS(未払予定一覧!$O$4:$O$830,未払予定一覧!$N$4:$N$830,A48,未払予定一覧!$A$4:$A$830,"レジデンス",未払予定一覧!$B$4:$B$830,"未払繰越")+SUMIFS(未払予定一覧!$O$4:$O$830,未払予定一覧!$N$4:$N$830,A48,未払予定一覧!$A$4:$A$830,"レジデンス",未払予定一覧!$B$4:$B$830,"月次予定") -> 3131908 | D48: =B48-C48-F48 -> -3131908 | E48: =E47+D48 -> -123446 | F48: =SUMIFS(未払予定一覧!$O$4:$O$830,未払予定一覧!$N$4:$N$830,A48,未払予定一覧!$A$4:$A$830,"レジデンス",未払予定一覧!$B$4:$B$830,"カード枠回復") -> 0 | G48: =G47+D48+F48 -> -123446
A49: 46183 | B49: =SUMIFS(入金入力!$E$4:$E$580,入金入力!$B$4:$B$580,A49,入金入力!$A$4:$A$580,"レジデンス")+SUMIFS(入金予測!$E$4:$E$603,入金予測!$A$4:$A$603,A49,入金予測!$B$4:$B$603,"レジデンス") -> 0 | C49: =SUMIFS(未払予定一覧!$O$4:$O$830,未払予定一覧!$N$4:$N$830,A49,未払予定一覧!$A$4:$A$830,"レジデンス",未払予定一覧!$B$4:$B$830,"未払繰越")+SUMIFS(未払予定一覧!$O$4:$O$830,未払予定一覧!$N$4:$N$830,A49,未払予定一覧!$A$4:$A$830,"レジデンス",未払予定一覧!$B$4:$B$830,"月次予定") -> 0 | D49: =B49-C49-F49 -> 0 | E49: =E48+D49 -> -123446 | F49: =SUMIFS(未払予定一覧!$O$4:$O$830,未払予定一覧!$N$4:$N$830,A49,未払予定一覧!$A$4:$A$830,"レジデンス",未払予定一覧!$B$4:$B$830,"カード枠回復") -> 0 | G49: =G48+D49+F49 -> -123446
A50: 46184 | B50: =SUMIFS(入金入力!$E$4:$E$580,入金入力!$B$4:$B$580,A50,入金入力!$A$4:$A$580,"レジデンス")+SUMIFS(入金予測!$E$4:$E$603,入金予測!$A$4:$A$603,A50,入金予測!$B$4:$B$603,"レジデンス") -> 0 | C50: =SUMIFS(未払予定一覧!$O$4:$O$830,未払予定一覧!$N$4:$N$830,A50,未払予定一覧!$A$4:$A$830,"レジデンス",未払予定一覧!$B$4:$B$830,"未払繰越")+SUMIFS(未払予定一覧!$O$4:$O$830,未払予定一覧!$N$4:$N$830,A50,未払予定一覧!$A$4:$A$830,"レジデンス",未払予定一覧!$B$4:$B$830,"月次予定") -> 0 | D50: =B50-C50-F50 -> 0 | E50: =E49+D50 -> -123446 | F50: =SUMIFS(未払予定一覧!$O$4:$O$830,未払予定一覧!$N$4:$N$830,A50,未払予定一覧!$A$4:$A$830,"レジデンス",未払予定一覧!$B$4:$B$830,"カード枠回復") -> 0 | G50: =G49+D50+F50 -> -123446
A51: 46185 | B51: =SUMIFS(入金入力!$E$4:$E$580,入金入力!$B$4:$B$580,A51,入金入力!$A$4:$A$580,"レジデンス")+SUMIFS(入金予測!$E$4:$E$603,入金予測!$A$4:$A$603,A51,入金予測!$B$4:$B$603,"レジデンス") -> 0 | C51: =SUMIFS(未払予定一覧!$O$4:$O$830,未払予定一覧!$N$4:$N$830,A51,未払予定一覧!$A$4:$A$830,"レジデンス",未払予定一覧!$B$4:$B$830,"未払繰越")+SUMIFS(未払予定一覧!$O$4:$O$830,未払予定一覧!$N$4:$N$830,A51,未払予定一覧!$A$4:$A$830,"レジデンス",未払予定一覧!$B$4:$B$830,"月次予定") -> 0 | D51: =B51-C51-F51 -> 0 | E51: =E50+D51 -> -123446 | F51: =SUMIFS(未払予定一覧!$O$4:$O$830,未払予定一覧!$N$4:$N$830,A51,未払予定一覧!$A$4:$A$830,"レジデンス",未払予定一覧!$B$4:$B$830,"カード枠回復") -> 0 | G51: =G50+D51+F51 -> -123446
A52: 46186 | B52: =SUMIFS(入金入力!$E$4:$E$580,入金入力!$B$4:$B$580,A52,入金入力!$A$4:$A$580,"レジデンス")+SUMIFS(入金予測!$E$4:$E$603,入金予測!$A$4:$A$603,A52,入金予測!$B$4:$B$603,"レジデンス") -> 0 | C52: =SUMIFS(未払予定一覧!$O$4:$O$830,未払予定一覧!$N$4:$N$830,A52,未払予定一覧!$A$4:$A$830,"レジデンス",未払予定一覧!$B$4:$B$830,"未払繰越")+SUMIFS(未払予定一覧!$O$4:$O$830,未払予定一覧!$N$4:$N$830,A52,未払予定一覧!$A$4:$A$830,"レジデンス",未払予定一覧!$B$4:$B$830,"月次予定") -> 0 | D52: =B52-C52-F52 -> 0 | E52: =E51+D52 -> -123446 | F52: =SUMIFS(未払予定一覧!$O$4:$O$830,未払予定一覧!$N$4:$N$830,A52,未払予定一覧!$A$4:$A$830,"レジデンス",未払予定一覧!$B$4:$B$830,"カード枠回復") -> 0 | G52: =G51+D52+F52 -> -123446 | H52: 土
A53: 46187 | B53: =SUMIFS(入金入力!$E$4:$E$580,入金入力!$B$4:$B$580,A53,入金入力!$A$4:$A$580,"レジデンス")+SUMIFS(入金予測!$E$4:$E$603,入金予測!$A$4:$A$603,A53,入金予測!$B$4:$B$603,"レジデンス") -> 0 | C53: =SUMIFS(未払予定一覧!$O$4:$O$830,未払予定一覧!$N$4:$N$830,A53,未払予定一覧!$A$4:$A$830,"レジデンス",未払予定一覧!$B$4:$B$830,"未払繰越")+SUMIFS(未払予定一覧!$O$4:$O$830,未払予定一覧!$N$4:$N$830,A53,未払予定一覧!$A$4:$A$830,"レジデンス",未払予定一覧!$B$4:$B$830,"月次予定") -> 0 | D53: =B53-C53-F53 -> 0 | E53: =E52+D53 -> -123446 | F53: =SUMIFS(未払予定一覧!$O$4:$O$830,未払予定一覧!$N$4:$N$830,A53,未払予定一覧!$A$4:$A$830,"レジデンス",未払予定一覧!$B$4:$B$830,"カード枠回復") -> 0 | G53: =G52+D53+F53 -> -123446 | H53: 日
A54: 46188 | B54: =SUMIFS(入金入力!$E$4:$E$580,入金入力!$B$4:$B$580,A54,入金入力!$A$4:$A$580,"レジデンス")+SUMIFS(入金予測!$E$4:$E$603,入金予測!$A$4:$A$603,A54,入金予測!$B$4:$B$603,"レジデンス") -> 0 | C54: =SUMIFS(未払予定一覧!$O$4:$O$830,未払予定一覧!$N$4:$N$830,A54,未払予定一覧!$A$4:$A$830,"レジデンス",未払予定一覧!$B$4:$B$830,"未払繰越")+SUMIFS(未払予定一覧!$O$4:$O$830,未払予定一覧!$N$4:$N$830,A54,未払予定一覧!$A$4:$A$830,"レジデンス",未払予定一覧!$B$4:$B$830,"月次予定") -> 0 | D54: =B54-C54-F54 -> 0 | E54: =E53+D54 -> -123446 | F54: =SUMIFS(未払予定一覧!$O$4:$O$830,未払予定一覧!$N$4:$N$830,A54,未払予定一覧!$A$4:$A$830,"レジデンス",未払予定一覧!$B$4:$B$830,"カード枠回復") -> 0 | G54: =G53+D54+F54 -> -123446
A55: 46189 | B55: =SUMIFS(入金入力!$E$4:$E$580,入金入力!$B$4:$B$580,A55,入金入力!$A$4:$A$580,"レジデンス")+SUMIFS(入金予測!$E$4:$E$603,入金予測!$A$4:$A$603,A55,入金予測!$B$4:$B$603,"レジデンス") -> 0 | C55: =SUMIFS(未払予定一覧!$O$4:$O$830,未払予定一覧!$N$4:$N$830,A55,未払予定一覧!$A$4:$A$830,"レジデンス",未払予定一覧!$B$4:$B$830,"未払繰越")+SUMIFS(未払予定一覧!$O$4:$O$830,未払予定一覧!$N$4:$N$830,A55,未払予定一覧!$A$4:$A$830,"レジデンス",未払予定一覧!$B$4:$B$830,"月次予定") -> 107395 | D55: =B55-C55-F55 -> -107395 | E55: =E54+D55 -> -230841 | F55: =SUMIFS(未払予定一覧!$O$4:$O$830,未払予定一覧!$N$4:$N$830,A55,未払予定一覧!$A$4:$A$830,"レジデンス",未払予定一覧!$B$4:$B$830,"カード枠回復") -> 0 | G55: =G54+D55+F55 -> -230841
A56: 46190 | B56: =SUMIFS(入金入力!$E$4:$E$580,入金入力!$B$4:$B$580,A56,入金入力!$A$4:$A$580,"レジデンス")+SUMIFS(入金予測!$E$4:$E$603,入金予測!$A$4:$A$603,A56,入金予測!$B$4:$B$603,"レジデンス") -> 0 | C56: =SUMIFS(未払予定一覧!$O$4:$O$830,未払予定一覧!$N$4:$N$830,A56,未払予定一覧!$A$4:$A$830,"レジデンス",未払予定一覧!$B$4:$B$830,"未払繰越")+SUMIFS(未払予定一覧!$O$4:$O$830,未払予定一覧!$N$4:$N$830,A56,未払予定一覧!$A$4:$A$830,"レジデンス",未払予定一覧!$B$4:$B$830,"月次予定") -> 0 | D56: =B56-C56-F56 -> 0 | E56: =E55+D56 -> -230841 | F56: =SUMIFS(未払予定一覧!$O$4:$O$830,未払予定一覧!$N$4:$N$830,A56,未払予定一覧!$A$4:$A$830,"レジデンス",未払予定一覧!$B$4:$B$830,"カード枠回復") -> 0 | G56: =G55+D56+F56 -> -230841
A57: 46191 | B57: =SUMIFS(入金入力!$E$4:$E$580,入金入力!$B$4:$B$580,A57,入金入力!$A$4:$A$580,"レジデンス")+SUMIFS(入金予測!$E$4:$E$603,入金予測!$A$4:$A$603,A57,入金予測!$B$4:$B$603,"レジデンス") -> 0 | C57: =SUMIFS(未払予定一覧!$O$4:$O$830,未払予定一覧!$N$4:$N$830,A57,未払予定一覧!$A$4:$A$830,"レジデンス",未払予定一覧!$B$4:$B$830,"未払繰越")+SUMIFS(未払予定一覧!$O$4:$O$830,未払予定一覧!$N$4:$N$830,A57,未払予定一覧!$A$4:$A$830,"レジデンス",未払予定一覧!$B$4:$B$830,"月次予定") -> 0 | D57: =B57-C57-F57 -> 0 | E57: =E56+D57 -> -230841 | F57: =SUMIFS(未払予定一覧!$O$4:$O$830,未払予定一覧!$N$4:$N$830,A57,未払予定一覧!$A$4:$A$830,"レジデンス",未払予定一覧!$B$4:$B$830,"カード枠回復") -> 0 | G57: =G56+D57+F57 -> -230841
A58: 46192 | B58: =SUMIFS(入金入力!$E$4:$E$580,入金入力!$B$4:$B$580,A58,入金入力!$A$4:$A$580,"レジデンス")+SUMIFS(入金予測!$E$4:$E$603,入金予測!$A$4:$A$603,A58,入金予測!$B$4:$B$603,"レジデンス") -> 0 | C58: =SUMIFS(未払予定一覧!$O$4:$O$830,未払予定一覧!$N$4:$N$830,A58,未払予定一覧!$A$4:$A$830,"レジデンス",未払予定一覧!$B$4:$B$830,"未払繰越")+SUMIFS(未払予定一覧!$O$4:$O$830,未払予定一覧!$N$4:$N$830,A58,未払予定一覧!$A$4:$A$830,"レジデンス",未払予定一覧!$B$4:$B$830,"月次予定") -> 0 | D58: =B58-C58-F58 -> 0 | E58: =E57+D58 -> -230841 | F58: =SUMIFS(未払予定一覧!$O$4:$O$830,未払予定一覧!$N$4:$N$830,A58,未払予定一覧!$A$4:$A$830,"レジデンス",未払予定一覧!$B$4:$B$830,"カード枠回復") -> 0 | G58: =G57+D58+F58 -> -230841
A59: 46193 | B59: =SUMIFS(入金入力!$E$4:$E$580,入金入力!$B$4:$B$580,A59,入金入力!$A$4:$A$580,"レジデンス")+SUMIFS(入金予測!$E$4:$E$603,入金予測!$A$4:$A$603,A59,入金予測!$B$4:$B$603,"レジデンス") -> 0 | C59: =SUMIFS(未払予定一覧!$O$4:$O$830,未払予定一覧!$N$4:$N$830,A59,未払予定一覧!$A$4:$A$830,"レジデンス",未払予定一覧!$B$4:$B$830,"未払繰越")+SUMIFS(未払予定一覧!$O$4:$O$830,未払予定一覧!$N$4:$N$830,A59,未払予定一覧!$A$4:$A$830,"レジデンス",未払予定一覧!$B$4:$B$830,"月次予定") -> 523618 | D59: =B59-C59-F59 -> -523618 | E59: =E58+D59 -> -754459 | F59: =SUMIFS(未払予定一覧!$O$4:$O$830,未払予定一覧!$N$4:$N$830,A59,未払予定一覧!$A$4:$A$830,"レジデンス",未払予定一覧!$B$4:$B$830,"カード枠回復") -> 0 | G59: =G58+D59+F59 -> -754459 | H59: 土
A60: 46194 | B60: =SUMIFS(入金入力!$E$4:$E$580,入金入力!$B$4:$B$580,A60,入金入力!$A$4:$A$580,"レジデンス")+SUMIFS(入金予測!$E$4:$E$603,入金予測!$A$4:$A$603,A60,入金予測!$B$4:$B$603,"レジデンス") -> 0 | C60: =SUMIFS(未払予定一覧!$O$4:$O$830,未払予定一覧!$N$4:$N$830,A60,未払予定一覧!$A$4:$A$830,"レジデンス",未払予定一覧!$B$4:$B$830,"未払繰越")+SUMIFS(未払予定一覧!$O$4:$O$830,未払予定一覧!$N$4:$N$830,A60,未払予定一覧!$A$4:$A$830,"レジデンス",未払予定一覧!$B$4:$B$830,"月次予定") -> 0 | D60: =B60-C60-F60 -> 0 | E60: =E59+D60 -> -754459 | F60: =SUMIFS(未払予定一覧!$O$4:$O$830,未払予定一覧!$N$4:$N$830,A60,未払予定一覧!$A$4:$A$830,"レジデンス",未払予定一覧!$B$4:$B$830,"カード枠回復") -> 0 | G60: =G59+D60+F60 -> -754459 | H60: 日
A61: 46195 | B61: =SUMIFS(入金入力!$E$4:$E$580,入金入力!$B$4:$B$580,A61,入金入力!$A$4:$A$580,"レジデンス")+SUMIFS(入金予測!$E$4:$E$603,入金予測!$A$4:$A$603,A61,入金予測!$B$4:$B$603,"レジデンス") -> 0 | C61: =SUMIFS(未払予定一覧!$O$4:$O$830,未払予定一覧!$N$4:$N$830,A61,未払予定一覧!$A$4:$A$830,"レジデンス",未払予定一覧!$B$4:$B$830,"未払繰越")+SUMIFS(未払予定一覧!$O$4:$O$830,未払予定一覧!$N$4:$N$830,A61,未払予定一覧!$A$4:$A$830,"レジデンス",未払予定一覧!$B$4:$B$830,"月次予定") -> 0 | D61: =B61-C61-F61 -> 0 | E61: =E60+D61 -> -754459 | F61: =SUMIFS(未払予定一覧!$O$4:$O$830,未払予定一覧!$N$4:$N$830,A61,未払予定一覧!$A$4:$A$830,"レジデンス",未払予定一覧!$B$4:$B$830,"カード枠回復") -> 0 | G61: =G60+D61+F61 -> -754459
A62: 46196 | B62: =SUMIFS(入金入力!$E$4:$E$580,入金入力!$B$4:$B$580,A62,入金入力!$A$4:$A$580,"レジデンス")+SUMIFS(入金予測!$E$4:$E$603,入金予測!$A$4:$A$603,A62,入金予測!$B$4:$B$603,"レジデンス") -> 0 | C62: =SUMIFS(未払予定一覧!$O$4:$O$830,未払予定一覧!$N$4:$N$830,A62,未払予定一覧!$A$4:$A$830,"レジデンス",未払予定一覧!$B$4:$B$830,"未払繰越")+SUMIFS(未払予定一覧!$O$4:$O$830,未払予定一覧!$N$4:$N$830,A62,未払予定一覧!$A$4:$A$830,"レジデンス",未払予定一覧!$B$4:$B$830,"月次予定") -> 0 | D62: =B62-C62-F62 -> 0 | E62: =E61+D62 -> -754459 | F62: =SUMIFS(未払予定一覧!$O$4:$O$830,未払予定一覧!$N$4:$N$830,A62,未払予定一覧!$A$4:$A$830,"レジデンス",未払予定一覧!$B$4:$B$830,"カード枠回復") -> 0 | G62: =G61+D62+F62 -> -754459
A63: 46197 | B63: =SUMIFS(入金入力!$E$4:$E$580,入金入力!$B$4:$B$580,A63,入金入力!$A$4:$A$580,"レジデンス")+SUMIFS(入金予測!$E$4:$E$603,入金予測!$A$4:$A$603,A63,入金予測!$B$4:$B$603,"レジデンス") -> 0 | C63: =SUMIFS(未払予定一覧!$O$4:$O$830,未払予定一覧!$N$4:$N$830,A63,未払予定一覧!$A$4:$A$830,"レジデンス",未払予定一覧!$B$4:$B$830,"未払繰越")+SUMIFS(未払予定一覧!$O$4:$O$830,未払予定一覧!$N$4:$N$830,A63,未払予定一覧!$A$4:$A$830,"レジデンス",未払予定一覧!$B$4:$B$830,"月次予定") -> 0 | D63: =B63-C63-F63 -> 0 | E63: =E62+D63 -> -754459 | F63: =SUMIFS(未払予定一覧!$O$4:$O$830,未払予定一覧!$N$4:$N$830,A63,未払予定一覧!$A$4:$A$830,"レジデンス",未払予定一覧!$B$4:$B$830,"カード枠回復") -> 0 | G63: =G62+D63+F63 -> -754459
A64: 46198 | B64: =SUMIFS(入金入力!$E$4:$E$580,入金入力!$B$4:$B$580,A64,入金入力!$A$4:$A$580,"レジデンス")+SUMIFS(入金予測!$E$4:$E$603,入金予測!$A$4:$A$603,A64,入金予測!$B$4:$B$603,"レジデンス") -> 0 | C64: =SUMIFS(未払予定一覧!$O$4:$O$830,未払予定一覧!$N$4:$N$830,A64,未払予定一覧!$A$4:$A$830,"レジデンス",未払予定一覧!$B$4:$B$830,"未払繰越")+SUMIFS(未払予定一覧!$O$4:$O$830,未払予定一覧!$N$4:$N$830,A64,未払予定一覧!$A$4:$A$830,"レジデンス",未払予定一覧!$B$4:$B$830,"月次予定") -> 1059878 | D64: =B64-C64-F64 -> -1059878 | E64: =E63+D64 -> -1814337 | F64: =SUMIFS(未払予定一覧!$O$4:$O$830,未払予定一覧!$N$4:$N$830,A64,未払予定一覧!$A$4:$A$830,"レジデンス",未払予定一覧!$B$4:$B$830,"カード枠回復") -> 0 | G64: =G63+D64+F64 -> -1814337
A65: 46199 | B65: =SUMIFS(入金入力!$E$4:$E$580,入金入力!$B$4:$B$580,A65,入金入力!$A$4:$A$580,"レジデンス")+SUMIFS(入金予測!$E$4:$E$603,入金予測!$A$4:$A$603,A65,入金予測!$B$4:$B$603,"レジデンス") -> 0 | C65: =SUMIFS(未払予定一覧!$O$4:$O$830,未払予定一覧!$N$4:$N$830,A65,未払予定一覧!$A$4:$A$830,"レジデンス",未払予定一覧!$B$4:$B$830,"未払繰越")+SUMIFS(未払予定一覧!$O$4:$O$830,未払予定一覧!$N$4:$N$830,A65,未払予定一覧!$A$4:$A$830,"レジデンス",未払予定一覧!$B$4:$B$830,"月次予定") -> 0 | D65: =B65-C65-F65 -> 0 | E65: =E64+D65 -> -1814337 | F65: =SUMIFS(未払予定一覧!$O$4:$O$830,未払予定一覧!$N$4:$N$830,A65,未払予定一覧!$A$4:$A$830,"レジデンス",未払予定一覧!$B$4:$B$830,"カード枠回復") -> 0 | G65: =G64+D65+F65 -> -1814337
A66: 46200 | B66: =SUMIFS(入金入力!$E$4:$E$580,入金入力!$B$4:$B$580,A66,入金入力!$A$4:$A$580,"レジデンス")+SUMIFS(入金予測!$E$4:$E$603,入金予測!$A$4:$A$603,A66,入金予測!$B$4:$B$603,"レジデンス") -> 0 | C66: =SUMIFS(未払予定一覧!$O$4:$O$830,未払予定一覧!$N$4:$N$830,A66,未払予定一覧!$A$4:$A$830,"レジデンス",未払予定一覧!$B$4:$B$830,"未払繰越")+SUMIFS(未払予定一覧!$O$4:$O$830,未払予定一覧!$N$4:$N$830,A66,未払予定一覧!$A$4:$A$830,"レジデンス",未払予定一覧!$B$4:$B$830,"月次予定") -> 0 | D66: =B66-C66-F66 -> 0 | E66: =E65+D66 -> -1814337 | F66: =SUMIFS(未払予定一覧!$O$4:$O$830,未払予定一覧!$N$4:$N$830,A66,未払予定一覧!$A$4:$A$830,"レジデンス",未払予定一覧!$B$4:$B$830,"カード枠回復") -> 0 | G66: =G65+D66+F66 -> -1814337 | H66: 土
A67: 46201 | B67: =SUMIFS(入金入力!$E$4:$E$580,入金入力!$B$4:$B$580,A67,入金入力!$A$4:$A$580,"レジデンス")+SUMIFS(入金予測!$E$4:$E$603,入金予測!$A$4:$A$603,A67,入金予測!$B$4:$B$603,"レジデンス") -> 0 | C67: =SUMIFS(未払予定一覧!$O$4:$O$830,未払予定一覧!$N$4:$N$830,A67,未払予定一覧!$A$4:$A$830,"レジデンス",未払予定一覧!$B$4:$B$830,"未払繰越")+SUMIFS(未払予定一覧!$O$4:$O$830,未払予定一覧!$N$4:$N$830,A67,未払予定一覧!$A$4:$A$830,"レジデンス",未払予定一覧!$B$4:$B$830,"月次予定") -> 310562 | D67: =B67-C67-F67 -> -310562 | E67: =E66+D67 -> -2124899 | F67: =SUMIFS(未払予定一覧!$O$4:$O$830,未払予定一覧!$N$4:$N$830,A67,未払予定一覧!$A$4:$A$830,"レジデンス",未払予定一覧!$B$4:$B$830,"カード枠回復") -> 0 | G67: =G66+D67+F67 -> -2124899 | H67: 日
A68: 46202 | B68: =SUMIFS(入金入力!$E$4:$E$580,入金入力!$B$4:$B$580,A68,入金入力!$A$4:$A$580,"レジデンス")+SUMIFS(入金予測!$E$4:$E$603,入金予測!$A$4:$A$603,A68,入金予測!$B$4:$B$603,"レジデンス") -> 0 | C68: =SUMIFS(未払予定一覧!$O$4:$O$830,未払予定一覧!$N$4:$N$830,A68,未払予定一覧!$A$4:$A$830,"レジデンス",未払予定一覧!$B$4:$B$830,"未払繰越")+SUMIFS(未払予定一覧!$O$4:$O$830,未払予定一覧!$N$4:$N$830,A68,未払予定一覧!$A$4:$A$830,"レジデンス",未払予定一覧!$B$4:$B$830,"月次予定") -> 550429 | D68: =B68-C68-F68 -> -550429 | E68: =E67+D68 -> -2675328 | F68: =SUMIFS(未払予定一覧!$O$4:$O$830,未払予定一覧!$N$4:$N$830,A68,未払予定一覧!$A$4:$A$830,"レジデンス",未払予定一覧!$B$4:$B$830,"カード枠回復") -> 0 | G68: =G67+D68+F68 -> -2675328
A69: 46203 | B69: =SUMIFS(入金入力!$E$4:$E$580,入金入力!$B$4:$B$580,A69,入金入力!$A$4:$A$580,"レジデンス")+SUMIFS(入金予測!$E$4:$E$603,入金予測!$A$4:$A$603,A69,入金予測!$B$4:$B$603,"レジデンス") -> 0 | C69: =SUMIFS(未払予定一覧!$O$4:$O$830,未払予定一覧!$N$4:$N$830,A69,未払予定一覧!$A$4:$A$830,"レジデンス",未払予定一覧!$B$4:$B$830,"未払繰越")+SUMIFS(未払予定一覧!$O$4:$O$830,未払予定一覧!$N$4:$N$830,A69,未払予定一覧!$A$4:$A$830,"レジデンス",未払予定一覧!$B$4:$B$830,"月次予定") -> 493348 | D69: =B69-C69-F69 -> -493348 | E69: =E68+D69 -> -3168676 | F69: =SUMIFS(未払予定一覧!$O$4:$O$830,未払予定一覧!$N$4:$N$830,A69,未払予定一覧!$A$4:$A$830,"レジデンス",未払予定一覧!$B$4:$B$830,"カード枠回復") -> 0 | G69: =G68+D69+F69 -> -3168676
A70: 6月合計 | B70: =SUM(B40:B69) -> 0 | C70: =SUM(C40:C69) -> 6177138 | D70: =B70-C70-F70 -> -6177138 | E70: =E69 -> -3168676 | F70: =SUM(F40:F69) -> 0 | G70: =G69 -> -3168676 | H70: 月合計
A72: ■ 7月
A73: 46204 | B73: =SUMIFS(入金入力!$E$4:$E$580,入金入力!$B$4:$B$580,A73,入金入力!$A$4:$A$580,"レジデンス")+SUMIFS(入金予測!$E$4:$E$603,入金予測!$A$4:$A$603,A73,入金予測!$B$4:$B$603,"レジデンス") -> 0 | C73: =SUMIFS(未払予定一覧!$O$4:$O$830,未払予定一覧!$N$4:$N$830,A73,未払予定一覧!$A$4:$A$830,"レジデンス",未払予定一覧!$B$4:$B$830,"未払繰越")+SUMIFS(未払予定一覧!$O$4:$O$830,未払予定一覧!$N$4:$N$830,A73,未払予定一覧!$A$4:$A$830,"レジデンス",未払予定一覧!$B$4:$B$830,"月次予定") -> 0 | D73: =B73-C73-F73 -> 0 | E73: =E70+D73 -> -3168676 | F73: =SUMIFS(未払予定一覧!$O$4:$O$830,未払予定一覧!$N$4:$N$830,A73,未払予定一覧!$A$4:$A$830,"レジデンス",未払予定一覧!$B$4:$B$830,"カード枠回復") -> 0 | G73: =G70+D73+F73 -> -3168676
A74: 46205 | B74: =SUMIFS(入金入力!$E$4:$E$580,入金入力!$B$4:$B$580,A74,入金入力!$A$4:$A$580,"レジデンス")+SUMIFS(入金予測!$E$4:$E$603,入金予測!$A$4:$A$603,A74,入金予測!$B$4:$B$603,"レジデンス") -> 0 | C74: =SUMIFS(未払予定一覧!$O$4:$O$830,未払予定一覧!$N$4:$N$830,A74,未払予定一覧!$A$4:$A$830,"レジデンス",未払予定一覧!$B$4:$B$830,"未払繰越")+SUMIFS(未払予定一覧!$O$4:$O$830,未払予定一覧!$N$4:$N$830,A74,未払予定一覧!$A$4:$A$830,"レジデンス",未払予定一覧!$B$4:$B$830,"月次予定") -> 0 | D74: =B74-C74-F74 -> 0 | E74: =E73+D74 -> -3168676 | F74: =SUMIFS(未払予定一覧!$O$4:$O$830,未払予定一覧!$N$4:$N$830,A74,未払予定一覧!$A$4:$A$830,"レジデンス",未払予定一覧!$B$4:$B$830,"カード枠回復") -> 0 | G74: =G73+D74+F74 -> -3168676
A75: 46206 | B75: =SUMIFS(入金入力!$E$4:$E$580,入金入力!$B$4:$B$580,A75,入金入力!$A$4:$A$580,"レジデンス")+SUMIFS(入金予測!$E$4:$E$603,入金予測!$A$4:$A$603,A75,入金予測!$B$4:$B$603,"レジデンス") -> 0 | C75: =SUMIFS(未払予定一覧!$O$4:$O$830,未払予定一覧!$N$4:$N$830,A75,未払予定一覧!$A$4:$A$830,"レジデンス",未払予定一覧!$B$4:$B$830,"未払繰越")+SUMIFS(未払予定一覧!$O$4:$O$830,未払予定一覧!$N$4:$N$830,A75,未払予定一覧!$A$4:$A$830,"レジデンス",未払予定一覧!$B$4:$B$830,"月次予定") -> 0 | D75: =B75-C75-F75 -> 0 | E75: =E74+D75 -> -3168676 | F75: =SUMIFS(未払予定一覧!$O$4:$O$830,未払予定一覧!$N$4:$N$830,A75,未払予定一覧!$A$4:$A$830,"レジデンス",未払予定一覧!$B$4:$B$830,"カード枠回復") -> 0 | G75: =G74+D75+F75 -> -3168676
A76: 46207 | B76: =SUMIFS(入金入力!$E$4:$E$580,入金入力!$B$4:$B$580,A76,入金入力!$A$4:$A$580,"レジデンス")+SUMIFS(入金予測!$E$4:$E$603,入金予測!$A$4:$A$603,A76,入金予測!$B$4:$B$603,"レジデンス") -> 0 | C76: =SUMIFS(未払予定一覧!$O$4:$O$830,未払予定一覧!$N$4:$N$830,A76,未払予定一覧!$A$4:$A$830,"レジデンス",未払予定一覧!$B$4:$B$830,"未払繰越")+SUMIFS(未払予定一覧!$O$4:$O$830,未払予定一覧!$N$4:$N$830,A76,未払予定一覧!$A$4:$A$830,"レジデンス",未払予定一覧!$B$4:$B$830,"月次予定") -> 0 | D76: =B76-C76-F76 -> 0 | E76: =E75+D76 -> -3168676 | F76: =SUMIFS(未払予定一覧!$O$4:$O$830,未払予定一覧!$N$4:$N$830,A76,未払予定一覧!$A$4:$A$830,"レジデンス",未払予定一覧!$B$4:$B$830,"カード枠回復") -> 0 | G76: =G75+D76+F76 -> -3168676 | H76: 土
A77: 46208 | B77: =SUMIFS(入金入力!$E$4:$E$580,入金入力!$B$4:$B$580,A77,入金入力!$A$4:$A$580,"レジデンス")+SUMIFS(入金予測!$E$4:$E$603,入金予測!$A$4:$A$603,A77,入金予測!$B$4:$B$603,"レジデンス") -> 0 | C77: =SUMIFS(未払予定一覧!$O$4:$O$830,未払予定一覧!$N$4:$N$830,A77,未払予定一覧!$A$4:$A$830,"レジデンス",未払予定一覧!$B$4:$B$830,"未払繰越")+SUMIFS(未払予定一覧!$O$4:$O$830,未払予定一覧!$N$4:$N$830,A77,未払予定一覧!$A$4:$A$830,"レジデンス",未払予定一覧!$B$4:$B$830,"月次予定") -> 0 | D77: =B77-C77-F77 -> 0 | E77: =E76+D77 -> -3168676 | F77: =SUMIFS(未払予定一覧!$O$4:$O$830,未払予定一覧!$N$4:$N$830,A77,未払予定一覧!$A$4:$A$830,"レジデンス",未払予定一覧!$B$4:$B$830,"カード枠回復") -> 0 | G77: =G76+D77+F77 -> -3168676 | H77: 日
A78: 46209 | B78: =SUMIFS(入金入力!$E$4:$E$580,入金入力!$B$4:$B$580,A78,入金入力!$A$4:$A$580,"レジデンス")+SUMIFS(入金予測!$E$4:$E$603,入金予測!$A$4:$A$603,A78,入金予測!$B$4:$B$603,"レジデンス") -> 0 | C78: =SUMIFS(未払予定一覧!$O$4:$O$830,未払予定一覧!$N$4:$N$830,A78,未払予定一覧!$A$4:$A$830,"レジデンス",未払予定一覧!$B$4:$B$830,"未払繰越")+SUMIFS(未払予定一覧!$O$4:$O$830,未払予定一覧!$N$4:$N$830,A78,未払予定一覧!$A$4:$A$830,"レジデンス",未払予定一覧!$B$4:$B$830,"月次予定") -> 0 | D78: =B78-C78-F78 -> 0 | E78: =E77+D78 -> -3168676 | F78: =SUMIFS(未払予定一覧!$O$4:$O$830,未払予定一覧!$N$4:$N$830,A78,未払予定一覧!$A$4:$A$830,"レジデンス",未払予定一覧!$B$4:$B$830,"カード枠回復") -> 0 | G78: =G77+D78+F78 -> -3168676
A79: 46210 | B79: =SUMIFS(入金入力!$E$4:$E$580,入金入力!$B$4:$B$580,A79,入金入力!$A$4:$A$580,"レジデンス")+SUMIFS(入金予測!$E$4:$E$603,入金予測!$A$4:$A$603,A79,入金予測!$B$4:$B$603,"レジデンス") -> 0 | C79: =SUMIFS(未払予定一覧!$O$4:$O$830,未払予定一覧!$N$4:$N$830,A79,未払予定一覧!$A$4:$A$830,"レジデンス",未払予定一覧!$B$4:$B$830,"未払繰越")+SUMIFS(未払予定一覧!$O$4:$O$830,未払予定一覧!$N$4:$N$830,A79,未払予定一覧!$A$4:$A$830,"レジデンス",未払予定一覧!$B$4:$B$830,"月次予定") -> 0 | D79: =B79-C79-F79 -> 0 | E79: =E78+D79 -> -3168676 | F79: =SUMIFS(未払予定一覧!$O$4:$O$830,未払予定一覧!$N$4:$N$830,A79,未払予定一覧!$A$4:$A$830,"レジデンス",未払予定一覧!$B$4:$B$830,"カード枠回復") -> 0 | G79: =G78+D79+F79 -> -3168676
A80: 46211 | B80: =SUMIFS(入金入力!$E$4:$E$580,入金入力!$B$4:$B$580,A80,入金入力!$A$4:$A$580,"レジデンス")+SUMIFS(入金予測!$E$4:$E$603,入金予測!$A$4:$A$603,A80,入金予測!$B$4:$B$603,"レジデンス") -> 0 | C80: =SUMIFS(未払予定一覧!$O$4:$O$830,未払予定一覧!$N$4:$N$830,A80,未払予定一覧!$A$4:$A$830,"レジデンス",未払予定一覧!$B$4:$B$830,"未払繰越")+SUMIFS(未払予定一覧!$O$4:$O$830,未払予定一覧!$N$4:$N$830,A80,未払予定一覧!$A$4:$A$830,"レジデンス",未払予定一覧!$B$4:$B$830,"月次予定") -> 0 | D80: =B80-C80-F80 -> 0 | E80: =E79+D80 -> -3168676 | F80: =SUMIFS(未払予定一覧!$O$4:$O$830,未払予定一覧!$N$4:$N$830,A80,未払予定一覧!$A$4:$A$830,"レジデンス",未払予定一覧!$B$4:$B$830,"カード枠回復") -> 0 | G80: =G79+D80+F80 -> -3168676
A81: 46212 | B81: =SUMIFS(入金入力!$E$4:$E$580,入金入力!$B$4:$B$580,A81,入金入力!$A$4:$A$580,"レジデンス")+SUMIFS(入金予測!$E$4:$E$603,入金予測!$A$4:$A$603,A81,入金予測!$B$4:$B$603,"レジデンス") -> 0 | C81: =SUMIFS(未払予定一覧!$O$4:$O$830,未払予定一覧!$N$4:$N$830,A81,未払予定一覧!$A$4:$A$830,"レジデンス",未払予定一覧!$B$4:$B$830,"未払繰越")+SUMIFS(未払予定一覧!$O$4:$O$830,未払予定一覧!$N$4:$N$830,A81,未払予定一覧!$A$4:$A$830,"レジデンス",未払予定一覧!$B$4:$B$830,"月次予定") -> 3131908 | D81: =B81-C81-F81 -> -3131908 | E81: =E80+D81 -> -6300584 | F81: =SUMIFS(未払予定一覧!$O$4:$O$830,未払予定一覧!$N$4:$N$830,A81,未払予定一覧!$A$4:$A$830,"レジデンス",未払予定一覧!$B$4:$B$830,"カード枠回復") -> 0 | G81: =G80+D81+F81 -> -6300584
A82: 46213 | B82: =SUMIFS(入金入力!$E$4:$E$580,入金入力!$B$4:$B$580,A82,入金入力!$A$4:$A$580,"レジデンス")+SUMIFS(入金予測!$E$4:$E$603,入金予測!$A$4:$A$603,A82,入金予測!$B$4:$B$603,"レジデンス") -> 0 | C82: =SUMIFS(未払予定一覧!$O$4:$O$830,未払予定一覧!$N$4:$N$830,A82,未払予定一覧!$A$4:$A$830,"レジデンス",未払予定一覧!$B$4:$B$830,"未払繰越")+SUMIFS(未払予定一覧!$O$4:$O$830,未払予定一覧!$N$4:$N$830,A82,未払予定一覧!$A$4:$A$830,"レジデンス",未払予定一覧!$B$4:$B$830,"月次予定") -> 0 | D82: =B82-C82-F82 -> 0 | E82: =E81+D82 -> -6300584 | F82: =SUMIFS(未払予定一覧!$O$4:$O$830,未払予定一覧!$N$4:$N$830,A82,未払予定一覧!$A$4:$A$830,"レジデンス",未払予定一覧!$B$4:$B$830,"カード枠回復") -> 0 | G82: =G81+D82+F82 -> -6300584
A83: 46214 | B83: =SUMIFS(入金入力!$E$4:$E$580,入金入力!$B$4:$B$580,A83,入金入力!$A$4:$A$580,"レジデンス")+SUMIFS(入金予測!$E$4:$E$603,入金予測!$A$4:$A$603,A83,入金予測!$B$4:$B$603,"レジデンス") -> 0 | C83: =SUMIFS(未払予定一覧!$O$4:$O$830,未払予定一覧!$N$4:$N$830,A83,未払予定一覧!$A$4:$A$830,"レジデンス",未払予定一覧!$B$4:$B$830,"未払繰越")+SUMIFS(未払予定一覧!$O$4:$O$830,未払予定一覧!$N$4:$N$830,A83,未払予定一覧!$A$4:$A$830,"レジデンス",未払予定一覧!$B$4:$B$830,"月次予定") -> 0 | D83: =B83-C83-F83 -> 0 | E83: =E82+D83 -> -6300584 | F83: =SUMIFS(未払予定一覧!$O$4:$O$830,未払予定一覧!$N$4:$N$830,A83,未払予定一覧!$A$4:$A$830,"レジデンス",未払予定一覧!$B$4:$B$830,"カード枠回復") -> 0 | G83: =G82+D83+F83 -> -6300584 | H83: 土
A84: 46215 | B84: =SUMIFS(入金入力!$E$4:$E$580,入金入力!$B$4:$B$580,A84,入金入力!$A$4:$A$580,"レジデンス")+SUMIFS(入金予測!$E$4:$E$603,入金予測!$A$4:$A$603,A84,入金予測!$B$4:$B$603,"レジデンス") -> 0 | C84: =SUMIFS(未払予定一覧!$O$4:$O$830,未払予定一覧!$N$4:$N$830,A84,未払予定一覧!$A$4:$A$830,"レジデンス",未払予定一覧!$B$4:$B$830,"未払繰越")+SUMIFS(未払予定一覧!$O$4:$O$830,未払予定一覧!$N$4:$N$830,A84,未払予定一覧!$A$4:$A$830,"レジデンス",未払予定一覧!$B$4:$B$830,"月次予定") -> 0 | D84: =B84-C84-F84 -> 0 | E84: =E83+D84 -> -6300584 | F84: =SUMIFS(未払予定一覧!$O$4:$O$830,未払予定一覧!$N$4:$N$830,A84,未払予定一覧!$A$4:$A$830,"レジデンス",未払予定一覧!$B$4:$B$830,"カード枠回復") -> 0 | G84: =G83+D84+F84 -> -6300584 | H84: 日
A85: 46216 | B85: =SUMIFS(入金入力!$E$4:$E$580,入金入力!$B$4:$B$580,A85,入金入力!$A$4:$A$580,"レジデンス")+SUMIFS(入金予測!$E$4:$E$603,入金予測!$A$4:$A$603,A85,入金予測!$B$4:$B$603,"レジデンス") -> 0 | C85: =SUMIFS(未払予定一覧!$O$4:$O$830,未払予定一覧!$N$4:$N$830,A85,未払予定一覧!$A$4:$A$830,"レジデンス",未払予定一覧!$B$4:$B$830,"未払繰越")+SUMIFS(未払予定一覧!$O$4:$O$830,未払予定一覧!$N$4:$N$830,A85,未払予定一覧!$A$4:$A$830,"レジデンス",未払予定一覧!$B$4:$B$830,"月次予定") -> 0 | D85: =B85-C85-F85 -> 0 | E85: =E84+D85 -> -6300584 | F85: =SUMIFS(未払予定一覧!$O$4:$O$830,未払予定一覧!$N$4:$N$830,A85,未払予定一覧!$A$4:$A$830,"レジデンス",未払予定一覧!$B$4:$B$830,"カード枠回復") -> 0 | G85: =G84+D85+F85 -> -6300584
A86: 46217 | B86: =SUMIFS(入金入力!$E$4:$E$580,入金入力!$B$4:$B$580,A86,入金入力!$A$4:$A$580,"レジデンス")+SUMIFS(入金予測!$E$4:$E$603,入金予測!$A$4:$A$603,A86,入金予測!$B$4:$B$603,"レジデンス") -> 0 | C86: =SUMIFS(未払予定一覧!$O$4:$O$830,未払予定一覧!$N$4:$N$830,A86,未払予定一覧!$A$4:$A$830,"レジデンス",未払予定一覧!$B$4:$B$830,"未払繰越")+SUMIFS(未払予定一覧!$O$4:$O$830,未払予定一覧!$N$4:$N$830,A86,未払予定一覧!$A$4:$A$830,"レジデンス",未払予定一覧!$B$4:$B$830,"月次予定") -> 0 | D86: =B86-C86-F86 -> 0 | E86: =E85+D86 -> -6300584 | F86: =SUMIFS(未払予定一覧!$O$4:$O$830,未払予定一覧!$N$4:$N$830,A86,未払予定一覧!$A$4:$A$830,"レジデンス",未払予定一覧!$B$4:$B$830,"カード枠回復") -> 0 | G86: =G85+D86+F86 -> -6300584
A87: 46218 | B87: =SUMIFS(入金入力!$E$4:$E$580,入金入力!$B$4:$B$580,A87,入金入力!$A$4:$A$580,"レジデンス")+SUMIFS(入金予測!$E$4:$E$603,入金予測!$A$4:$A$603,A87,入金予測!$B$4:$B$603,"レジデンス") -> 0 | C87: =SUMIFS(未払予定一覧!$O$4:$O$830,未払予定一覧!$N$4:$N$830,A87,未払予定一覧!$A$4:$A$830,"レジデンス",未払予定一覧!$B$4:$B$830,"未払繰越")+SUMIFS(未払予定一覧!$O$4:$O$830,未払予定一覧!$N$4:$N$830,A87,未払予定一覧!$A$4:$A$830,"レジデンス",未払予定一覧!$B$4:$B$830,"月次予定") -> 0 | D87: =B87-C87-F87 -> 0 | E87: =E86+D87 -> -6300584 | F87: =SUMIFS(未払予定一覧!$O$4:$O$830,未払予定一覧!$N$4:$N$830,A87,未払予定一覧!$A$4:$A$830,"レジデンス",未払予定一覧!$B$4:$B$830,"カード枠回復") -> 0 | G87: =G86+D87+F87 -> -6300584
A88: 46219 | B88: =SUMIFS(入金入力!$E$4:$E$580,入金入力!$B$4:$B$580,A88,入金入力!$A$4:$A$580,"レジデンス")+SUMIFS(入金予測!$E$4:$E$603,入金予測!$A$4:$A$603,A88,入金予測!$B$4:$B$603,"レジデンス") -> 0 | C88: =SUMIFS(未払予定一覧!$O$4:$O$830,未払予定一覧!$N$4:$N$830,A88,未払予定一覧!$A$4:$A$830,"レジデンス",未払予定一覧!$B$4:$B$830,"未払繰越")+SUMIFS(未払予定一覧!$O$4:$O$830,未払予定一覧!$N$4:$N$830,A88,未払予定一覧!$A$4:$A$830,"レジデンス",未払予定一覧!$B$4:$B$830,"月次予定") -> 107395 | D88: =B88-C88-F88 -> -107395 | E88: =E87+D88 -> -6407979 | F88: =SUMIFS(未払予定一覧!$O$4:$O$830,未払予定一覧!$N$4:$N$830,A88,未払予定一覧!$A$4:$A$830,"レジデンス",未払予定一覧!$B$4:$B$830,"カード枠回復") -> 0 | G88: =G87+D88+F88 -> -6407979
A89: 46220 | B89: =SUMIFS(入金入力!$E$4:$E$580,入金入力!$B$4:$B$580,A89,入金入力!$A$4:$A$580,"レジデンス")+SUMIFS(入金予測!$E$4:$E$603,入金予測!$A$4:$A$603,A89,入金予測!$B$4:$B$603,"レジデンス") -> 0 | C89: =SUMIFS(未払予定一覧!$O$4:$O$830,未払予定一覧!$N$4:$N$830,A89,未払予定一覧!$A$4:$A$830,"レジデンス",未払予定一覧!$B$4:$B$830,"未払繰越")+SUMIFS(未払予定一覧!$O$4:$O$830,未払予定一覧!$N$4:$N$830,A89,未払予定一覧!$A$4:$A$830,"レジデンス",未払予定一覧!$B$4:$B$830,"月次予定") -> 0 | D89: =B89-C89-F89 -> 0 | E89: =E88+D89 -> -6407979 | F89: =SUMIFS(未払予定一覧!$O$4:$O$830,未払予定一覧!$N$4:$N$830,A89,未払予定一覧!$A$4:$A$830,"レジデンス",未払予定一覧!$B$4:$B$830,"カード枠回復") -> 0 | G89: =G88+D89+F89 -> -6407979
A90: 46221 | B90: =SUMIFS(入金入力!$E$4:$E$580,入金入力!$B$4:$B$580,A90,入金入力!$A$4:$A$580,"レジデンス")+SUMIFS(入金予測!$E$4:$E$603,入金予測!$A$4:$A$603,A90,入金予測!$B$4:$B$603,"レジデンス") -> 0 | C90: =SUMIFS(未払予定一覧!$O$4:$O$830,未払予定一覧!$N$4:$N$830,A90,未払予定一覧!$A$4:$A$830,"レジデンス",未払予定一覧!$B$4:$B$830,"未払繰越")+SUMIFS(未払予定一覧!$O$4:$O$830,未払予定一覧!$N$4:$N$830,A90,未払予定一覧!$A$4:$A$830,"レジデンス",未払予定一覧!$B$4:$B$830,"月次予定") -> 0 | D90: =B90-C90-F90 -> 0 | E90: =E89+D90 -> -6407979 | F90: =SUMIFS(未払予定一覧!$O$4:$O$830,未払予定一覧!$N$4:$N$830,A90,未払予定一覧!$A$4:$A$830,"レジデンス",未払予定一覧!$B$4:$B$830,"カード枠回復") -> 0 | G90: =G89+D90+F90 -> -6407979 | H90: 土
A91: 46222 | B91: =SUMIFS(入金入力!$E$4:$E$580,入金入力!$B$4:$B$580,A91,入金入力!$A$4:$A$580,"レジデンス")+SUMIFS(入金予測!$E$4:$E$603,入金予測!$A$4:$A$603,A91,入金予測!$B$4:$B$603,"レジデンス") -> 0 | C91: =SUMIFS(未払予定一覧!$O$4:$O$830,未払予定一覧!$N$4:$N$830,A91,未払予定一覧!$A$4:$A$830,"レジデンス",未払予定一覧!$B$4:$B$830,"未払繰越")+SUMIFS(未払予定一覧!$O$4:$O$830,未払予定一覧!$N$4:$N$830,A91,未払予定一覧!$A$4:$A$830,"レジデンス",未払予定一覧!$B$4:$B$830,"月次予定") -> 0 | D91: =B91-C91-F91 -> 0 | E91: =E90+D91 -> -6407979 | F91: =SUMIFS(未払予定一覧!$O$4:$O$830,未払予定一覧!$N$4:$N$830,A91,未払予定一覧!$A$4:$A$830,"レジデンス",未払予定一覧!$B$4:$B$830,"カード枠回復") -> 0 | G91: =G90+D91+F91 -> -6407979 | H91: 日
A92: 46223 | B92: =SUMIFS(入金入力!$E$4:$E$580,入金入力!$B$4:$B$580,A92,入金入力!$A$4:$A$580,"レジデンス")+SUMIFS(入金予測!$E$4:$E$603,入金予測!$A$4:$A$603,A92,入金予測!$B$4:$B$603,"レジデンス") -> 0 | C92: =SUMIFS(未払予定一覧!$O$4:$O$830,未払予定一覧!$N$4:$N$830,A92,未払予定一覧!$A$4:$A$830,"レジデンス",未払予定一覧!$B$4:$B$830,"未払繰越")+SUMIFS(未払予定一覧!$O$4:$O$830,未払予定一覧!$N$4:$N$830,A92,未払予定一覧!$A$4:$A$830,"レジデンス",未払予定一覧!$B$4:$B$830,"月次予定") -> 523618 | D92: =B92-C92-F92 -> -523618 | E92: =E91+D92 -> -6931597 | F92: =SUMIFS(未払予定一覧!$O$4:$O$830,未払予定一覧!$N$4:$N$830,A92,未払予定一覧!$A$4:$A$830,"レジデンス",未払予定一覧!$B$4:$B$830,"カード枠回復") -> 0 | G92: =G91+D92+F92 -> -6931597
A93: 46224 | B93: =SUMIFS(入金入力!$E$4:$E$580,入金入力!$B$4:$B$580,A93,入金入力!$A$4:$A$580,"レジデンス")+SUMIFS(入金予測!$E$4:$E$603,入金予測!$A$4:$A$603,A93,入金予測!$B$4:$B$603,"レジデンス") -> 0 | C93: =SUMIFS(未払予定一覧!$O$4:$O$830,未払予定一覧!$N$4:$N$830,A93,未払予定一覧!$A$4:$A$830,"レジデンス",未払予定一覧!$B$4:$B$830,"未払繰越")+SUMIFS(未払予定一覧!$O$4:$O$830,未払予定一覧!$N$4:$N$830,A93,未払予定一覧!$A$4:$A$830,"レジデンス",未払予定一覧!$B$4:$B$830,"月次予定") -> 0 | D93: =B93-C93-F93 -> 0 | E93: =E92+D93 -> -6931597 | F93: =SUMIFS(未払予定一覧!$O$4:$O$830,未払予定一覧!$N$4:$N$830,A93,未払予定一覧!$A$4:$A$830,"レジデンス",未払予定一覧!$B$4:$B$830,"カード枠回復") -> 0 | G93: =G92+D93+F93 -> -6931597
A94: 46225 | B94: =SUMIFS(入金入力!$E$4:$E$580,入金入力!$B$4:$B$580,A94,入金入力!$A$4:$A$580,"レジデンス")+SUMIFS(入金予測!$E$4:$E$603,入金予測!$A$4:$A$603,A94,入金予測!$B$4:$B$603,"レジデンス") -> 0 | C94: =SUMIFS(未払予定一覧!$O$4:$O$830,未払予定一覧!$N$4:$N$830,A94,未払予定一覧!$A$4:$A$830,"レジデンス",未払予定一覧!$B$4:$B$830,"未払繰越")+SUMIFS(未払予定一覧!$O$4:$O$830,未払予定一覧!$N$4:$N$830,A94,未払予定一覧!$A$4:$A$830,"レジデンス",未払予定一覧!$B$4:$B$830,"月次予定") -> 0 | D94: =B94-C94-F94 -> 0 | E94: =E93+D94 -> -6931597 | F94: =SUMIFS(未払予定一覧!$O$4:$O$830,未払予定一覧!$N$4:$N$830,A94,未払予定一覧!$A$4:$A$830,"レジデンス",未払予定一覧!$B$4:$B$830,"カード枠回復") -> 0 | G94: =G93+D94+F94 -> -6931597
A95: 46226 | B95: =SUMIFS(入金入力!$E$4:$E$580,入金入力!$B$4:$B$580,A95,入金入力!$A$4:$A$580,"レジデンス")+SUMIFS(入金予測!$E$4:$E$603,入金予測!$A$4:$A$603,A95,入金予測!$B$4:$B$603,"レジデンス") -> 0 | C95: =SUMIFS(未払予定一覧!$O$4:$O$830,未払予定一覧!$N$4:$N$830,A95,未払予定一覧!$A$4:$A$830,"レジデンス",未払予定一覧!$B$4:$B$830,"未払繰越")+SUMIFS(未払予定一覧!$O$4:$O$830,未払予定一覧!$N$4:$N$830,A95,未払予定一覧!$A$4:$A$830,"レジデンス",未払予定一覧!$B$4:$B$830,"月次予定") -> 0 | D95: =B95-C95-F95 -> 0 | E95: =E94+D95 -> -6931597 | F95: =SUMIFS(未払予定一覧!$O$4:$O$830,未払予定一覧!$N$4:$N$830,A95,未払予定一覧!$A$4:$A$830,"レジデンス",未払予定一覧!$B$4:$B$830,"カード枠回復") -> 0 | G95: =G94+D95+F95 -> -6931597
A96: 46227 | B96: =SUMIFS(入金入力!$E$4:$E$580,入金入力!$B$4:$B$580,A96,入金入力!$A$4:$A$580,"レジデンス")+SUMIFS(入金予測!$E$4:$E$603,入金予測!$A$4:$A$603,A96,入金予測!$B$4:$B$603,"レジデンス") -> 0 | C96: =SUMIFS(未払予定一覧!$O$4:$O$830,未払予定一覧!$N$4:$N$830,A96,未払予定一覧!$A$4:$A$830,"レジデンス",未払予定一覧!$B$4:$B$830,"未払繰越")+SUMIFS(未払予定一覧!$O$4:$O$830,未払予定一覧!$N$4:$N$830,A96,未払予定一覧!$A$4:$A$830,"レジデンス",未払予定一覧!$B$4:$B$830,"月次予定") -> 0 | D96: =B96-C96-F96 -> 0 | E96: =E95+D96 -> -6931597 | F96: =SUMIFS(未払予定一覧!$O$4:$O$830,未払予定一覧!$N$4:$N$830,A96,未払予定一覧!$A$4:$A$830,"レジデンス",未払予定一覧!$B$4:$B$830,"カード枠回復") -> 0 | G96: =G95+D96+F96 -> -6931597
A97: 46228 | B97: =SUMIFS(入金入力!$E$4:$E$580,入金入力!$B$4:$B$580,A97,入金入力!$A$4:$A$580,"レジデンス")+SUMIFS(入金予測!$E$4:$E$603,入金予測!$A$4:$A$603,A97,入金予測!$B$4:$B$603,"レジデンス") -> 0 | C97: =SUMIFS(未払予定一覧!$O$4:$O$830,未払予定一覧!$N$4:$N$830,A97,未払予定一覧!$A$4:$A$830,"レジデンス",未払予定一覧!$B$4:$B$830,"未払繰越")+SUMIFS(未払予定一覧!$O$4:$O$830,未払予定一覧!$N$4:$N$830,A97,未払予定一覧!$A$4:$A$830,"レジデンス",未払予定一覧!$B$4:$B$830,"月次予定") -> 1059878 | D97: =B97-C97-F97 -> -1059878 | E97: =E96+D97 -> -7991475 | F97: =SUMIFS(未払予定一覧!$O$4:$O$830,未払予定一覧!$N$4:$N$830,A97,未払予定一覧!$A$4:$A$830,"レジデンス",未払予定一覧!$B$4:$B$830,"カード枠回復") -> 0 | G97: =G96+D97+F97 -> -7991475 | H97: 土
A98: 46229 | B98: =SUMIFS(入金入力!$E$4:$E$580,入金入力!$B$4:$B$580,A98,入金入力!$A$4:$A$580,"レジデンス")+SUMIFS(入金予測!$E$4:$E$603,入金予測!$A$4:$A$603,A98,入金予測!$B$4:$B$603,"レジデンス") -> 0 | C98: =SUMIFS(未払予定一覧!$O$4:$O$830,未払予定一覧!$N$4:$N$830,A98,未払予定一覧!$A$4:$A$830,"レジデンス",未払予定一覧!$B$4:$B$830,"未払繰越")+SUMIFS(未払予定一覧!$O$4:$O$830,未払予定一覧!$N$4:$N$830,A98,未払予定一覧!$A$4:$A$830,"レジデンス",未払予定一覧!$B$4:$B$830,"月次予定") -> 0 | D98: =B98-C98-F98 -> 0 | E98: =E97+D98 -> -7991475 | F98: =SUMIFS(未払予定一覧!$O$4:$O$830,未払予定一覧!$N$4:$N$830,A98,未払予定一覧!$A$4:$A$830,"レジデンス",未払予定一覧!$B$4:$B$830,"カード枠回復") -> 0 | G98: =G97+D98+F98 -> -7991475 | H98: 日
A99: 46230 | B99: =SUMIFS(入金入力!$E$4:$E$580,入金入力!$B$4:$B$580,A99,入金入力!$A$4:$A$580,"レジデンス")+SUMIFS(入金予測!$E$4:$E$603,入金予測!$A$4:$A$603,A99,入金予測!$B$4:$B$603,"レジデンス") -> 0 | C99: =SUMIFS(未払予定一覧!$O$4:$O$830,未払予定一覧!$N$4:$N$830,A99,未払予定一覧!$A$4:$A$830,"レジデンス",未払予定一覧!$B$4:$B$830,"未払繰越")+SUMIFS(未払予定一覧!$O$4:$O$830,未払予定一覧!$N$4:$N$830,A99,未払予定一覧!$A$4:$A$830,"レジデンス",未払予定一覧!$B$4:$B$830,"月次予定") -> 0 | D99: =B99-C99-F99 -> 0 | E99: =E98+D99 -> -7991475 | F99: =SUMIFS(未払予定一覧!$O$4:$O$830,未払予定一覧!$N$4:$N$830,A99,未払予定一覧!$A$4:$A$830,"レジデンス",未払予定一覧!$B$4:$B$830,"カード枠回復") -> 0 | G99: =G98+D99+F99 -> -7991475
A100: 46231 | B100: =SUMIFS(入金入力!$E$4:$E$580,入金入力!$B$4:$B$580,A100,入金入力!$A$4:$A$580,"レジデンス")+SUMIFS(入金予測!$E$4:$E$603,入金予測!$A$4:$A$603,A100,入金予測!$B$4:$B$603,"レジデンス") -> 0 | C100: =SUMIFS(未払予定一覧!$O$4:$O$830,未払予定一覧!$N$4:$N$830,A100,未払予定一覧!$A$4:$A$830,"レジデンス",未払予定一覧!$B$4:$B$830,"未払繰越")+SUMIFS(未払予定一覧!$O$4:$O$830,未払予定一覧!$N$4:$N$830,A100,未払予定一覧!$A$4:$A$830,"レジデンス",未払予定一覧!$B$4:$B$830,"月次予定") -> 310562 | D100: =B100-C100-F100 -> -310562 | E100: =E99+D100 -> -8302037 | F100: =SUMIFS(未払予定一覧!$O$4:$O$830,未払予定一覧!$N$4:$N$830,A100,未払予定一覧!$A$4:$A$830,"レジデンス",未払予定一覧!$B$4:$B$830,"カード枠回復") -> 0 | G100: =G99+D100+F100 -> -8302037
A101: 46232 | B101: =SUMIFS(入金入力!$E$4:$E$580,入金入力!$B$4:$B$580,A101,入金入力!$A$4:$A$580,"レジデンス")+SUMIFS(入金予測!$E$4:$E$603,入金予測!$A$4:$A$603,A101,入金予測!$B$4:$B$603,"レジデンス") -> 0 | C101: =SUMIFS(未払予定一覧!$O$4:$O$830,未払予定一覧!$N$4:$N$830,A101,未払予定一覧!$A$4:$A$830,"レジデンス",未払予定一覧!$B$4:$B$830,"未払繰越")+SUMIFS(未払予定一覧!$O$4:$O$830,未払予定一覧!$N$4:$N$830,A101,未払予定一覧!$A$4:$A$830,"レジデンス",未払予定一覧!$B$4:$B$830,"月次予定") -> 550429 | D101: =B101-C101-F101 -> -550429 | E101: =E100+D101 -> -8852466 | F101: =SUMIFS(未払予定一覧!$O$4:$O$830,未払予定一覧!$N$4:$N$830,A101,未払予定一覧!$A$4:$A$830,"レジデンス",未払予定一覧!$B$4:$B$830,"カード枠回復") -> 0 | G101: =G100+D101+F101 -> -8852466
A102: 46233 | B102: =SUMIFS(入金入力!$E$4:$E$580,入金入力!$B$4:$B$580,A102,入金入力!$A$4:$A$580,"レジデンス")+SUMIFS(入金予測!$E$4:$E$603,入金予測!$A$4:$A$603,A102,入金予測!$B$4:$B$603,"レジデンス") -> 0 | C102: =SUMIFS(未払予定一覧!$O$4:$O$830,未払予定一覧!$N$4:$N$830,A102,未払予定一覧!$A$4:$A$830,"レジデンス",未払予定一覧!$B$4:$B$830,"未払繰越")+SUMIFS(未払予定一覧!$O$4:$O$830,未払予定一覧!$N$4:$N$830,A102,未払予定一覧!$A$4:$A$830,"レジデンス",未払予定一覧!$B$4:$B$830,"月次予定") -> 493348 | D102: =B102-C102-F102 -> -493348 | E102: =E101+D102 -> -9345814 | F102: =SUMIFS(未払予定一覧!$O$4:$O$830,未払予定一覧!$N$4:$N$830,A102,未払予定一覧!$A$4:$A$830,"レジデンス",未払予定一覧!$B$4:$B$830,"カード枠回復") -> 0 | G102: =G101+D102+F102 -> -9345814
...

Sheet 日次_リゾート
A1: 日次キャッシュフロー — リゾート（5月〜8月 縦積み）
A2: 入金=入金入力（会社=本社）+入金予測／支出=未払予定一覧（カード枠回復除く）／使用可能額=累計差引+累計カード枠回復
A3: 日付 | B3: 入金（円） | C3: 支出（円） | D3: 日次差引（円） | E3: 累計差引（円） | F3: カード枠回復額（円） | G3: 使用可能額（円） | H3: 備考
A4: ■ 5月
A5: 46142 | B5: =SUMIFS(入金入力!$E$4:$E$580,入金入力!$B$4:$B$580,A5,入金入力!$A$4:$A$580,"リゾート")+SUMIFS(入金予測!$E$4:$E$603,入金予測!$A$4:$A$603,A5,入金予測!$B$4:$B$603,"リゾート") -> 3210163 | C5: =SUMIFS(未払予定一覧!$O$4:$O$830,未払予定一覧!$N$4:$N$830,A5,未払予定一覧!$A$4:$A$830,"リゾート",未払予定一覧!$B$4:$B$830,"未払繰越")+SUMIFS(未払予定一覧!$O$4:$O$830,未払予定一覧!$N$4:$N$830,A5,未払予定一覧!$A$4:$A$830,"リゾート",未払予定一覧!$B$4:$B$830,"月次予定") -> 0 | D5: =B5-C5-F5 -> 3210163 | E5: =D5 -> 3210163 | F5: =SUMIFS(未払予定一覧!$O$4:$O$830,未払予定一覧!$N$4:$N$830,A5,未払予定一覧!$A$4:$A$830,"リゾート",未払予定一覧!$B$4:$B$830,"カード枠回復") -> 0 | G5: =D5+F5 -> 3210163
A6: 46143 | B6: =SUMIFS(入金入力!$E$4:$E$580,入金入力!$B$4:$B$580,A6,入金入力!$A$4:$A$580,"リゾート")+SUMIFS(入金予測!$E$4:$E$603,入金予測!$A$4:$A$603,A6,入金予測!$B$4:$B$603,"リゾート") -> 0 | C6: =SUMIFS(未払予定一覧!$O$4:$O$830,未払予定一覧!$N$4:$N$830,A6,未払予定一覧!$A$4:$A$830,"リゾート",未払予定一覧!$B$4:$B$830,"未払繰越")+SUMIFS(未払予定一覧!$O$4:$O$830,未払予定一覧!$N$4:$N$830,A6,未払予定一覧!$A$4:$A$830,"リゾート",未払予定一覧!$B$4:$B$830,"月次予定") -> 0 | D6: =B6-C6-F6 -> 0 | E6: =E5+D6 -> 3210163 | F6: =SUMIFS(未払予定一覧!$O$4:$O$830,未払予定一覧!$N$4:$N$830,A6,未払予定一覧!$A$4:$A$830,"リゾート",未払予定一覧!$B$4:$B$830,"カード枠回復") -> 0 | G6: =G5+D6+F6 -> 3210163
A7: 46144 | B7: =SUMIFS(入金入力!$E$4:$E$580,入金入力!$B$4:$B$580,A7,入金入力!$A$4:$A$580,"リゾート")+SUMIFS(入金予測!$E$4:$E$603,入金予測!$A$4:$A$603,A7,入金予測!$B$4:$B$603,"リゾート") -> 0 | C7: =SUMIFS(未払予定一覧!$O$4:$O$830,未払予定一覧!$N$4:$N$830,A7,未払予定一覧!$A$4:$A$830,"リゾート",未払予定一覧!$B$4:$B$830,"未払繰越")+SUMIFS(未払予定一覧!$O$4:$O$830,未払予定一覧!$N$4:$N$830,A7,未払予定一覧!$A$4:$A$830,"リゾート",未払予定一覧!$B$4:$B$830,"月次予定") -> 0 | D7: =B7-C7-F7 -> 0 | E7: =E6+D7 -> 3210163 | F7: =SUMIFS(未払予定一覧!$O$4:$O$830,未払予定一覧!$N$4:$N$830,A7,未払予定一覧!$A$4:$A$830,"リゾート",未払予定一覧!$B$4:$B$830,"カード枠回復") -> 0 | G7: =G6+D7+F7 -> 3210163 | H7: 土
A8: 46145 | B8: =SUMIFS(入金入力!$E$4:$E$580,入金入力!$B$4:$B$580,A8,入金入力!$A$4:$A$580,"リゾート")+SUMIFS(入金予測!$E$4:$E$603,入金予測!$A$4:$A$603,A8,入金予測!$B$4:$B$603,"リゾート") -> 0 | C8: =SUMIFS(未払予定一覧!$O$4:$O$830,未払予定一覧!$N$4:$N$830,A8,未払予定一覧!$A$4:$A$830,"リゾート",未払予定一覧!$B$4:$B$830,"未払繰越")+SUMIFS(未払予定一覧!$O$4:$O$830,未払予定一覧!$N$4:$N$830,A8,未払予定一覧!$A$4:$A$830,"リゾート",未払予定一覧!$B$4:$B$830,"月次予定") -> 800000 | D8: =B8-C8-F8 -> -800000 | E8: =E7+D8 -> 2410163 | F8: =SUMIFS(未払予定一覧!$O$4:$O$830,未払予定一覧!$N$4:$N$830,A8,未払予定一覧!$A$4:$A$830,"リゾート",未払予定一覧!$B$4:$B$830,"カード枠回復") -> 0 | G8: =G7+D8+F8 -> 2410163 | H8: 日
A9: 46146 | B9: =SUMIFS(入金入力!$E$4:$E$580,入金入力!$B$4:$B$580,A9,入金入力!$A$4:$A$580,"リゾート")+SUMIFS(入金予測!$E$4:$E$603,入金予測!$A$4:$A$603,A9,入金予測!$B$4:$B$603,"リゾート") -> 0 | C9: =SUMIFS(未払予定一覧!$O$4:$O$830,未払予定一覧!$N$4:$N$830,A9,未払予定一覧!$A$4:$A$830,"リゾート",未払予定一覧!$B$4:$B$830,"未払繰越")+SUMIFS(未払予定一覧!$O$4:$O$830,未払予定一覧!$N$4:$N$830,A9,未払予定一覧!$A$4:$A$830,"リゾート",未払予定一覧!$B$4:$B$830,"月次予定") -> 182265 | D9: =B9-C9-F9 -> -182265 | E9: =E8+D9 -> 2227898 | F9: =SUMIFS(未払予定一覧!$O$4:$O$830,未払予定一覧!$N$4:$N$830,A9,未払予定一覧!$A$4:$A$830,"リゾート",未払予定一覧!$B$4:$B$830,"カード枠回復") -> 0 | G9: =G8+D9+F9 -> 2227898
A10: 46147 | B10: =SUMIFS(入金入力!$E$4:$E$580,入金入力!$B$4:$B$580,A10,入金入力!$A$4:$A$580,"リゾート")+SUMIFS(入金予測!$E$4:$E$603,入金予測!$A$4:$A$603,A10,入金予測!$B$4:$B$603,"リゾート") -> 0 | C10: =SUMIFS(未払予定一覧!$O$4:$O$830,未払予定一覧!$N$4:$N$830,A10,未払予定一覧!$A$4:$A$830,"リゾート",未払予定一覧!$B$4:$B$830,"未払繰越")+SUMIFS(未払予定一覧!$O$4:$O$830,未払予定一覧!$N$4:$N$830,A10,未払予定一覧!$A$4:$A$830,"リゾート",未払予定一覧!$B$4:$B$830,"月次予定") -> 0 | D10: =B10-C10-F10 -> 0 | E10: =E9+D10 -> 2227898 | F10: =SUMIFS(未払予定一覧!$O$4:$O$830,未払予定一覧!$N$4:$N$830,A10,未払予定一覧!$A$4:$A$830,"リゾート",未払予定一覧!$B$4:$B$830,"カード枠回復") -> 0 | G10: =G9+D10+F10 -> 2227898
A11: 46148 | B11: =SUMIFS(入金入力!$E$4:$E$580,入金入力!$B$4:$B$580,A11,入金入力!$A$4:$A$580,"リゾート")+SUMIFS(入金予測!$E$4:$E$603,入金予測!$A$4:$A$603,A11,入金予測!$B$4:$B$603,"リゾート") -> 0 | C11: =SUMIFS(未払予定一覧!$O$4:$O$830,未払予定一覧!$N$4:$N$830,A11,未払予定一覧!$A$4:$A$830,"リゾート",未払予定一覧!$B$4:$B$830,"未払繰越")+SUMIFS(未払予定一覧!$O$4:$O$830,未払予定一覧!$N$4:$N$830,A11,未払予定一覧!$A$4:$A$830,"リゾート",未払予定一覧!$B$4:$B$830,"月次予定") -> 380771 | D11: =B11-C11-F11 -> -380771 | E11: =E10+D11 -> 1847127 | F11: =SUMIFS(未払予定一覧!$O$4:$O$830,未払予定一覧!$N$4:$N$830,A11,未払予定一覧!$A$4:$A$830,"リゾート",未払予定一覧!$B$4:$B$830,"カード枠回復") -> 0 | G11: =G10+D11+F11 -> 1847127
A12: 46149 | B12: =SUMIFS(入金入力!$E$4:$E$580,入金入力!$B$4:$B$580,A12,入金入力!$A$4:$A$580,"リゾート")+SUMIFS(入金予測!$E$4:$E$603,入金予測!$A$4:$A$603,A12,入金予測!$B$4:$B$603,"リゾート") -> 1370155 | C12: =SUMIFS(未払予定一覧!$O$4:$O$830,未払予定一覧!$N$4:$N$830,A12,未払予定一覧!$A$4:$A$830,"リゾート",未払予定一覧!$B$4:$B$830,"未払繰越")+SUMIFS(未払予定一覧!$O$4:$O$830,未払予定一覧!$N$4:$N$830,A12,未払予定一覧!$A$4:$A$830,"リゾート",未払予定一覧!$B$4:$B$830,"月次予定") -> 1476189 | D12: =B12-C12-F12 -> -4406034 | E12: =E11+D12 -> -2558907 | F12: =SUMIFS(未払予定一覧!$O$4:$O$830,未払予定一覧!$N$4:$N$830,A12,未払予定一覧!$A$4:$A$830,"リゾート",未払予定一覧!$B$4:$B$830,"カード枠回復") -> 4300000 | G12: =G11+D12+F12 -> 1741093
A13: 46150 | B13: =SUMIFS(入金入力!$E$4:$E$580,入金入力!$B$4:$B$580,A13,入金入力!$A$4:$A$580,"リゾート")+SUMIFS(入金予測!$E$4:$E$603,入金予測!$A$4:$A$603,A13,入金予測!$B$4:$B$603,"リゾート") -> 0 | C13: =SUMIFS(未払予定一覧!$O$4:$O$830,未払予定一覧!$N$4:$N$830,A13,未払予定一覧!$A$4:$A$830,"リゾート",未払予定一覧!$B$4:$B$830,"未払繰越")+SUMIFS(未払予定一覧!$O$4:$O$830,未払予定一覧!$N$4:$N$830,A13,未払予定一覧!$A$4:$A$830,"リゾート",未払予定一覧!$B$4:$B$830,"月次予定") -> 22550 | D13: =B13-C13-F13 -> -22550 | E13: =E12+D13 -> -2581457 | F13: =SUMIFS(未払予定一覧!$O$4:$O$830,未払予定一覧!$N$4:$N$830,A13,未払予定一覧!$A$4:$A$830,"リゾート",未払予定一覧!$B$4:$B$830,"カード枠回復") -> 0 | G13: =G12+D13+F13 -> 1718543
A14: 46151 | B14: =SUMIFS(入金入力!$E$4:$E$580,入金入力!$B$4:$B$580,A14,入金入力!$A$4:$A$580,"リゾート")+SUMIFS(入金予測!$E$4:$E$603,入金予測!$A$4:$A$603,A14,入金予測!$B$4:$B$603,"リゾート") -> 0 | C14: =SUMIFS(未払予定一覧!$O$4:$O$830,未払予定一覧!$N$4:$N$830,A14,未払予定一覧!$A$4:$A$830,"リゾート",未払予定一覧!$B$4:$B$830,"未払繰越")+SUMIFS(未払予定一覧!$O$4:$O$830,未払予定一覧!$N$4:$N$830,A14,未払予定一覧!$A$4:$A$830,"リゾート",未払予定一覧!$B$4:$B$830,"月次予定") -> 880 | D14: =B14-C14-F14 -> -880 | E14: =E13+D14 -> -2582337 | F14: =SUMIFS(未払予定一覧!$O$4:$O$830,未払予定一覧!$N$4:$N$830,A14,未払予定一覧!$A$4:$A$830,"リゾート",未払予定一覧!$B$4:$B$830,"カード枠回復") -> 0 | G14: =G13+D14+F14 -> 1717663 | H14: 土
A15: 46152 | B15: =SUMIFS(入金入力!$E$4:$E$580,入金入力!$B$4:$B$580,A15,入金入力!$A$4:$A$580,"リゾート")+SUMIFS(入金予測!$E$4:$E$603,入金予測!$A$4:$A$603,A15,入金予測!$B$4:$B$603,"リゾート") -> 0 | C15: =SUMIFS(未払予定一覧!$O$4:$O$830,未払予定一覧!$N$4:$N$830,A15,未払予定一覧!$A$4:$A$830,"リゾート",未払予定一覧!$B$4:$B$830,"未払繰越")+SUMIFS(未払予定一覧!$O$4:$O$830,未払予定一覧!$N$4:$N$830,A15,未払予定一覧!$A$4:$A$830,"リゾート",未払予定一覧!$B$4:$B$830,"月次予定") -> 29077 | D15: =B15-C15-F15 -> -29077 | E15: =E14+D15 -> -2611414 | F15: =SUMIFS(未払予定一覧!$O$4:$O$830,未払予定一覧!$N$4:$N$830,A15,未払予定一覧!$A$4:$A$830,"リゾート",未払予定一覧!$B$4:$B$830,"カード枠回復") -> 0 | G15: =G14+D15+F15 -> 1688586 | H15: 日
A16: 46153 | B16: =SUMIFS(入金入力!$E$4:$E$580,入金入力!$B$4:$B$580,A16,入金入力!$A$4:$A$580,"リゾート")+SUMIFS(入金予測!$E$4:$E$603,入金予測!$A$4:$A$603,A16,入金予測!$B$4:$B$603,"リゾート") -> 2813543 | C16: =SUMIFS(未払予定一覧!$O$4:$O$830,未払予定一覧!$N$4:$N$830,A16,未払予定一覧!$A$4:$A$830,"リゾート",未払予定一覧!$B$4:$B$830,"未払繰越")+SUMIFS(未払予定一覧!$O$4:$O$830,未払予定一覧!$N$4:$N$830,A16,未払予定一覧!$A$4:$A$830,"リゾート",未払予定一覧!$B$4:$B$830,"月次予定") -> 3907700 | D16: =B16-C16-F16 -> -2064157 | E16: =E15+D16 -> -4675571 | F16: =SUMIFS(未払予定一覧!$O$4:$O$830,未払予定一覧!$N$4:$N$830,A16,未払予定一覧!$A$4:$A$830,"リゾート",未払予定一覧!$B$4:$B$830,"カード枠回復") -> 970000 | G16: =G15+D16+F16 -> 594429
A17: 46154 | B17: =SUMIFS(入金入力!$E$4:$E$580,入金入力!$B$4:$B$580,A17,入金入力!$A$4:$A$580,"リゾート")+SUMIFS(入金予測!$E$4:$E$603,入金予測!$A$4:$A$603,A17,入金予測!$B$4:$B$603,"リゾート") -> 0 | C17: =SUMIFS(未払予定一覧!$O$4:$O$830,未払予定一覧!$N$4:$N$830,A17,未払予定一覧!$A$4:$A$830,"リゾート",未払予定一覧!$B$4:$B$830,"未払繰越")+SUMIFS(未払予定一覧!$O$4:$O$830,未払予定一覧!$N$4:$N$830,A17,未払予定一覧!$A$4:$A$830,"リゾート",未払予定一覧!$B$4:$B$830,"月次予定") -> 0 | D17: =B17-C17-F17 -> 0 | E17: =E16+D17 -> -4675571 | F17: =SUMIFS(未払予定一覧!$O$4:$O$830,未払予定一覧!$N$4:$N$830,A17,未払予定一覧!$A$4:$A$830,"リゾート",未払予定一覧!$B$4:$B$830,"カード枠回復") -> 0 | G17: =G16+D17+F17 -> 594429
A18: 46155 | B18: =SUMIFS(入金入力!$E$4:$E$580,入金入力!$B$4:$B$580,A18,入金入力!$A$4:$A$580,"リゾート")+SUMIFS(入金予測!$E$4:$E$603,入金予測!$A$4:$A$603,A18,入金予測!$B$4:$B$603,"リゾート") -> 0 | C18: =SUMIFS(未払予定一覧!$O$4:$O$830,未払予定一覧!$N$4:$N$830,A18,未払予定一覧!$A$4:$A$830,"リゾート",未払予定一覧!$B$4:$B$830,"未払繰越")+SUMIFS(未払予定一覧!$O$4:$O$830,未払予定一覧!$N$4:$N$830,A18,未払予定一覧!$A$4:$A$830,"リゾート",未払予定一覧!$B$4:$B$830,"月次予定") -> 114777 | D18: =B18-C18-F18 -> -114777 | E18: =E17+D18 -> -4790348 | F18: =SUMIFS(未払予定一覧!$O$4:$O$830,未払予定一覧!$N$4:$N$830,A18,未払予定一覧!$A$4:$A$830,"リゾート",未払予定一覧!$B$4:$B$830,"カード枠回復") -> 0 | G18: =G17+D18+F18 -> 479652
A19: 46156 | B19: =SUMIFS(入金入力!$E$4:$E$580,入金入力!$B$4:$B$580,A19,入金入力!$A$4:$A$580,"リゾート")+SUMIFS(入金予測!$E$4:$E$603,入金予測!$A$4:$A$603,A19,入金予測!$B$4:$B$603,"リゾート") -> 0 | C19: =SUMIFS(未払予定一覧!$O$4:$O$830,未払予定一覧!$N$4:$N$830,A19,未払予定一覧!$A$4:$A$830,"リゾート",未払予定一覧!$B$4:$B$830,"未払繰越")+SUMIFS(未払予定一覧!$O$4:$O$830,未払予定一覧!$N$4:$N$830,A19,未払予定一覧!$A$4:$A$830,"リゾート",未払予定一覧!$B$4:$B$830,"月次予定") -> 0 | D19: =B19-C19-F19 -> 0 | E19: =E18+D19 -> -4790348 | F19: =SUMIFS(未払予定一覧!$O$4:$O$830,未払予定一覧!$N$4:$N$830,A19,未払予定一覧!$A$4:$A$830,"リゾート",未払予定一覧!$B$4:$B$830,"カード枠回復") -> 0 | G19: =G18+D19+F19 -> 479652
A20: 46157 | B20: =SUMIFS(入金入力!$E$4:$E$580,入金入力!$B$4:$B$580,A20,入金入力!$A$4:$A$580,"リゾート")+SUMIFS(入金予測!$E$4:$E$603,入金予測!$A$4:$A$603,A20,入金予測!$B$4:$B$603,"リゾート") -> 3804366 | C20: =SUMIFS(未払予定一覧!$O$4:$O$830,未払予定一覧!$N$4:$N$830,A20,未払予定一覧!$A$4:$A$830,"リゾート",未払予定一覧!$B$4:$B$830,"未払繰越")+SUMIFS(未払予定一覧!$O$4:$O$830,未払予定一覧!$N$4:$N$830,A20,未払予定一覧!$A$4:$A$830,"リゾート",未払予定一覧!$B$4:$B$830,"月次予定") -> 4384337 | D20: =B20-C20-F20 -> -579971 | E20: =E19+D20 -> -5370319 | F20: =SUMIFS(未払予定一覧!$O$4:$O$830,未払予定一覧!$N$4:$N$830,A20,未払予定一覧!$A$4:$A$830,"リゾート",未払予定一覧!$B$4:$B$830,"カード枠回復") -> 0 | G20: =G19+D20+F20 -> -100319
A21: 46158 | B21: =SUMIFS(入金入力!$E$4:$E$580,入金入力!$B$4:$B$580,A21,入金入力!$A$4:$A$580,"リゾート")+SUMIFS(入金予測!$E$4:$E$603,入金予測!$A$4:$A$603,A21,入金予測!$B$4:$B$603,"リゾート") -> 0 | C21: =SUMIFS(未払予定一覧!$O$4:$O$830,未払予定一覧!$N$4:$N$830,A21,未払予定一覧!$A$4:$A$830,"リゾート",未払予定一覧!$B$4:$B$830,"未払繰越")+SUMIFS(未払予定一覧!$O$4:$O$830,未払予定一覧!$N$4:$N$830,A21,未払予定一覧!$A$4:$A$830,"リゾート",未払予定一覧!$B$4:$B$830,"月次予定") -> 43896 | D21: =B21-C21-F21 -> -43896 | E21: =E20+D21 -> -5414215 | F21: =SUMIFS(未払予定一覧!$O$4:$O$830,未払予定一覧!$N$4:$N$830,A21,未払予定一覧!$A$4:$A$830,"リゾート",未払予定一覧!$B$4:$B$830,"カード枠回復") -> 0 | G21: =G20+D21+F21 -> -144215 | H21: 土
A22: 46159 | B22: =SUMIFS(入金入力!$E$4:$E$580,入金入力!$B$4:$B$580,A22,入金入力!$A$4:$A$580,"リゾート")+SUMIFS(入金予測!$E$4:$E$603,入金予測!$A$4:$A$603,A22,入金予測!$B$4:$B$603,"リゾート") -> 0 | C22: =SUMIFS(未払予定一覧!$O$4:$O$830,未払予定一覧!$N$4:$N$830,A22,未払予定一覧!$A$4:$A$830,"リゾート",未払予定一覧!$B$4:$B$830,"未払繰越")+SUMIFS(未払予定一覧!$O$4:$O$830,未払予定一覧!$N$4:$N$830,A22,未払予定一覧!$A$4:$A$830,"リゾート",未払予定一覧!$B$4:$B$830,"月次予定") -> 0 | D22: =B22-C22-F22 -> 0 | E22: =E21+D22 -> -5414215 | F22: =SUMIFS(未払予定一覧!$O$4:$O$830,未払予定一覧!$N$4:$N$830,A22,未払予定一覧!$A$4:$A$830,"リゾート",未払予定一覧!$B$4:$B$830,"カード枠回復") -> 0 | G22: =G21+D22+F22 -> -144215 | H22: 日
A23: 46160 | B23: =SUMIFS(入金入力!$E$4:$E$580,入金入力!$B$4:$B$580,A23,入金入力!$A$4:$A$580,"リゾート")+SUMIFS(入金予測!$E$4:$E$603,入金予測!$A$4:$A$603,A23,入金予測!$B$4:$B$603,"リゾート") -> 0 | C23: =SUMIFS(未払予定一覧!$O$4:$O$830,未払予定一覧!$N$4:$N$830,A23,未払予定一覧!$A$4:$A$830,"リゾート",未払予定一覧!$B$4:$B$830,"未払繰越")+SUMIFS(未払予定一覧!$O$4:$O$830,未払予定一覧!$N$4:$N$830,A23,未払予定一覧!$A$4:$A$830,"リゾート",未払予定一覧!$B$4:$B$830,"月次予定") -> 865927 | D23: =B23-C23-F23 -> -865927 | E23: =E22+D23 -> -6280142 | F23: =SUMIFS(未払予定一覧!$O$4:$O$830,未払予定一覧!$N$4:$N$830,A23,未払予定一覧!$A$4:$A$830,"リゾート",未払予定一覧!$B$4:$B$830,"カード枠回復") -> 0 | G23: =G22+D23+F23 -> -1010142
A24: 46161 | B24: =SUMIFS(入金入力!$E$4:$E$580,入金入力!$B$4:$B$580,A24,入金入力!$A$4:$A$580,"リゾート")+SUMIFS(入金予測!$E$4:$E$603,入金予測!$A$4:$A$603,A24,入金予測!$B$4:$B$603,"リゾート") -> 0 | C24: =SUMIFS(未払予定一覧!$O$4:$O$830,未払予定一覧!$N$4:$N$830,A24,未払予定一覧!$A$4:$A$830,"リゾート",未払予定一覧!$B$4:$B$830,"未払繰越")+SUMIFS(未払予定一覧!$O$4:$O$830,未払予定一覧!$N$4:$N$830,A24,未払予定一覧!$A$4:$A$830,"リゾート",未払予定一覧!$B$4:$B$830,"月次予定") -> 0 | D24: =B24-C24-F24 -> 0 | E24: =E23+D24 -> -6280142 | F24: =SUMIFS(未払予定一覧!$O$4:$O$830,未払予定一覧!$N$4:$N$830,A24,未払予定一覧!$A$4:$A$830,"リゾート",未払予定一覧!$B$4:$B$830,"カード枠回復") -> 0 | G24: =G23+D24+F24 -> -1010142
A25: 46162 | B25: =SUMIFS(入金入力!$E$4:$E$580,入金入力!$B$4:$B$580,A25,入金入力!$A$4:$A$580,"リゾート")+SUMIFS(入金予測!$E$4:$E$603,入金予測!$A$4:$A$603,A25,入金予測!$B$4:$B$603,"リゾート") -> 5262857.9 | C25: =SUMIFS(未払予定一覧!$O$4:$O$830,未払予定一覧!$N$4:$N$830,A25,未払予定一覧!$A$4:$A$830,"リゾート",未払予定一覧!$B$4:$B$830,"未払繰越")+SUMIFS(未払予定一覧!$O$4:$O$830,未払予定一覧!$N$4:$N$830,A25,未払予定一覧!$A$4:$A$830,"リゾート",未払予定一覧!$B$4:$B$830,"月次予定") -> 189434 | D25: =B25-C25-F25 -> 5073423.9 | E25: =E24+D25 -> -1206718.1 | F25: =SUMIFS(未払予定一覧!$O$4:$O$830,未払予定一覧!$N$4:$N$830,A25,未払予定一覧!$A$4:$A$830,"リゾート",未払予定一覧!$B$4:$B$830,"カード枠回復") -> 0 | G25: =G24+D25+F25 -> 4063281.9
A26: 46163 | B26: =SUMIFS(入金入力!$E$4:$E$580,入金入力!$B$4:$B$580,A26,入金入力!$A$4:$A$580,"リゾート")+SUMIFS(入金予測!$E$4:$E$603,入金予測!$A$4:$A$603,A26,入金予測!$B$4:$B$603,"リゾート") -> 0 | C26: =SUMIFS(未払予定一覧!$O$4:$O$830,未払予定一覧!$N$4:$N$830,A26,未払予定一覧!$A$4:$A$830,"リゾート",未払予定一覧!$B$4:$B$830,"未払繰越")+SUMIFS(未払予定一覧!$O$4:$O$830,未払予定一覧!$N$4:$N$830,A26,未払予定一覧!$A$4:$A$830,"リゾート",未払予定一覧!$B$4:$B$830,"月次予定") -> 0 | D26: =B26-C26-F26 -> 0 | E26: =E25+D26 -> -1206718.1 | F26: =SUMIFS(未払予定一覧!$O$4:$O$830,未払予定一覧!$N$4:$N$830,A26,未払予定一覧!$A$4:$A$830,"リゾート",未払予定一覧!$B$4:$B$830,"カード枠回復") -> 0 | G26: =G25+D26+F26 -> 4063281.9
A27: 46164 | B27: =SUMIFS(入金入力!$E$4:$E$580,入金入力!$B$4:$B$580,A27,入金入力!$A$4:$A$580,"リゾート")+SUMIFS(入金予測!$E$4:$E$603,入金予測!$A$4:$A$603,A27,入金予測!$B$4:$B$603,"リゾート") -> 0 | C27: =SUMIFS(未払予定一覧!$O$4:$O$830,未払予定一覧!$N$4:$N$830,A27,未払予定一覧!$A$4:$A$830,"リゾート",未払予定一覧!$B$4:$B$830,"未払繰越")+SUMIFS(未払予定一覧!$O$4:$O$830,未払予定一覧!$N$4:$N$830,A27,未払予定一覧!$A$4:$A$830,"リゾート",未払予定一覧!$B$4:$B$830,"月次予定") -> 0 | D27: =B27-C27-F27 -> 0 | E27: =E26+D27 -> -1206718.1 | F27: =SUMIFS(未払予定一覧!$O$4:$O$830,未払予定一覧!$N$4:$N$830,A27,未払予定一覧!$A$4:$A$830,"リゾート",未払予定一覧!$B$4:$B$830,"カード枠回復") -> 0 | G27: =G26+D27+F27 -> 4063281.9
A28: 46165 | B28: =SUMIFS(入金入力!$E$4:$E$580,入金入力!$B$4:$B$580,A28,入金入力!$A$4:$A$580,"リゾート")+SUMIFS(入金予測!$E$4:$E$603,入金予測!$A$4:$A$603,A28,入金予測!$B$4:$B$603,"リゾート") -> 0 | C28: =SUMIFS(未払予定一覧!$O$4:$O$830,未払予定一覧!$N$4:$N$830,A28,未払予定一覧!$A$4:$A$830,"リゾート",未払予定一覧!$B$4:$B$830,"未払繰越")+SUMIFS(未払予定一覧!$O$4:$O$830,未払予定一覧!$N$4:$N$830,A28,未払予定一覧!$A$4:$A$830,"リゾート",未払予定一覧!$B$4:$B$830,"月次予定") -> 0 | D28: =B28-C28-F28 -> 0 | E28: =E27+D28 -> -1206718.1 | F28: =SUMIFS(未払予定一覧!$O$4:$O$830,未払予定一覧!$N$4:$N$830,A28,未払予定一覧!$A$4:$A$830,"リゾート",未払予定一覧!$B$4:$B$830,"カード枠回復") -> 0 | G28: =G27+D28+F28 -> 4063281.9 | H28: 土
A29: 46166 | B29: =SUMIFS(入金入力!$E$4:$E$580,入金入力!$B$4:$B$580,A29,入金入力!$A$4:$A$580,"リゾート")+SUMIFS(入金予測!$E$4:$E$603,入金予測!$A$4:$A$603,A29,入金予測!$B$4:$B$603,"リゾート") -> 0 | C29: =SUMIFS(未払予定一覧!$O$4:$O$830,未払予定一覧!$N$4:$N$830,A29,未払予定一覧!$A$4:$A$830,"リゾート",未払予定一覧!$B$4:$B$830,"未払繰越")+SUMIFS(未払予定一覧!$O$4:$O$830,未払予定一覧!$N$4:$N$830,A29,未払予定一覧!$A$4:$A$830,"リゾート",未払予定一覧!$B$4:$B$830,"月次予定") -> 608628 | D29: =B29-C29-F29 -> -608628 | E29: =E28+D29 -> -1815346.1 | F29: =SUMIFS(未払予定一覧!$O$4:$O$830,未払予定一覧!$N$4:$N$830,A29,未払予定一覧!$A$4:$A$830,"リゾート",未払予定一覧!$B$4:$B$830,"カード枠回復") -> 0 | G29: =G28+D29+F29 -> 3454653.9 | H29: 日
A30: 46167 | B30: =SUMIFS(入金入力!$E$4:$E$580,入金入力!$B$4:$B$580,A30,入金入力!$A$4:$A$580,"リゾート")+SUMIFS(入金予測!$E$4:$E$603,入金予測!$A$4:$A$603,A30,入金予測!$B$4:$B$603,"リゾート") -> 1421676 | C30: =SUMIFS(未払予定一覧!$O$4:$O$830,未払予定一覧!$N$4:$N$830,A30,未払予定一覧!$A$4:$A$830,"リゾート",未払予定一覧!$B$4:$B$830,"未払繰越")+SUMIFS(未払予定一覧!$O$4:$O$830,未払予定一覧!$N$4:$N$830,A30,未払予定一覧!$A$4:$A$830,"リゾート",未払予定一覧!$B$4:$B$830,"月次予定") -> 11043496 | D30: =B30-C30-F30 -> -9621820 | E30: =E29+D30 -> -11437166 | F30: =SUMIFS(未払予定一覧!$O$4:$O$830,未払予定一覧!$N$4:$N$830,A30,未払予定一覧!$A$4:$A$830,"リゾート",未払予定一覧!$B$4:$B$830,"カード枠回復") -> 0 | G30: =G29+D30+F30 -> -6167166.1
A31: 46168 | B31: =SUMIFS(入金入力!$E$4:$E$580,入金入力!$B$4:$B$580,A31,入金入力!$A$4:$A$580,"リゾート")+SUMIFS(入金予測!$E$4:$E$603,入金予測!$A$4:$A$603,A31,入金予測!$B$4:$B$603,"リゾート") -> 1990010 | C31: =SUMIFS(未払予定一覧!$O$4:$O$830,未払予定一覧!$N$4:$N$830,A31,未払予定一覧!$A$4:$A$830,"リゾート",未払予定一覧!$B$4:$B$830,"未払繰越")+SUMIFS(未払予定一覧!$O$4:$O$830,未払予定一覧!$N$4:$N$830,A31,未払予定一覧!$A$4:$A$830,"リゾート",未払予定一覧!$B$4:$B$830,"月次予定") -> 0 | D31: =B31-C31-F31 -> 1990010 | E31: =E30+D31 -> -9447156.1 | F31: =SUMIFS(未払予定一覧!$O$4:$O$830,未払予定一覧!$N$4:$N$830,A31,未払予定一覧!$A$4:$A$830,"リゾート",未払予定一覧!$B$4:$B$830,"カード枠回復") -> 0 | G31: =G30+D31+F31 -> -4177156.1
A32: 46169 | B32: =SUMIFS(入金入力!$E$4:$E$580,入金入力!$B$4:$B$580,A32,入金入力!$A$4:$A$580,"リゾート")+SUMIFS(入金予測!$E$4:$E$603,入金予測!$A$4:$A$603,A32,入金予測!$B$4:$B$603,"リゾート") -> 0 | C32: =SUMIFS(未払予定一覧!$O$4:$O$830,未払予定一覧!$N$4:$N$830,A32,未払予定一覧!$A$4:$A$830,"リゾート",未払予定一覧!$B$4:$B$830,"未払繰越")+SUMIFS(未払予定一覧!$O$4:$O$830,未払予定一覧!$N$4:$N$830,A32,未払予定一覧!$A$4:$A$830,"リゾート",未払予定一覧!$B$4:$B$830,"月次予定") -> 944225 | D32: =B32-C32-F32 -> -944225 | E32: =E31+D32 -> -10391381 | F32: =SUMIFS(未払予定一覧!$O$4:$O$830,未払予定一覧!$N$4:$N$830,A32,未払予定一覧!$A$4:$A$830,"リゾート",未払予定一覧!$B$4:$B$830,"カード枠回復") -> 0 | G32: =G31+D32+F32 -> -5121381.1
A33: 46170 | B33: =SUMIFS(入金入力!$E$4:$E$580,入金入力!$B$4:$B$580,A33,入金入力!$A$4:$A$580,"リゾート")+SUMIFS(入金予測!$E$4:$E$603,入金予測!$A$4:$A$603,A33,入金予測!$B$4:$B$603,"リゾート") -> 0 | D33: =B33-C33-F33 -> 0 | E33: =E32+D33 -> -10391381 | F33: =SUMIFS(未払予定一覧!$O$4:$O$830,未払予定一覧!$N$4:$N$830,A33,未払予定一覧!$A$4:$A$830,"リゾート",未払予定一覧!$B$4:$B$830,"カード枠回復") -> 0 | G33: =G32+D33+F33 -> -5121381.1
A34: 46171 | B34: =SUMIFS(入金入力!$E$4:$E$580,入金入力!$B$4:$B$580,A34,入金入力!$A$4:$A$580,"リゾート")+SUMIFS(入金予測!$E$4:$E$603,入金予測!$A$4:$A$603,A34,入金予測!$B$4:$B$603,"リゾート") -> 4631177 | C34: =SUMIFS(未払予定一覧!$O$4:$O$830,未払予定一覧!$N$4:$N$830,A34,未払予定一覧!$A$4:$A$830,"リゾート",未払予定一覧!$B$4:$B$830,"未払繰越")+SUMIFS(未払予定一覧!$O$4:$O$830,未払予定一覧!$N$4:$N$830,A34,未払予定一覧!$A$4:$A$830,"リゾート",未払予定一覧!$B$4:$B$830,"月次予定") -> 6415375 | D34: =B34-C34-F34 -> -1784198 | E34: =E33+D34 -> -12175579 | F34: =SUMIFS(未払予定一覧!$O$4:$O$830,未払予定一覧!$N$4:$N$830,A34,未払予定一覧!$A$4:$A$830,"リゾート",未払予定一覧!$B$4:$B$830,"カード枠回復") -> 0 | G34: =G33+D34+F34 -> -6905579.1
A35: 46172 | B35: =SUMIFS(入金入力!$E$4:$E$580,入金入力!$B$4:$B$580,A35,入金入力!$A$4:$A$580,"リゾート")+SUMIFS(入金予測!$E$4:$E$603,入金予測!$A$4:$A$603,A35,入金予測!$B$4:$B$603,"リゾート") -> 0 | C35: =SUMIFS(未払予定一覧!$O$4:$O$830,未払予定一覧!$N$4:$N$830,A35,未払予定一覧!$A$4:$A$830,"リゾート",未払予定一覧!$B$4:$B$830,"未払繰越")+SUMIFS(未払予定一覧!$O$4:$O$830,未払予定一覧!$N$4:$N$830,A35,未払予定一覧!$A$4:$A$830,"リゾート",未払予定一覧!$B$4:$B$830,"月次予定") -> 2673495 | D35: =B35-C35-F35 -> -2673495 | E35: =E34+D35 -> -14849074 | F35: =SUMIFS(未払予定一覧!$O$4:$O$830,未払予定一覧!$N$4:$N$830,A35,未払予定一覧!$A$4:$A$830,"リゾート",未払予定一覧!$B$4:$B$830,"カード枠回復") -> 0 | G35: =G34+D35+F35 -> -9579074.1 | H35: 土
A36: 46173 | B36: =SUMIFS(入金入力!$E$4:$E$580,入金入力!$B$4:$B$580,A36,入金入力!$A$4:$A$580,"リゾート")+SUMIFS(入金予測!$E$4:$E$603,入金予測!$A$4:$A$603,A36,入金予測!$B$4:$B$603,"リゾート") -> 0 | C36: =SUMIFS(未払予定一覧!$O$4:$O$830,未払予定一覧!$N$4:$N$830,A36,未払予定一覧!$A$4:$A$830,"リゾート",未払予定一覧!$B$4:$B$830,"未払繰越")+SUMIFS(未払予定一覧!$O$4:$O$830,未払予定一覧!$N$4:$N$830,A36,未払予定一覧!$A$4:$A$830,"リゾート",未払予定一覧!$B$4:$B$830,"月次予定") -> 170000 | D36: =B36-C36-F36 -> -170000 | E36: =E35+D36 -> -15019074 | F36: =SUMIFS(未払予定一覧!$O$4:$O$830,未払予定一覧!$N$4:$N$830,A36,未払予定一覧!$A$4:$A$830,"リゾート",未払予定一覧!$B$4:$B$830,"カード枠回復") -> 0 | G36: =G35+D36+F36 -> -9749074.1 | H36: 日
A37: 5月合計 | B37: =SUM(B5:B36) -> 24503948 | C37: =SUM(C5:C36) -> 34253022 | D37: =B37-C37-F37 -> -15019074 | E37: =E36 -> -15019074 | F37: =SUM(F5:F36) -> 5270000 | G37: =G36 -> -9749074.1 | H37: 月合計
A39: ■ 6月
A40: 46174 | B40: =SUMIFS(入金入力!$E$4:$E$580,入金入力!$B$4:$B$580,A40,入金入力!$A$4:$A$580,"リゾート")+SUMIFS(入金予測!$E$4:$E$603,入金予測!$A$4:$A$603,A40,入金予測!$B$4:$B$603,"リゾート") -> 0 | C40: =SUMIFS(未払予定一覧!$O$4:$O$830,未払予定一覧!$N$4:$N$830,A40,未払予定一覧!$A$4:$A$830,"リゾート",未払予定一覧!$B$4:$B$830,"未払繰越")+SUMIFS(未払予定一覧!$O$4:$O$830,未払予定一覧!$N$4:$N$830,A40,未払予定一覧!$A$4:$A$830,"リゾート",未払予定一覧!$B$4:$B$830,"月次予定") -> 0 | D40: =B40-C40-F40 -> 0 | E40: =E37+D40 -> -15019074 | F40: =SUMIFS(未払予定一覧!$O$4:$O$830,未払予定一覧!$N$4:$N$830,A40,未払予定一覧!$A$4:$A$830,"リゾート",未払予定一覧!$B$4:$B$830,"カード枠回復") -> 0 | G40: =G37+D40+F40 -> -9749074.1
A41: 46175 | B41: =SUMIFS(入金入力!$E$4:$E$580,入金入力!$B$4:$B$580,A41,入金入力!$A$4:$A$580,"リゾート")+SUMIFS(入金予測!$E$4:$E$603,入金予測!$A$4:$A$603,A41,入金予測!$B$4:$B$603,"リゾート") -> 0 | C41: =SUMIFS(未払予定一覧!$O$4:$O$830,未払予定一覧!$N$4:$N$830,A41,未払予定一覧!$A$4:$A$830,"リゾート",未払予定一覧!$B$4:$B$830,"未払繰越")+SUMIFS(未払予定一覧!$O$4:$O$830,未払予定一覧!$N$4:$N$830,A41,未払予定一覧!$A$4:$A$830,"リゾート",未払予定一覧!$B$4:$B$830,"月次予定") -> 0 | D41: =B41-C41-F41 -> 0 | E41: =E40+D41 -> -15019074 | F41: =SUMIFS(未払予定一覧!$O$4:$O$830,未払予定一覧!$N$4:$N$830,A41,未払予定一覧!$A$4:$A$830,"リゾート",未払予定一覧!$B$4:$B$830,"カード枠回復") -> 0 | G41: =G40+D41+F41 -> -9749074.1
A42: 46176 | B42: =SUMIFS(入金入力!$E$4:$E$580,入金入力!$B$4:$B$580,A42,入金入力!$A$4:$A$580,"リゾート")+SUMIFS(入金予測!$E$4:$E$603,入金予測!$A$4:$A$603,A42,入金予測!$B$4:$B$603,"リゾート") -> 0 | C42: =SUMIFS(未払予定一覧!$O$4:$O$830,未払予定一覧!$N$4:$N$830,A42,未払予定一覧!$A$4:$A$830,"リゾート",未払予定一覧!$B$4:$B$830,"未払繰越")+SUMIFS(未払予定一覧!$O$4:$O$830,未払予定一覧!$N$4:$N$830,A42,未払予定一覧!$A$4:$A$830,"リゾート",未払予定一覧!$B$4:$B$830,"月次予定") -> 800000 | D42: =B42-C42-F42 -> -800000 | E42: =E41+D42 -> -15819074 | F42: =SUMIFS(未払予定一覧!$O$4:$O$830,未払予定一覧!$N$4:$N$830,A42,未払予定一覧!$A$4:$A$830,"リゾート",未払予定一覧!$B$4:$B$830,"カード枠回復") -> 0 | G42: =G41+D42+F42 -> -10549074
A43: 46177 | B43: =SUMIFS(入金入力!$E$4:$E$580,入金入力!$B$4:$B$580,A43,入金入力!$A$4:$A$580,"リゾート")+SUMIFS(入金予測!$E$4:$E$603,入金予測!$A$4:$A$603,A43,入金予測!$B$4:$B$603,"リゾート") -> 0 | C43: =SUMIFS(未払予定一覧!$O$4:$O$830,未払予定一覧!$N$4:$N$830,A43,未払予定一覧!$A$4:$A$830,"リゾート",未払予定一覧!$B$4:$B$830,"未払繰越")+SUMIFS(未払予定一覧!$O$4:$O$830,未払予定一覧!$N$4:$N$830,A43,未払予定一覧!$A$4:$A$830,"リゾート",未払予定一覧!$B$4:$B$830,"月次予定") -> 0 | D43: =B43-C43-F43 -> 0 | E43: =E42+D43 -> -15819074 | F43: =SUMIFS(未払予定一覧!$O$4:$O$830,未払予定一覧!$N$4:$N$830,A43,未払予定一覧!$A$4:$A$830,"リゾート",未払予定一覧!$B$4:$B$830,"カード枠回復") -> 0 | G43: =G42+D43+F43 -> -10549074
A44: 46178 | B44: =SUMIFS(入金入力!$E$4:$E$580,入金入力!$B$4:$B$580,A44,入金入力!$A$4:$A$580,"リゾート")+SUMIFS(入金予測!$E$4:$E$603,入金予測!$A$4:$A$603,A44,入金予測!$B$4:$B$603,"リゾート") -> 0 | C44: =SUMIFS(未払予定一覧!$O$4:$O$830,未払予定一覧!$N$4:$N$830,A44,未払予定一覧!$A$4:$A$830,"リゾート",未払予定一覧!$B$4:$B$830,"未払繰越")+SUMIFS(未払予定一覧!$O$4:$O$830,未払予定一覧!$N$4:$N$830,A44,未払予定一覧!$A$4:$A$830,"リゾート",未払予定一覧!$B$4:$B$830,"月次予定") -> 0 | D44: =B44-C44-F44 -> 0 | E44: =E43+D44 -> -15819074 | F44: =SUMIFS(未払予定一覧!$O$4:$O$830,未払予定一覧!$N$4:$N$830,A44,未払予定一覧!$A$4:$A$830,"リゾート",未払予定一覧!$B$4:$B$830,"カード枠回復") -> 0 | G44: =G43+D44+F44 -> -10549074
A45: 46179 | B45: =SUMIFS(入金入力!$E$4:$E$580,入金入力!$B$4:$B$580,A45,入金入力!$A$4:$A$580,"リゾート")+SUMIFS(入金予測!$E$4:$E$603,入金予測!$A$4:$A$603,A45,入金予測!$B$4:$B$603,"リゾート") -> 0 | C45: =SUMIFS(未払予定一覧!$O$4:$O$830,未払予定一覧!$N$4:$N$830,A45,未払予定一覧!$A$4:$A$830,"リゾート",未払予定一覧!$B$4:$B$830,"未払繰越")+SUMIFS(未払予定一覧!$O$4:$O$830,未払予定一覧!$N$4:$N$830,A45,未払予定一覧!$A$4:$A$830,"リゾート",未払予定一覧!$B$4:$B$830,"月次予定") -> 380771 | D45: =B45-C45-F45 -> -380771 | E45: =E44+D45 -> -16199845 | F45: =SUMIFS(未払予定一覧!$O$4:$O$830,未払予定一覧!$N$4:$N$830,A45,未払予定一覧!$A$4:$A$830,"リゾート",未払予定一覧!$B$4:$B$830,"カード枠回復") -> 0 | G45: =G44+D45+F45 -> -10929845 | H45: 土
A46: 46180 | B46: =SUMIFS(入金入力!$E$4:$E$580,入金入力!$B$4:$B$580,A46,入金入力!$A$4:$A$580,"リゾート")+SUMIFS(入金予測!$E$4:$E$603,入金予測!$A$4:$A$603,A46,入金予測!$B$4:$B$603,"リゾート") -> 0 | C46: =SUMIFS(未払予定一覧!$O$4:$O$830,未払予定一覧!$N$4:$N$830,A46,未払予定一覧!$A$4:$A$830,"リゾート",未払予定一覧!$B$4:$B$830,"未払繰越")+SUMIFS(未払予定一覧!$O$4:$O$830,未払予定一覧!$N$4:$N$830,A46,未払予定一覧!$A$4:$A$830,"リゾート",未払予定一覧!$B$4:$B$830,"月次予定") -> 0 | D46: =B46-C46-F46 -> 0 | E46: =E45+D46 -> -16199845 | F46: =SUMIFS(未払予定一覧!$O$4:$O$830,未払予定一覧!$N$4:$N$830,A46,未払予定一覧!$A$4:$A$830,"リゾート",未払予定一覧!$B$4:$B$830,"カード枠回復") -> 0 | G46: =G45+D46+F46 -> -10929845 | H46: 日
A47: 46181 | B47: =SUMIFS(入金入力!$E$4:$E$580,入金入力!$B$4:$B$580,A47,入金入力!$A$4:$A$580,"リゾート")+SUMIFS(入金予測!$E$4:$E$603,入金予測!$A$4:$A$603,A47,入金予測!$B$4:$B$603,"リゾート") -> 0 | C47: =SUMIFS(未払予定一覧!$O$4:$O$830,未払予定一覧!$N$4:$N$830,A47,未払予定一覧!$A$4:$A$830,"リゾート",未払予定一覧!$B$4:$B$830,"未払繰越")+SUMIFS(未払予定一覧!$O$4:$O$830,未払予定一覧!$N$4:$N$830,A47,未払予定一覧!$A$4:$A$830,"リゾート",未払予定一覧!$B$4:$B$830,"月次予定") -> 22550 | D47: =B47-C47-F47 -> -22550 | E47: =E46+D47 -> -16222395 | F47: =SUMIFS(未払予定一覧!$O$4:$O$830,未払予定一覧!$N$4:$N$830,A47,未払予定一覧!$A$4:$A$830,"リゾート",未払予定一覧!$B$4:$B$830,"カード枠回復") -> 0 | G47: =G46+D47+F47 -> -10952395
A48: 46182 | B48: =SUMIFS(入金入力!$E$4:$E$580,入金入力!$B$4:$B$580,A48,入金入力!$A$4:$A$580,"リゾート")+SUMIFS(入金予測!$E$4:$E$603,入金予測!$A$4:$A$603,A48,入金予測!$B$4:$B$603,"リゾート") -> 0 | C48: =SUMIFS(未払予定一覧!$O$4:$O$830,未払予定一覧!$N$4:$N$830,A48,未払予定一覧!$A$4:$A$830,"リゾート",未払予定一覧!$B$4:$B$830,"未払繰越")+SUMIFS(未払予定一覧!$O$4:$O$830,未払予定一覧!$N$4:$N$830,A48,未払予定一覧!$A$4:$A$830,"リゾート",未払予定一覧!$B$4:$B$830,"月次予定") -> 880 | D48: =B48-C48-F48 -> -880 | E48: =E47+D48 -> -16223275 | F48: =SUMIFS(未払予定一覧!$O$4:$O$830,未払予定一覧!$N$4:$N$830,A48,未払予定一覧!$A$4:$A$830,"リゾート",未払予定一覧!$B$4:$B$830,"カード枠回復") -> 0 | G48: =G47+D48+F48 -> -10953275
A49: 46183 | B49: =SUMIFS(入金入力!$E$4:$E$580,入金入力!$B$4:$B$580,A49,入金入力!$A$4:$A$580,"リゾート")+SUMIFS(入金予測!$E$4:$E$603,入金予測!$A$4:$A$603,A49,入金予測!$B$4:$B$603,"リゾート") -> 21886345 | C49: =SUMIFS(未払予定一覧!$O$4:$O$830,未払予定一覧!$N$4:$N$830,A49,未払予定一覧!$A$4:$A$830,"リゾート",未払予定一覧!$B$4:$B$830,"未払繰越")+SUMIFS(未払予定一覧!$O$4:$O$830,未払予定一覧!$N$4:$N$830,A49,未払予定一覧!$A$4:$A$830,"リゾート",未払予定一覧!$B$4:$B$830,"月次予定") -> 28197 | D49: =B49-C49-F49 -> 21858148 | E49: =E48+D49 -> 5634872.7 | F49: =SUMIFS(未払予定一覧!$O$4:$O$830,未払予定一覧!$N$4:$N$830,A49,未払予定一覧!$A$4:$A$830,"リゾート",未払予定一覧!$B$4:$B$830,"カード枠回復") -> 0 | G49: =G48+D49+F49 -> 10904873
A50: 46184 | B50: =SUMIFS(入金入力!$E$4:$E$580,入金入力!$B$4:$B$580,A50,入金入力!$A$4:$A$580,"リゾート")+SUMIFS(入金予測!$E$4:$E$603,入金予測!$A$4:$A$603,A50,入金予測!$B$4:$B$603,"リゾート") -> 0 | C50: =SUMIFS(未払予定一覧!$O$4:$O$830,未払予定一覧!$N$4:$N$830,A50,未払予定一覧!$A$4:$A$830,"リゾート",未払予定一覧!$B$4:$B$830,"未払繰越")+SUMIFS(未払予定一覧!$O$4:$O$830,未払予定一覧!$N$4:$N$830,A50,未払予定一覧!$A$4:$A$830,"リゾート",未払予定一覧!$B$4:$B$830,"月次予定") -> 0 | D50: =B50-C50-F50 -> 0 | E50: =E49+D50 -> 5634872.7 | F50: =SUMIFS(未払予定一覧!$O$4:$O$830,未払予定一覧!$N$4:$N$830,A50,未払予定一覧!$A$4:$A$830,"リゾート",未払予定一覧!$B$4:$B$830,"カード枠回復") -> 0 | G50: =G49+D50+F50 -> 10904873
A51: 46185 | B51: =SUMIFS(入金入力!$E$4:$E$580,入金入力!$B$4:$B$580,A51,入金入力!$A$4:$A$580,"リゾート")+SUMIFS(入金予測!$E$4:$E$603,入金予測!$A$4:$A$603,A51,入金予測!$B$4:$B$603,"リゾート") -> 0 | C51: =SUMIFS(未払予定一覧!$O$4:$O$830,未払予定一覧!$N$4:$N$830,A51,未払予定一覧!$A$4:$A$830,"リゾート",未払予定一覧!$B$4:$B$830,"未払繰越")+SUMIFS(未払予定一覧!$O$4:$O$830,未払予定一覧!$N$4:$N$830,A51,未払予定一覧!$A$4:$A$830,"リゾート",未払予定一覧!$B$4:$B$830,"月次予定") -> 0 | D51: =B51-C51-F51 -> 0 | E51: =E50+D51 -> 5634872.7 | F51: =SUMIFS(未払予定一覧!$O$4:$O$830,未払予定一覧!$N$4:$N$830,A51,未払予定一覧!$A$4:$A$830,"リゾート",未払予定一覧!$B$4:$B$830,"カード枠回復") -> 0 | G51: =G50+D51+F51 -> 10904873
A52: 46186 | B52: =SUMIFS(入金入力!$E$4:$E$580,入金入力!$B$4:$B$580,A52,入金入力!$A$4:$A$580,"リゾート")+SUMIFS(入金予測!$E$4:$E$603,入金予測!$A$4:$A$603,A52,入金予測!$B$4:$B$603,"リゾート") -> 0 | C52: =SUMIFS(未払予定一覧!$O$4:$O$830,未払予定一覧!$N$4:$N$830,A52,未払予定一覧!$A$4:$A$830,"リゾート",未払予定一覧!$B$4:$B$830,"未払繰越")+SUMIFS(未払予定一覧!$O$4:$O$830,未払予定一覧!$N$4:$N$830,A52,未払予定一覧!$A$4:$A$830,"リゾート",未払予定一覧!$B$4:$B$830,"月次予定") -> 114777 | D52: =B52-C52-F52 -> -114777 | E52: =E51+D52 -> 5520095.7 | F52: =SUMIFS(未払予定一覧!$O$4:$O$830,未払予定一覧!$N$4:$N$830,A52,未払予定一覧!$A$4:$A$830,"リゾート",未払予定一覧!$B$4:$B$830,"カード枠回復") -> 0 | G52: =G51+D52+F52 -> 10790096 | H52: 土
A53: 46187 | B53: =SUMIFS(入金入力!$E$4:$E$580,入金入力!$B$4:$B$580,A53,入金入力!$A$4:$A$580,"リゾート")+SUMIFS(入金予測!$E$4:$E$603,入金予測!$A$4:$A$603,A53,入金予測!$B$4:$B$603,"リゾート") -> 0 | C53: =SUMIFS(未払予定一覧!$O$4:$O$830,未払予定一覧!$N$4:$N$830,A53,未払予定一覧!$A$4:$A$830,"リゾート",未払予定一覧!$B$4:$B$830,"未払繰越")+SUMIFS(未払予定一覧!$O$4:$O$830,未払予定一覧!$N$4:$N$830,A53,未払予定一覧!$A$4:$A$830,"リゾート",未払予定一覧!$B$4:$B$830,"月次予定") -> 0 | D53: =B53-C53-F53 -> 0 | E53: =E52+D53 -> 5520095.7 | F53: =SUMIFS(未払予定一覧!$O$4:$O$830,未払予定一覧!$N$4:$N$830,A53,未払予定一覧!$A$4:$A$830,"リゾート",未払予定一覧!$B$4:$B$830,"カード枠回復") -> 0 | G53: =G52+D53+F53 -> 10790096 | H53: 日
A54: 46188 | B54: =SUMIFS(入金入力!$E$4:$E$580,入金入力!$B$4:$B$580,A54,入金入力!$A$4:$A$580,"リゾート")+SUMIFS(入金予測!$E$4:$E$603,入金予測!$A$4:$A$603,A54,入金予測!$B$4:$B$603,"リゾート") -> 789000 | C54: =SUMIFS(未払予定一覧!$O$4:$O$830,未払予定一覧!$N$4:$N$830,A54,未払予定一覧!$A$4:$A$830,"リゾート",未払予定一覧!$B$4:$B$830,"未払繰越")+SUMIFS(未払予定一覧!$O$4:$O$830,未払予定一覧!$N$4:$N$830,A54,未払予定一覧!$A$4:$A$830,"リゾート",未払予定一覧!$B$4:$B$830,"月次予定") -> 1008975 | D54: =B54-C54-F54 -> -219975 | E54: =E53+D54 -> 5300120.7 | F54: =SUMIFS(未払予定一覧!$O$4:$O$830,未払予定一覧!$N$4:$N$830,A54,未払予定一覧!$A$4:$A$830,"リゾート",未払予定一覧!$B$4:$B$830,"カード枠回復") -> 0 | G54: =G53+D54+F54 -> 10570121
A55: 46189 | B55: =SUMIFS(入金入力!$E$4:$E$580,入金入力!$B$4:$B$580,A55,入金入力!$A$4:$A$580,"リゾート")+SUMIFS(入金予測!$E$4:$E$603,入金予測!$A$4:$A$603,A55,入金予測!$B$4:$B$603,"リゾート") -> 0 | C55: =SUMIFS(未払予定一覧!$O$4:$O$830,未払予定一覧!$N$4:$N$830,A55,未払予定一覧!$A$4:$A$830,"リゾート",未払予定一覧!$B$4:$B$830,"未払繰越")+SUMIFS(未払予定一覧!$O$4:$O$830,未払予定一覧!$N$4:$N$830,A55,未払予定一覧!$A$4:$A$830,"リゾート",未払予定一覧!$B$4:$B$830,"月次予定") -> 0 | D55: =B55-C55-F55 -> 0 | E55: =E54+D55 -> 5300120.7 | F55: =SUMIFS(未払予定一覧!$O$4:$O$830,未払予定一覧!$N$4:$N$830,A55,未払予定一覧!$A$4:$A$830,"リゾート",未払予定一覧!$B$4:$B$830,"カード枠回復") -> 0 | G55: =G54+D55+F55 -> 10570121
A56: 46190 | B56: =SUMIFS(入金入力!$E$4:$E$580,入金入力!$B$4:$B$580,A56,入金入力!$A$4:$A$580,"リゾート")+SUMIFS(入金予測!$E$4:$E$603,入金予測!$A$4:$A$603,A56,入金予測!$B$4:$B$603,"リゾート") -> 0 | C56: =SUMIFS(未払予定一覧!$O$4:$O$830,未払予定一覧!$N$4:$N$830,A56,未払予定一覧!$A$4:$A$830,"リゾート",未払予定一覧!$B$4:$B$830,"未払繰越")+SUMIFS(未払予定一覧!$O$4:$O$830,未払予定一覧!$N$4:$N$830,A56,未払予定一覧!$A$4:$A$830,"リゾート",未払予定一覧!$B$4:$B$830,"月次予定") -> 0 | D56: =B56-C56-F56 -> 0 | E56: =E55+D56 -> 5300120.7 | F56: =SUMIFS(未払予定一覧!$O$4:$O$830,未払予定一覧!$N$4:$N$830,A56,未払予定一覧!$A$4:$A$830,"リゾート",未払予定一覧!$B$4:$B$830,"カード枠回復") -> 0 | G56: =G55+D56+F56 -> 10570121
A57: 46191 | B57: =SUMIFS(入金入力!$E$4:$E$580,入金入力!$B$4:$B$580,A57,入金入力!$A$4:$A$580,"リゾート")+SUMIFS(入金予測!$E$4:$E$603,入金予測!$A$4:$A$603,A57,入金予測!$B$4:$B$603,"リゾート") -> 0 | C57: =SUMIFS(未払予定一覧!$O$4:$O$830,未払予定一覧!$N$4:$N$830,A57,未払予定一覧!$A$4:$A$830,"リゾート",未払予定一覧!$B$4:$B$830,"未払繰越")+SUMIFS(未払予定一覧!$O$4:$O$830,未払予定一覧!$N$4:$N$830,A57,未払予定一覧!$A$4:$A$830,"リゾート",未払予定一覧!$B$4:$B$830,"月次予定") -> 0 | D57: =B57-C57-F57 -> 0 | E57: =E56+D57 -> 5300120.7 | F57: =SUMIFS(未払予定一覧!$O$4:$O$830,未払予定一覧!$N$4:$N$830,A57,未払予定一覧!$A$4:$A$830,"リゾート",未払予定一覧!$B$4:$B$830,"カード枠回復") -> 0 | G57: =G56+D57+F57 -> 10570121
A58: 46192 | B58: =SUMIFS(入金入力!$E$4:$E$580,入金入力!$B$4:$B$580,A58,入金入力!$A$4:$A$580,"リゾート")+SUMIFS(入金予測!$E$4:$E$603,入金予測!$A$4:$A$603,A58,入金予測!$B$4:$B$603,"リゾート") -> 0 | C58: =SUMIFS(未払予定一覧!$O$4:$O$830,未払予定一覧!$N$4:$N$830,A58,未払予定一覧!$A$4:$A$830,"リゾート",未払予定一覧!$B$4:$B$830,"未払繰越")+SUMIFS(未払予定一覧!$O$4:$O$830,未払予定一覧!$N$4:$N$830,A58,未払予定一覧!$A$4:$A$830,"リゾート",未払予定一覧!$B$4:$B$830,"月次予定") -> 0 | D58: =B58-C58-F58 -> 0 | E58: =E57+D58 -> 5300120.7 | F58: =SUMIFS(未払予定一覧!$O$4:$O$830,未払予定一覧!$N$4:$N$830,A58,未払予定一覧!$A$4:$A$830,"リゾート",未払予定一覧!$B$4:$B$830,"カード枠回復") -> 0 | G58: =G57+D58+F58 -> 10570121
A59: 46193 | B59: =SUMIFS(入金入力!$E$4:$E$580,入金入力!$B$4:$B$580,A59,入金入力!$A$4:$A$580,"リゾート")+SUMIFS(入金予測!$E$4:$E$603,入金予測!$A$4:$A$603,A59,入金予測!$B$4:$B$603,"リゾート") -> 2920518.8 | C59: =SUMIFS(未払予定一覧!$O$4:$O$830,未払予定一覧!$N$4:$N$830,A59,未払予定一覧!$A$4:$A$830,"リゾート",未払予定一覧!$B$4:$B$830,"未払繰越")+SUMIFS(未払予定一覧!$O$4:$O$830,未払予定一覧!$N$4:$N$830,A59,未払予定一覧!$A$4:$A$830,"リゾート",未払予定一覧!$B$4:$B$830,"月次予定") -> 0 | D59: =B59-C59-F59 -> 2920518.8 | E59: =E58+D59 -> 8220639.4 | F59: =SUMIFS(未払予定一覧!$O$4:$O$830,未払予定一覧!$N$4:$N$830,A59,未払予定一覧!$A$4:$A$830,"リゾート",未払予定一覧!$B$4:$B$830,"カード枠回復") -> 0 | G59: =G58+D59+F59 -> 13490639 | H59: 土
A60: 46194 | B60: =SUMIFS(入金入力!$E$4:$E$580,入金入力!$B$4:$B$580,A60,入金入力!$A$4:$A$580,"リゾート")+SUMIFS(入金予測!$E$4:$E$603,入金予測!$A$4:$A$603,A60,入金予測!$B$4:$B$603,"リゾート") -> 0 | C60: =SUMIFS(未払予定一覧!$O$4:$O$830,未払予定一覧!$N$4:$N$830,A60,未払予定一覧!$A$4:$A$830,"リゾート",未払予定一覧!$B$4:$B$830,"未払繰越")+SUMIFS(未払予定一覧!$O$4:$O$830,未払予定一覧!$N$4:$N$830,A60,未払予定一覧!$A$4:$A$830,"リゾート",未払予定一覧!$B$4:$B$830,"月次予定") -> 0 | D60: =B60-C60-F60 -> 0 | E60: =E59+D60 -> 8220639.4 | F60: =SUMIFS(未払予定一覧!$O$4:$O$830,未払予定一覧!$N$4:$N$830,A60,未払予定一覧!$A$4:$A$830,"リゾート",未払予定一覧!$B$4:$B$830,"カード枠回復") -> 0 | G60: =G59+D60+F60 -> 13490639 | H60: 日
A61: 46195 | B61: =SUMIFS(入金入力!$E$4:$E$580,入金入力!$B$4:$B$580,A61,入金入力!$A$4:$A$580,"リゾート")+SUMIFS(入金予測!$E$4:$E$603,入金予測!$A$4:$A$603,A61,入金予測!$B$4:$B$603,"リゾート") -> 0 | C61: =SUMIFS(未払予定一覧!$O$4:$O$830,未払予定一覧!$N$4:$N$830,A61,未払予定一覧!$A$4:$A$830,"リゾート",未払予定一覧!$B$4:$B$830,"未払繰越")+SUMIFS(未払予定一覧!$O$4:$O$830,未払予定一覧!$N$4:$N$830,A61,未払予定一覧!$A$4:$A$830,"リゾート",未払予定一覧!$B$4:$B$830,"月次予定") -> 0 | D61: =B61-C61-F61 -> 0 | E61: =E60+D61 -> 8220639.4 | F61: =SUMIFS(未払予定一覧!$O$4:$O$830,未払予定一覧!$N$4:$N$830,A61,未払予定一覧!$A$4:$A$830,"リゾート",未払予定一覧!$B$4:$B$830,"カード枠回復") -> 0 | G61: =G60+D61+F61 -> 13490639
A62: 46196 | B62: =SUMIFS(入金入力!$E$4:$E$580,入金入力!$B$4:$B$580,A62,入金入力!$A$4:$A$580,"リゾート")+SUMIFS(入金予測!$E$4:$E$603,入金予測!$A$4:$A$603,A62,入金予測!$B$4:$B$603,"リゾート") -> 0 | C62: =SUMIFS(未払予定一覧!$O$4:$O$830,未払予定一覧!$N$4:$N$830,A62,未払予定一覧!$A$4:$A$830,"リゾート",未払予定一覧!$B$4:$B$830,"未払繰越")+SUMIFS(未払予定一覧!$O$4:$O$830,未払予定一覧!$N$4:$N$830,A62,未払予定一覧!$A$4:$A$830,"リゾート",未払予定一覧!$B$4:$B$830,"月次予定") -> 0 | D62: =B62-C62-F62 -> 0 | E62: =E61+D62 -> 8220639.4 | F62: =SUMIFS(未払予定一覧!$O$4:$O$830,未払予定一覧!$N$4:$N$830,A62,未払予定一覧!$A$4:$A$830,"リゾート",未払予定一覧!$B$4:$B$830,"カード枠回復") -> 0 | G62: =G61+D62+F62 -> 13490639
A63: 46197 | B63: =SUMIFS(入金入力!$E$4:$E$580,入金入力!$B$4:$B$580,A63,入金入力!$A$4:$A$580,"リゾート")+SUMIFS(入金予測!$E$4:$E$603,入金予測!$A$4:$A$603,A63,入金予測!$B$4:$B$603,"リゾート") -> 0 | C63: =SUMIFS(未払予定一覧!$O$4:$O$830,未払予定一覧!$N$4:$N$830,A63,未払予定一覧!$A$4:$A$830,"リゾート",未払予定一覧!$B$4:$B$830,"未払繰越")+SUMIFS(未払予定一覧!$O$4:$O$830,未払予定一覧!$N$4:$N$830,A63,未払予定一覧!$A$4:$A$830,"リゾート",未払予定一覧!$B$4:$B$830,"月次予定") -> 608628 | D63: =B63-C63-F63 -> -608628 | E63: =E62+D63 -> 7612011.4 | F63: =SUMIFS(未払予定一覧!$O$4:$O$830,未払予定一覧!$N$4:$N$830,A63,未払予定一覧!$A$4:$A$830,"リゾート",未払予定一覧!$B$4:$B$830,"カード枠回復") -> 0 | G63: =G62+D63+F63 -> 12882011
A64: 46198 | B64: =SUMIFS(入金入力!$E$4:$E$580,入金入力!$B$4:$B$580,A64,入金入力!$A$4:$A$580,"リゾート")+SUMIFS(入金予測!$E$4:$E$603,入金予測!$A$4:$A$603,A64,入金予測!$B$4:$B$603,"リゾート") -> 0 | C64: =SUMIFS(未払予定一覧!$O$4:$O$830,未払予定一覧!$N$4:$N$830,A64,未払予定一覧!$A$4:$A$830,"リゾート",未払予定一覧!$B$4:$B$830,"未払繰越")+SUMIFS(未払予定一覧!$O$4:$O$830,未払予定一覧!$N$4:$N$830,A64,未払予定一覧!$A$4:$A$830,"リゾート",未払予定一覧!$B$4:$B$830,"月次予定") -> 10795122 | D64: =B64-C64-F64 -> -10795122 | E64: =E63+D64 -> -3183110.6 | F64: =SUMIFS(未払予定一覧!$O$4:$O$830,未払予定一覧!$N$4:$N$830,A64,未払予定一覧!$A$4:$A$830,"リゾート",未払予定一覧!$B$4:$B$830,"カード枠回復") -> 0 | G64: =G63+D64+F64 -> 2086889.4
A65: 46199 | B65: =SUMIFS(入金入力!$E$4:$E$580,入金入力!$B$4:$B$580,A65,入金入力!$A$4:$A$580,"リゾート")+SUMIFS(入金予測!$E$4:$E$603,入金予測!$A$4:$A$603,A65,入金予測!$B$4:$B$603,"リゾート") -> 0 | C65: =SUMIFS(未払予定一覧!$O$4:$O$830,未払予定一覧!$N$4:$N$830,A65,未払予定一覧!$A$4:$A$830,"リゾート",未払予定一覧!$B$4:$B$830,"未払繰越")+SUMIFS(未払予定一覧!$O$4:$O$830,未払予定一覧!$N$4:$N$830,A65,未払予定一覧!$A$4:$A$830,"リゾート",未払予定一覧!$B$4:$B$830,"月次予定") -> 0 | D65: =B65-C65-F65 -> 0 | E65: =E64+D65 -> -3183110.6 | F65: =SUMIFS(未払予定一覧!$O$4:$O$830,未払予定一覧!$N$4:$N$830,A65,未払予定一覧!$A$4:$A$830,"リゾート",未払予定一覧!$B$4:$B$830,"カード枠回復") -> 0 | G65: =G64+D65+F65 -> 2086889.4
A66: 46200 | B66: =SUMIFS(入金入力!$E$4:$E$580,入金入力!$B$4:$B$580,A66,入金入力!$A$4:$A$580,"リゾート")+SUMIFS(入金予測!$E$4:$E$603,入金予測!$A$4:$A$603,A66,入金予測!$B$4:$B$603,"リゾート") -> 0 | C66: =SUMIFS(未払予定一覧!$O$4:$O$830,未払予定一覧!$N$4:$N$830,A66,未払予定一覧!$A$4:$A$830,"リゾート",未払予定一覧!$B$4:$B$830,"未払繰越")+SUMIFS(未払予定一覧!$O$4:$O$830,未払予定一覧!$N$4:$N$830,A66,未払予定一覧!$A$4:$A$830,"リゾート",未払予定一覧!$B$4:$B$830,"月次予定") -> 944225 | D66: =B66-C66-F66 -> -944225 | E66: =E65+D66 -> -4127335.6 | F66: =SUMIFS(未払予定一覧!$O$4:$O$830,未払予定一覧!$N$4:$N$830,A66,未払予定一覧!$A$4:$A$830,"リゾート",未払予定一覧!$B$4:$B$830,"カード枠回復") -> 0 | G66: =G65+D66+F66 -> 1142664.4 | H66: 土
A67: 46201 | B67: =SUMIFS(入金入力!$E$4:$E$580,入金入力!$B$4:$B$580,A67,入金入力!$A$4:$A$580,"リゾート")+SUMIFS(入金予測!$E$4:$E$603,入金予測!$A$4:$A$603,A67,入金予測!$B$4:$B$603,"リゾート") -> 0 | C67: =SUMIFS(未払予定一覧!$O$4:$O$830,未払予定一覧!$N$4:$N$830,A67,未払予定一覧!$A$4:$A$830,"リゾート",未払予定一覧!$B$4:$B$830,"未払繰越")+SUMIFS(未払予定一覧!$O$4:$O$830,未払予定一覧!$N$4:$N$830,A67,未払予定一覧!$A$4:$A$830,"リゾート",未払予定一覧!$B$4:$B$830,"月次予定") -> 13282890 | D67: =B67-C67-F67 -> -13282890 | E67: =E66+D67 -> -17410226 | F67: =SUMIFS(未払予定一覧!$O$4:$O$830,未払予定一覧!$N$4:$N$830,A67,未払予定一覧!$A$4:$A$830,"リゾート",未払予定一覧!$B$4:$B$830,"カード枠回復") -> 0 | G67: =G66+D67+F67 -> -12140226 | H67: 日
A68: 46202 | B68: =SUMIFS(入金入力!$E$4:$E$580,入金入力!$B$4:$B$580,A68,入金入力!$A$4:$A$580,"リゾート")+SUMIFS(入金予測!$E$4:$E$603,入金予測!$A$4:$A$603,A68,入金予測!$B$4:$B$603,"リゾート") -> 0 | C68: =SUMIFS(未払予定一覧!$O$4:$O$830,未払予定一覧!$N$4:$N$830,A68,未払予定一覧!$A$4:$A$830,"リゾート",未払予定一覧!$B$4:$B$830,"未払繰越")+SUMIFS(未払予定一覧!$O$4:$O$830,未払予定一覧!$N$4:$N$830,A68,未払予定一覧!$A$4:$A$830,"リゾート",未払予定一覧!$B$4:$B$830,"月次予定") -> 0 | D68: =B68-C68-F68 -> 0 | E68: =E67+D68 -> -17410226 | F68: =SUMIFS(未払予定一覧!$O$4:$O$830,未払予定一覧!$N$4:$N$830,A68,未払予定一覧!$A$4:$A$830,"リゾート",未払予定一覧!$B$4:$B$830,"カード枠回復") -> 0 | G68: =G67+D68+F68 -> -12140226
A69: 46203 | B69: =SUMIFS(入金入力!$E$4:$E$580,入金入力!$B$4:$B$580,A69,入金入力!$A$4:$A$580,"リゾート")+SUMIFS(入金予測!$E$4:$E$603,入金予測!$A$4:$A$603,A69,入金予測!$B$4:$B$603,"リゾート") -> 0 | C69: =SUMIFS(未払予定一覧!$O$4:$O$830,未払予定一覧!$N$4:$N$830,A69,未払予定一覧!$A$4:$A$830,"リゾート",未払予定一覧!$B$4:$B$830,"未払繰越")+SUMIFS(未払予定一覧!$O$4:$O$830,未払予定一覧!$N$4:$N$830,A69,未払予定一覧!$A$4:$A$830,"リゾート",未払予定一覧!$B$4:$B$830,"月次予定") -> 2753695 | D69: =B69-C69-F69 -> -2753695 | E69: =E68+D69 -> -20163921 | F69: =SUMIFS(未払予定一覧!$O$4:$O$830,未払予定一覧!$N$4:$N$830,A69,未払予定一覧!$A$4:$A$830,"リゾート",未払予定一覧!$B$4:$B$830,"カード枠回復") -> 0 | G69: =G68+D69+F69 -> -14893921
A70: 6月合計 | B70: =SUM(B40:B69) -> 25595864 | C70: =SUM(C40:C69) -> 30740710 | D70: =B70-C70-F70 -> -5144846.5 | E70: =E69 -> -20163921 | F70: =SUM(F40:F69) -> 0 | G70: =G69 -> -14893921 | H70: 月合計
A72: ■ 7月
A73: 46204 | B73: =SUMIFS(入金入力!$E$4:$E$580,入金入力!$B$4:$B$580,A73,入金入力!$A$4:$A$580,"リゾート")+SUMIFS(入金予測!$E$4:$E$603,入金予測!$A$4:$A$603,A73,入金予測!$B$4:$B$603,"リゾート") -> 0 | C73: =SUMIFS(未払予定一覧!$O$4:$O$830,未払予定一覧!$N$4:$N$830,A73,未払予定一覧!$A$4:$A$830,"リゾート",未払予定一覧!$B$4:$B$830,"未払繰越")+SUMIFS(未払予定一覧!$O$4:$O$830,未払予定一覧!$N$4:$N$830,A73,未払予定一覧!$A$4:$A$830,"リゾート",未払予定一覧!$B$4:$B$830,"月次予定") -> 0 | D73: =B73-C73-F73 -> 0 | E73: =E70+D73 -> -20163921 | F73: =SUMIFS(未払予定一覧!$O$4:$O$830,未払予定一覧!$N$4:$N$830,A73,未払予定一覧!$A$4:$A$830,"リゾート",未払予定一覧!$B$4:$B$830,"カード枠回復") -> 0 | G73: =G70+D73+F73 -> -14893921
A74: 46205 | B74: =SUMIFS(入金入力!$E$4:$E$580,入金入力!$B$4:$B$580,A74,入金入力!$A$4:$A$580,"リゾート")+SUMIFS(入金予測!$E$4:$E$603,入金予測!$A$4:$A$603,A74,入金予測!$B$4:$B$603,"リゾート") -> 0 | C74: =SUMIFS(未払予定一覧!$O$4:$O$830,未払予定一覧!$N$4:$N$830,A74,未払予定一覧!$A$4:$A$830,"リゾート",未払予定一覧!$B$4:$B$830,"未払繰越")+SUMIFS(未払予定一覧!$O$4:$O$830,未払予定一覧!$N$4:$N$830,A74,未払予定一覧!$A$4:$A$830,"リゾート",未払予定一覧!$B$4:$B$830,"月次予定") -> 0 | D74: =B74-C74-F74 -> 0 | E74: =E73+D74 -> -20163921 | F74: =SUMIFS(未払予定一覧!$O$4:$O$830,未払予定一覧!$N$4:$N$830,A74,未払予定一覧!$A$4:$A$830,"リゾート",未払予定一覧!$B$4:$B$830,"カード枠回復") -> 0 | G74: =G73+D74+F74 -> -14893921
A75: 46206 | B75: =SUMIFS(入金入力!$E$4:$E$580,入金入力!$B$4:$B$580,A75,入金入力!$A$4:$A$580,"リゾート")+SUMIFS(入金予測!$E$4:$E$603,入金予測!$A$4:$A$603,A75,入金予測!$B$4:$B$603,"リゾート") -> 0 | C75: =SUMIFS(未払予定一覧!$O$4:$O$830,未払予定一覧!$N$4:$N$830,A75,未払予定一覧!$A$4:$A$830,"リゾート",未払予定一覧!$B$4:$B$830,"未払繰越")+SUMIFS(未払予定一覧!$O$4:$O$830,未払予定一覧!$N$4:$N$830,A75,未払予定一覧!$A$4:$A$830,"リゾート",未払予定一覧!$B$4:$B$830,"月次予定") -> 800000 | D75: =B75-C75-F75 -> -800000 | E75: =E74+D75 -> -20963921 | F75: =SUMIFS(未払予定一覧!$O$4:$O$830,未払予定一覧!$N$4:$N$830,A75,未払予定一覧!$A$4:$A$830,"リゾート",未払予定一覧!$B$4:$B$830,"カード枠回復") -> 0 | G75: =G74+D75+F75 -> -15693921
A76: 46207 | B76: =SUMIFS(入金入力!$E$4:$E$580,入金入力!$B$4:$B$580,A76,入金入力!$A$4:$A$580,"リゾート")+SUMIFS(入金予測!$E$4:$E$603,入金予測!$A$4:$A$603,A76,入金予測!$B$4:$B$603,"リゾート") -> 0 | C76: =SUMIFS(未払予定一覧!$O$4:$O$830,未払予定一覧!$N$4:$N$830,A76,未払予定一覧!$A$4:$A$830,"リゾート",未払予定一覧!$B$4:$B$830,"未払繰越")+SUMIFS(未払予定一覧!$O$4:$O$830,未払予定一覧!$N$4:$N$830,A76,未払予定一覧!$A$4:$A$830,"リゾート",未払予定一覧!$B$4:$B$830,"月次予定") -> 0 | D76: =B76-C76-F76 -> 0 | E76: =E75+D76 -> -20963921 | F76: =SUMIFS(未払予定一覧!$O$4:$O$830,未払予定一覧!$N$4:$N$830,A76,未払予定一覧!$A$4:$A$830,"リゾート",未払予定一覧!$B$4:$B$830,"カード枠回復") -> 0 | G76: =G75+D76+F76 -> -15693921 | H76: 土
A77: 46208 | B77: =SUMIFS(入金入力!$E$4:$E$580,入金入力!$B$4:$B$580,A77,入金入力!$A$4:$A$580,"リゾート")+SUMIFS(入金予測!$E$4:$E$603,入金予測!$A$4:$A$603,A77,入金予測!$B$4:$B$603,"リゾート") -> 0 | C77: =SUMIFS(未払予定一覧!$O$4:$O$830,未払予定一覧!$N$4:$N$830,A77,未払予定一覧!$A$4:$A$830,"リゾート",未払予定一覧!$B$4:$B$830,"未払繰越")+SUMIFS(未払予定一覧!$O$4:$O$830,未払予定一覧!$N$4:$N$830,A77,未払予定一覧!$A$4:$A$830,"リゾート",未払予定一覧!$B$4:$B$830,"月次予定") -> 0 | D77: =B77-C77-F77 -> 0 | E77: =E76+D77 -> -20963921 | F77: =SUMIFS(未払予定一覧!$O$4:$O$830,未払予定一覧!$N$4:$N$830,A77,未払予定一覧!$A$4:$A$830,"リゾート",未払予定一覧!$B$4:$B$830,"カード枠回復") -> 0 | G77: =G76+D77+F77 -> -15693921 | H77: 日
A78: 46209 | B78: =SUMIFS(入金入力!$E$4:$E$580,入金入力!$B$4:$B$580,A78,入金入力!$A$4:$A$580,"リゾート")+SUMIFS(入金予測!$E$4:$E$603,入金予測!$A$4:$A$603,A78,入金予測!$B$4:$B$603,"リゾート") -> 0 | C78: =SUMIFS(未払予定一覧!$O$4:$O$830,未払予定一覧!$N$4:$N$830,A78,未払予定一覧!$A$4:$A$830,"リゾート",未払予定一覧!$B$4:$B$830,"未払繰越")+SUMIFS(未払予定一覧!$O$4:$O$830,未払予定一覧!$N$4:$N$830,A78,未払予定一覧!$A$4:$A$830,"リゾート",未払予定一覧!$B$4:$B$830,"月次予定") -> 380771 | D78: =B78-C78-F78 -> -380771 | E78: =E77+D78 -> -21344692 | F78: =SUMIFS(未払予定一覧!$O$4:$O$830,未払予定一覧!$N$4:$N$830,A78,未払予定一覧!$A$4:$A$830,"リゾート",未払予定一覧!$B$4:$B$830,"カード枠回復") -> 0 | G78: =G77+D78+F78 -> -16074692
A79: 46210 | B79: =SUMIFS(入金入力!$E$4:$E$580,入金入力!$B$4:$B$580,A79,入金入力!$A$4:$A$580,"リゾート")+SUMIFS(入金予測!$E$4:$E$603,入金予測!$A$4:$A$603,A79,入金予測!$B$4:$B$603,"リゾート") -> 0 | C79: =SUMIFS(未払予定一覧!$O$4:$O$830,未払予定一覧!$N$4:$N$830,A79,未払予定一覧!$A$4:$A$830,"リゾート",未払予定一覧!$B$4:$B$830,"未払繰越")+SUMIFS(未払予定一覧!$O$4:$O$830,未払予定一覧!$N$4:$N$830,A79,未払予定一覧!$A$4:$A$830,"リゾート",未払予定一覧!$B$4:$B$830,"月次予定") -> 0 | D79: =B79-C79-F79 -> 0 | E79: =E78+D79 -> -21344692 | F79: =SUMIFS(未払予定一覧!$O$4:$O$830,未払予定一覧!$N$4:$N$830,A79,未払予定一覧!$A$4:$A$830,"リゾート",未払予定一覧!$B$4:$B$830,"カード枠回復") -> 0 | G79: =G78+D79+F79 -> -16074692
A80: 46211 | B80: =SUMIFS(入金入力!$E$4:$E$580,入金入力!$B$4:$B$580,A80,入金入力!$A$4:$A$580,"リゾート")+SUMIFS(入金予測!$E$4:$E$603,入金予測!$A$4:$A$603,A80,入金予測!$B$4:$B$603,"リゾート") -> 0 | C80: =SUMIFS(未払予定一覧!$O$4:$O$830,未払予定一覧!$N$4:$N$830,A80,未払予定一覧!$A$4:$A$830,"リゾート",未払予定一覧!$B$4:$B$830,"未払繰越")+SUMIFS(未払予定一覧!$O$4:$O$830,未払予定一覧!$N$4:$N$830,A80,未払予定一覧!$A$4:$A$830,"リゾート",未払予定一覧!$B$4:$B$830,"月次予定") -> 22550 | D80: =B80-C80-F80 -> -22550 | E80: =E79+D80 -> -21367242 | F80: =SUMIFS(未払予定一覧!$O$4:$O$830,未払予定一覧!$N$4:$N$830,A80,未払予定一覧!$A$4:$A$830,"リゾート",未払予定一覧!$B$4:$B$830,"カード枠回復") -> 0 | G80: =G79+D80+F80 -> -16097242
A81: 46212 | B81: =SUMIFS(入金入力!$E$4:$E$580,入金入力!$B$4:$B$580,A81,入金入力!$A$4:$A$580,"リゾート")+SUMIFS(入金予測!$E$4:$E$603,入金予測!$A$4:$A$603,A81,入金予測!$B$4:$B$603,"リゾート") -> 0 | C81: =SUMIFS(未払予定一覧!$O$4:$O$830,未払予定一覧!$N$4:$N$830,A81,未払予定一覧!$A$4:$A$830,"リゾート",未払予定一覧!$B$4:$B$830,"未払繰越")+SUMIFS(未払予定一覧!$O$4:$O$830,未払予定一覧!$N$4:$N$830,A81,未払予定一覧!$A$4:$A$830,"リゾート",未払予定一覧!$B$4:$B$830,"月次予定") -> 880 | D81: =B81-C81-F81 -> -880 | E81: =E80+D81 -> -21368122 | F81: =SUMIFS(未払予定一覧!$O$4:$O$830,未払予定一覧!$N$4:$N$830,A81,未払予定一覧!$A$4:$A$830,"リゾート",未払予定一覧!$B$4:$B$830,"カード枠回復") -> 0 | G81: =G80+D81+F81 -> -16098122
A82: 46213 | B82: =SUMIFS(入金入力!$E$4:$E$580,入金入力!$B$4:$B$580,A82,入金入力!$A$4:$A$580,"リゾート")+SUMIFS(入金予測!$E$4:$E$603,入金予測!$A$4:$A$603,A82,入金予測!$B$4:$B$603,"リゾート") -> 14602594 | C82: =SUMIFS(未払予定一覧!$O$4:$O$830,未払予定一覧!$N$4:$N$830,A82,未払予定一覧!$A$4:$A$830,"リゾート",未払予定一覧!$B$4:$B$830,"未払繰越")+SUMIFS(未払予定一覧!$O$4:$O$830,未払予定一覧!$N$4:$N$830,A82,未払予定一覧!$A$4:$A$830,"リゾート",未払予定一覧!$B$4:$B$830,"月次予定") -> 28197 | D82: =B82-C82-F82 -> 14574397 | E82: =E81+D82 -> -6793724.8 | F82: =SUMIFS(未払予定一覧!$O$4:$O$830,未払予定一覧!$N$4:$N$830,A82,未払予定一覧!$A$4:$A$830,"リゾート",未払予定一覧!$B$4:$B$830,"カード枠回復") -> 0 | G82: =G81+D82+F82 -> -1523724.8
